Workbook

Sheet BANK
A1: This is a list of active account/product types currently available on T24.
A2: BRANCH_CO_MNE | B2: @ID | C2: DESCRIPTION | D2: PRODUCT_GROUP | E2: PARENT.PRODUCT | F2: CATEGORY CODE | G2: ONLINE ACCESS | H2: View Only | I2: Transfer to Internal Accounts (A2A) | J2: Transfer from Internal Accounts (A2A) | K2: Transfer To External Accounts | L2: Transfer From External Accounts | M2: Loan Payment (From) | N2: CC Payment (From) | O2: Bill Pay (From) | P2: RDC (Deposit to) | Q2: P2P (From) | R2: Comments
A3: BNK | B3: AD.BRO.BB.FR.NONP | C3: Book-Based GIC - Non Personal | D3: BROKER.TERM.DEPOSITS | E3: =VLOOKUP(B3,'PARENT PRODUCT'!$A:$B,2,FALSE) -> AD.BRO.PARENT.FR | F3: 6611 | G3: =VLOOKUP(B3,'ONLINE ACCESS'!$A:$B,2,FALSE) -> #N/A
A4: BNK | B4: AD.BRO.BB.FR.NONP.WHS | C4: Book-Based GIC - Non Personal WHS | D4: BROKER.TERM.DEPOSITS | E4: =VLOOKUP(B4,'PARENT PRODUCT'!$A:$B,2,FALSE) -> AD.BRO.PARENT.FR | F4: 6617 | G4: =VLOOKUP(B4,'ONLINE ACCESS'!$A:$B,2,FALSE) -> #N/A
A5: BNK | B5: AD.BRO.BB.FR.PERS | C5: Book-Based GIC - Personal | D5: BROKER.TERM.DEPOSITS | E5: =VLOOKUP(B5,'PARENT PRODUCT'!$A:$B,2,FALSE) -> AD.BRO.PARENT.FR | F5: =VLOOKUP(B5,'CATEGORY CODE'!$A:$B,2,FALSE) -> 6712 | G5: =VLOOKUP(B5,'ONLINE ACCESS'!$A:$B,2,FALSE) -> #N/A
A6: BNK | B6: AD.BRO.BB.FR.PERS.WHS | C6: Book-Based GIC - Personal WHS | D6: BROKER.TERM.DEPOSITS | E6: =VLOOKUP(B6,'PARENT PRODUCT'!$A:$B,2,FALSE) -> AD.BRO.PARENT.FR | F6: =VLOOKUP(B6,'CATEGORY CODE'!$A:$B,2,FALSE) -> 6717 | G6: =VLOOKUP(B6,'ONLINE ACCESS'!$A:$B,2,FALSE) -> #N/A
A7: BNK | B7: AD.BRO.CSC.NONPER | C7: CSC - Non-Personal | D7: BROKER.TERM.DEPOSITS | E7: =VLOOKUP(B7,'PARENT PRODUCT'!$A:$B,2,FALSE) -> AD.BRO.PARENT.FR | F7: 6651 | G7: =VLOOKUP(B7,'ONLINE ACCESS'!$A:$B,2,FALSE) -> #N/A
A8: BNK | B8: AD.BRO.CSC.NONPER.WH | C8: CSC - Non Personal Wholesale | D8: BROKER.TERM.DEPOSITS | E8: =VLOOKUP(B8,'PARENT PRODUCT'!$A:$B,2,FALSE) -> AD.BRO.PARENT.FR | F8: 6656 | G8: =VLOOKUP(B8,'ONLINE ACCESS'!$A:$B,2,FALSE) -> #N/A
A9: BNK | B9: AD.BRO.CSC.PER | C9: CSC - Personal | D9: BROKER.TERM.DEPOSITS | E9: =VLOOKUP(B9,'PARENT PRODUCT'!$A:$B,2,FALSE) -> AD.BRO.PARENT.FR | F9: 6751 | G9: =VLOOKUP(B9,'ONLINE ACCESS'!$A:$B,2,FALSE) -> #N/A
A10: BNK | B10: AD.BRO.CSC.PER.WH | C10: CSC - Personal Wholesale | D10: BROKER.TERM.DEPOSITS | E10: =VLOOKUP(B10,'PARENT PRODUCT'!$A:$B,2,FALSE) -> AD.BRO.PARENT.FR | F10: 6756 | G10: =VLOOKUP(B10,'ONLINE ACCESS'!$A:$B,2,FALSE) -> #N/A
A11: BNK | B11: AD.BRO.FLR.NONPERS | C11: FLR - Non Personal | D11: BROKER.TERM.DEPOSITS | E11: =VLOOKUP(B11,'PARENT PRODUCT'!$A:$B,2,FALSE) -> AD.BRO.PARENT.FR | F11: =VLOOKUP(B11,'CATEGORY CODE'!$A:$B,2,FALSE) -> 6602 | G11: =VLOOKUP(B11,'ONLINE ACCESS'!$A:$B,2,FALSE) -> #N/A
A12: BNK | B12: AD.BRO.FLR.NONPERS.WH | C12: FLR - Non Personal Wholesale | D12: BROKER.TERM.DEPOSITS | E12: =VLOOKUP(B12,'PARENT PRODUCT'!$A:$B,2,FALSE) -> AD.BRO.PARENT.FR | F12: 6607 | G12: =VLOOKUP(B12,'ONLINE ACCESS'!$A:$B,2,FALSE) -> #N/A
A13: BNK | B13: AD.BRO.FLR.PERS | C13: FLR - Personal | D13: BROKER.TERM.DEPOSITS | E13: =VLOOKUP(B13,'PARENT PRODUCT'!$A:$B,2,FALSE) -> AD.BRO.PARENT.FR | F13: =VLOOKUP(B13,'CATEGORY CODE'!$A:$B,2,FALSE) -> 6702 | G13: =VLOOKUP(B13,'ONLINE ACCESS'!$A:$B,2,FALSE) -> #N/A
A14: BNK | B14: AD.BRO.FLR.PERS.WH | C14: FLR - Personal Wholesale | D14: BROKER.TERM.DEPOSITS | E14: =VLOOKUP(B14,'PARENT PRODUCT'!$A:$B,2,FALSE) -> AD.BRO.PARENT.FR | F14: 6706 | G14: =VLOOKUP(B14,'ONLINE ACCESS'!$A:$B,2,FALSE) -> #N/A
A15: BNK | B15: AD.BRO.FR.NONPERS | C15: GIC - Non Personal | D15: BROKER.TERM.DEPOSITS | E15: =VLOOKUP(B15,'PARENT PRODUCT'!$A:$B,2,FALSE) -> AD.BRO.PARENT.FR | F15: =VLOOKUP(B15,'CATEGORY CODE'!$A:$B,2,FALSE) -> 6611 | G15: =VLOOKUP(B15,'ONLINE ACCESS'!$A:$B,2,FALSE) -> #N/A
A16: BNK | B16: AD.BRO.FR.NONPERS.WHS | C16: GIC - Non Personal Wholesale | D16: BROKER.TERM.DEPOSITS | E16: =VLOOKUP(B16,'PARENT PRODUCT'!$A:$B,2,FALSE) -> AD.BRO.PARENT.FR | F16: =VLOOKUP(B16,'CATEGORY CODE'!$A:$B,2,FALSE) -> 6617 | G16: =VLOOKUP(B16,'ONLINE ACCESS'!$A:$B,2,FALSE) -> #N/A
A17: BNK | B17: AD.BRO.FR.PERS | C17: GIC - Personal | D17: BROKER.TERM.DEPOSITS | E17: =VLOOKUP(B17,'PARENT PRODUCT'!$A:$B,2,FALSE) -> AD.BRO.PARENT.FR | F17: =VLOOKUP(B17,'CATEGORY CODE'!$A:$B,2,FALSE) -> 6712 | G17: =VLOOKUP(B17,'ONLINE ACCESS'!$A:$B,2,FALSE) -> #N/A
A18: BNK | B18: AD.BRO.FR.PERS.WHS | C18: GIC - Personal Wholesale | D18: BROKER.TERM.DEPOSITS | E18: =VLOOKUP(B18,'PARENT PRODUCT'!$A:$B,2,FALSE) -> AD.BRO.PARENT.FR | F18: =VLOOKUP(B18,'CATEGORY CODE'!$A:$B,2,FALSE) -> 6717 | G18: =VLOOKUP(B18,'ONLINE ACCESS'!$A:$B,2,FALSE) -> #N/A
A19: BNK | B19: AD.BRO.RIF.CON.PER | C19: RRIF Convertible GIC | D19: BROKER.REG.TERM.DEPOSITS | E19: =VLOOKUP(B19,'PARENT PRODUCT'!$A:$B,2,FALSE) -> AD.BRO.RIF.PARENT.FR | F19: 6911 | G19: =VLOOKUP(B19,'ONLINE ACCESS'!$A:$B,2,FALSE) -> #N/A
A20: BNK | B20: AD.BRO.RIF.CON.PER.WH | C20: Broker RRIF Conv-Personal Wholesale | D20: BROKER.TERM.DEPOSITS | E20: =VLOOKUP(B20,'PARENT PRODUCT'!$A:$B,2,FALSE) -> #N/A | F20: 6915 | G20: =VLOOKUP(B20,'ONLINE ACCESS'!$A:$B,2,FALSE) -> #N/A
A21: BNK | B21: AD.BRO.RIF.FR.PERS | C21: RRIF Premium GIC | D21: BROKER.REG.TERM.DEPOSITS | E21: =VLOOKUP(B21,'PARENT PRODUCT'!$A:$B,2,FALSE) -> AD.BRO.RIF.PARENT.FR | F21: =VLOOKUP(B21,'CATEGORY CODE'!$A:$B,2,FALSE) -> 6921 | G21: =VLOOKUP(B21,'ONLINE ACCESS'!$A:$B,2,FALSE) -> #N/A
A22: BNK | B22: AD.BRO.RIF.FR.PERS.WH | C22: Broker RRIF FR - Personal Wholesale | D22: BROKER.TERM.DEPOSITS | E22: =VLOOKUP(B22,'PARENT PRODUCT'!$A:$B,2,FALSE) -> #N/A | F22: 6925 | G22: =VLOOKUP(B22,'ONLINE ACCESS'!$A:$B,2,FALSE) -> #N/A
A23: BNK | B23: AD.BRO.RIF.FRE.PER | C23: RRIF Fully Redeemable GIC | D23: BROKER.REG.TERM.DEPOSITS | E23: =VLOOKUP(B23,'PARENT PRODUCT'!$A:$B,2,FALSE) -> AD.BRO.RIF.PARENT.FR | F23: 6941 | G23: =VLOOKUP(B23,'ONLINE ACCESS'!$A:$B,2,FALSE) -> #N/A
A24: BNK | B24: AD.BRO.RIF.FRE.PER.WH | C24: Broker RRIF Fully Redeem Pers WHS | D24: BROKER.TERM.DEPOSITS | E24: =VLOOKUP(B24,'PARENT PRODUCT'!$A:$B,2,FALSE) -> #N/A | F24: 6945 | G24: =VLOOKUP(B24,'ONLINE ACCESS'!$A:$B,2,FALSE) -> #N/A
A25: BNK | B25: AD.BRO.RSP.CON.PER | C25: RRSP Convertible GIC | D25: BROKER.REG.TERM.DEPOSITS | E25: =VLOOKUP(B25,'PARENT PRODUCT'!$A:$B,2,FALSE) -> AD.BRO.RSP.PARENT.FR | F25: 6821 | G25: =VLOOKUP(B25,'ONLINE ACCESS'!$A:$B,2,FALSE) -> #N/A
A26: BNK | B26: AD.BRO.RSP.CON.PER.WH | C26: Broker RRSP Conv-Pers Wholesale | D26: BROKER.TERM.DEPOSITS | E26: =VLOOKUP(B26,'PARENT PRODUCT'!$A:$B,2,FALSE) -> #N/A | F26: 6815 | G26: =VLOOKUP(B26,'ONLINE ACCESS'!$A:$B,2,FALSE) -> #N/A
A27: BNK | B27: AD.BRO.RSP.FR.PERS | C27: RRSP Premium GIC | D27: BROKER.REG.TERM.DEPOSITS | E27: =VLOOKUP(B27,'PARENT PRODUCT'!$A:$B,2,FALSE) -> AD.BRO.RSP.PARENT.FR | F27: =VLOOKUP(B27,'CATEGORY CODE'!$A:$B,2,FALSE) -> 6821 | G27: =VLOOKUP(B27,'ONLINE ACCESS'!$A:$B,2,FALSE) -> #N/A
A28: BNK | B28: AD.BRO.RSP.FR.PERS.WH | C28: Broker RRSP FR - Personal Wholesale | D28: BROKER.TERM.DEPOSITS | E28: =VLOOKUP(B28,'PARENT PRODUCT'!$A:$B,2,FALSE) -> #N/A | F28: 6825 | G28: =VLOOKUP(B28,'ONLINE ACCESS'!$A:$B,2,FALSE) -> #N/A
A29: BNK | B29: AD.BRO.TFSA.FR.PER | C29: TFSA Premium GIC | D29: BROKER.REG.TERM.DEPOSITS | E29: =VLOOKUP(B29,'PARENT PRODUCT'!$A:$B,2,FALSE) -> AD.BRO.TFSA.PARENT.FR | F29: 6761 | G29: =VLOOKUP(B29,'ONLINE ACCESS'!$A:$B,2,FALSE) -> #N/A
A30: BNK | B30: AD.BRO.TFSA.FR.PER.WH | C30: Broker TFSA FR - Personal Wholesale | D30: BROKER.TERM.DEPOSITS | E30: =VLOOKUP(B30,'PARENT PRODUCT'!$A:$B,2,FALSE) -> #N/A | F30: 6717 | G30: =VLOOKUP(B30,'ONLINE ACCESS'!$A:$B,2,FALSE) -> #N/A
A31: BNK | B31: AD.CDF.FR.PERS | C31: Motive GIC - Personal | D31: CDF.TERM.DEPOSITS | E31: =VLOOKUP(B31,'PARENT PRODUCT'!$A:$B,2,FALSE) -> AD.CDF.PARENT.FR | F31: =VLOOKUP(B31,'CATEGORY CODE'!$A:$B,2,FALSE) -> 6710 | G31: =VLOOKUP(B31,'ONLINE ACCESS'!$A:$B,2,FALSE) -> CDF
A32: BNK | B32: AD.CDF.FR.PERS.WHS | C32: Motive GIC - Personal Wholesale | D32: CDF.TERM.DEPOSITS | E32: =VLOOKUP(B32,'PARENT PRODUCT'!$A:$B,2,FALSE) -> AD.CDF.PARENT.FR | F32: =VLOOKUP(B32,'CATEGORY CODE'!$A:$B,2,FALSE) -> 6715 | G32: =VLOOKUP(B32,'ONLINE ACCESS'!$A:$B,2,FALSE) -> CDF
A33: BNK | B33: AD.CDF.RIF.FR.PERS | C33: Motive RRIF GIC | D33: CDF.REG.TERM.DEPOSITS | E33: =VLOOKUP(B33,'PARENT PRODUCT'!$A:$B,2,FALSE) -> AD.CDF.RIF.PARENT.FR | F33: =VLOOKUP(B33,'CATEGORY CODE'!$A:$B,2,FALSE) -> 6920 | G33: =VLOOKUP(B33,'ONLINE ACCESS'!$A:$B,2,FALSE) -> CDF
A34: BNK | B34: AD.CDF.RSP.FR.PERS | C34: Motive RRSP GIC | D34: CDF.REG.TERM.DEPOSITS | E34: =VLOOKUP(B34,'PARENT PRODUCT'!$A:$B,2,FALSE) -> AD.CDF.RSP.PARENT.FR | F34: =VLOOKUP(B34,'CATEGORY CODE'!$A:$B,2,FALSE) -> 6820 | G34: =VLOOKUP(B34,'ONLINE ACCESS'!$A:$B,2,FALSE) -> CDF
A35: BNK | B35: AD.CDF.RSP.FR.PERS.WH | C35: CDF RRSP FR - Personal Wholesale | D35: CDF.TERM.DEPOSITS | E35: =VLOOKUP(B35,'PARENT PRODUCT'!$A:$B,2,FALSE) -> #N/A | F35: 6715 | G35: =VLOOKUP(B35,'ONLINE ACCESS'!$A:$B,2,FALSE) -> CDF
A36: BNK | B36: AD.CDF.TFSA.FR.PER | C36: Motive TFSA GIC | D36: CDF.REG.TERM.DEPOSITS | E36: =VLOOKUP(B36,'PARENT PRODUCT'!$A:$B,2,FALSE) -> AD.CDF.TFSA.PARENT.FR | F36: 6760 | G36: =VLOOKUP(B36,'ONLINE ACCESS'!$A:$B,2,FALSE) -> CDF
A37: BNK | B37: AD.CDF.TFSA.FR.PER.WH | C37: CDF TFSA FR - Personal Wholesale | D37: CDF.TERM.DEPOSITS | E37: =VLOOKUP(B37,'PARENT PRODUCT'!$A:$B,2,FALSE) -> #N/A | F37: 6715 | G37: =VLOOKUP(B37,'ONLINE ACCESS'!$A:$B,2,FALSE) -> CDF
A38: BNK | B38: AD.FLR.NONPER.WHS.USD | C38: USD FLR - Non Personal Wholesale | D38: NONREG.TERM.DEPOSITS | E38: =VLOOKUP(B38,'PARENT PRODUCT'!$A:$B,2,FALSE) -> AD.PARENT.FR | F38: 6606 | G38: =VLOOKUP(B38,'ONLINE ACCESS'!$A:$B,2,FALSE) -> CWB
A39: BNK | B39: AD.FLR.NONPERS | C39: FLR - Non Personal | D39: NONREG.TERM.DEPOSITS | E39: =VLOOKUP(B39,'PARENT PRODUCT'!$A:$B,2,FALSE) -> AD.PARENT.FR | F39: =VLOOKUP(B39,'CATEGORY CODE'!$A:$B,2,FALSE) -> 6601 | G39: =VLOOKUP(B39,'ONLINE ACCESS'!$A:$B,2,FALSE) -> CWB
A40: BNK | B40: AD.FLR.NONPERS.USD | C40: USD FLR - Non Personal | D40: NONREG.TERM.DEPOSITS | E40: =VLOOKUP(B40,'PARENT PRODUCT'!$A:$B,2,FALSE) -> AD.PARENT.FR | F40: =VLOOKUP(B40,'CATEGORY CODE'!$A:$B,2,FALSE) -> 6601 | G40: =VLOOKUP(B40,'ONLINE ACCESS'!$A:$B,2,FALSE) -> CWB
A41: BNK | B41: AD.FLR.NONPERS.WHS | C41: FLR - Non Personal Wholesale | D41: NONREG.TERM.DEPOSITS | E41: =VLOOKUP(B41,'PARENT PRODUCT'!$A:$B,2,FALSE) -> AD.PARENT.FR | F41: 6606 | G41: =VLOOKUP(B41,'ONLINE ACCESS'!$A:$B,2,FALSE) -> CWB
A42: BNK | B42: AD.FLR.PERS | C42: FLR - Personal | D42: NONREG.TERM.DEPOSITS | E42: =VLOOKUP(B42,'PARENT PRODUCT'!$A:$B,2,FALSE) -> AD.PARENT.FR | F42: =VLOOKUP(B42,'CATEGORY CODE'!$A:$B,2,FALSE) -> 6701 | G42: =VLOOKUP(B42,'ONLINE ACCESS'!$A:$B,2,FALSE) -> CWB
A43: BNK | B43: AD.FLR.PERS.USD | C43: USD FLR - Personal | D43: NONREG.TERM.DEPOSITS | E43: =VLOOKUP(B43,'PARENT PRODUCT'!$A:$B,2,FALSE) -> AD.PARENT.FR | F43: =VLOOKUP(B43,'CATEGORY CODE'!$A:$B,2,FALSE) -> 6701 | G43: =VLOOKUP(B43,'ONLINE ACCESS'!$A:$B,2,FALSE) -> CWB
A44: BNK | B44: AD.FLR.PERS.WHS | C44: FLR - Personal Wholesale | D44: NONREG.TERM.DEPOSITS | E44: =VLOOKUP(B44,'PARENT PRODUCT'!$A:$B,2,FALSE) -> AD.PARENT.FR | F44: 6705 | G44: =VLOOKUP(B44,'ONLINE ACCESS'!$A:$B,2,FALSE) -> CWB
A45: BNK | B45: AD.FLR.PERS.WHS.USD | C45: USD FLR - Personal Wholesale | D45: NONREG.TERM.DEPOSITS | E45: =VLOOKUP(B45,'PARENT PRODUCT'!$A:$B,2,FALSE) -> AD.PARENT.FR | F45: 6705 | G45: =VLOOKUP(B45,'ONLINE ACCESS'!$A:$B,2,FALSE) -> CWB
A46: BNK | B46: AD.FLR.STFANDFAM | C46: FLR - Staff & Family | D46: NONREG.TERM.DEPOSITS | E46: =VLOOKUP(B46,'PARENT PRODUCT'!$A:$B,2,FALSE) -> AD.PARENT.FR | F46: 6701 | G46: =VLOOKUP(B46,'ONLINE ACCESS'!$A:$B,2,FALSE) -> CWB
A47: BNK | B47: AD.FLR.STFANDFAM.WHS | C47: FLR - Staff & Family Wholesale | D47: NONREG.TERM.DEPOSITS | E47: =VLOOKUP(B47,'PARENT PRODUCT'!$A:$B,2,FALSE) -> AD.PARENT.FR | F47: 6705 | G47: =VLOOKUP(B47,'ONLINE ACCESS'!$A:$B,2,FALSE) -> CWB
A48: BNK | B48: AD.FLR.STFFAM.USD | C48: USD FLR - Staff & Family | D48: NONREG.TERM.DEPOSITS | E48: =VLOOKUP(B48,'PARENT PRODUCT'!$A:$B,2,FALSE) -> AD.PARENT.FR | F48: 6701 | G48: =VLOOKUP(B48,'ONLINE ACCESS'!$A:$B,2,FALSE) -> CWB
A49: BNK | B49: AD.FLR.STFFAM.WHS.USD | C49: USD FLR-Staff & Staff Fam Wholesale | D49: NONREG.TERM.DEPOSITS | E49: =VLOOKUP(B49,'PARENT PRODUCT'!$A:$B,2,FALSE) -> #N/A | F49: =VLOOKUP(B49,'CATEGORY CODE'!$A:$B,2,TRUE) -> 6605 | G49: =VLOOKUP(B49,'ONLINE ACCESS'!$A:$B,2,FALSE) -> #N/A
A50: BNK | B50: AD.FR.NONPERS | C50: GIC - Non Personal | D50: NONREG.TERM.DEPOSITS | E50: =VLOOKUP(B50,'PARENT PRODUCT'!$A:$B,2,FALSE) -> AD.PARENT.FR | F50: =VLOOKUP(B50,'CATEGORY CODE'!$A:$B,2,FALSE) -> 6610 | G50: =VLOOKUP(B50,'ONLINE ACCESS'!$A:$B,2,FALSE) -> CWB
A51: BNK | B51: AD.FR.NONPERS.USD | C51: USD GIC - Non Personal | D51: NONREG.TERM.DEPOSITS | E51: =VLOOKUP(B51,'PARENT PRODUCT'!$A:$B,2,FALSE) -> AD.PARENT.FR | F51: =VLOOKUP(B51,'CATEGORY CODE'!$A:$B,2,FALSE) -> 6610 | G51: =VLOOKUP(B51,'ONLINE ACCESS'!$A:$B,2,FALSE) -> CWB
A52: BNK | B52: AD.FR.NONPERS.WHS | C52: GIC - Non Personal Wholesale | D52: NONREG.TERM.DEPOSITS | E52: =VLOOKUP(B52,'PARENT PRODUCT'!$A:$B,2,FALSE) -> AD.PARENT.FR | F52: =VLOOKUP(B52,'CATEGORY CODE'!$A:$B,2,TRUE) -> 6616 | G52: =VLOOKUP(B52,'ONLINE ACCESS'!$A:$B,2,FALSE) -> CWB
A53: BNK | B53: AD.FR.NONPERS.WHS.USD | C53: USD GIC - Non Personal Wholesale | D53: NONREG.TERM.DEPOSITS | E53: =VLOOKUP(B53,'PARENT PRODUCT'!$A:$B,2,FALSE) -> AD.PARENT.FR | F53: =VLOOKUP(B53,'CATEGORY CODE'!$A:$B,2,FALSE) -> 6616 | G53: =VLOOKUP(B53,'ONLINE ACCESS'!$A:$B,2,FALSE) -> CWB
A54: BNK | B54: AD.FR.PERS | C54: GIC - Personal | D54: NONREG.TERM.DEPOSITS | E54: =VLOOKUP(B54,'PARENT PRODUCT'!$A:$B,2,FALSE) -> AD.PARENT.FR | F54: =VLOOKUP(B54,'CATEGORY CODE'!$A:$B,2,FALSE) -> 6710 | G54: =VLOOKUP(B54,'ONLINE ACCESS'!$A:$B,2,FALSE) -> CWB
A55: BNK | B55: AD.FR.PERS.USD | C55: USD GIC - Personal | D55: NONREG.TERM.DEPOSITS | E55: =VLOOKUP(B55,'PARENT PRODUCT'!$A:$B,2,FALSE) -> AD.PARENT.FR | F55: =VLOOKUP(B55,'CATEGORY CODE'!$A:$B,2,FALSE) -> 6710 | G55: =VLOOKUP(B55,'ONLINE ACCESS'!$A:$B,2,FALSE) -> CWB
A56: BNK | B56: AD.FR.PERS.WHS | C56: GIC - Personal Wholesale | D56: NONREG.TERM.DEPOSITS | E56: =VLOOKUP(B56,'PARENT PRODUCT'!$A:$B,2,FALSE) -> AD.PARENT.FR | F56: =VLOOKUP(B56,'CATEGORY CODE'!$A:$B,2,TRUE) -> 6715 | G56: =VLOOKUP(B56,'ONLINE ACCESS'!$A:$B,2,FALSE) -> CWB
A57: BNK | B57: AD.FR.PERS.WHS.USD | C57: USD GIC - Personal Wholesale | D57: NONREG.TERM.DEPOSITS | E57: =VLOOKUP(B57,'PARENT PRODUCT'!$A:$B,2,FALSE) -> AD.PARENT.FR | F57: =VLOOKUP(B57,'CATEGORY CODE'!$A:$B,2,FALSE) -> 6715 | G57: =VLOOKUP(B57,'ONLINE ACCESS'!$A:$B,2,FALSE) -> CWB
A58: BNK | B58: AD.FR.STFANDFAM | C58: GIC - Staff & Family | D58: NONREG.TERM.DEPOSITS | E58: =VLOOKUP(B58,'PARENT PRODUCT'!$A:$B,2,FALSE) -> AD.PARENT.FR | F58: =VLOOKUP(B58,'CATEGORY CODE'!$A:$B,2,FALSE) -> 6710 | G58: =VLOOKUP(B58,'ONLINE ACCESS'!$A:$B,2,FALSE) -> CWB
A59: BNK | B59: AD.FR.STFANDFAM.WHS | C59: GIC - Staff & Family Wholesale | D59: NONREG.TERM.DEPOSITS | E59: =VLOOKUP(B59,'PARENT PRODUCT'!$A:$B,2,FALSE) -> AD.PARENT.FR | F59: =VLOOKUP(B59,'CATEGORY CODE'!$A:$B,2,TRUE) -> 6715 | G59: =VLOOKUP(B59,'ONLINE ACCESS'!$A:$B,2,FALSE) -> CWB
A60: BNK | B60: AD.FR.STFFAM.USD | C60: USD GIC - Staff & Family | D60: NONREG.TERM.DEPOSITS | E60: =VLOOKUP(B60,'PARENT PRODUCT'!$A:$B,2,FALSE) -> AD.PARENT.FR | F60: 6710 | G60: =VLOOKUP(B60,'ONLINE ACCESS'!$A:$B,2,FALSE) -> CWB
A61: BNK | B61: AD.FR.STFFAM.WHS.USD | C61: USD GIC - Staff & Family Wholesale | D61: NONREG.TERM.DEPOSITS | E61: =VLOOKUP(B61,'PARENT PRODUCT'!$A:$B,2,FALSE) -> AD.PARENT.FR | F61: 6715 | G61: =VLOOKUP(B61,'ONLINE ACCESS'!$A:$B,2,FALSE) -> CWB
A62: BNK | B62: AD.HR.3YR.NONPERS | C62: HR 3 Year Non Personal GIC | D62: NONREG.TERM.DEPOSITS | E62: =VLOOKUP(B62,'PARENT PRODUCT'!$A:$B,2,FALSE) -> #N/A | F62: =VLOOKUP(B62,'CATEGORY CODE'!$A:$B,2,FALSE) -> 6620 | G62: =VLOOKUP(B62,'ONLINE ACCESS'!$A:$B,2,FALSE) -> #N/A
A63: BNK | B63: AD.HR.3YR.NONPERS.WHS | C63: HR 3 Year Non Pers GIC Wholesale | D63: NONREG.TERM.DEPOSITS | E63: =VLOOKUP(B63,'PARENT PRODUCT'!$A:$B,2,FALSE) -> #N/A | F63: 6621 | G63: =VLOOKUP(B63,'ONLINE ACCESS'!$A:$B,2,FALSE) -> #N/A
A64: BNK | B64: AD.HR.3YR.PERS | C64: HR 3 Year Personal GIC | D64: NONREG.TERM.DEPOSITS | E64: =VLOOKUP(B64,'PARENT PRODUCT'!$A:$B,2,FALSE) -> #N/A | F64: =VLOOKUP(B64,'CATEGORY CODE'!$A:$B,2,FALSE) -> 6620 | G64: =VLOOKUP(B64,'ONLINE ACCESS'!$A:$B,2,FALSE) -> #N/A
A65: BNK | B65: AD.HR.3YR.PERS.WHS | C65: HR 3 Year Personal GIC-Wholesale | D65: NONREG.TERM.DEPOSITS | E65: =VLOOKUP(B65,'PARENT PRODUCT'!$A:$B,2,FALSE) -> #N/A | F65: 6621 | G65: =VLOOKUP(B65,'ONLINE ACCESS'!$A:$B,2,FALSE) -> #N/A
A66: BNK | B66: AD.HR.3YR.STFFAM | C66: HR 3 Year Stf & Fam GIC | D66: NONREG.TERM.DEPOSITS | E66: =VLOOKUP(B66,'PARENT PRODUCT'!$A:$B,2,FALSE) -> #N/A | F66: 6620 | G66: =VLOOKUP(B66,'ONLINE ACCESS'!$A:$B,2,FALSE) -> #N/A
A67: BNK | B67: AD.HR.3YR.STFFAM.WHS | C67: HR 3 Year Stf & Fam GIC-Wholesale | D67: NONREG.TERM.DEPOSITS | E67: =VLOOKUP(B67,'PARENT PRODUCT'!$A:$B,2,FALSE) -> #N/A | F67: 6621 | G67: =VLOOKUP(B67,'ONLINE ACCESS'!$A:$B,2,FALSE) -> #N/A
A68: BNK | B68: AD.HR.5YR.NONPERS | C68: HR 5 Year Non Personal GIC | D68: NONREG.TERM.DEPOSITS | E68: =VLOOKUP(B68,'PARENT PRODUCT'!$A:$B,2,FALSE) -> #N/A | F68: =VLOOKUP(B68,'CATEGORY CODE'!$A:$B,2,FALSE) -> 6620 | G68: =VLOOKUP(B68,'ONLINE ACCESS'!$A:$B,2,FALSE) -> #N/A
A69: BNK | B69: AD.HR.5YR.NONPERS.WHS | C69: HR 5 Year Non Pers GIC-Wholesale | D69: NONREG.TERM.DEPOSITS | E69: =VLOOKUP(B69,'PARENT PRODUCT'!$A:$B,2,FALSE) -> #N/A | F69: 6621 | G69: =VLOOKUP(B69,'ONLINE ACCESS'!$A:$B,2,FALSE) -> #N/A
A70: BNK | B70: AD.HR.5YR.PERS | C70: HR 5 Year Personal GIC | D70: NONREG.TERM.DEPOSITS | E70: =VLOOKUP(B70,'PARENT PRODUCT'!$A:$B,2,FALSE) -> #N/A | F70: =VLOOKUP(B70,'CATEGORY CODE'!$A:$B,2,FALSE) -> 6620 | G70: =VLOOKUP(B70,'ONLINE ACCESS'!$A:$B,2,FALSE) -> #N/A
A71: BNK | B71: AD.HR.5YR.PERS.WHS | C71: HR 5 Year Personal GIC-Wholesale | D71: NONREG.TERM.DEPOSITS | E71: =VLOOKUP(B71,'PARENT PRODUCT'!$A:$B,2,FALSE) -> #N/A | F71: 6621 | G71: =VLOOKUP(B71,'ONLINE ACCESS'!$A:$B,2,FALSE) -> #N/A
A72: BNK | B72: AD.HR.5YR.STFFAM | C72: HR 5 Year Stf & Fam GIC | D72: NONREG.TERM.DEPOSITS | E72: =VLOOKUP(B72,'PARENT PRODUCT'!$A:$B,2,FALSE) -> #N/A | F72: 6620 | G72: =VLOOKUP(B72,'ONLINE ACCESS'!$A:$B,2,FALSE) -> #N/A
A73: BNK | B73: AD.HR.5YR.STFFAM.WHS | C73: HR 5 Year Stf & Fam GIC-Wholesale | D73: NONREG.TERM.DEPOSITS | E73: =VLOOKUP(B73,'PARENT PRODUCT'!$A:$B,2,FALSE) -> #N/A | F73: 6621 | G73: =VLOOKUP(B73,'ONLINE ACCESS'!$A:$B,2,FALSE) -> #N/A
A74: BNK | B74: AD.RIF.CONV.PERS | C74: RRIF Convertible GIC - Personal | D74: REG.TERM.DEPOSITS | E74: =VLOOKUP(B74,'PARENT PRODUCT'!$A:$B,2,FALSE) -> AD.RIF.PARENT.FR | F74: =VLOOKUP(B74,'CATEGORY CODE'!$A:$B,2,FALSE) -> 6910 | G74: =VLOOKUP(B74,'ONLINE ACCESS'!$A:$B,2,FALSE) -> CWB
A75: BNK | B75: AD.RIF.CONV.PERS.WHS | C75: RRIF Convert Personal GIC Wholesale | D75: REG.TERM.DEPOSITS | E75: =VLOOKUP(B75,'PARENT PRODUCT'!$A:$B,2,FALSE) -> #N/A | F75: =VLOOKUP(B75,'CATEGORY CODE'!$A:$B,2,FALSE) -> 6915 | G75: =VLOOKUP(B75,'ONLINE ACCESS'!$A:$B,2,FALSE) -> CWB
A76: BNK | B76: AD.RIF.CONV.STF | C76: RRIF Convertible GIC - Staff | D76: REG.TERM.DEPOSITS | E76: =VLOOKUP(B76,'PARENT PRODUCT'!$A:$B,2,FALSE) -> AD.RIF.PARENT.FR | F76: =VLOOKUP(B76,'CATEGORY CODE'!$A:$B,2,FALSE) -> 6910 | G76: =VLOOKUP(B76,'ONLINE ACCESS'!$A:$B,2,FALSE) -> CWB
A77: BNK | B77: AD.RIF.CONV.STF.WH | C77: RRIF Convert Stf GIC Wholesale | D77: REG.TERM.DEPOSITS | E77: =VLOOKUP(B77,'PARENT PRODUCT'!$A:$B,2,FALSE) -> #N/A | F77: 6910 | G77: =VLOOKUP(B77,'ONLINE ACCESS'!$A:$B,2,FALSE) -> CWB
A78: BNK | B78: AD.RIF.CONV.STFFAM | C78: RRIF Convertible GIC - Staff Family | D78: REG.TERM.DEPOSITS | E78: =VLOOKUP(B78,'PARENT PRODUCT'!$A:$B,2,FALSE) -> AD.RIF.PARENT.FR | F78: =VLOOKUP(B78,'CATEGORY CODE'!$A:$B,2,FALSE) -> 6910 | G78: =VLOOKUP(B78,'ONLINE ACCESS'!$A:$B,2,FALSE) -> CWB
A79: BNK | B79: AD.RIF.CONV.STFFAM.WH | C79: RRIF Convert Stf Fam GIC Wholesale | D79: REG.TERM.DEPOSITS | E79: =VLOOKUP(B79,'PARENT PRODUCT'!$A:$B,2,FALSE) -> #N/A | F79: 6915 | G79: =VLOOKUP(B79,'ONLINE ACCESS'!$A:$B,2,FALSE) -> CWB
A80: BNK | B80: AD.RIF.FR.PERS | C80: RRIF Premium GIC - Personal | D80: REG.TERM.DEPOSITS | E80: =VLOOKUP(B80,'PARENT PRODUCT'!$A:$B,2,FALSE) -> AD.RIF.PARENT.FR | F80: =VLOOKUP(B80,'CATEGORY CODE'!$A:$B,2,FALSE) -> 6920 | G80: =VLOOKUP(B80,'ONLINE ACCESS'!$A:$B,2,FALSE) -> CWB
A81: BNK | B81: AD.RIF.FR.PERS.WHS | C81: RRIF FR Personal GIC Wholesale | D81: REG.TERM.DEPOSITS | E81: =VLOOKUP(B81,'PARENT PRODUCT'!$A:$B,2,FALSE) -> #N/A | F81: =VLOOKUP(B81,'CATEGORY CODE'!$A:$B,2,FALSE) -> 6925 | G81: =VLOOKUP(B81,'ONLINE ACCESS'!$A:$B,2,FALSE) -> CWB
A82: BNK | B82: AD.RIF.FR.STF | C82: RRIF Premium GIC - Staff | D82: REG.TERM.DEPOSITS | E82: =VLOOKUP(B82,'PARENT PRODUCT'!$A:$B,2,FALSE) -> AD.RIF.PARENT.FR | F82: =VLOOKUP(B82,'CATEGORY CODE'!$A:$B,2,FALSE) -> 6920 | G82: =VLOOKUP(B82,'ONLINE ACCESS'!$A:$B,2,FALSE) -> CWB
A83: BNK | B83: AD.RIF.FR.STF.WHS | C83: RRIF FR Staff GIC Wholesale | D83: REG.TERM.DEPOSITS | E83: =VLOOKUP(B83,'PARENT PRODUCT'!$A:$B,2,FALSE) -> #N/A | F83: =VLOOKUP(B83,'CATEGORY CODE'!$A:$B,2,FALSE) -> 6925 | G83: =VLOOKUP(B83,'ONLINE ACCESS'!$A:$B,2,FALSE) -> CWB
A84: BNK | B84: AD.RIF.FR.STFFAM | C84: RRIF Premium GIC - Staff Family | D84: REG.TERM.DEPOSITS | E84: =VLOOKUP(B84,'PARENT PRODUCT'!$A:$B,2,FALSE) -> AD.RIF.PARENT.FR | F84: =VLOOKUP(B84,'CATEGORY CODE'!$A:$B,2,FALSE) -> 6920 | G84: =VLOOKUP(B84,'ONLINE ACCESS'!$A:$B,2,FALSE) -> CWB
A85: BNK | B85: AD.RIF.FR.STFFAM.WHS | C85: RRIF FR Stf Fam GIC Wholesale | D85: REG.TERM.DEPOSITS | E85: =VLOOKUP(B85,'PARENT PRODUCT'!$A:$B,2,FALSE) -> #N/A | F85: =VLOOKUP(B85,'CATEGORY CODE'!$A:$B,2,FALSE) -> 6925 | G85: =VLOOKUP(B85,'ONLINE ACCESS'!$A:$B,2,FALSE) -> CWB
A86: BNK | B86: AD.RIF.FULRED.PERS | C86: RRIF Full Redeem GIC - Personal | D86: REG.TERM.DEPOSITS | E86: =VLOOKUP(B86,'PARENT PRODUCT'!$A:$B,2,FALSE) -> AD.RIF.PARENT.FR | F86: =VLOOKUP(B86,'CATEGORY CODE'!$A:$B,2,FALSE) -> 6940 | G86: =VLOOKUP(B86,'ONLINE ACCESS'!$A:$B,2,FALSE) -> CWB
A87: BNK | B87: AD.RIF.FULRED.PERS.WH | C87: RRIF Ful Red Pers GIC Wholesale | D87: REG.TERM.DEPOSITS | E87: =VLOOKUP(B87,'PARENT PRODUCT'!$A:$B,2,FALSE) -> #N/A | F87: 6945 | G87: =VLOOKUP(B87,'ONLINE ACCESS'!$A:$B,2,FALSE) -> CWB
A88: BNK | B88: AD.RIF.FULRED.SFAM | C88: RRIF Full Redeem GIC - Staff Family | D88: REG.TERM.DEPOSITS | E88: =VLOOKUP(B88,'PARENT PRODUCT'!$A:$B,2,FALSE) -> AD.RIF.PARENT.FR | F88: 6940 | G88: =VLOOKUP(B88,'ONLINE ACCESS'!$A:$B,2,FALSE) -> CWB
A89: BNK | B89: AD.RIF.FULRED.SFAM.WH | C89: RRIF Ful Red Stf Fam GIC Wholesale | D89: REG.TERM.DEPOSITS | E89: =VLOOKUP(B89,'PARENT PRODUCT'!$A:$B,2,FALSE) -> #N/A | F89: 6945 | G89: =VLOOKUP(B89,'ONLINE ACCESS'!$A:$B,2,FALSE) -> CWB
A90: BNK | B90: AD.RIF.FULRED.STF | C90: RRIF Full Redeem GIC - Staff | D90: REG.TERM.DEPOSITS | E90: =VLOOKUP(B90,'PARENT PRODUCT'!$A:$B,2,FALSE) -> AD.RIF.PARENT.FR | F90: =VLOOKUP(B90,'CATEGORY CODE'!$A:$B,2,FALSE) -> 6940 | G90: =VLOOKUP(B90,'ONLINE ACCESS'!$A:$B,2,FALSE) -> CWB
A91: BNK | B91: AD.RIF.FULRED.STF.WH | C91: RRIF Ful Red Staff GIC Wholesale | D91: REG.TERM.DEPOSITS | E91: =VLOOKUP(B91,'PARENT PRODUCT'!$A:$B,2,FALSE) -> #N/A | F91: 6945 | G91: =VLOOKUP(B91,'ONLINE ACCESS'!$A:$B,2,FALSE) -> CWB
A92: BNK | B92: AD.RSP.CONV.PERS | C92: RRSP Convertible GIC - Personal | D92: REG.TERM.DEPOSITS | E92: =VLOOKUP(B92,'PARENT PRODUCT'!$A:$B,2,FALSE) -> AD.RSP.PARENT.FR | F92: =VLOOKUP(B92,'CATEGORY CODE'!$A:$B,2,FALSE) -> 6820 | G92: =VLOOKUP(B92,'ONLINE ACCESS'!$A:$B,2,FALSE) -> CWB
A93: BNK | B93: AD.RSP.CONV.PERS.WHS | C93: RRSP Convertible Pers GIC Wholesale | D93: REG.TERM.DEPOSITS | E93: =VLOOKUP(B93,'PARENT PRODUCT'!$A:$B,2,FALSE) -> #N/A | F93: =VLOOKUP(B93,'CATEGORY CODE'!$A:$B,2,FALSE) -> 6815 | G93: =VLOOKUP(B93,'ONLINE ACCESS'!$A:$B,2,FALSE) -> CWB
A94: BNK | B94: AD.RSP.CONV.STF | C94: RRSP Convertible GIC - Staff | D94: REG.TERM.DEPOSITS | E94: =VLOOKUP(B94,'PARENT PRODUCT'!$A:$B,2,FALSE) -> AD.RSP.PARENT.FR | F94: =VLOOKUP(B94,'CATEGORY CODE'!$A:$B,2,FALSE) -> 6820 | G94: =VLOOKUP(B94,'ONLINE ACCESS'!$A:$B,2,FALSE) -> CWB
A95: BNK | B95: AD.RSP.CONV.STF.WH | C95: RRSP Convert Staff GIC Wholesale | D95: REG.TERM.DEPOSITS | E95: =VLOOKUP(B95,'PARENT PRODUCT'!$A:$B,2,FALSE) -> #N/A | F95: 6815 | G95: =VLOOKUP(B95,'ONLINE ACCESS'!$A:$B,2,FALSE) -> CWB
A96: BNK | B96: AD.RSP.CONV.STFFAM | C96: RRSP Convertible GIC - Staff Family | D96: REG.TERM.DEPOSITS | E96: =VLOOKUP(B96,'PARENT PRODUCT'!$A:$B,2,FALSE) -> AD.RSP.PARENT.FR | F96: =VLOOKUP(B96,'CATEGORY CODE'!$A:$B,2,FALSE) -> 6820 | G96: =VLOOKUP(B96,'ONLINE ACCESS'!$A:$B,2,FALSE) -> CWB
A97: BNK | B97: AD.RSP.CONV.STFFAM.WH | C97: RRSP Convert Stf Fam GIC Wholesale | D97: REG.TERM.DEPOSITS | E97: =VLOOKUP(B97,'PARENT PRODUCT'!$A:$B,2,FALSE) -> #N/A | F97: 6815 | G97: =VLOOKUP(B97,'ONLINE ACCESS'!$A:$B,2,FALSE) -> CWB
A98: BNK | B98: AD.RSP.FR.PERS | C98: RRSP Premium GIC - Personal | D98: REG.TERM.DEPOSITS | E98: =VLOOKUP(B98,'PARENT PRODUCT'!$A:$B,2,FALSE) -> AD.RSP.PARENT.FR | F98: =VLOOKUP(B98,'CATEGORY CODE'!$A:$B,2,FALSE) -> 6820 | G98: =VLOOKUP(B98,'ONLINE ACCESS'!$A:$B,2,FALSE) -> CWB
A99: BNK | B99: AD.RSP.FR.PERS.WHS | C99: RRSP Fixed Rate Personal Wholesale | D99: REG.TERM.DEPOSITS | E99: =VLOOKUP(B99,'PARENT PRODUCT'!$A:$B,2,FALSE) -> #N/A | F99: =VLOOKUP(B99,'CATEGORY CODE'!$A:$B,2,FALSE) -> 6825 | G99: =VLOOKUP(B99,'ONLINE ACCESS'!$A:$B,2,FALSE) -> CWB
A100: BNK | B100: AD.RSP.FR.STF | C100: RRSP Premium GIC - Staff | D100: REG.TERM.DEPOSITS | E100: =VLOOKUP(B100,'PARENT PRODUCT'!$A:$B,2,FALSE) -> AD.RSP.PARENT.FR | F100: =VLOOKUP(B100,'CATEGORY CODE'!$A:$B,2,FALSE) -> 6820 | G100: =VLOOKUP(B100,'ONLINE ACCESS'!$A:$B,2,FALSE) -> CWB
...

Sheet PARENT PRODUCT
A1: @ID | B1: PARENT_PRODUCT | C1: PRODUCT_GROUP
A2: AD.BRO.BB.FR.NONP | B2: AD.BRO.PARENT.FR | C2: BROKER.TERM.DEPOSITS
A3: AD.BRO.BB.FR.NONP.WHS | B3: AD.BRO.PARENT.FR | C3: BROKER.TERM.DEPOSITS
A4: AD.BRO.BB.FR.PERS | B4: AD.BRO.PARENT.FR | C4: BROKER.TERM.DEPOSITS
A5: AD.BRO.BB.FR.PERS.WHS | B5: AD.BRO.PARENT.FR | C5: BROKER.TERM.DEPOSITS
A6: AD.BRO.CSC.NONPER | B6: AD.BRO.PARENT.FR | C6: BROKER.TERM.DEPOSITS
A7: AD.BRO.CSC.NONPER.WH | B7: AD.BRO.PARENT.FR | C7: BROKER.TERM.DEPOSITS
A8: AD.BRO.CSC.PER | B8: AD.BRO.PARENT.FR | C8: BROKER.TERM.DEPOSITS
A9: AD.BRO.CSC.PER.WH | B9: AD.BRO.PARENT.FR | C9: BROKER.TERM.DEPOSITS
A10: AD.BRO.FLR.NONPERS | B10: AD.BRO.PARENT.FR | C10: BROKER.TERM.DEPOSITS
A11: AD.BRO.FLR.NONPERS.WH | B11: AD.BRO.PARENT.FR | C11: BROKER.TERM.DEPOSITS
A12: AD.BRO.FLR.PERS | B12: AD.BRO.PARENT.FR | C12: BROKER.TERM.DEPOSITS
... A255: NHA.MBS.FLOATING | B255: AD.PARENT.NHA | C255: NHA.MBS

Sheet CATEGORY CODE
A1: @ID | B1: CATEGORY
A2: AD.BRO.BB.FR.NONPERS | B2: 6611
A3: AD.BRO.BB.FR.NONPERS.WHS | B3: 6617
A4: AD.BRO.BB.FR.PERS | B4: 6712
A5: AD.BRO.BB.FR.PERS.WHS | B5: 6717
A6: AD.BRO.CSC.NONPERS | B6: 6651
A7: AD.BRO.CSC.NONPERS.WHS | B7: 6656
A8: AD.BRO.CSC.PERS | B8: 6751
A9: AD.BRO.CSC.PERS.WHS | B9: 6756
A10: AD.BRO.FLR.NONPERS | B10: 6602
A11: AD.BRO.FLR.NONPERS.WHS | B11: 6607
A12: AD.BRO.FLR.PERS | B12: 6702
A13: AD.BRO.FLR.PERS.WHS | B13: 6706
... A260: LENDING | B260: 3001

Sheet ONLINE ACCESS
A1: PRODUCT ID | B1: Card Type
A2: AD.CDF.FR.PERS | B2: CDF
A3: AD.CDF.FR.PERS | B3: MOT
A4: AD.CDF.FR.PERS.WHS | B4: CDF
A5: AD.CDF.FR.PERS.WHS | B5: MOT
A6: AD.CDF.RIF.FR.PERS | B6: CDF
A7: AD.CDF.RIF.FR.PERS | B7: MOT
A8: AD.CDF.RSP.FR.PERS | B8: CDF
A9: AD.CDF.RSP.FR.PERS | B9: MOT
A10: AD.CDF.RSP.FR.PERS.WH | B10: CDF
A11: AD.CDF.RSP.FR.PERS.WH | B11: MOT
A12: AD.CDF.TFSA.FR.PER | B12: CDF
... A409: AR.YOUTH.ACCOUNT.STF | B409: FLS
