Workbook
Name ◇在籍DB（送付用）: #REF!
Name a: #REF!
Name Actuals2: OFFSET([1]Usage!$F$1,1,0,COUNTA([1]Usage!$A:$A),1)
Name AED: [2]Rates!$B$4
Name Alico0115: #REF!
Name all_print: #REF!
Name Annualongoing: #REF!
Name Asset_Requirements: #REF!
Name b: #REF!
Name BD: [2]Rates!$B$5
Name Billing_Query___for_Kris_Yager_2___Ben_Flach: #REF!
Name Billing_Table_Build_step3__Billable_Amount_by_SE___Ben_Flach: #REF!
Name Buildup: #REF!
Name Cable_Category: #REF!
Name Carrier_Name: #REF!
Name ChargeType: #REF!
Name com_sched: #REF!
Name Comp_ProfitCenter: #REF!
Name cost_element: #REF!
Name date: #REF!
Name Desktop: #REF!
Name desktopassum: #REF!
Name DlvBy: #REF!
Name DlvryMthd: #REF!
Name DS: #REF!
Name e: #REF!
Name esc_yr0: '[3]Assumptions - In'!$B$12
Name esc_yr1: '[3]Assumptions - In'!$C$12
Name esc_yr10: '[3]Assumptions - In'!$L$12
Name esc_yr2: '[3]Assumptions - In'!$D$12
Name esc_yr3: '[3]Assumptions - In'!$E$12
Name esc_yr4: '[3]Assumptions - In'!$F$12
Name esc_yr5: '[3]Assumptions - In'!$G$12
Name esc_yr6: '[3]Assumptions - In'!$H$12
Name esc_yr7: '[3]Assumptions - In'!$I$12
Name esc_yr8: '[3]Assumptions - In'!$J$12
Name esc_yr9: '[3]Assumptions - In'!$K$12
Name f: #REF!
Name Frequency: #REF!
Name FY03onetime: #REF!
Name FY04onetime: #REF!
Name g: #REF!
Name GCCAction: #REF!
Name gch: #REF!
Name GLAcct: #REF!
Name glcd: #REF!
Name GLCode: #REF!
Name glList: #REF!
Name Handset_Technology: #REF!
Name Hauling_or_Collection: #REF!
Name headcount: #REF!
Name helpdesk: #REF!
Name helpdeskassum: #REF!
Name hi: #REF!
Name Holding_Company: #REF!
Name hw_deprec: #REF!
Name i: #REF!
Name input: #REF!
Name intel: #REF!
Name intelassum: #REF!

Sheet BANK
A1: BRANCH_CO_MNE | B1: @ID | C1: DESCRIPTION | D1: PRODUCT_GROUP | E1: PARENT.PRODUCT | F1: CATEGORY CODE | G1: ONLINE ACCESS | H1: VIEW | I1: TRANSFER IN | J1: TRANSFER OUT | K1: BILL PAYMENTS | L1: Interc e-Transfer | M1: Me2Me
A2: BNK | B2: AD.BRO.BB.FR.NONP | C2: Book-Based GIC - Non Personal | D2: BROKER.TERM.DEPOSITS | E2: =VLOOKUP(B2,'PARENT PRODUCT'!$A:$B,2,FALSE) -> AD.BRO.PARENT.FR | F2: 6611 | G2: =VLOOKUP(B2,'ONLINE ACCESS'!$A:$B,2,FALSE) -> #N/A | H2: NO | I2: NO | J2: NO | K2: NO | L2: NO | M2: NO
A3: BNK | B3: AD.BRO.BB.FR.NONP.WHS | C3: Book-Based GIC - Non Personal WHS | D3: BROKER.TERM.DEPOSITS | E3: =VLOOKUP(B3,'PARENT PRODUCT'!$A:$B,2,FALSE) -> AD.BRO.PARENT.FR | F3: 6617 | G3: =VLOOKUP(B3,'ONLINE ACCESS'!$A:$B,2,FALSE) -> #N/A | H3: NO | I3: NO | J3: NO | K3: NO | L3: NO | M3: NO
A4: BNK | B4: AD.BRO.BB.FR.PERS | C4: Book-Based GIC - Personal | D4: BROKER.TERM.DEPOSITS | E4: =VLOOKUP(B4,'PARENT PRODUCT'!$A:$B,2,FALSE) -> AD.BRO.PARENT.FR | F4: =VLOOKUP(B4,'CATEGORY CODE'!$A:$B,2,FALSE) -> 6712 | G4: =VLOOKUP(B4,'ONLINE ACCESS'!$A:$B,2,FALSE) -> #N/A | H4: NO | I4: NO | J4: NO | K4: NO | L4: NO | M4: NO
A5: BNK | B5: AD.BRO.BB.FR.PERS.WHS | C5: Book-Based GIC - Personal WHS | D5: BROKER.TERM.DEPOSITS | E5: =VLOOKUP(B5,'PARENT PRODUCT'!$A:$B,2,FALSE) -> AD.BRO.PARENT.FR | F5: =VLOOKUP(B5,'CATEGORY CODE'!$A:$B,2,FALSE) -> 6717 | G5: =VLOOKUP(B5,'ONLINE ACCESS'!$A:$B,2,FALSE) -> #N/A | H5: NO | I5: NO | J5: NO | K5: NO | L5: NO | M5: NO
A6: BNK | B6: AD.BRO.CSC.NONPER | C6: CSC - Non-Personal | D6: BROKER.TERM.DEPOSITS | E6: =VLOOKUP(B6,'PARENT PRODUCT'!$A:$B,2,FALSE) -> AD.BRO.PARENT.FR | F6: 6651 | G6: =VLOOKUP(B6,'ONLINE ACCESS'!$A:$B,2,FALSE) -> #N/A | H6: NO | I6: NO | J6: NO | K6: NO | L6: NO | M6: NO
A7: BNK | B7: AD.BRO.CSC.NONPER.WH | C7: CSC - Non Personal Wholesale | D7: BROKER.TERM.DEPOSITS | E7: =VLOOKUP(B7,'PARENT PRODUCT'!$A:$B,2,FALSE) -> AD.BRO.PARENT.FR | F7: 6656 | G7: =VLOOKUP(B7,'ONLINE ACCESS'!$A:$B,2,FALSE) -> #N/A | H7: NO | I7: NO | J7: NO | K7: NO | L7: NO | M7: NO
A8: BNK | B8: AD.BRO.CSC.PER | C8: CSC - Personal | D8: BROKER.TERM.DEPOSITS | E8: =VLOOKUP(B8,'PARENT PRODUCT'!$A:$B,2,FALSE) -> AD.BRO.PARENT.FR | F8: 6751 | G8: =VLOOKUP(B8,'ONLINE ACCESS'!$A:$B,2,FALSE) -> #N/A | H8: NO | I8: NO | J8: NO | K8: NO | L8: NO | M8: NO
A9: BNK | B9: AD.BRO.CSC.PER.WH | C9: CSC - Personal Wholesale | D9: BROKER.TERM.DEPOSITS | E9: =VLOOKUP(B9,'PARENT PRODUCT'!$A:$B,2,FALSE) -> AD.BRO.PARENT.FR | F9: 6756 | G9: =VLOOKUP(B9,'ONLINE ACCESS'!$A:$B,2,FALSE) -> #N/A | H9: NO | I9: NO | J9: NO | K9: NO | L9: NO | M9: NO
A10: BNK | B10: AD.BRO.FLR.NONPERS | C10: FLR - Non Personal | D10: BROKER.TERM.DEPOSITS | E10: =VLOOKUP(B10,'PARENT PRODUCT'!$A:$B,2,FALSE) -> AD.BRO.PARENT.FR | F10: =VLOOKUP(B10,'CATEGORY CODE'!$A:$B,2,FALSE) -> 6602 | G10: =VLOOKUP(B10,'ONLINE ACCESS'!$A:$B,2,FALSE) -> #N/A | H10: NO | I10: NO | J10: NO | K10: NO | L10: NO | M10: NO
A11: BNK | B11: AD.BRO.FLR.NONPERS.WH | C11: FLR - Non Personal Wholesale | D11: BROKER.TERM.DEPOSITS | E11: =VLOOKUP(B11,'PARENT PRODUCT'!$A:$B,2,FALSE) -> AD.BRO.PARENT.FR | F11: 6607 | G11: =VLOOKUP(B11,'ONLINE ACCESS'!$A:$B,2,FALSE) -> #N/A | H11: NO | I11: NO | J11: NO | K11: NO | L11: NO | M11: NO
A12: BNK | B12: AD.BRO.FLR.PERS | C12: FLR - Personal | D12: BROKER.TERM.DEPOSITS | E12: =VLOOKUP(B12,'PARENT PRODUCT'!$A:$B,2,FALSE) -> AD.BRO.PARENT.FR | F12: =VLOOKUP(B12,'CATEGORY CODE'!$A:$B,2,FALSE) -> 6702 | G12: =VLOOKUP(B12,'ONLINE ACCESS'!$A:$B,2,FALSE) -> #N/A | H12: NO | I12: NO | J12: NO | K12: NO | L12: NO | M12: NO
A13: BNK | B13: AD.BRO.FLR.PERS.WH | C13: FLR - Personal Wholesale | D13: BROKER.TERM.DEPOSITS | E13: =VLOOKUP(B13,'PARENT PRODUCT'!$A:$B,2,FALSE) -> AD.BRO.PARENT.FR | F13: 6706 | G13: =VLOOKUP(B13,'ONLINE ACCESS'!$A:$B,2,FALSE) -> #N/A | H13: NO | I13: NO | J13: NO | K13: NO | L13: NO | M13: NO
A14: BNK | B14: AD.BRO.FR.NONPERS | C14: GIC - Non Personal | D14: BROKER.TERM.DEPOSITS | E14: =VLOOKUP(B14,'PARENT PRODUCT'!$A:$B,2,FALSE) -> AD.BRO.PARENT.FR | F14: =VLOOKUP(B14,'CATEGORY CODE'!$A:$B,2,FALSE) -> 6611 | G14: =VLOOKUP(B14,'ONLINE ACCESS'!$A:$B,2,FALSE) -> #N/A | H14: NO | I14: NO | J14: NO | K14: NO | L14: NO | M14: NO
A15: BNK | B15: AD.BRO.FR.NONPERS.WHS | C15: GIC - Non Personal Wholesale | D15: BROKER.TERM.DEPOSITS | E15: =VLOOKUP(B15,'PARENT PRODUCT'!$A:$B,2,FALSE) -> AD.BRO.PARENT.FR | F15: =VLOOKUP(B15,'CATEGORY CODE'!$A:$B,2,FALSE) -> 6617 | G15: =VLOOKUP(B15,'ONLINE ACCESS'!$A:$B,2,FALSE) -> #N/A | H15: NO | I15: NO | J15: NO | K15: NO | L15: NO | M15: NO
A16: BNK | B16: AD.BRO.FR.PERS | C16: GIC - Personal | D16: BROKER.TERM.DEPOSITS | E16: =VLOOKUP(B16,'PARENT PRODUCT'!$A:$B,2,FALSE) -> AD.BRO.PARENT.FR | F16: =VLOOKUP(B16,'CATEGORY CODE'!$A:$B,2,FALSE) -> 6712 | G16: =VLOOKUP(B16,'ONLINE ACCESS'!$A:$B,2,FALSE) -> #N/A | H16: NO | I16: NO | J16: NO | K16: NO | L16: NO | M16: NO
A17: BNK | B17: AD.BRO.FR.PERS.WHS | C17: GIC - Personal Wholesale | D17: BROKER.TERM.DEPOSITS | E17: =VLOOKUP(B17,'PARENT PRODUCT'!$A:$B,2,FALSE) -> AD.BRO.PARENT.FR | F17: =VLOOKUP(B17,'CATEGORY CODE'!$A:$B,2,FALSE) -> 6717 | G17: =VLOOKUP(B17,'ONLINE ACCESS'!$A:$B,2,FALSE) -> #N/A | H17: NO | I17: NO | J17: NO | K17: NO | L17: NO | M17: NO
A18: BNK | B18: AD.BRO.RIF.CON.PER | C18: RRIF Convertible GIC | D18: BROKER.REG.TERM.DEPOSITS | E18: =VLOOKUP(B18,'PARENT PRODUCT'!$A:$B,2,FALSE) -> AD.BRO.RIF.PARENT.FR | F18: 6911 | G18: =VLOOKUP(B18,'ONLINE ACCESS'!$A:$B,2,FALSE) -> #N/A | H18: NO | I18: NO | J18: NO | K18: NO | L18: NO | M18: NO
A19: BNK | B19: AD.BRO.RIF.CON.PER.WH | C19: Broker RRIF Conv-Personal Wholesale | D19: BROKER.TERM.DEPOSITS | E19: =VLOOKUP(B19,'PARENT PRODUCT'!$A:$B,2,FALSE) -> #N/A | F19: 6915 | G19: =VLOOKUP(B19,'ONLINE ACCESS'!$A:$B,2,FALSE) -> #N/A | H19: NO | I19: NO | J19: NO | K19: NO | L19: NO | M19: NO
A20: BNK | B20: AD.BRO.RIF.FR.PERS | C20: RRIF Premium GIC | D20: BROKER.REG.TERM.DEPOSITS | E20: =VLOOKUP(B20,'PARENT PRODUCT'!$A:$B,2,FALSE) -> AD.BRO.RIF.PARENT.FR | F20: =VLOOKUP(B20,'CATEGORY CODE'!$A:$B,2,FALSE) -> 6921 | G20: =VLOOKUP(B20,'ONLINE ACCESS'!$A:$B,2,FALSE) -> #N/A | H20: NO | I20: NO | J20: NO | K20: NO | L20: NO | M20: NO
A21: BNK | B21: AD.BRO.RIF.FR.PERS.WH | C21: Broker RRIF FR - Personal Wholesale | D21: BROKER.TERM.DEPOSITS | E21: =VLOOKUP(B21,'PARENT PRODUCT'!$A:$B,2,FALSE) -> #N/A | F21: 6925 | G21: =VLOOKUP(B21,'ONLINE ACCESS'!$A:$B,2,FALSE) -> #N/A | H21: NO | I21: NO | J21: NO | K21: NO | L21: NO | M21: NO
A22: BNK | B22: AD.BRO.RIF.FRE.PER | C22: RRIF Fully Redeemable GIC | D22: BROKER.REG.TERM.DEPOSITS | E22: =VLOOKUP(B22,'PARENT PRODUCT'!$A:$B,2,FALSE) -> AD.BRO.RIF.PARENT.FR | F22: 6941 | G22: =VLOOKUP(B22,'ONLINE ACCESS'!$A:$B,2,FALSE) -> #N/A | H22: NO | I22: NO | J22: NO | K22: NO | L22: NO | M22: NO
A23: BNK | B23: AD.BRO.RIF.FRE.PER.WH | C23: Broker RRIF Fully Redeem Pers WHS | D23: BROKER.TERM.DEPOSITS | E23: =VLOOKUP(B23,'PARENT PRODUCT'!$A:$B,2,FALSE) -> #N/A | F23: 6945 | G23: =VLOOKUP(B23,'ONLINE ACCESS'!$A:$B,2,FALSE) -> #N/A | H23: NO | I23: NO | J23: NO | K23: NO | L23: NO | M23: NO
A24: BNK | B24: AD.BRO.RSP.CON.PER | C24: RRSP Convertible GIC | D24: BROKER.REG.TERM.DEPOSITS | E24: =VLOOKUP(B24,'PARENT PRODUCT'!$A:$B,2,FALSE) -> AD.BRO.RSP.PARENT.FR | F24: 6821 | G24: =VLOOKUP(B24,'ONLINE ACCESS'!$A:$B,2,FALSE) -> #N/A | H24: NO | I24: NO | J24: NO | K24: NO | L24: NO | M24: NO
A25: BNK | B25: AD.BRO.RSP.CON.PER.WH | C25: Broker RRSP Conv-Pers Wholesale | D25: BROKER.TERM.DEPOSITS | E25: =VLOOKUP(B25,'PARENT PRODUCT'!$A:$B,2,FALSE) -> #N/A | F25: 6815 | G25: =VLOOKUP(B25,'ONLINE ACCESS'!$A:$B,2,FALSE) -> #N/A | H25: NO | I25: NO | J25: NO | K25: NO | L25: NO | M25: NO
A26: BNK | B26: AD.BRO.RSP.FR.PERS | C26: RRSP Premium GIC | D26: BROKER.REG.TERM.DEPOSITS | E26: =VLOOKUP(B26,'PARENT PRODUCT'!$A:$B,2,FALSE) -> AD.BRO.RSP.PARENT.FR | F26: =VLOOKUP(B26,'CATEGORY CODE'!$A:$B,2,FALSE) -> 6821 | G26: =VLOOKUP(B26,'ONLINE ACCESS'!$A:$B,2,FALSE) -> #N/A | H26: NO | I26: NO | J26: NO | K26: NO | L26: NO | M26: NO
A27: BNK | B27: AD.BRO.RSP.FR.PERS.WH | C27: Broker RRSP FR - Personal Wholesale | D27: BROKER.TERM.DEPOSITS | E27: =VLOOKUP(B27,'PARENT PRODUCT'!$A:$B,2,FALSE) -> #N/A | F27: 6825 | G27: =VLOOKUP(B27,'ONLINE ACCESS'!$A:$B,2,FALSE) -> #N/A | H27: NO | I27: NO | J27: NO | K27: NO | L27: NO | M27: NO
A28: BNK | B28: AD.BRO.TFSA.FR.PER | C28: TFSA Premium GIC | D28: BROKER.REG.TERM.DEPOSITS | E28: =VLOOKUP(B28,'PARENT PRODUCT'!$A:$B,2,FALSE) -> AD.BRO.TFSA.PARENT.FR | F28: 6761 | G28: =VLOOKUP(B28,'ONLINE ACCESS'!$A:$B,2,FALSE) -> #N/A | H28: NO | I28: NO | J28: NO | K28: NO | L28: NO | M28: NO
A29: BNK | B29: AD.BRO.TFSA.FR.PER.WH | C29: Broker TFSA FR - Personal Wholesale | D29: BROKER.TERM.DEPOSITS | E29: =VLOOKUP(B29,'PARENT PRODUCT'!$A:$B,2,FALSE) -> #N/A | F29: 6717 | G29: =VLOOKUP(B29,'ONLINE ACCESS'!$A:$B,2,FALSE) -> #N/A | H29: NO | I29: NO | J29: NO | K29: NO | L29: NO | M29: NO
A30: BNK | B30: AD.CDF.FR.PERS | C30: Motive GIC - Personal | D30: CDF.TERM.DEPOSITS | E30: =VLOOKUP(B30,'PARENT PRODUCT'!$A:$B,2,FALSE) -> AD.CDF.PARENT.FR | F30: =VLOOKUP(B30,'CATEGORY CODE'!$A:$B,2,FALSE) -> 6710 | G30: =VLOOKUP(B30,'ONLINE ACCESS'!$A:$B,2,FALSE) -> CDF | H30: YES | I30: NO | J30: NO | K30: NO | L30: NO | M30: NO
A31: BNK | B31: AD.CDF.FR.PERS.WHS | C31: Motive GIC - Personal Wholesale | D31: CDF.TERM.DEPOSITS | E31: =VLOOKUP(B31,'PARENT PRODUCT'!$A:$B,2,FALSE) -> AD.CDF.PARENT.FR | F31: =VLOOKUP(B31,'CATEGORY CODE'!$A:$B,2,FALSE) -> 6715 | G31: =VLOOKUP(B31,'ONLINE ACCESS'!$A:$B,2,FALSE) -> CDF | H31: YES | I31: NO | J31: NO | K31: NO | L31: NO | M31: NO
A32: BNK | B32: AD.CDF.RIF.FR.PERS | C32: Motive RRIF GIC | D32: CDF.REG.TERM.DEPOSITS | E32: =VLOOKUP(B32,'PARENT PRODUCT'!$A:$B,2,FALSE) -> AD.CDF.RIF.PARENT.FR | F32: =VLOOKUP(B32,'CATEGORY CODE'!$A:$B,2,FALSE) -> 6920 | G32: =VLOOKUP(B32,'ONLINE ACCESS'!$A:$B,2,FALSE) -> CDF | H32: YES | I32: NO | J32: NO | K32: NO | L32: NO | M32: NO
A33: BNK | B33: AD.CDF.RSP.FR.PERS | C33: Motive RRSP GIC | D33: CDF.REG.TERM.DEPOSITS | E33: =VLOOKUP(B33,'PARENT PRODUCT'!$A:$B,2,FALSE) -> AD.CDF.RSP.PARENT.FR | F33: =VLOOKUP(B33,'CATEGORY CODE'!$A:$B,2,FALSE) -> 6820 | G33: =VLOOKUP(B33,'ONLINE ACCESS'!$A:$B,2,FALSE) -> CDF | H33: YES | I33: NO | J33: NO | K33: NO | L33: NO | M33: NO
A34: BNK | B34: AD.CDF.RSP.FR.PERS.WH | C34: CDF RRSP FR - Personal Wholesale | D34: CDF.TERM.DEPOSITS | E34: =VLOOKUP(B34,'PARENT PRODUCT'!$A:$B,2,FALSE) -> #N/A | F34: 6715 | G34: =VLOOKUP(B34,'ONLINE ACCESS'!$A:$B,2,FALSE) -> CDF | H34: YES | I34: NO | J34: NO | K34: NO | L34: NO | M34: NO
A35: BNK | B35: AD.CDF.TFSA.FR.PER | C35: Motive TFSA GIC | D35: CDF.REG.TERM.DEPOSITS | E35: =VLOOKUP(B35,'PARENT PRODUCT'!$A:$B,2,FALSE) -> AD.CDF.TFSA.PARENT.FR | F35: 6760 | G35: =VLOOKUP(B35,'ONLINE ACCESS'!$A:$B,2,FALSE) -> CDF | H35: YES | I35: NO | J35: NO | K35: NO | L35: NO | M35: NO
A36: BNK | B36: AD.CDF.TFSA.FR.PER.WH | C36: CDF TFSA FR - Personal Wholesale | D36: CDF.TERM.DEPOSITS | E36: =VLOOKUP(B36,'PARENT PRODUCT'!$A:$B,2,FALSE) -> #N/A | F36: 6715 | G36: =VLOOKUP(B36,'ONLINE ACCESS'!$A:$B,2,FALSE) -> CDF | H36: YES | I36: NO | J36: NO | K36: NO | L36: NO | M36: NO
A37: BNK | B37: AD.FLR.NONPER.WHS.USD | C37: USD FLR - Non Personal Wholesale | D37: NONREG.TERM.DEPOSITS | E37: =VLOOKUP(B37,'PARENT PRODUCT'!$A:$B,2,FALSE) -> AD.PARENT.FR | F37: 6606 | G37: =VLOOKUP(B37,'ONLINE ACCESS'!$A:$B,2,FALSE) -> CWB | H37: YES | I37: NO | J37: NO | K37: NO | L37: NO | M37: NO
A38: BNK | B38: AD.FLR.NONPERS | C38: FLR - Non Personal | D38: NONREG.TERM.DEPOSITS | E38: =VLOOKUP(B38,'PARENT PRODUCT'!$A:$B,2,FALSE) -> AD.PARENT.FR | F38: =VLOOKUP(B38,'CATEGORY CODE'!$A:$B,2,FALSE) -> 6601 | G38: =VLOOKUP(B38,'ONLINE ACCESS'!$A:$B,2,FALSE) -> CWB | H38: YES | I38: NO | J38: NO | K38: NO | L38: NO | M38: NO
A39: BNK | B39: AD.FLR.NONPERS.USD | C39: USD FLR - Non Personal | D39: NONREG.TERM.DEPOSITS | E39: =VLOOKUP(B39,'PARENT PRODUCT'!$A:$B,2,FALSE) -> AD.PARENT.FR | F39: =VLOOKUP(B39,'CATEGORY CODE'!$A:$B,2,FALSE) -> 6601 | G39: =VLOOKUP(B39,'ONLINE ACCESS'!$A:$B,2,FALSE) -> CWB | H39: YES | I39: NO | J39: NO | K39: NO | L39: NO | M39: NO
A40: BNK | B40: AD.FLR.NONPERS.WHS | C40: FLR - Non Personal Wholesale | D40: NONREG.TERM.DEPOSITS | E40: =VLOOKUP(B40,'PARENT PRODUCT'!$A:$B,2,FALSE) -> AD.PARENT.FR | F40: 6606 | G40: =VLOOKUP(B40,'ONLINE ACCESS'!$A:$B,2,FALSE) -> CWB | H40: YES | I40: NO | J40: NO | K40: NO | L40: NO | M40: NO
A41: BNK | B41: AD.FLR.PERS | C41: FLR - Personal | D41: NONREG.TERM.DEPOSITS | E41: =VLOOKUP(B41,'PARENT PRODUCT'!$A:$B,2,FALSE) -> AD.PARENT.FR | F41: =VLOOKUP(B41,'CATEGORY CODE'!$A:$B,2,FALSE) -> 6701 | G41: =VLOOKUP(B41,'ONLINE ACCESS'!$A:$B,2,FALSE) -> CWB | H41: YES | I41: NO | J41: NO | K41: NO | L41: NO | M41: NO
A42: BNK | B42: AD.FLR.PERS.USD | C42: USD FLR - Personal | D42: NONREG.TERM.DEPOSITS | E42: =VLOOKUP(B42,'PARENT PRODUCT'!$A:$B,2,FALSE) -> AD.PARENT.FR | F42: =VLOOKUP(B42,'CATEGORY CODE'!$A:$B,2,FALSE) -> 6701 | G42: =VLOOKUP(B42,'ONLINE ACCESS'!$A:$B,2,FALSE) -> CWB | H42: YES | I42: NO | J42: NO | K42: NO | L42: NO | M42: NO
A43: BNK | B43: AD.FLR.PERS.WHS | C43: FLR - Personal Wholesale | D43: NONREG.TERM.DEPOSITS | E43: =VLOOKUP(B43,'PARENT PRODUCT'!$A:$B,2,FALSE) -> AD.PARENT.FR | F43: 6705 | G43: =VLOOKUP(B43,'ONLINE ACCESS'!$A:$B,2,FALSE) -> CWB | H43: YES | I43: NO | J43: NO | K43: NO | L43: NO | M43: NO
A44: BNK | B44: AD.FLR.PERS.WHS.USD | C44: USD FLR - Personal Wholesale | D44: NONREG.TERM.DEPOSITS | E44: =VLOOKUP(B44,'PARENT PRODUCT'!$A:$B,2,FALSE) -> AD.PARENT.FR | F44: 6705 | G44: =VLOOKUP(B44,'ONLINE ACCESS'!$A:$B,2,FALSE) -> CWB | H44: YES | I44: NO | J44: NO | K44: NO | L44: NO | M44: NO
A45: BNK | B45: AD.FLR.STFANDFAM | C45: FLR - Staff & Family | D45: NONREG.TERM.DEPOSITS | E45: =VLOOKUP(B45,'PARENT PRODUCT'!$A:$B,2,FALSE) -> AD.PARENT.FR | F45: 6701 | G45: =VLOOKUP(B45,'ONLINE ACCESS'!$A:$B,2,FALSE) -> CWB | H45: YES | I45: NO | J45: NO | K45: NO | L45: NO | M45: NO
A46: BNK | B46: AD.FLR.STFANDFAM.WHS | C46: FLR - Staff & Family Wholesale | D46: NONREG.TERM.DEPOSITS | E46: =VLOOKUP(B46,'PARENT PRODUCT'!$A:$B,2,FALSE) -> AD.PARENT.FR | F46: 6705 | G46: =VLOOKUP(B46,'ONLINE ACCESS'!$A:$B,2,FALSE) -> CWB | H46: YES | I46: NO | J46: NO | K46: NO | L46: NO | M46: NO
A47: BNK | B47: AD.FLR.STFFAM.USD | C47: USD FLR - Staff & Family | D47: NONREG.TERM.DEPOSITS | E47: =VLOOKUP(B47,'PARENT PRODUCT'!$A:$B,2,FALSE) -> AD.PARENT.FR | F47: 6701 | G47: =VLOOKUP(B47,'ONLINE ACCESS'!$A:$B,2,FALSE) -> CWB | H47: YES | I47: NO | J47: NO | K47: NO | L47: NO | M47: NO
A48: BNK | B48: AD.FLR.STFFAM.WHS.USD | C48: USD FLR-Staff & Staff Fam Wholesale | D48: NONREG.TERM.DEPOSITS | E48: =VLOOKUP(B48,'PARENT PRODUCT'!$A:$B,2,FALSE) -> #N/A | F48: =VLOOKUP(B48,'CATEGORY CODE'!$A:$B,2,TRUE) -> 6605 | G48: =VLOOKUP(B48,'ONLINE ACCESS'!$A:$B,2,FALSE) -> #N/A | H48: NO | I48: NO | J48: NO | K48: NO | L48: NO | M48: NO
A49: BNK | B49: AD.FR.NONPERS | C49: GIC - Non Personal | D49: NONREG.TERM.DEPOSITS | E49: =VLOOKUP(B49,'PARENT PRODUCT'!$A:$B,2,FALSE) -> AD.PARENT.FR | F49: =VLOOKUP(B49,'CATEGORY CODE'!$A:$B,2,FALSE) -> 6610 | G49: =VLOOKUP(B49,'ONLINE ACCESS'!$A:$B,2,FALSE) -> CWB | H49: YES | I49: NO | J49: NO | K49: NO | L49: NO | M49: NO
A50: BNK | B50: AD.FR.NONPERS.USD | C50: USD GIC - Non Personal | D50: NONREG.TERM.DEPOSITS | E50: =VLOOKUP(B50,'PARENT PRODUCT'!$A:$B,2,FALSE) -> AD.PARENT.FR | F50: =VLOOKUP(B50,'CATEGORY CODE'!$A:$B,2,FALSE) -> 6610 | G50: =VLOOKUP(B50,'ONLINE ACCESS'!$A:$B,2,FALSE) -> CWB | H50: YES | I50: NO | J50: NO | K50: NO | L50: NO | M50: NO
A51: BNK | B51: AD.FR.NONPERS.WHS | C51: GIC - Non Personal Wholesale | D51: NONREG.TERM.DEPOSITS | E51: =VLOOKUP(B51,'PARENT PRODUCT'!$A:$B,2,FALSE) -> AD.PARENT.FR | F51: =VLOOKUP(B51,'CATEGORY CODE'!$A:$B,2,TRUE) -> 6616 | G51: =VLOOKUP(B51,'ONLINE ACCESS'!$A:$B,2,FALSE) -> CWB | H51: YES | I51: NO | J51: NO | K51: NO | L51: NO | M51: NO
A52: BNK | B52: AD.FR.NONPERS.WHS.USD | C52: USD GIC - Non Personal Wholesale | D52: NONREG.TERM.DEPOSITS | E52: =VLOOKUP(B52,'PARENT PRODUCT'!$A:$B,2,FALSE) -> AD.PARENT.FR | F52: =VLOOKUP(B52,'CATEGORY CODE'!$A:$B,2,FALSE) -> 6616 | G52: =VLOOKUP(B52,'ONLINE ACCESS'!$A:$B,2,FALSE) -> CWB | H52: YES | I52: NO | J52: NO | K52: NO | L52: NO | M52: NO
A53: BNK | B53: AD.FR.PERS | C53: GIC - Personal | D53: NONREG.TERM.DEPOSITS | E53: =VLOOKUP(B53,'PARENT PRODUCT'!$A:$B,2,FALSE) -> AD.PARENT.FR | F53: =VLOOKUP(B53,'CATEGORY CODE'!$A:$B,2,FALSE) -> 6710 | G53: =VLOOKUP(B53,'ONLINE ACCESS'!$A:$B,2,FALSE) -> CWB | H53: YES | I53: NO | J53: NO | K53: NO | L53: NO | M53: NO
A54: BNK | B54: AD.FR.PERS.USD | C54: USD GIC - Personal | D54: NONREG.TERM.DEPOSITS | E54: =VLOOKUP(B54,'PARENT PRODUCT'!$A:$B,2,FALSE) -> AD.PARENT.FR | F54: =VLOOKUP(B54,'CATEGORY CODE'!$A:$B,2,FALSE) -> 6710 | G54: =VLOOKUP(B54,'ONLINE ACCESS'!$A:$B,2,FALSE) -> CWB | H54: YES | I54: NO | J54: NO | K54: NO | L54: NO | M54: NO
A55: BNK | B55: AD.FR.PERS.WHS | C55: GIC - Personal Wholesale | D55: NONREG.TERM.DEPOSITS | E55: =VLOOKUP(B55,'PARENT PRODUCT'!$A:$B,2,FALSE) -> AD.PARENT.FR | F55: =VLOOKUP(B55,'CATEGORY CODE'!$A:$B,2,TRUE) -> 6715 | G55: =VLOOKUP(B55,'ONLINE ACCESS'!$A:$B,2,FALSE) -> CWB | H55: YES | I55: NO | J55: NO | K55: NO | L55: NO | M55: NO
A56: BNK | B56: AD.FR.PERS.WHS.USD | C56: USD GIC - Personal Wholesale | D56: NONREG.TERM.DEPOSITS | E56: =VLOOKUP(B56,'PARENT PRODUCT'!$A:$B,2,FALSE) -> AD.PARENT.FR | F56: =VLOOKUP(B56,'CATEGORY CODE'!$A:$B,2,FALSE) -> 6715 | G56: =VLOOKUP(B56,'ONLINE ACCESS'!$A:$B,2,FALSE) -> CWB | H56: YES | I56: NO | J56: NO | K56: NO | L56: NO | M56: NO
A57: BNK | B57: AD.FR.STFANDFAM | C57: GIC - Staff & Family | D57: NONREG.TERM.DEPOSITS | E57: =VLOOKUP(B57,'PARENT PRODUCT'!$A:$B,2,FALSE) -> AD.PARENT.FR | F57: =VLOOKUP(B57,'CATEGORY CODE'!$A:$B,2,FALSE) -> 6710 | G57: =VLOOKUP(B57,'ONLINE ACCESS'!$A:$B,2,FALSE) -> CWB | H57: YES | I57: NO | J57: NO | K57: NO | L57: NO | M57: NO
A58: BNK | B58: AD.FR.STFANDFAM.WHS | C58: GIC - Staff & Family Wholesale | D58: NONREG.TERM.DEPOSITS | E58: =VLOOKUP(B58,'PARENT PRODUCT'!$A:$B,2,FALSE) -> AD.PARENT.FR | F58: =VLOOKUP(B58,'CATEGORY CODE'!$A:$B,2,TRUE) -> 6715 | G58: =VLOOKUP(B58,'ONLINE ACCESS'!$A:$B,2,FALSE) -> CWB | H58: YES | I58: NO | J58: NO | K58: NO | L58: NO | M58: NO
A59: BNK | B59: AD.FR.STFFAM.USD | C59: USD GIC - Staff & Family | D59: NONREG.TERM.DEPOSITS | E59: =VLOOKUP(B59,'PARENT PRODUCT'!$A:$B,2,FALSE) -> AD.PARENT.FR | F59: 6710 | G59: =VLOOKUP(B59,'ONLINE ACCESS'!$A:$B,2,FALSE) -> CWB | H59: YES | I59: NO | J59: NO | K59: NO | L59: NO | M59: NO
A60: BNK | B60: AD.FR.STFFAM.WHS.USD | C60: USD GIC - Staff & Family Wholesale | D60: NONREG.TERM.DEPOSITS | E60: =VLOOKUP(B60,'PARENT PRODUCT'!$A:$B,2,FALSE) -> AD.PARENT.FR | F60: 6715 | G60: =VLOOKUP(B60,'ONLINE ACCESS'!$A:$B,2,FALSE) -> CWB | H60: YES | I60: NO | J60: NO | K60: NO | L60: NO | M60: NO
A61: BNK | B61: AD.HR.3YR.NONPERS | C61: HR 3 Year Non Personal GIC | D61: NONREG.TERM.DEPOSITS | E61: =VLOOKUP(B61,'PARENT PRODUCT'!$A:$B,2,FALSE) -> #N/A | F61: =VLOOKUP(B61,'CATEGORY CODE'!$A:$B,2,FALSE) -> 6620 | G61: =VLOOKUP(B61,'ONLINE ACCESS'!$A:$B,2,FALSE) -> #N/A | H61: NO | I61: NO | J61: NO | K61: NO | L61: NO | M61: NO
A62: BNK | B62: AD.HR.3YR.NONPERS.WHS | C62: HR 3 Year Non Pers GIC Wholesale | D62: NONREG.TERM.DEPOSITS | E62: =VLOOKUP(B62,'PARENT PRODUCT'!$A:$B,2,FALSE) -> #N/A | F62: 6621 | G62: =VLOOKUP(B62,'ONLINE ACCESS'!$A:$B,2,FALSE) -> #N/A | H62: NO | I62: NO | J62: NO | K62: NO | L62: NO | M62: NO
A63: BNK | B63: AD.HR.3YR.PERS | C63: HR 3 Year Personal GIC | D63: NONREG.TERM.DEPOSITS | E63: =VLOOKUP(B63,'PARENT PRODUCT'!$A:$B,2,FALSE) -> #N/A | F63: =VLOOKUP(B63,'CATEGORY CODE'!$A:$B,2,FALSE) -> 6620 | G63: =VLOOKUP(B63,'ONLINE ACCESS'!$A:$B,2,FALSE) -> #N/A | H63: NO | I63: NO | J63: NO | K63: NO | L63: NO | M63: NO
A64: BNK | B64: AD.HR.3YR.PERS.WHS | C64: HR 3 Year Personal GIC-Wholesale | D64: NONREG.TERM.DEPOSITS | E64: =VLOOKUP(B64,'PARENT PRODUCT'!$A:$B,2,FALSE) -> #N/A | F64: 6621 | G64: =VLOOKUP(B64,'ONLINE ACCESS'!$A:$B,2,FALSE) -> #N/A | H64: NO | I64: NO | J64: NO | K64: NO | L64: NO | M64: NO
A65: BNK | B65: AD.HR.3YR.STFFAM | C65: HR 3 Year Stf & Fam GIC | D65: NONREG.TERM.DEPOSITS | E65: =VLOOKUP(B65,'PARENT PRODUCT'!$A:$B,2,FALSE) -> #N/A | F65: 6620 | G65: =VLOOKUP(B65,'ONLINE ACCESS'!$A:$B,2,FALSE) -> #N/A | H65: NO | I65: NO | J65: NO | K65: NO | L65: NO | M65: NO
A66: BNK | B66: AD.HR.3YR.STFFAM.WHS | C66: HR 3 Year Stf & Fam GIC-Wholesale | D66: NONREG.TERM.DEPOSITS | E66: =VLOOKUP(B66,'PARENT PRODUCT'!$A:$B,2,FALSE) -> #N/A | F66: 6621 | G66: =VLOOKUP(B66,'ONLINE ACCESS'!$A:$B,2,FALSE) -> #N/A | H66: NO | I66: NO | J66: NO | K66: NO | L66: NO | M66: NO
A67: BNK | B67: AD.HR.5YR.NONPERS | C67: HR 5 Year Non Personal GIC | D67: NONREG.TERM.DEPOSITS | E67: =VLOOKUP(B67,'PARENT PRODUCT'!$A:$B,2,FALSE) -> #N/A | F67: =VLOOKUP(B67,'CATEGORY CODE'!$A:$B,2,FALSE) -> 6620 | G67: =VLOOKUP(B67,'ONLINE ACCESS'!$A:$B,2,FALSE) -> #N/A | H67: NO | I67: NO | J67: NO | K67: NO | L67: NO | M67: NO
A68: BNK | B68: AD.HR.5YR.NONPERS.WHS | C68: HR 5 Year Non Pers GIC-Wholesale | D68: NONREG.TERM.DEPOSITS | E68: =VLOOKUP(B68,'PARENT PRODUCT'!$A:$B,2,FALSE) -> #N/A | F68: 6621 | G68: =VLOOKUP(B68,'ONLINE ACCESS'!$A:$B,2,FALSE) -> #N/A | H68: NO | I68: NO | J68: NO | K68: NO | L68: NO | M68: NO
A69: BNK | B69: AD.HR.5YR.PERS | C69: HR 5 Year Personal GIC | D69: NONREG.TERM.DEPOSITS | E69: =VLOOKUP(B69,'PARENT PRODUCT'!$A:$B,2,FALSE) -> #N/A | F69: =VLOOKUP(B69,'CATEGORY CODE'!$A:$B,2,FALSE) -> 6620 | G69: =VLOOKUP(B69,'ONLINE ACCESS'!$A:$B,2,FALSE) -> #N/A | H69: NO | I69: NO | J69: NO | K69: NO | L69: NO | M69: NO
A70: BNK | B70: AD.HR.5YR.PERS.WHS | C70: HR 5 Year Personal GIC-Wholesale | D70: NONREG.TERM.DEPOSITS | E70: =VLOOKUP(B70,'PARENT PRODUCT'!$A:$B,2,FALSE) -> #N/A | F70: 6621 | G70: =VLOOKUP(B70,'ONLINE ACCESS'!$A:$B,2,FALSE) -> #N/A | H70: NO | I70: NO | J70: NO | K70: NO | L70: NO | M70: NO
A71: BNK | B71: AD.HR.5YR.STFFAM | C71: HR 5 Year Stf & Fam GIC | D71: NONREG.TERM.DEPOSITS | E71: =VLOOKUP(B71,'PARENT PRODUCT'!$A:$B,2,FALSE) -> #N/A | F71: 6620 | G71: =VLOOKUP(B71,'ONLINE ACCESS'!$A:$B,2,FALSE) -> #N/A | H71: NO | I71: NO | J71: NO | K71: NO | L71: NO | M71: NO
A72: BNK | B72: AD.HR.5YR.STFFAM.WHS | C72: HR 5 Year Stf & Fam GIC-Wholesale | D72: NONREG.TERM.DEPOSITS | E72: =VLOOKUP(B72,'PARENT PRODUCT'!$A:$B,2,FALSE) -> #N/A | F72: 6621 | G72: =VLOOKUP(B72,'ONLINE ACCESS'!$A:$B,2,FALSE) -> #N/A | H72: NO | I72: NO | J72: NO | K72: NO | L72: NO | M72: NO
A73: BNK | B73: AD.RIF.CONV.PERS | C73: RRIF Convertible GIC - Personal | D73: REG.TERM.DEPOSITS | E73: =VLOOKUP(B73,'PARENT PRODUCT'!$A:$B,2,FALSE) -> AD.RIF.PARENT.FR | F73: =VLOOKUP(B73,'CATEGORY CODE'!$A:$B,2,FALSE) -> 6910 | G73: =VLOOKUP(B73,'ONLINE ACCESS'!$A:$B,2,FALSE) -> CWB | H73: YES | I73: NO | J73: NO | K73: NO | L73: NO | M73: NO
A74: BNK | B74: AD.RIF.CONV.PERS.WHS | C74: RRIF Convert Personal GIC Wholesale | D74: REG.TERM.DEPOSITS | E74: =VLOOKUP(B74,'PARENT PRODUCT'!$A:$B,2,FALSE) -> #N/A | F74: =VLOOKUP(B74,'CATEGORY CODE'!$A:$B,2,FALSE) -> 6915 | G74: =VLOOKUP(B74,'ONLINE ACCESS'!$A:$B,2,FALSE) -> CWB | H74: YES | I74: NO | J74: NO | K74: NO | L74: NO | M74: NO
A75: BNK | B75: AD.RIF.CONV.STF | C75: RRIF Convertible GIC - Staff | D75: REG.TERM.DEPOSITS | E75: =VLOOKUP(B75,'PARENT PRODUCT'!$A:$B,2,FALSE) -> AD.RIF.PARENT.FR | F75: =VLOOKUP(B75,'CATEGORY CODE'!$A:$B,2,FALSE) -> 6910 | G75: =VLOOKUP(B75,'ONLINE ACCESS'!$A:$B,2,FALSE) -> CWB | H75: YES | I75: NO | J75: NO | K75: NO | L75: NO | M75: NO
A76: BNK | B76: AD.RIF.CONV.STF.WH | C76: RRIF Convert Stf GIC Wholesale | D76: REG.TERM.DEPOSITS | E76: =VLOOKUP(B76,'PARENT PRODUCT'!$A:$B,2,FALSE) -> #N/A | F76: 6910 | G76: =VLOOKUP(B76,'ONLINE ACCESS'!$A:$B,2,FALSE) -> CWB | H76: YES | I76: NO | J76: NO | K76: NO | L76: NO | M76: NO
A77: BNK | B77: AD.RIF.CONV.STFFAM | C77: RRIF Convertible GIC - Staff Family | D77: REG.TERM.DEPOSITS | E77: =VLOOKUP(B77,'PARENT PRODUCT'!$A:$B,2,FALSE) -> AD.RIF.PARENT.FR | F77: =VLOOKUP(B77,'CATEGORY CODE'!$A:$B,2,FALSE) -> 6910 | G77: =VLOOKUP(B77,'ONLINE ACCESS'!$A:$B,2,FALSE) -> CWB | H77: YES | I77: NO | J77: NO | K77: NO | L77: NO | M77: NO
A78: BNK | B78: AD.RIF.CONV.STFFAM.WH | C78: RRIF Convert Stf Fam GIC Wholesale | D78: REG.TERM.DEPOSITS | E78: =VLOOKUP(B78,'PARENT PRODUCT'!$A:$B,2,FALSE) -> #N/A | F78: 6915 | G78: =VLOOKUP(B78,'ONLINE ACCESS'!$A:$B,2,FALSE) -> CWB | H78: YES | I78: NO | J78: NO | K78: NO | L78: NO | M78: NO
A79: BNK | B79: AD.RIF.FR.PERS | C79: RRIF Premium GIC - Personal | D79: REG.TERM.DEPOSITS | E79: =VLOOKUP(B79,'PARENT PRODUCT'!$A:$B,2,FALSE) -> AD.RIF.PARENT.FR | F79: =VLOOKUP(B79,'CATEGORY CODE'!$A:$B,2,FALSE) -> 6920 | G79: =VLOOKUP(B79,'ONLINE ACCESS'!$A:$B,2,FALSE) -> CWB | H79: YES | I79: NO | J79: NO | K79: NO | L79: NO | M79: NO
A80: BNK | B80: AD.RIF.FR.PERS.WHS | C80: RRIF FR Personal GIC Wholesale | D80: REG.TERM.DEPOSITS | E80: =VLOOKUP(B80,'PARENT PRODUCT'!$A:$B,2,FALSE) -> #N/A | F80: =VLOOKUP(B80,'CATEGORY CODE'!$A:$B,2,FALSE) -> 6925 | G80: =VLOOKUP(B80,'ONLINE ACCESS'!$A:$B,2,FALSE) -> CWB | H80: YES | I80: NO | J80: NO | K80: NO | L80: NO | M80: NO
A81: BNK | B81: AD.RIF.FR.STF | C81: RRIF Premium GIC - Staff | D81: REG.TERM.DEPOSITS | E81: =VLOOKUP(B81,'PARENT PRODUCT'!$A:$B,2,FALSE) -> AD.RIF.PARENT.FR | F81: =VLOOKUP(B81,'CATEGORY CODE'!$A:$B,2,FALSE) -> 6920 | G81: =VLOOKUP(B81,'ONLINE ACCESS'!$A:$B,2,FALSE) -> CWB | H81: YES | I81: NO | J81: NO | K81: NO | L81: NO | M81: NO
A82: BNK | B82: AD.RIF.FR.STF.WHS | C82: RRIF FR Staff GIC Wholesale | D82: REG.TERM.DEPOSITS | E82: =VLOOKUP(B82,'PARENT PRODUCT'!$A:$B,2,FALSE) -> #N/A | F82: =VLOOKUP(B82,'CATEGORY CODE'!$A:$B,2,FALSE) -> 6925 | G82: =VLOOKUP(B82,'ONLINE ACCESS'!$A:$B,2,FALSE) -> CWB | H82: YES | I82: NO | J82: NO | K82: NO | L82: NO | M82: NO
A83: BNK | B83: AD.RIF.FR.STFFAM | C83: RRIF Premium GIC - Staff Family | D83: REG.TERM.DEPOSITS | E83: =VLOOKUP(B83,'PARENT PRODUCT'!$A:$B,2,FALSE) -> AD.RIF.PARENT.FR | F83: =VLOOKUP(B83,'CATEGORY CODE'!$A:$B,2,FALSE) -> 6920 | G83: =VLOOKUP(B83,'ONLINE ACCESS'!$A:$B,2,FALSE) -> CWB | H83: YES | I83: NO | J83: NO | K83: NO | L83: NO | M83: NO
A84: BNK | B84: AD.RIF.FR.STFFAM.WHS | C84: RRIF FR Stf Fam GIC Wholesale | D84: REG.TERM.DEPOSITS | E84: =VLOOKUP(B84,'PARENT PRODUCT'!$A:$B,2,FALSE) -> #N/A | F84: =VLOOKUP(B84,'CATEGORY CODE'!$A:$B,2,FALSE) -> 6925 | G84: =VLOOKUP(B84,'ONLINE ACCESS'!$A:$B,2,FALSE) -> CWB | H84: YES | I84: NO | J84: NO | K84: NO | L84: NO | M84: NO
A85: BNK | B85: AD.RIF.FULRED.PERS | C85: RRIF Full Redeem GIC - Personal | D85: REG.TERM.DEPOSITS | E85: =VLOOKUP(B85,'PARENT PRODUCT'!$A:$B,2,FALSE) -> AD.RIF.PARENT.FR | F85: =VLOOKUP(B85,'CATEGORY CODE'!$A:$B,2,FALSE) -> 6940 | G85: =VLOOKUP(B85,'ONLINE ACCESS'!$A:$B,2,FALSE) -> CWB | H85: YES | I85: NO | J85: NO | K85: NO | L85: NO | M85: NO
A86: BNK | B86: AD.RIF.FULRED.PERS.WH | C86: RRIF Ful Red Pers GIC Wholesale | D86: REG.TERM.DEPOSITS | E86: =VLOOKUP(B86,'PARENT PRODUCT'!$A:$B,2,FALSE) -> #N/A | F86: 6945 | G86: =VLOOKUP(B86,'ONLINE ACCESS'!$A:$B,2,FALSE) -> CWB | H86: YES | I86: NO | J86: NO | K86: NO | L86: NO | M86: NO
A87: BNK | B87: AD.RIF.FULRED.SFAM | C87: RRIF Full Redeem GIC - Staff Family | D87: REG.TERM.DEPOSITS | E87: =VLOOKUP(B87,'PARENT PRODUCT'!$A:$B,2,FALSE) -> AD.RIF.PARENT.FR | F87: 6940 | G87: =VLOOKUP(B87,'ONLINE ACCESS'!$A:$B,2,FALSE) -> CWB | H87: YES | I87: NO | J87: NO | K87: NO | L87: NO | M87: NO
A88: BNK | B88: AD.RIF.FULRED.SFAM.WH | C88: RRIF Ful Red Stf Fam GIC Wholesale | D88: REG.TERM.DEPOSITS | E88: =VLOOKUP(B88,'PARENT PRODUCT'!$A:$B,2,FALSE) -> #N/A | F88: 6945 | G88: =VLOOKUP(B88,'ONLINE ACCESS'!$A:$B,2,FALSE) -> CWB | H88: YES | I88: NO | J88: NO | K88: NO | L88: NO | M88: NO
A89: BNK | B89: AD.RIF.FULRED.STF | C89: RRIF Full Redeem GIC - Staff | D89: REG.TERM.DEPOSITS | E89: =VLOOKUP(B89,'PARENT PRODUCT'!$A:$B,2,FALSE) -> AD.RIF.PARENT.FR | F89: =VLOOKUP(B89,'CATEGORY CODE'!$A:$B,2,FALSE) -> 6940 | G89: =VLOOKUP(B89,'ONLINE ACCESS'!$A:$B,2,FALSE) -> CWB | H89: YES | I89: NO | J89: NO | K89: NO | L89: NO | M89: NO
A90: BNK | B90: AD.RIF.FULRED.STF.WH | C90: RRIF Ful Red Staff GIC Wholesale | D90: REG.TERM.DEPOSITS | E90: =VLOOKUP(B90,'PARENT PRODUCT'!$A:$B,2,FALSE) -> #N/A | F90: 6945 | G90: =VLOOKUP(B90,'ONLINE ACCESS'!$A:$B,2,FALSE) -> CWB | H90: YES | I90: NO | J90: NO | K90: NO | L90: NO | M90: NO
A91: BNK | B91: AD.RSP.CONV.PERS | C91: RRSP Convertible GIC - Personal | D91: REG.TERM.DEPOSITS | E91: =VLOOKUP(B91,'PARENT PRODUCT'!$A:$B,2,FALSE) -> AD.RSP.PARENT.FR | F91: =VLOOKUP(B91,'CATEGORY CODE'!$A:$B,2,FALSE) -> 6820 | G91: =VLOOKUP(B91,'ONLINE ACCESS'!$A:$B,2,FALSE) -> CWB | H91: YES | I91: NO | J91: NO | K91: NO | L91: NO | M91: NO
A92: BNK | B92: AD.RSP.CONV.PERS.WHS | C92: RRSP Convertible Pers GIC Wholesale | D92: REG.TERM.DEPOSITS | E92: =VLOOKUP(B92,'PARENT PRODUCT'!$A:$B,2,FALSE) -> #N/A | F92: =VLOOKUP(B92,'CATEGORY CODE'!$A:$B,2,FALSE) -> 6815 | G92: =VLOOKUP(B92,'ONLINE ACCESS'!$A:$B,2,FALSE) -> CWB | H92: YES | I92: NO | J92: NO | K92: NO | L92: NO | M92: NO
A93: BNK | B93: AD.RSP.CONV.STF | C93: RRSP Convertible GIC - Staff | D93: REG.TERM.DEPOSITS | E93: =VLOOKUP(B93,'PARENT PRODUCT'!$A:$B,2,FALSE) -> AD.RSP.PARENT.FR | F93: =VLOOKUP(B93,'CATEGORY CODE'!$A:$B,2,FALSE) -> 6820 | G93: =VLOOKUP(B93,'ONLINE ACCESS'!$A:$B,2,FALSE) -> CWB | H93: YES | I93: NO | J93: NO | K93: NO | L93: NO | M93: NO
A94: BNK | B94: AD.RSP.CONV.STF.WH | C94: RRSP Convert Staff GIC Wholesale | D94: REG.TERM.DEPOSITS | E94: =VLOOKUP(B94,'PARENT PRODUCT'!$A:$B,2,FALSE) -> #N/A | F94: 6815 | G94: =VLOOKUP(B94,'ONLINE ACCESS'!$A:$B,2,FALSE) -> CWB | H94: YES | I94: NO | J94: NO | K94: NO | L94: NO | M94: NO
A95: BNK | B95: AD.RSP.CONV.STFFAM | C95: RRSP Convertible GIC - Staff Family | D95: REG.TERM.DEPOSITS | E95: =VLOOKUP(B95,'PARENT PRODUCT'!$A:$B,2,FALSE) -> AD.RSP.PARENT.FR | F95: =VLOOKUP(B95,'CATEGORY CODE'!$A:$B,2,FALSE) -> 6820 | G95: =VLOOKUP(B95,'ONLINE ACCESS'!$A:$B,2,FALSE) -> CWB | H95: YES | I95: NO | J95: NO | K95: NO | L95: NO | M95: NO
A96: BNK | B96: AD.RSP.CONV.STFFAM.WH | C96: RRSP Convert Stf Fam GIC Wholesale | D96: REG.TERM.DEPOSITS | E96: =VLOOKUP(B96,'PARENT PRODUCT'!$A:$B,2,FALSE) -> #N/A | F96: 6815 | G96: =VLOOKUP(B96,'ONLINE ACCESS'!$A:$B,2,FALSE) -> CWB | H96: YES | I96: NO | J96: NO | K96: NO | L96: NO | M96: NO
A97: BNK | B97: AD.RSP.FR.PERS | C97: RRSP Premium GIC - Personal | D97: REG.TERM.DEPOSITS | E97: =VLOOKUP(B97,'PARENT PRODUCT'!$A:$B,2,FALSE) -> AD.RSP.PARENT.FR | F97: =VLOOKUP(B97,'CATEGORY CODE'!$A:$B,2,FALSE) -> 6820 | G97: =VLOOKUP(B97,'ONLINE ACCESS'!$A:$B,2,FALSE) -> CWB | H97: YES | I97: NO | J97: NO | K97: NO | L97: NO | M97: NO
A98: BNK | B98: AD.RSP.FR.PERS.WHS | C98: RRSP Fixed Rate Personal Wholesale | D98: REG.TERM.DEPOSITS | E98: =VLOOKUP(B98,'PARENT PRODUCT'!$A:$B,2,FALSE) -> #N/A | F98: =VLOOKUP(B98,'CATEGORY CODE'!$A:$B,2,FALSE) -> 6825 | G98: =VLOOKUP(B98,'ONLINE ACCESS'!$A:$B,2,FALSE) -> CWB | H98: YES | I98: NO | J98: NO | K98: NO | L98: NO | M98: NO
A99: BNK | B99: AD.RSP.FR.STF | C99: RRSP Premium GIC - Staff | D99: REG.TERM.DEPOSITS | E99: =VLOOKUP(B99,'PARENT PRODUCT'!$A:$B,2,FALSE) -> AD.RSP.PARENT.FR | F99: =VLOOKUP(B99,'CATEGORY CODE'!$A:$B,2,FALSE) -> 6820 | G99: =VLOOKUP(B99,'ONLINE ACCESS'!$A:$B,2,FALSE) -> CWB | H99: YES | I99: NO | J99: NO | K99: NO | L99: NO | M99: NO
A100: BNK | B100: AD.RSP.FR.STF.WHS | C100: RRSP Fixed Rate Staff Wholesale | D100: REG.TERM.DEPOSITS | E100: =VLOOKUP(B100,'PARENT PRODUCT'!$A:$B,2,FALSE) -> #N/A | F100: =VLOOKUP(B100,'CATEGORY CODE'!$A:$B,2,FALSE) -> 6825 | G100: =VLOOKUP(B100,'ONLINE ACCESS'!$A:$B,2,FALSE) -> CWB | H100: YES | I100: NO | J100: NO | K100: NO | L100: NO | M100: NO
...

Sheet PARENT PRODUCT
A1: @ID | B1: PARENT_PRODUCT | C1: PRODUCT_GROUP | D1: Account Type | E1: Account Sub-type | F1: Where will these appear? Personal/Business/Both | G1: Notes
A2: AD.BRO.BB.FR.NONP | B2: AD.BRO.PARENT.FR | C2: BROKER.TERM.DEPOSITS | D2: Deposit | E2: Brokered Deposit
A3: AD.BRO.BB.FR.NONP.WHS | B3: AD.BRO.PARENT.FR | C3: BROKER.TERM.DEPOSITS | D3: Deposit | E3: Brokered Deposit
A4: AD.BRO.BB.FR.PERS | B4: AD.BRO.PARENT.FR | C4: BROKER.TERM.DEPOSITS | D4: Deposit | E4: Brokered Deposit
A5: AD.BRO.BB.FR.PERS.WHS | B5: AD.BRO.PARENT.FR | C5: BROKER.TERM.DEPOSITS | D5: Deposit | E5: Brokered Deposit
A6: AD.BRO.CSC.NONPER | B6: AD.BRO.PARENT.FR | C6: BROKER.TERM.DEPOSITS | D6: Deposit | E6: Brokered Deposit
A7: AD.BRO.CSC.NONPER.WH | B7: AD.BRO.PARENT.FR | C7: BROKER.TERM.DEPOSITS | D7: Deposit | E7: Brokered Deposit
A8: AD.BRO.CSC.PER | B8: AD.BRO.PARENT.FR | C8: BROKER.TERM.DEPOSITS | D8: Deposit | E8: Brokered Deposit
A9: AD.BRO.CSC.PER.WH | B9: AD.BRO.PARENT.FR | C9: BROKER.TERM.DEPOSITS | D9: Deposit | E9: Brokered Deposit
A10: AD.BRO.FLR.NONPERS | B10: AD.BRO.PARENT.FR | C10: BROKER.TERM.DEPOSITS | D10: Deposit | E10: Brokered Deposit
A11: AD.BRO.FLR.NONPERS.WH | B11: AD.BRO.PARENT.FR | C11: BROKER.TERM.DEPOSITS | D11: Deposit | E11: Brokered Deposit
A12: AD.BRO.FLR.PERS | B12: AD.BRO.PARENT.FR | C12: BROKER.TERM.DEPOSITS | D12: Deposit | E12: Brokered Deposit
A13: AD.BRO.FLR.PERS.WH | B13: AD.BRO.PARENT.FR | C13: BROKER.TERM.DEPOSITS | D13: Deposit | E13: Brokered Deposit
... A17: AD.BRO.FR.PERS.WHS | B17: AD.BRO.PARENT.FR | C17: BROKER.TERM.DEPOSITS | D17: Deposit | E17: Brokered Deposit
A18: AD.BRO.PARENT.FR | B18: NULL | C18: BROKER.TERM.DEPOSITS | D18: Backoffice account | E18: Backoffice account | G18: Not available via online banking platform
A19: AD.BRO.RIF.CON.PER | B19: AD.BRO.RIF.PARENT.FR | C19: BROKER.REG.TERM.DEPOSITS | D19: Deposit | E19: Registered Brokered Deposit
A20: AD.BRO.RIF.FR.PERS | B20: AD.BRO.RIF.PARENT.FR | C20: BROKER.REG.TERM.DEPOSITS | D20: Deposit | E20: Registered Brokered Deposit
A21: AD.BRO.RIF.FRE.PER | B21: AD.BRO.RIF.PARENT.FR | C21: BROKER.REG.TERM.DEPOSITS | D21: Deposit | E21: Registered Brokered Deposit
A22: AD.BRO.RIF.PARENT.FR | B22: NULL | C22: BROKER.REG.TERM.DEPOSITS | D22: Backoffice account | E22: Backoffice account | G22: Not available via online banking platform
A23: AD.BRO.RSP.CON.PER | B23: AD.BRO.RSP.PARENT.FR | C23: BROKER.REG.TERM.DEPOSITS | D23: Deposit | E23: Registered Brokered Deposit
A24: AD.BRO.RSP.FR.PERS | B24: AD.BRO.RSP.PARENT.FR | C24: BROKER.REG.TERM.DEPOSITS | D24: Deposit | E24: Registered Brokered Deposit
A25: AD.BRO.RSP.PARENT.FR | B25: NULL | C25: BROKER.REG.TERM.DEPOSITS | D25: Backoffice account | E25: Backoffice account | G25: Not available via online banking platform
A26: AD.BRO.TFSA.FR.PER | B26: AD.BRO.TFSA.PARENT.FR | C26: BROKER.REG.TERM.DEPOSITS | D26: Deposit | E26: Registered Brokered Deposit
A27: AD.BRO.TFSA.PARENT.FR | B27: NULL | C27: BROKER.REG.TERM.DEPOSITS | D27: Backoffice account | E27: Backoffice account | G27: Not available via online banking platform
A28: AD.CDF.FR.PERS | B28: AD.CDF.PARENT.FR | C28: CDF.TERM.DEPOSITS | D28: Deposit | E28: Non-registered deposit
A29: AD.CDF.FR.PERS.WHS | B29: AD.CDF.PARENT.FR | C29: CDF.TERM.DEPOSITS | D29: Deposit | E29: Non-registered deposit
A30: AD.CDF.PARENT.FR | B30: NULL | C30: CDF.TERM.DEPOSITS | D30: Backoffice account | E30: Backoffice account | G30: Not available via online banking platform
A31: AD.CDF.RIF.FR.PERS | B31: AD.CDF.RIF.PARENT.FR | C31: CDF.REG.TERM.DEPOSITS | D31: Deposit | E31: Registered Term Deposit
A32: AD.CDF.RIF.PARENT.FR | B32: NULL | C32: CDF.REG.TERM.DEPOSITS | D32: Backoffice account | E32: Backoffice account | G32: Not available via online banking platform
A33: AD.CDF.RSP.FR.PERS | B33: AD.CDF.RSP.PARENT.FR | C33: CDF.REG.TERM.DEPOSITS | D33: Deposit | E33: Registered Term Deposit
A34: AD.CDF.RSP.PARENT.FR | B34: NULL | C34: CDF.REG.TERM.DEPOSITS | D34: Backoffice account | E34: Backoffice account | G34: Not available via online banking platform
A35: AD.CDF.TFSA.FR.PER | B35: AD.CDF.TFSA.PARENT.FR | C35: CDF.REG.TERM.DEPOSITS | D35: Deposit | E35: Registered Term Deposit
A36: AD.CDF.TFSA.PARENT.FR | B36: NULL | C36: CDF.REG.TERM.DEPOSITS | D36: Backoffice account | E36: Backoffice account | G36: Not available via online banking platform
A37: AD.FLR.NONPER.WHS.USD | B37: AD.PARENT.FR | C37: NONREG.TERM.DEPOSITS | D37: Deposit | E37: Non-registered deposit
A38: AD.FLR.NONPERS | B38: AD.PARENT.FR | C38: NONREG.TERM.DEPOSITS | D38: Deposit | E38: Non-registered deposit
A39: AD.FLR.NONPERS.USD | B39: AD.PARENT.FR | C39: NONREG.TERM.DEPOSITS | D39: Deposit | E39: Non-registered deposit
A40: AD.FLR.NONPERS.WHS | B40: AD.PARENT.FR | C40: NONREG.TERM.DEPOSITS | D40: Deposit | E40: Non-registered deposit
A41: AD.FLR.PERS | B41: AD.PARENT.FR | C41: NONREG.TERM.DEPOSITS | D41: Deposit | E41: Non-registered deposit
A42: AD.FLR.PERS.USD | B42: AD.PARENT.FR | C42: NONREG.TERM.DEPOSITS | D42: Deposit | E42: Non-registered deposit
A43: AD.FLR.PERS.WHS | B43: AD.PARENT.FR | C43: NONREG.TERM.DEPOSITS | D43: Deposit | E43: Non-registered deposit
A44: AD.FLR.PERS.WHS.USD | B44: AD.PARENT.FR | C44: NONREG.TERM.DEPOSITS | D44: Deposit | E44: Non-registered deposit
A45: AD.FLR.STFANDFAM | B45: AD.PARENT.FR | C45: NONREG.TERM.DEPOSITS | D45: Deposit | E45: Non-registered deposit
A46: AD.FLR.STFANDFAM.WHS | B46: AD.PARENT.FR | C46: NONREG.TERM.DEPOSITS | D46: Deposit | E46: Non-registered deposit
A47: AD.FLR.STFFAM.USD | B47: AD.PARENT.FR | C47: NONREG.TERM.DEPOSITS | D47: Deposit | E47: Non-registered deposit
A48: AD.FR.NONPERS | B48: AD.PARENT.FR | C48: NONREG.TERM.DEPOSITS | D48: Deposit | E48: Non-registered deposit
... A59: AD.FR.STFFAM.WHS.USD | B59: AD.PARENT.FR | C59: NONREG.TERM.DEPOSITS | D59: Deposit | E59: Non-registered deposit
A60: AD.PARENT.FR | B60: NULL | C60: NONREG.TERM.DEPOSITS | D60: Backoffice account | E60: Backoffice account | G60: Not available via online banking platform
A61: AD.PARENT.NHA | B61: NULL | C61: NHA.MBS | D61: Backoffice account | E61: Backoffice account | G61: Not available via online banking platform
A62: AD.RIF.CONV.PERS | B62: AD.RIF.PARENT.FR | C62: REG.TERM.DEPOSITS | D62: Deposit | E62: Registered Term Deposit
A63: AD.RIF.CONV.STF | B63: AD.RIF.PARENT.FR | C63: REG.TERM.DEPOSITS | D63: Deposit | E63: Registered Term Deposit
A64: AD.RIF.CONV.STFFAM | B64: AD.RIF.PARENT.FR | C64: REG.TERM.DEPOSITS | D64: Deposit | E64: Registered Term Deposit
A65: AD.RIF.FR.PERS | B65: AD.RIF.PARENT.FR | C65: REG.TERM.DEPOSITS | D65: Deposit | E65: Registered Term Deposit
A66: AD.RIF.FR.STF | B66: AD.RIF.PARENT.FR | C66: REG.TERM.DEPOSITS | D66: Deposit | E66: Registered Term Deposit
A67: AD.RIF.FR.STFFAM | B67: AD.RIF.PARENT.FR | C67: REG.TERM.DEPOSITS | D67: Deposit | E67: Registered Term Deposit
A68: AD.RIF.FULRED.PERS | B68: AD.RIF.PARENT.FR | C68: REG.TERM.DEPOSITS | D68: Deposit | E68: Registered Term Deposit
A69: AD.RIF.FULRED.SFAM | B69: AD.RIF.PARENT.FR | C69: REG.TERM.DEPOSITS | D69: Deposit | E69: Registered Term Deposit
A70: AD.RIF.FULRED.STF | B70: AD.RIF.PARENT.FR | C70: REG.TERM.DEPOSITS | D70: Deposit | E70: Registered Term Deposit
A71: AD.RIF.PARENT.FR | B71: NULL | C71: REG.TERM.DEPOSITS | D71: Backoffice account | E71: Backoffice account | G71: Not available via online banking platform
A72: AD.RSP.CONV.PERS | B72: AD.RSP.PARENT.FR | C72: REG.TERM.DEPOSITS | D72: Deposit | E72: Registered Term Deposit
A73: AD.RSP.CONV.STF | B73: AD.RSP.PARENT.FR | C73: REG.TERM.DEPOSITS | D73: Deposit | E73: Registered Term Deposit
A74: AD.RSP.CONV.STFFAM | B74: AD.RSP.PARENT.FR | C74: REG.TERM.DEPOSITS | D74: Deposit | E74: Registered Term Deposit
A75: AD.RSP.FR.PERS | B75: AD.RSP.PARENT.FR | C75: REG.TERM.DEPOSITS | D75: Deposit | E75: Registered Term Deposit
A76: AD.RSP.FR.STF | B76: AD.RSP.PARENT.FR | C76: REG.TERM.DEPOSITS | D76: Deposit | E76: Registered Term Deposit
A77: AD.RSP.FR.STFFAM | B77: AD.RSP.PARENT.FR | C77: REG.TERM.DEPOSITS | D77: Deposit | E77: Registered Term Deposit
A78: AD.RSP.PARENT.FR | B78: NULL | C78: REG.TERM.DEPOSITS | D78: Backoffice account | E78: Backoffice account | G78: Not available via online banking platform
A79: AD.TFSA.FR.PERS | B79: AD.TFSA.PARENT.FR | C79: REG.TERM.DEPOSITS | D79: Deposit | E79: Registered Term Deposit
A80: AD.TFSA.FR.SFAM | B80: AD.TFSA.PARENT.FR | C80: REG.TERM.DEPOSITS | D80: Deposit | E80: Registered Term Deposit
A81: AD.TFSA.PARENT.FR | B81: NULL | C81: REG.TERM.DEPOSITS | D81: Backoffice account | E81: Backoffice account | G81: Not available via online banking platform
A82: AD.TRS.INTERCO | B82: AD.TRS.PARENT.INTERCO | C82: TREASURY.INSTRUMENTS | D82: Deposit | E82: Deposit | G82: Not available via online banking
A83: AD.TRS.PARENT.INTERCO | B83: NULL | C83: TREASURY.INSTRUMENTS | D83: Backoffice account | E83: Backoffice account | G83: Not available via online banking platform
A84: AL.1TO5Y.CLOSED.MTG | B84: AL.FR.CLO.MTG.PAR | C84: RETAIL.MTG | D84: Loan | E84: Mortgage | F84: Retail
A85: AL.1Y.OPEN.MTG | B85: AL.FR.OPEN.MTG.PAR | C85: RETAIL.MTG | D85: Loan | E85: Mortgage | F85: Retail
A86: AL.6M.CONVERT.MTG | B86: AL.FR.CLO.MTG.PAR | C86: RETAIL.MTG | D86: Loan | E86: Mortgage | F86: Retail
A87: AL.6M.OPEN.MTG | B87: AL.FR.OPEN.MTG.PAR | C87: RETAIL.MTG | D87: Loan | E87: Mortgage | F87: Retail
A88: AL.BUS.FIXED.RATE.MTG | B88: AL.BUS.TERM.LN.PAR | C88: BUSINESS.TERM.LENDING | D88: Loan | E88: Mortgage | F88: Business
A89: AL.BUS.FIXED.TERM.LN | B89: AL.BUS.TERM.LN.PAR | C89: BUSINESS.TERM.LENDING | D89: Loan | E89: Term loan | F89: Business
A90: AL.BUS.TERM.LN.PAR | B90: NULL | C90: BUSINESS.TERM.LENDING | D90: Backoffice account | E90: Backoffice account | G90: Not available via online banking platform
A91: AL.BUS.VAR.RATE.MTG | B91: AL.BUS.TERM.LN.PAR | C91: BUSINESS.TERM.LENDING | D91: Loan | E91: Mortgage | F91: Business
A92: AL.BUS.VAR.TERM.LN | B92: AL.BUS.TERM.LN.PAR | C92: BUSINESS.TERM.LENDING | D92: Loan | E92: Term loan | F92: Business
A93: AL.BUSINESS.LOC | B93: AL.BUSINESS.LOC.PAR | C93: BUSINESS.LOC | D93: Line of Credit | E93: Line of Credit | F93: Business
A94: AL.BUSINESS.LOC.PAR | B94: NULL | C94: BUSINESS.LOC | D94: Backoffice account | E94: Backoffice account | G94: Not available via online banking platform
A95: AL.CDF.LOC.PARENT | B95: NULL | C95: CDF.LOC | D95: Backoffice account | E95: Backoffice account | G95: Not available via online banking platform
A96: AL.CDF.POP | B96: AL.CDF.LOC.PARENT | C96: CDF.LOC | D96: Line of Credit | E96: Line of Credit
A97: AL.DEALER.FLEET.FR.LN | B97: AL.DEALER.FLEET.PAR | C97: DEALER.FLEET.LENDING | D97: Loan | E97: Term loan | F97: Business
A98: AL.DEALER.FLEET.PAR | B98: NULL | C98: DEALER.FLEET.LENDING | D98: Backoffice account | E98: Backoffice account | G98: Not available via online banking platform
A99: AL.DEALER.FLEET.VR.LN | B99: AL.DEALER.FLEET.PAR | C99: DEALER.FLEET.LENDING | D99: Loan | E99: Term loan | F99: Business
A100: AL.FIXED.PROJECT.LN | B100: AL.BUS.TERM.LN.PAR | C100: BUSINESS.TERM.LENDING | D100: Loan | E100: Term loan | F100: Business
A101: AL.FIXED.RATE.LEASE | B101: AL.LEASING.PAR | C101: LEASING | D101: Loan | E101: Lease
A102: AL.FR.CLO.MTG.PAR | B102: NULL | C102: RETAIL.MTG | D102: Backoffice account | E102: Backoffice account | G102: Not available via online banking platform
A103: AL.FR.LEASE.SERVICING | B103: AL.LEASING.PAR | C103: LEASING | D103: Loan | E103: Lease
A104: AL.FR.OPEN.MTG.PAR | B104: NULL | C104: RETAIL.MTG | D104: Backoffice account | E104: Backoffice account | G104: Not available via online banking platform
A105: AL.HW.1TO5Y.CLOSE.MTG | B105: AL.FR.CLO.MTG.PAR | C105: RETAIL.MTG | D105: Loan | E105: Mortgage | F105: Retail
A106: AL.HW.1Y.OPEN.MTG | B106: AL.FR.OPEN.MTG.PAR | C106: RETAIL.MTG | D106: Loan | E106: Mortgage | F106: Retail
A107: AL.HW.6M.CONVERT.MTG | B107: AL.FR.CLO.MTG.PAR | C107: RETAIL.MTG | D107: Loan | E107: Mortgage | F107: Retail
A108: AL.HW.6M.OPEN.MTG | B108: AL.FR.OPEN.MTG.PAR | C108: RETAIL.MTG | D108: Loan | E108: Mortgage | F108: Retail
A109: AL.HW.FIXED.TERM.LN | B109: AL.RET.TERM.LOAN.PAR | C109: RETAIL.TERM.LOAN | D109: Loan | E109: Term loan | F109: Retail
A110: AL.HW.INTERIM.STF | B110: AL.VAR.MTG.RET.PAR | C110: RETAIL.MTG | D110: Loan | E110: Mortgage | F110: Retail
A111: AL.HW.RET.INTERIM.MTG | B111: AL.VAR.MTG.RET.PAR | C111: RETAIL.MTG | D111: Loan | E111: Mortgage | F111: Retail
A112: AL.HW.RET.VAR.MTG | B112: AL.VAR.MTG.RET.PAR | C112: RETAIL.MTG | D112: Loan | E112: Mortgage | F112: Retail
A113: AL.HW.RET.VR.TERM.LN | B113: AL.RET.TERM.LOAN.PAR | C113: RETAIL.TERM.LOAN | D113: Loan | E113: Term loan | F113: Retail
...

Sheet CATEGORY CODE
A1: @ID | B1: CATEGORY
A2: AD.BRO.BB.FR.NONPERS | B2: 6611
A3: AD.BRO.BB.FR.NONPERS.WHS | B3: 6617
A4: AD.BRO.BB.FR.PERS | B4: 6712
A5: AD.BRO.BB.FR.PERS.WHS | B5: 6717
A6: AD.BRO.CSC.NONPERS | B6: 6651
A7: AD.BRO.CSC.NONPERS.WHS | B7: 6656
A8: AD.BRO.CSC.PERS | B8: 6751
A9: AD.BRO.CSC.PERS.WHS | B9: 6756
A10: AD.BRO.FLR.NONPERS | B10: 6602
A11: AD.BRO.FLR.NONPERS.WHS | B11: 6607
A12: AD.BRO.FLR.PERS | B12: 6702
A13: AD.BRO.FLR.PERS.WHS | B13: 6706
... A260: LENDING | B260: 3001

Sheet ONLINE ACCESS
A1: PRODUCT ID | B1: Card Type
A2: AD.CDF.FR.PERS | B2: CDF
A3: AD.CDF.FR.PERS | B3: MOT
A4: AD.CDF.FR.PERS.WHS | B4: CDF
A5: AD.CDF.FR.PERS.WHS | B5: MOT
A6: AD.CDF.RIF.FR.PERS | B6: CDF
A7: AD.CDF.RIF.FR.PERS | B7: MOT
A8: AD.CDF.RSP.FR.PERS | B8: CDF
A9: AD.CDF.RSP.FR.PERS | B9: MOT
A10: AD.CDF.RSP.FR.PERS.WH | B10: CDF
A11: AD.CDF.RSP.FR.PERS.WH | B11: MOT
A12: AD.CDF.TFSA.FR.PER | B12: CDF
... A409: AR.YOUTH.ACCOUNT.STF | B409: FLS

Sheet Accounts Dashboard
B7: This section lists balances that are shown on Account Dashboard.
W9: Account Summary Screens for different Account Types
B11: OLB | J11: OLB | S11: Mobile | T11: (max 2) - STANDARD
B12: Account Type | C12: Fields To Show | J12: Elipsis Options | T12: Quick Buttons
C13: Account Description | D13: Account Number | E13: Available Balance | F13: Current Balance | G13: Outstanding Balance | H13: Due Date | J13: Withdraw Cash | K13: Pay Bill | L13: Pay Due Amount | M13: New Deposit | N13: Transfer | O13: View Statements | P13: Stop Check Payment | Q13: Update Account Settings | R13: Account Alerts | T13: Button 1 | U13: Button 2
B14: Checking | C14: Y | D14: last 4 digits | E14: Y | F14: N | G14: N | H14: N | J14: N | K14: Y | L14: N | M14: N | N14: Y | O14: Y | P14: Y | Q14: N | R14: N | T14: Withdraw Cash | U14: Statements
B15: Savings | C15: Y | D15: last 4 digits | E15: Y | F15: N | G15: N | H15: N | J15: N | K15: N | L15: N | M15: N | N15: Y | O15: Y | P15: Y | Q15: N | R15: N | T15: Withdraw Cash | U15: Statements
B16: Credit Card | C16: Y | D16: last 4 digits | E16: N | F16: Y | G16: N | H16: N | J16: N | K16: Y | L16: N | M16: N | N16: N | O16: Y | P16: N | Q16: N | R16: N | T16: Make a Payment | U16: Statements | V16: -->
B17: Line of Credit | C17: Y | D17: last 4 digits | E17: N | F17: Y | G17: N | H17: N | J17: N | K17: N | L17: Y | M17: N | N17: N | O17: Y | P17: N | Q17: Y | R17: N | T17: Pay Due Amount | U17: Statements
B18: Mortgage | C18: Y | D18: last 4 digits | E18: N | F18: Y | G18: N | H18: N | J18: N | K18: N | L18: Y | M18: N | N18: N | O18: Y | P18: N | Q18: Y | R18: N | T18: Pay Due Amount | U18: Statements
B19: Loan | C19: Y | D19: last 4 digits | E19: N | F19: N | G19: Y | H19: N | J19: N | K19: N | L19: Y | M19: N | N19: N | O19: Y | P19: N | Q19: Y | R19: N | T19: Pay Due Amount | U19: Statements
B20: Deposit | C20: Y | D20: last 4 digits | E20: N | F20: Y | G20: N | H20: N | J20: N | K20: N | L20: N | M20: N | N20: N | O20: Y | P20: N | Q20: Y | R20: N | T20: New Deposit | U20: Statements
D22: | v | M22: | v
B61: Details of fields, buttons, search filters for each of the Accounts
B66: Account Type | C66: Transactions To Show | F66: Search By Transaction Type
C67: Pending Trasactions | D67: Posted Transactions | F67: Deposits | G67: Withdrawals | H67: Checks | I67: Transfers | J67: Bill Pay | K67: P2P Debits | L67: P2P Credits
B68: Checking | C68: Y | D68: Y | F68: Y | G68: Y | H68: Y | I68: Y | J68: Y | K68: N | L68: N
B69: Savings | C69: Y | D69: Y | F69: Y | G69: Y | H69: Y | I69: Y | J69: Y | K69: N | L69: N
B70: Credit Card | C70: Y | D70: Y | F70: Y | G70: Y | H70: Y | I70: Y | J70: Y | K70: N | L70: N
B71: Line of Credit | C71: Y | D71: Y | F71: Y | G71: Y | H71: Y | I71: Y | J71: Y | K71: N | L71: N
B72: Mortgage | C72: N | D72: Y | F72: Y | G72: Y | H72: Y | I72: Y | J72: Y | K72: N | L72: N
B73: Loan | C73: N | D73: Y | F73: Y | G73: Y | H73: Y | I73: Y | J73: Y | K73: N | L73: N
B74: Deposit | C74: N | D74: Y | F74: Y | G74: Y | H74: Y | I74: Y | J74: Y | K74: N | L74: N
F75: Y | G75: Y | H75: Y | I75: Y | J75: Y | K75: N | L75: N
E76: | v
B117: Contextual Menus
B118: Account Type | C118: Contextual Menu Options | M118: What else do you want to do?
C119: Scheduled Transactions | D119: Withdraw Cash | E119: Pay Bill | F119: Pay Due Amount | G119: New Deposit | H119: Transfer | I119: View Statements | J119: Stop Check Payment | K119: Update Account Settings | M119: Withdraw Cash | N119: Pay Bill | O119: Pay Due Amount | P119: New Deposit | Q119: Transfer | R119: View Statements | S119: Stop Check Payment | T119: Update Account Settings | U119: Pay Off a Loan
B120: Checking | C120: Y | D120: N | E120: Y | F120: N | G120: N | H120: Y | I120: N | J120: N | K120: N | M120: N | N120: N | O120: N | P120: N | Q120: N | R120: Y | S120: Y | T120: Y | U120: N
B121: Savings | C121: Y | D121: N | E121: N | F121: N | G121: N | H121: Y | I121: N | J121: N | K121: N | M121: N | N121: N | O121: N | P121: N | Q121: N | R121: Y | S121: Y | T121: Y | U121: N
B122: Credit Card | C122: Y | D122: N | E122: N | F122: N | G122: N | H122: Y | I122: Y | J122: N | K122: N | M122: N | N122: Y | O122: N | P122: N | Q122: N | R122: N | S122: N | T122: Y | U122: N
B123: Line of Credit | C123: N | D123: N | E123: N | F123: Y | G123: N | H123: N | I123: Y | J123: N | K123: Y | M123: N | N123: N | O123: N | P123: N | Q123: N | R123: N | S123: N | T123: Y | U123: Y
B124: Mortgage | C124: N | D124: N | E124: N | F124: Y | G124: N | H124: N | I124: Y | J124: N | K124: Y | M124: N | N124: N | O124: N | P124: N | Q124: N | R124: N | S124: N | T124: Y | U124: Y
B125: Loan | C125: N | D125: N | E125: N | F125: Y | G125: N | H125: N | I125: Y | J125: N | K125: Y | M125: N | N125: N | O125: N | P125: N | Q125: N | R125: N | S125: N | T125: Y | U125: Y
B126: Deposit | C126: N | D126: N | E126: N | F126: N | G126: N | H126: N | I126: Y | J126: N | K126: Y | M126: N | N126: N | O126: N | P126: N | Q126: N | R126: N | S126: N | T126: Y | U126: N
L128: | v

Sheet Account Info
B2: Fields that will be shown on Account Info screen for each of the Accounts
C5: Account Summary | N5: Balance & Interest Detail | AB5: Interest and Maturity Detial | AJ5: Account Info
B6: Account Type | C6: Current Balance | D6: Outstanding Balance | E6: Pending Deposits | F6: Pending Withdrawals | G6: As Of Date | H6: Available Balance | I6: Maturity Date | J6: Interest Earned | K6: Principal Balance | L6: Principal Amount | M6: Current Due | N6: Total Credits (This month) | O6: Total Debits (This Month) | P6: Bond Interest Last Year | Q6: Dividend Paid Last Year | R6: Dividend Rate | S6: Divident Paid (YTD) | T6: Last Paid Dividend | U6: Paid On | V6: Interest Rate | W6: Interest Paid Last Year | X6: Last Payment Amount | Y6: Last Payment Date | Z6: Origination Amount | AA6: Payoff Amount | AB6: Maturity Date | AC6: Maturity Amount | AD6: Maturity Option | AE6: Dividend Paid Last Year | AF6: Dividend Rate | AG6: Divident Paid (YTD) | AH6: Last Paid Dividend | AI6: Paid On | AJ6: Account Number | AK6: Routing Number | AL6: SWIFT Code | AM6: Primary Account Holder | AN6: Joint Account Holder | AO6: IBAN Code
B7: Checking | C7: Y | D7: N | E7: Y | F7: Y | G7: Y | H7: Y | I7: N | J7: N | K7: N | L7: N | M7: N | N7: Y | O7: Y | P7: N | Q7: N | R7: N | S7: N | T7: N | U7: N | V7: Y | W7: Y | X7: N | Y7: N | Z7: N | AA7: N | AB7: N/A | AC7: N/A | AD7: N/A | AE7: N/A | AF7: N/A | AG7: N/A | AH7: N/A | AI7: N/A | AJ7: Y | AK7: Y | AL7: Y | AM7: Y | AN7: Y | AO7: Y
B8: Savings | C8: Y | D8: N | E8: Y | F8: Y | G8: Y | H8: Y | I8: N | J8: N | K8: N | L8: N | M8: N | N8: Y | O8: Y | P8: N | Q8: N | R8: N | S8: N | T8: N | U8: N | V8: Y | W8: Y | X8: N | Y8: N | Z8: N | AA8: N | AB8: N/A | AC8: N/A | AD8: N/A | AE8: N/A | AF8: N/A | AG8: N/A | AH8: N/A | AI8: N/A | AJ8: Y | AK8: Y | AL8: Y | AM8: Y | AN8: Y | AO8: Y
B9: Credit Card | C9: Y | D9: Y | E9: Y | F9: Y | G9: Y | H9: Y | I9: N | J9: N | K9: Y | L9: Y | M9: Y | N9: Y | O9: Y | P9: N | Q9: N | R9: N | S9: N | T9: N | U9: N | V9: Y | W9: Y | X9: Y | Y9: Y | Z9: N | AA9: N | AB9: N/A | AC9: N/A | AD9: N/A | AE9: N/A | AF9: N/A | AG9: N/A | AH9: N/A | AI9: N/A | AJ9: Y | AK9: Y | AL9: N/A | AM9: Y | AN9: Y | AO9: Y
B10: Line of Credit | C10: Y | D10: N | E10: Y | F10: Y | G10: Y | H10: Y | I10: N | J10: N | K10: Y | L10: Y | M10: Y | N10: Y | O10: Y | P10: N | Q10: N | R10: N | S10: N | T10: N | U10: N | V10: Y | W10: Y | X10: Y | Y10: Y | Z10: Y | AA10: Y | AB10: N/A | AC10: N/A | AD10: N/A | AE10: N/A | AF10: N/A | AG10: N/A | AH10: N/A | AI10: N/A | AJ10: Y | AK10: Y | AL10: Y | AM10: Y | AN10: Y | AO10: Y
B11: Mortgage | C11: Y | D11: Y | E11: Y | F11: Y | G11: Y | H11: Y | I11: N | J11: N | K11: Y | L11: Y | M11: Y | N11: Y | O11: Y | P11: N | Q11: N | R11: N | S11: N | T11: N | U11: N | V11: Y | W11: Y | X11: Y | Y11: Y | Z11: Y | AA11: Y | AB11: N/A | AC11: N/A | AD11: N/A | AE11: N/A | AF11: N/A | AG11: N/A | AH11: N/A | AI11: N/A | AJ11: Y | AK11: Y | AL11: N/A | AM11: Y | AN11: Y | AO11: Y
B12: Loan | C12: Y | D12: Y | E12: Y | F12: Y | G12: Y | H12: Y | I12: N | J12: N | K12: Y | L12: Y | M12: Y | N12: Y | O12: Y | P12: N | Q12: N | R12: N | S12: N | T12: N | U12: N | V12: Y | W12: Y | X12: Y | Y12: Y | Z12: Y | AA12: Y | AB12: N/A | AC12: N/A | AD12: N/A | AE12: N/A | AF12: N/A | AG12: N/A | AH12: N/A | AI12: N/A | AJ12: Y | AK12: Y | AL12: N/A | AM12: Y | AN12: Y | AO12: Y
B13: Deposit | C13: Y | D13: N | E13: N | F13: N | G13: Y | H13: Y | I13: Y | J13: Y | K13: N | L13: N | M13: N | N13: N/A | O13: N/A | P13: N/A | Q13: N/A | R13: N/A | S13: N/A | T13: N/A | U13: N/A | V13: N/A | W13: N/A | X13: N/A | Y13: N/A | Z13: N/A | AA13: N/A | AB13: Y | AC13: Y | AD13: Y | AE13: N | AF13: N | AG13: N | AH13: N | AI13: N | AJ13: Y | AK13: Y | AL13: N/A | AM13: Y | AN13: Y | AO13: Y
