Workbook

Sheet Sprint Status Dashboard
A1: Sprint# | B1: 14
A3: Count of User Story #
A4: Status | B4: Total
A5: Decision Updated | B5: 3
A6: In Review | B6: 3
A7: Approved | B7: 26
A8: UI Pending | B8: 2
A9: Grand Total | B9: 34

Sheet DBX Sprint
A1: SOW291, | B1: Sprint# | C1: Sprint Start Date | D1: Sprint End Date | E1: User Story Approval Due Date | F1: Module | G1: Feature | H1: Functionality | I1: SOW Description | J1: User Story # | K1: Status | L1: Decision Date if the Status is "Decision Updated" | M1: Decision Details if the Status is "Decision Updated" | N1: Decision Made by if the Status is "Decision Updated" | O1: Additonal Notes | P1: Story Approval Date
A2: SOW170 | B2: TBD | F2: Transfers | G2: Fund Transfers | H2: Transfer to own account in other financial institutions (Me2Me) | I2: Add a new account in another domestic bank/CU as an external account (recipient) to the profile, by providing account information. Users can transfer funds to the external account once it has been verified and activated. | K2: Decision Updated | L2: 44183 | M2: 12/18/2020 CM: Defer Me2Me from R1 to a post R1 release. This needs to be there with Motive as it is a retail function. Temenos and CWB agreed both recommended deferring M2M, and collectively indicated it would put R1 at risk in the workshop this morning. | N2: Christina Mullin | O2: This needs to be there with Motive as it is a retail function.
A3: SOW190 | B3: TBD | F3: Cheque Management | G3: Stop Cheque Payment | H3: Stop Cheque payment | I3: The Infinity Stop Cheque and Stop Payment function includes a field for the Date of Request Field. The intent of this field is to display the date the stop request was made. This date is captured and sent to T24. However when a user is review the request history, the Date Requested field is not returned from T24. CWB does require this field (should) and a decision is required on how to solution this field. The four options discussed are as follows: • Change the API to return the Date of Request • Suppress the field • Display the date based on what Infinity captures when (needs to be validated if this is technically possible). This would be a temporary solution. • Leave it blank | K3: Decision Updated | M3: The request create date is required. Suppresssing and leaving it blank are not options as date is on the screen and part of the user story. Next step is to ask Temenos what would suffice as a solution. | O3: Neil (1/15/20) set email to Grant to request solution scope)
A4: SOW283 | B4: 11 | F4: Payments & Withdrawals | G4: Pay Business Taxes | H4: Remit Tax | I4: Ability to remit Provincial Business Tax (separate forms from CRA) | J4: 11.1.1 | K4: Approved
A5: SOW283 | B5: 11 | F5: Payments & Withdrawals | G5: Pay Business Taxes | H5: Remit Tax | I5: Ability to remit Provincial Business Tax (separate forms from CRA) | J5: 11.1.2 | K5: Approved | P5: Jan 18-22
A6: SOW283 | B6: 11 | F6: Payments & Withdrawals | G6: Pay Business Taxes | H6: Remit Tax | I6: Ability to remit Provincial Business Tax (separate forms from CRA) | J6: 11.1.3 | K6: Approved
A7: SOW283 | B7: 11 | F7: Payments & Withdrawals | G7: Pay Business Taxes | H7: Remit Tax | I7: Ability to remit Provincial Business Tax (separate forms from CRA) | J7: 11.1.4 | K7: Approved
A8: SOW283 | B8: 11 | F8: Payments & Withdrawals | G8: Pay Business Taxes | H8: Remit Tax | I8: Ability to remit Provincial Business Tax (separate forms from CRA) | J8: 11.1.5 | K8: Approved | P8: 44222
A9: SOW283 | B9: 11 | F9: Payments & Withdrawals | G9: Pay Business Taxes | H9: Remit Tax | I9: Ability to remit Provincial Business Tax (separate forms from CRA) | J9: 11.1.6 | K9: Approved | P9: 44222
A10: SOW70 | B10: 11 | F10: Payments & Withdrawals | G10: CRA Fund Transfer | H10: View CRA Payment History | I10: Ability to view payment history | J10: 11.2.1 | K10: Approved
A11: SOW70 | B11: 11 | F11: Payments & Withdrawals | G11: CRA Fund Transfer | H11: View CRA Payment History | I11: Ability to view payment history | J11: 11.2.2 | K11: Approved
A12: SOW70 | B12: 11 | F12: Payments & Withdrawals | G12: CRA Fund Transfer | H12: View CRA Payment History | I12: Ability to view payment history | J12: 11.2.3 | K12: Approved
A13: SOW71 | B13: 11 | F13: Payments & Withdrawals | G13: CRA Fund Transfer | H13: View CRA Payment History | I13: Ability to view payment history | J13: 11.2.4 | K13: Approved
A14: SOW72 | B14: 11 | F14: Payments & Withdrawals | G14: CRA Fund Transfer | H14: View CRA Payment History | I14: Ability to view payment history | J14: 11.2.5 | K14: Approved
A15: SOW73 | B15: 11 | F15: Payments & Withdrawals | G15: CRA Fund Transfer | H15: View CRA Payment History | I15: Ability to view payment history | J15: 11.2.6 | K15: Approved
A16: SOW83 | B16: 11 | F16: Accounts | G16: Transactions | H16: Pagination | I16: Increase pagination beyond 10 transactions at a time. The requirement is to allow User to see 50 per page. Parameter of the pagination has to be passed to MS, need a cursor value back for next and previous transaction pages. | J16: 11.3.1 | K16: In Review
A17: SOW282 | B17: 11 | F17: Transfers | G17: External Accounts | H17: Manage External Bank accounts | I17: Remove external accounts added for transfers | J17: 1 | K17: In Review
A18: SOW282 | B18: 11 | F18: Transfers | G18: External Accounts | H18: Manage External Bank accounts | I18: Remove external accounts added for transfers | J18: 2 | K18: Draft
A19: SOW60 | B19: 12 | F19: Bill Payment | G19: Bill Pay | H19: Transaction / Payment Receipts | I19: Ability to view list of bill payments, with the option to manage each transaction ( i.e. print and download each receipt). The list can contain the beneficiary name, transaction description, type, from account, transaction ID, date, status, amount | J19: 12.1.1 | K19: In Review
A20: SOW60 | B20: 12 | F20: Bill Payment | G20: Bill Pay | H20: Transaction / Payment Receipts | I20: Ability to view list of bill payments, with the option to manage each transaction ( i.e. print and download each receipt). The list can contain the beneficiary name, transaction description, type, from account, transaction ID, date, status, amount | J20: 12.1.2 | K20: Approved
A21: SOW1000 | B21: 12 | F21: Cheque Management | G21: Stop Payment | H21: Stop payment | I21: Stop Payment for Pre-Authorized Payment | J21: 12.3.1 | K21: Approved
A22: SOW1000 | B22: 12 | F22: Cheque Management | G22: Stop Payment | H22: Stop payment | I22: Stop Payment for Pre-Authorized Payment | J22: 12.3.2 | K22: Approved
A23: SOW1000 | B23: 12 | F23: Cheque Management | G23: Stop Payment | H23: Stop payment | I23: Stop Payment for Pre-Authorized Payment | J23: 12.3.3 | K23: Approved
A24: SOW1000 | B24: 12 | F24: Cheque Management | G24: Stop Payment | H24: Stop payment | I24: Stop Payment for Pre-Authorized Payment | J24: 12.3.4 | K24: Approved
A25: SOW1000 | B25: 12 | F25: Cheque Management | G25: Stop Payment | H25: Stop payment | I25: Stop Payment for Pre-Authorized Payment | J25: 12.3.5 | K25: Approved
A26: SOW1000 | B26: 12 | F26: Cheque Management | G26: Stop Payment | H26: Stop payment | I26: Stop Payment for Pre-Authorized Payment | J26: 12.3.6 | K26: Approved
A27: SOW1000 | B27: 12 | F27: Cheque Management | G27: Stop Payment | H27: Stop payment | I27: Stop Payment for Pre-Authorized Payment | J27: 12.3.7 | K27: UI Pending
A28: SOW1000 | B28: 12 | F28: Cheque Management | G28: Stop Payment | H28: Stop payment | I28: Stop Payment for Pre-Authorized Payment | J28: 12.3.8 | K28: Approved
A29: SOW1000 | B29: 12 | F29: Cheque Management | G29: Stop Payment | H29: Stop payment | I29: Stop Payment for Pre-Authorized Payment | J29: 12.3.9 | K29: Approved
A30: SOW1000 | B30: 12 | F30: Cheque Management | G30: Stop Payment | H30: Stop payment | I30: Stop Payment for Pre-Authorized Payment | J30: 12.3.10 | K30: Approved
A31: SOW1000 | B31: 12 | F31: Cheque Management | G31: Stop Payment | H31: Stop payment | I31: Stop Payment for Pre-Authorized Payment | J31: 12.3.11 | K31: Approved
A32: SOW1000 | B32: 12 | F32: Cheque Management | G32: Stop Payment | H32: Stop payment | I32: Stop Payment for Pre-Authorized Payment | J32: 12.3.12 | K32: Draft | L32: 44187 | M32: Revoke PAP will not be in R1 | N32: Include in Scope to manage multiple statuses for PAP. | O32: removed b/c Stop Cheque is not in r1 1/14/21- Notified Temenos, stories moved to In Draft Status in Confluence
A33: SOW1000 | B33: 12 | F33: Cheque Management | G33: Stop Payment | H33: Stop payment | I33: Stop Payment for Pre-Authorized Payment | J33: 12.3.13 | K33: Approved | L33: 44187 | M33: Revoke PAP will not be in R1 | N33: Include in Scope to manage multiple statuses for PAP. | O33: removed b/c Stop Cheque is not in r1 1/14/21- Notified Temenos, stories moved to In Draft Status in Confluence | P33: 44221
A34: SOW1000 | B34: 12 | F34: Cheque Management | G34: Stop Payment | H34: Stop payment | I34: Stop Payment for Pre-Authorized Payment | J34: 12.3.14 | K34: Approved
A35: SOW1000 | B35: 12 | F35: Cheque Management | G35: Stop Payment | H35: Stop payment | I35: Stop Payment for Pre-Authorized Payment | J35: 12.3.15 | K35: Approved
A36: SOW1000 | B36: 12 | F36: Cheque Management | G36: Stop Payment | H36: Stop payment | I36: Stop Payment for Pre-Authorized Payment | J36: 12.3.16 | K36: Approved
A37: SOW1000 | B37: 12 | F37: Cheque Management | G37: Stop Payment | H37: Stop payment | I37: Stop Payment for Pre-Authorized Payment | J37: 12.3.17 | K37: Approved
A38: SOW1000 | B38: 12 | F38: Cheque Management | G38: Stop Payment | H38: Stop payment | I38: Stop Payment for Pre-Authorized Payment | J38: 12.3.18 | K38: Approved | P38: 44221
A39: SOW97 | B39: 13 | F39: User Interface | G39: Menu | H39: Navigation and Configuration | I39: Deliver a configurable menu in Release 1 (not a customization that would impact future upgrades). They require two sections for money movement at the top hierarchy of the menu structure: Transfers – includes only internal A2A and external A2A transfers) Payments – includes all other payment type CRA (Tax Payments) Bill Pay EFT / ACH eTransfers (P2P) – This mean splitting the transfers module into two and adding restrictions Wires (Domestic and International) CWB requests Product team take this item Note - 9/18 - EFT is no longer in scope for Release 1 and is in the backlog | J39: 13.2.1 | K39: In Review
A40: SOW97 | B40: 13 | F40: User Interface | G40: Menu | H40: Navigation and Configuration | I40: Deliver a configurable menu in Release 1 (not a customization that would impact future upgrades). They require two sections for money movement at the top hierarchy of the menu structure: Transfers – includes only internal A2A and external A2A transfers) Payments – includes all other payment type CRA (Tax Payments) Bill Pay EFT / ACH eTransfers (P2P) – This mean splitting the transfers module into two and adding restrictions Wires (Domestic and International) CWB requests Product team take this item Note - 9/18 - EFT is no longer in scope for Release 1 and is in the backlog | J40: 13.2.2 | K40: Approved
A41: SOW34, SOW35 | B41: 13 | F41: Foreign Exchange | G41: Rate Display | H41: FX Rate Display | I41: Display info on buying or selling US cash, cheques or traveler's cheques exchange rates. (C1 Returns the exchange rates from the institution) FX calculator to assist users while converting foreign currencies to CAD or vice versa - User inputs a value, currency to and from and can generate a quote for the exhange rate. | J41: 13.4.1 | K41: Approved
A42: SOW34, SOW35 | B42: 13 | F42: Foreign Exchange | G42: Rate Display | H42: FX Rate Display | I42: Display info on buying or selling US cash, cheques or traveler's cheques exchange rates. (C1 Returns the exchange rates from the institution) FX calculator to assist users while converting foreign currencies to CAD or vice versa - User inputs a value, currency to and from and can generate a quote for the exhange rate. | J42: 13.4.2 | K42: Approved
A43: SOW34, SOW35 | B43: 13 | F43: Foreign Exchange | G43: Rate Display | H43: FX Rate Display | I43: Display info on buying or selling US cash, cheques or traveler's cheques exchange rates. (C1 Returns the exchange rates from the institution) FX calculator to assist users while converting foreign currencies to CAD or vice versa - User inputs a value, currency to and from and can generate a quote for the exhange rate. | J43: 13.4.3 | K43: Approved
A44: SOW34, SOW35 | B44: 13 | F44: Foreign Exchange | G44: Rate Display | H44: FX Rate Display | I44: Display info on buying or selling US cash, cheques or traveler's cheques exchange rates. (C1 Returns the exchange rates from the institution) FX calculator to assist users while converting foreign currencies to CAD or vice versa - User inputs a value, currency to and from and can generate a quote for the exhange rate. | J44: 13.4.4 | K44: Approved
A45: SOW290, SOW291, SOW292, SOW325 | B45: 15 | F45: Approvals and Request | G45: Transactions | H45: Recall Transactions Expired Transactions List of Approved, Rejected, Pending approval by Business user Include Expired and Recalled into the list of Approved, Rejected, and Pending approval by Business user | I45: See Delivery Plan | J45: 15.1.1 | K45: Approved
A46: SOW290, SOW291, SOW292, SOW325 | B46: 15 | F46: Approvals and Request | G46: Transactions | H46: Recall Transactions Expired Transactions List of Approved, Rejected, Pending approval by Business user Include Expired and Recalled into the list of Approved, Rejected, and Pending approval by Business user | I46: See Delivery Plan | J46: 15.1.2 | K46: Approved
A47: SOW290, SOW291, SOW292, SOW325 | B47: 15 | F47: Approvals and Request | G47: Transactions | H47: Recall Transactions Expired Transactions List of Approved, Rejected, Pending approval by Business user Include Expired and Recalled into the list of Approved, Rejected, and Pending approval by Business user | I47: See Delivery Plan | J47: 15.1.3 | K47: Approved
A48: SOW301 | B48: 13 | F48: Payments & Withdrawals | G48: Pay Business Taxes | H48: Delete CRA Business Account Number | I48: Ability to delete CRA Business Account Number registered to file | J48: 13.6.1 | K48: Approved
A49: SOW301 | B49: 13 | F49: Payments & Withdrawals | G49: Pay Business Taxes | H49: Delete CRA Business Account Number | I49: Ability to delete CRA Business Account Number registered to file | J49: 13.6.2 | K49: Approved
A50: SOW301 | B50: 13 | F50: Payments & Withdrawals | G50: Pay Business Taxes | H50: Delete CRA Business Account Number | I50: Ability to delete CRA Business Account Number registered to file | J50: 13.6.3 | K50: Approved
A51: SOW169 | B51: 11 | F51: Transfers | G51: Fund Transfers | H51: Beneficiary management | I51: View the recipients added to the profile so that the user can initiate transfers to a recipient, edit a recipient’s details, or delete the recipient the user no longer wishes to transfer money to and view the transfer history for a recipient. | J51: 11.6.1 | K51: UI Pending | O51: Neil 1/15/21) Pending UI Approval
A52: SOW169 | B52: 11 | F52: Transfers | G52: Fund Transfers | H52: Beneficiary management | I52: View the recipients added to the profile so that the user can initiate transfers to a recipient, edit a recipient’s details, or delete the recipient the user no longer wishes to transfer money to and view the transfer history for a recipient. | J52: 11.6.2 | K52: Approved
A53: SOW169 | B53: 11 | F53: Transfers | G53: Fund Transfers | H53: Beneficiary management | I53: View the recipients added to the profile so that the user can initiate transfers to a recipient, edit a recipient’s details, or delete the recipient the user no longer wishes to transfer money to and view the transfer history for a recipient. | J53: 11.6.3 | K53: UI Pending
A54: SOW 138 | B54: 10 | F54: Accounts | G54: Transactions | H54: Transaction Search | I54: Transaction Search Current Search Capabilities are documented in the linked documents. Here is a summary: Show most recent 50 transactions (50 is default) User needs to see 50 transactions per page. By Date Range: From Date, to Date (calendar Selector) (five years is max) By Month for the last 12 months. (Drop Down Menu) Advanced Search Options: All Statement Items (default) Deposits only Withdrawals Cheques Bill Payments Search by Descriptor Search by Cheque Number Search by Amount Search by Confirmation Number The User can select the display format . These include: On Screen with details (Date, Description, Credits, Debits, Balance)* this is the default On Screen without details (Date, Limited Description, Credits, Debits, Balance) | J54: 11.4.1 | K54: Approved
A55: SOW 138 | B55: 10 | F55: Accounts | G55: Transactions | H55: Transaction Search | I55: Transaction Search Current Search Capabilities are documented in the linked documents. Here is a summary: Show most recent 50 transactions (50 is default) User needs to see 50 transactions per page. By Date Range: From Date, to Date (calendar Selector) (five years is max) By Month for the last 12 months. (Drop Down Menu) Advanced Search Options: All Statement Items (default) Deposits only Withdrawals Cheques Bill Payments Search by Descriptor Search by Cheque Number Search by Amount Search by Confirmation Number The User can select the display format . These include: On Screen with details (Date, Description, Credits, Debits, Balance)* this is the default On Screen without details (Date, Limited Description, Credits, Debits, Balance) | J55: 11.4.2 | K55: Approved
A56: SOW 138 | B56: 11 | F56: Accounts | G56: Transactions | H56: Transaction Search | I56: Transaction Search Current Search Capabilities are documented in the linked documents. Here is a summary: Show most recent 50 transactions (50 is default) User needs to see 50 transactions per page. By Date Range: From Date, to Date (calendar Selector) (five years is max) By Month for the last 12 months. (Drop Down Menu) Advanced Search Options: All Statement Items (default) Deposits only Withdrawals Cheques Bill Payments Search by Descriptor Search by Cheque Number Search by Amount Search by Confirmation Number The User can select the display format . These include: On Screen with details (Date, Description, Credits, Debits, Balance)* this is the default On Screen without details (Date, Limited Description, Credits, Debits, Balance) | J56: 11.4.3 | K56: Approved
A57: SOW 138 | B57: 11 | F57: Accounts | G57: Transactions | H57: Transaction Search | I57: Transaction Search Current Search Capabilities are documented in the linked documents. Here is a summary: Show most recent 50 transactions (50 is default) User needs to see 50 transactions per page. By Date Range: From Date, to Date (calendar Selector) (five years is max) By Month for the last 12 months. (Drop Down Menu) Advanced Search Options: All Statement Items (default) Deposits only Withdrawals Cheques Bill Payments Search by Descriptor Search by Cheque Number Search by Amount Search by Confirmation Number The User can select the display format . These include: On Screen with details (Date, Description, Credits, Debits, Balance)* this is the default On Screen without details (Date, Limited Description, Credits, Debits, Balance) | J57: 11.4.4 | K57: UI Pending
A58: SOW3 | B58: 14 | F58: Payments & Withdrawals | G58: Pay Business Taxes | H58: Remit Tax | I58: Ability to remit CRA Business Tax (sepearate forms from Provincial Business Tax) | J58: 14.1.1 | K58: Approved | P58: 44221
A59: SOW3 | B59: 14 | F59: Payments & Withdrawals | G59: Pay Business Taxes | H59: Remit Tax | I59: Ability to remit CRA Business Tax (sepearate forms from Provincial Business Tax) | J59: 14.1.2 | K59: Approved | P59: 44222
A60: SOW3 | B60: 14 | F60: Payments & Withdrawals | G60: Pay Business Taxes | H60: Remit Tax | I60: Ability to remit CRA Business Tax (sepearate forms from Provincial Business Tax) | J60: 14.1.3 | K60: UI Pending
A61: SOW3 | B61: 14 | F61: Payments & Withdrawals | G61: Pay Business Taxes | H61: Remit Tax | I61: Ability to remit CRA Business Tax (sepearate forms from Provincial Business Tax) | J61: 14.1.4 | K61: UI Pending
A62: SOW3 | B62: 14 | F62: Payments & Withdrawals | G62: Pay Business Taxes | H62: Remit Tax | I62: Ability to remit CRA Business Tax (sepearate forms from Provincial Business Tax) | J62: 14.1.5 | K62: Approved | P62: 44223
A63: SOW3 | B63: 14 | F63: Payments & Withdrawals | G63: Pay Business Taxes | H63: Remit Tax | I63: Ability to remit CRA Business Tax (sepearate forms from Provincial Business Tax) | J63: 14.1.6 | K63: Approved | P63: 44222
A64: SOW3 | B64: 14 | F64: Payments & Withdrawals | G64: Pay Business Taxes | H64: Remit Tax | I64: Ability to remit CRA Business Tax (sepearate forms from Provincial Business Tax) | J64: 14.1.7 | K64: In Review | P64: 44223
A65: SOW3 | B65: 14 | F65: Payments & Withdrawals | G65: Pay Business Taxes | H65: Remit Tax | I65: Ability to remit CRA Business Tax (sepearate forms from Provincial Business Tax) | J65: 14.1.8 | K65: Approved | P65: 44223
A66: SOW4 | B66: 15 | F66: Payments & Withdrawals | G66: Pay Business Taxes | H66: Remit Tax | I66: Ability to remit CRA Business Tax (sepearate forms from Provincial Business Tax) | J66: 14.1.9 | K66: Approved | P66: 44223
A67: SOW5 | B67: 16 | F67: Payments & Withdrawals | G67: Pay Business Taxes | H67: Remit Tax | I67: Ability to remit CRA Business Tax (sepearate forms from Provincial Business Tax) | J67: 14.1.10 | K67: In Review
A68: SOW6 | B68: 17 | F68: Payments & Withdrawals | G68: Pay Business Taxes | H68: Remit Tax | I68: Ability to remit CRA Business Tax (sepearate forms from Provincial Business Tax) | J68: 14.1.11 | K68: In Review
A69: SOW7 | B69: 18 | F69: Payments & Withdrawals | G69: Pay Business Taxes | H69: Remit Tax | I69: Ability to remit CRA Business Tax (sepearate forms from Provincial Business Tax) | J69: 14.1.12 | K69: In Review
A70: SOW8 | B70: 19 | F70: Payments & Withdrawals | G70: Pay Business Taxes | H70: Remit Tax | I70: Ability to remit CRA Business Tax (sepearate forms from Provincial Business Tax) | J70: 14.1.13 | K70: In Review
A71: SOW9 | B71: 20 | F71: Payments & Withdrawals | G71: Pay Business Taxes | H71: Remit Tax | I71: Ability to remit CRA Business Tax (sepearate forms from Provincial Business Tax) | J71: 14.1.14 | K71: Approved | P71: 44223
A72: SOW10 | B72: 21 | F72: Payments & Withdrawals | G72: Pay Business Taxes | H72: Remit Tax | I72: Ability to remit CRA Business Tax (sepearate forms from Provincial Business Tax) | J72: 14.1.15 | K72: Approved | P72: 44223
A73: SOW11 | B73: 22 | F73: Payments & Withdrawals | G73: Pay Business Taxes | H73: Remit Tax | I73: Ability to remit CRA Business Tax (sepearate forms from Provincial Business Tax) | J73: 14.1.16 | K73: Approved | P73: 44223
A74: SOW12 | B74: 23 | F74: Payments & Withdrawals | G74: Pay Business Taxes | H74: Remit Tax | I74: Ability to remit CRA Business Tax (sepearate forms from Provincial Business Tax) | J74: 14.1.17 | K74: In Review
A75: SOW13 | B75: 24 | F75: Payments & Withdrawals | G75: Pay Business Taxes | H75: Remit Tax | I75: Ability to remit CRA Business Tax (sepearate forms from Provincial Business Tax) | J75: 14.1.18 | K75: In Review
A76: SOW14 | B76: 25 | F76: Payments & Withdrawals | G76: Pay Business Taxes | H76: Remit Tax | I76: Ability to remit CRA Business Tax (sepearate forms from Provincial Business Tax) | J76: 14.1.19 | K76: In Review
A77: SOW15 | B77: 26 | F77: Payments & Withdrawals | G77: Pay Business Taxes | H77: Remit Tax | I77: Ability to remit CRA Business Tax (sepearate forms from Provincial Business Tax) | J77: 14.1.20 | K77: In Review
A78: SOW16 | B78: 27 | F78: Payments & Withdrawals | G78: Pay Business Taxes | H78: Remit Tax | I78: Ability to remit CRA Business Tax (sepearate forms from Provincial Business Tax) | J78: 14.1.21 | K78: Draft
A79: SOW290, SOW291, SOW292, SOW325 | B79: 15 | F79: Approvals and Request | G79: Transactions | H79: Recall Transactions Expired Transactions List of Approved, Rejected, Pending approval by Business user Include Expired and Recalled into the list of Approved, Rejected, and Pending approval by Business user | I79: See Delivery Plan | J79: 15.1.4 | K79: Approved
A80: SOW290, SOW291, SOW292, SOW325 | B80: 15 | F80: Approvals and Request | G80: Transactions | H80: Recall Transactions Expired Transactions List of Approved, Rejected, Pending approval by Business user Include Expired and Recalled into the list of Approved, Rejected, and Pending approval by Business user | I80: See Delivery Plan | J80: 15.1.5 | K80: Approved
A81: SOW290, SOW291, SOW292, SOW325 | B81: 15 | F81: Approvals and Request | G81: Transactions | H81: Recall Transactions Expired Transactions List of Approved, Rejected, Pending approval by Business user Include Expired and Recalled into the list of Approved, Rejected, and Pending approval by Business user | I81: See Delivery Plan | J81: 15.1.6 | K81: Approved
A82: SOW 138 | B82: 10 | F82: Accounts | G82: Transactions | H82: Transaction Search | I82: Transaction Search Current Search Capabilities are documented in the linked documents. Here is a summary: Show most recent 50 transactions (50 is default) User needs to see 50 transactions per page. By Date Range: From Date, to Date (calendar Selector) (five years is max) By Month for the last 12 months. (Drop Down Menu) Advanced Search Options: All Statement Items (default) Deposits only Withdrawals Cheques Bill Payments Search by Descriptor Search by Cheque Number Search by Amount Search by Confirmation Number The User can select the display format . These include: On Screen with details (Date, Description, Credits, Debits, Balance)* this is the default On Screen without details (Date, Limited Description, Credits, Debits, Balance) | J82: 11.4.3
A83: SOW198 | B83: 2 | F83: Customer Service | G83: Contact Us | H83: Click to call or text-message | I83: Ability to call, email the bank. | J83: 2.2.7 | K83: Approved
A84: SOW198 | B84: 2 | F84: Customer Service | G84: Contact Us | H84: Click to call or text-message | I84: Ability to call, email the bank. | J84: 2.2.8 | K84: Approved
A85: SOW68 | B85: 13 | F85: Transfers | G85: Fund Transfers | H85: Cross Currency Transfer | I85: Ability to make cross-currency transfers between Canadian and U.S. dollar accounts | J85: 13.1.1 | K85: Approved | P85: 44218
A86: SOW68 | B86: 13 | F86: Transfers | G86: Fund Transfers | H86: Cross Currency Transfer | I86: Ability to make cross-currency transfers between Canadian and U.S. dollar accounts | J86: 13.1.2 | K86: Approved | P86: 44218
A87: SOW68 | B87: 13 | F87: Transfers | G87: Fund Transfers | H87: Cross Currency Transfer | I87: Ability to make cross-currency transfers between Canadian and U.S. dollar accounts | J87: 13.1.3 | K87: Approved | P87: 44218
A88: SOW68 | B88: 13 | F88: Transfers | G88: Fund Transfers | H88: Cross Currency Transfer | I88: Ability to make cross-currency transfers between Canadian and U.S. dollar accounts | J88: 13.1.4 | K88: Approved | P88: 44221
A89: SOW7 | B89: TBD | F89: Payments & Withdrawals | G89: CRA Fund Transfer | H89: CRA Fund Transfer | I89: Ability to perform multiple transfers to and from different accounts at the same time (similar to bulk transfer - paying one tax payment from multiple accounts or multiple tax payments at the same time). | J89: TBD | K89: Decision Updated | L89: 44214 | M89: Remove this from scope from R1. Let's keep on the list for post R1 and revisit priority later. | N89: Christina Mullin | O89: This is not standard functionality today (for both CWB and Infinity), so it would go against the direction of the project in taking out of the box where applicable. There is limited perceived value from the client perspective given the overall complexity of each tax form making it difficult from a UX viewpoint to offer a bill payment interaction that could encompass multiple tax forms within one experience. Potential reconciliation issues were raised for the back office staff if a single payment was made from multiple accounts given the nature of how T24 process and records these transactions. T24 transact can only process a single payment at one time, which would then require a mechanism by which Infinity/Mule would store the multiple payments in sequential order to be processed by T24 transact. This level of functionality would require development and would introduce additional risk into the payment process. Given the above points and the overall sensitive nature of the CRA payments overall, we are recommending to exclude SOW7 from delivery for the R1 release and potentially entirely from the development schedule.
A90: SOW68 | B90: 13 | F90: Transfers | G90: Fund Transfers | H90: Cross Currency Transfer | I90: Ability to make cross-currency transfers between Canadian and U.S. dollar accounts | J90: 13.1.5 | K90: Approved | P90: 44228
A91: SOW290, SOW291, SOW292, SOW325 | B91: 15 | F91: Approvals and Request | G91: Transactions | H91: Recall Transactions Expired Transactions List of Approved, Rejected, Pending approval by Business user Include Expired and Recalled into the list of Approved, Rejected, and Pending approval by Business user | I91: See Delivery Plan | J91: 15.1.7 | K91: Approved
A92: SOW290, SOW291, SOW292, SOW325 | B92: 15 | F92: Approvals and Request | G92: Transactions | H92: Recall Transactions Expired Transactions List of Approved, Rejected, Pending approval by Business user Include Expired and Recalled into the list of Approved, Rejected, and Pending approval by Business user | I92: See Delivery Plan | J92: 15.1.8 | K92: Approved
A93: SOW290, SOW291, SOW292, SOW325 | B93: 15 | F93: Approvals and Request | G93: Transactions | H93: Recall Transactions Expired Transactions List of Approved, Rejected, Pending approval by Business user Include Expired and Recalled into the list of Approved, Rejected, and Pending approval by Business user | I93: See Delivery Plan | J93: 15.1.9 | K93: Approved
A94: SOW290, SOW291, SOW292, SOW325 | B94: 15 | F94: Approvals and Request | G94: Transactions | H94: Recall Transactions Expired Transactions List of Approved, Rejected, Pending approval by Business user Include Expired and Recalled into the list of Approved, Rejected, and Pending approval by Business user | I94: See Delivery Plan | J94: 15.1.10 | K94: Approved
A95: SOW290, SOW291, SOW292, SOW325 | B95: 15 | F95: Approvals and Request | G95: Transactions | H95: Recall Transactions Expired Transactions List of Approved, Rejected, Pending approval by Business user Include Expired and Recalled into the list of Approved, Rejected, and Pending approval by Business user | I95: See Delivery Plan | J95: 15.1.11 | K95: Approved
A96: SOW142, SOW155, SOW15 | B96: 14 | F96: Bill Payment | G96: Bill Pay Enrollment | H96: Activate Bill Payment for a user | I96: E-Bills | J96: TBD | K96: Decision Updated | L96: 44217 | M96: E-Bill functionality not available for CWB. | N96: Christina Mullin
A97: SOW1000 | B97: 12 | F97: Cheque Management | G97: Stop Payment | H97: Stop payment | I97: Stop Payment for Pre-Authorized Payment | J97: 12.3.19 | K97: Approved | P97: 44221
A98: SOW1000 | B98: 12 | F98: Cheque Management | G98: Stop Payment | H98: Stop payment | I98: Stop Payment for Pre-Authorized Payment | J98: 12.3.20 | K98: Approved
A99: SOW88 | B99: 13 | F99: Payments & Withdrawals | G99: Pay Business Taxes | H99: CRA "Vendor" list for Small Business Banking | I99: Enhance vendor list or create new Vendor list in Spotlight to allow input of Canadian Revenue Agency (CRA) payees. This is specific to Canada. Today, the vendor list that exists in Spotlight is used to Bill Pay vendors, e.g. Gov. of Alberta, etc. Similarly, there are CRA vendors for paying country-wide and provincial payees. This would function like a bill pay vendor list, but needs a focus for CRA vendors. Requirements include everything from the existing vendor list. This is required if we are to move away from storing these in Central 1. | J99: 13.5.1 | K99: Approved | P99: 44221
A100: SOW283 | B100: 11 | F100: Payments & Withdrawals | G100: Pay Business Taxes | H100: Remit Tax | I100: Ability to remit Provincial Business Tax (separate forms from CRA) | J100: 11.1.7 | K100: Approved | P100: 44222
...

Sheet PM Dashboard
C3: OOTB without customization | D3: =COUNTIF('DBX Sprint'!#REF!,"OOTB without Customization") -> #REF! | F3: Functionality items per sprint
C4: OOTB with customization | D4: =COUNTIF('DBX Sprint'!#REF!,"OOTB with Customization") -> #REF! | F4: Sprint 8 | G4: =COUNTIF('DBX Sprint'!$B$1:$B$62,"Sprint 08") -> 0
C5: New Feature | D5: =COUNTIF('DBX Sprint'!#REF!,"New Feature") -> #REF! | F5: Sprint 9 | G5: =COUNTIF('DBX Sprint'!$B$1:$B$62,"Sprint 09") -> 0
C6: Other | D6: =(COUNTA('DBX Sprint'!#REF!))-SUM(D3:D5) -> #REF! | F6: Sprint 10 | G6: =COUNTIF('DBX Sprint'!$B$1:$B$62,"Sprint 10") -> 0
C7: TOTAL | D7: =SUM(D3:D6) -> #REF! | F7: Sprint 11 | G7: =COUNTIF('DBX Sprint'!$B$1:$B$62,"Sprint 11") -> 0
F8: Sprint 12 | G8: =COUNTIF('DBX Sprint'!$B$1:$B$62,"Sprint 12") -> 0
F9: Sprint 13 | G9: =COUNTIF('DBX Sprint'!$B$1:$B$62,"Sprint 13") -> 0
F10: Sprint 14 | G10: =COUNTIF('DBX Sprint'!$B$1:$B$62,"Sprint 14") -> 0
F11: Sprint 15 | G11: =COUNTIF('DBX Sprint'!$B$1:$B$62,"Sprint 15") -> 0
F12: TOTAL | G12: =SUM(G4:G11) -> 0
D19: OOTB without customization | E19: OOTB with customization | F19: New Feature | G19: TOTAL
C20: Sprint 8 | D20: =COUNTIFS('DBX Sprint'!$B$1:$B$62,"Sprint 08",'DBX Sprint'!#REF!,"OOTB without Customization") -> #REF! | E20: =COUNTIFS('DBX Sprint'!$B$1:$B$62,"Sprint 08",'DBX Sprint'!#REF!,"OOTB with Customization") -> #REF! | F20: =COUNTIFS('DBX Sprint'!$B$1:$B$62,"Sprint 08",'DBX Sprint'!#REF!,"New Feature") -> #REF! | G20: =SUM(D20:F20) -> #REF!
C21: Sprint 9 | D21: =COUNTIFS('DBX Sprint'!$B$1:$B$62,"Sprint 09",'DBX Sprint'!#REF!,"OOTB without Customization") -> #REF! | E21: =COUNTIFS('DBX Sprint'!$B$1:$B$62,"Sprint 09",'DBX Sprint'!#REF!,"OOTB with Customization") -> #REF! | F21: =COUNTIFS('DBX Sprint'!$B$1:$B$62,"Sprint 09",'DBX Sprint'!#REF!,"New Feature") -> #REF! | G21: =SUM(D21:F21) -> #REF!
C22: Sprint 10 | D22: =COUNTIFS('DBX Sprint'!$B$1:$B$62,"Sprint 10",'DBX Sprint'!#REF!,"OOTB without Customization") -> #REF! | E22: =COUNTIFS('DBX Sprint'!$B$1:$B$62,"Sprint 10",'DBX Sprint'!#REF!,"OOTB with Customization") -> #REF! | F22: =COUNTIFS('DBX Sprint'!$B$1:$B$62,"Sprint 10",'DBX Sprint'!#REF!,"New Feature") -> #REF! | G22: =SUM(D22:F22) -> #REF!
C23: Sprint 11 | D23: =COUNTIFS('DBX Sprint'!$B$1:$B$62,"Sprint 11",'DBX Sprint'!#REF!,"OOTB without Customization") -> #REF! | E23: =COUNTIFS('DBX Sprint'!$B$1:$B$62,"Sprint 11",'DBX Sprint'!#REF!,"OOTB with Customization") -> #REF! | F23: =COUNTIFS('DBX Sprint'!$B$1:$B$62,"Sprint 11",'DBX Sprint'!#REF!,"New Feature") -> #REF! | G23: =SUM(D23:F23) -> #REF!
C24: Sprint 12 | D24: =COUNTIFS('DBX Sprint'!$B$1:$B$62,"Sprint 12",'DBX Sprint'!#REF!,"OOTB without Customization") -> #REF! | E24: =COUNTIFS('DBX Sprint'!$B$1:$B$62,"Sprint 12",'DBX Sprint'!#REF!,"OOTB with Customization") -> #REF! | F24: =COUNTIFS('DBX Sprint'!$B$1:$B$62,"Sprint 12",'DBX Sprint'!#REF!,"New Feature") -> #REF! | G24: =SUM(D24:F24) -> #REF!
C25: Sprint 13 | D25: =COUNTIFS('DBX Sprint'!$B$1:$B$62,"Sprint 13",'DBX Sprint'!#REF!,"OOTB without Customization") -> #REF! | E25: =COUNTIFS('DBX Sprint'!$B$1:$B$62,"Sprint 13",'DBX Sprint'!#REF!,"OOTB with Customization") -> #REF! | F25: =COUNTIFS('DBX Sprint'!$B$1:$B$62,"Sprint 13",'DBX Sprint'!#REF!,"New Feature") -> #REF! | G25: =SUM(D25:F25) -> #REF!
C26: Sprint 14 | D26: =COUNTIFS('DBX Sprint'!$B$1:$B$62,"Sprint 14",'DBX Sprint'!#REF!,"OOTB without Customization") -> #REF! | E26: =COUNTIFS('DBX Sprint'!$B$1:$B$62,"Sprint 14",'DBX Sprint'!#REF!,"OOTB with Customization") -> #REF! | F26: =COUNTIFS('DBX Sprint'!$B$1:$B$62,"Sprint 14",'DBX Sprint'!#REF!,"New Feature") -> #REF! | G26: =SUM(D26:F26) -> #REF!
C27: Sprint 15 | D27: =COUNTIFS('DBX Sprint'!$B$1:$B$62,"Sprint 15",'DBX Sprint'!#REF!,"OOTB without Customization") -> #REF! | E27: =COUNTIFS('DBX Sprint'!$B$1:$B$62,"Sprint 15",'DBX Sprint'!#REF!,"OOTB with Customization") -> #REF! | F27: =COUNTIFS('DBX Sprint'!$B$1:$B$62,"Sprint 15",'DBX Sprint'!#REF!,"New Feature") -> #REF! | G27: =SUM(D27:F27) -> #REF!
C28: TOTAL | D28: =SUM(D20:D27) -> #REF! | E28: =SUM(E20:E27) -> #REF! | F28: =SUM(F20:F27) -> #REF! | G28: =SUM(G20:G27) -> #REF!
C32: T24 Data mapping | I32: Technical Design | O32: Services/RAML Definition | U32: UI/UX | AA32: User Story | AG32: CWB Story Approval | AM32: Mulesoft and third-party
C33: Completed | D33: Overdue | E33: Due Tomorrow | F33: Due 2-5 days from today | G33: Due 6-10 days from today | I33: Completed | J33: Overdue | K33: Due Tomorrow | L33: Due 2-5 days from today | M33: Due 6-10 days from today | O33: Completed | P33: Overdue | Q33: Due Tomorrow | R33: Due 2-5 days from today | S33: Due 6-10 days from today | U33: Completed | V33: Overdue | W33: Due Tomorrow | X33: Due 2-5 days from today | Y33: Due 6-10 days from today | AA33: Completed | AB33: Overdue | AC33: Due Tomorrow | AD33: Due 2-5 days from today | AE33: Due 6-10 days from today | AG33: Completed | AH33: Overdue | AI33: Due Tomorrow | AJ33: Due 2-5 days from today | AK33: Due 6-10 days from today | AM33: Completed | AN33: Overdue | AO33: Due Tomorrow | AP33: Due 2-5 days from today | AQ33: Due 6-10 days from today
C34: {=IFERROR(INDEX('DBX Sprint'!$A$7:$K$62, SMALL(IF((INDEX('DBX Sprint'!$A$7:$K$62, ,13)=("Complete"))*(INDEX('DBX Sprint'!$A$7:$K$62, ,13)="Complete"),MATCH(ROW('DBX Sprint'!$A$7:$K$62),ROW('DBX Sprint'!$A$7:$K$62)),""),ROWS(C$34:$C34)),COLUMNS('DBX Sprint'!$A$1:A1)),"")} | D34: {=IFERROR(INDEX('DBX Sprint'!$A$7:$K$62, SMALL(IF((INDEX('DBX Sprint'!$A$7:$K$62, ,13)<(TODAY()))*(INDEX('DBX Sprint'!$A$7:$K$62, ,13)<>"Complete"),MATCH(ROW('DBX Sprint'!$A$7:$K$62),ROW('DBX Sprint'!$A$7:$K$62)),""),ROWS(D$34:$D34)),COLUMNS('DBX Sprint'!$A$1:A1)),"")} | E34: {=IFERROR(INDEX('DBX Sprint'!$A$7:$K$62, SMALL(IF((INDEX('DBX Sprint'!$A$7:$K$62, ,13)<=(TODAY()+1))*(INDEX('DBX Sprint'!$A$7:$K$62, ,13)>=TODAY()),MATCH(ROW('DBX Sprint'!$A$7:$K$62),ROW('DBX Sprint'!$A$7:$K$62)),""),ROWS(E$34:$E34)),COLUMNS('DBX Sprint'!$A$1:A1)),"")} | F34: {=IFERROR(INDEX('DBX Sprint'!$A$7:$K$62, SMALL(IF((INDEX('DBX Sprint'!$A$7:$K$62, ,13)<=(TODAY()+5))*(INDEX('DBX Sprint'!$A$7:$K$62, ,13)>(TODAY()+1)),MATCH(ROW('DBX Sprint'!$A$7:$K$62),ROW('DBX Sprint'!$A$7:$K$62)),""),ROWS($F$34:F34)),COLUMNS('DBX Sprint'!$A$1:A1)),"")} | G34: {=IFERROR(INDEX('DBX Sprint'!$A$7:$K$62, SMALL(IF((INDEX('DBX Sprint'!$A$7:$K$62, ,13)<=(TODAY()+10))*(INDEX('DBX Sprint'!$A$7:$K$62, ,13)>(TODAY()+5)),MATCH(ROW('DBX Sprint'!$A$7:$K$62),ROW('DBX Sprint'!$A$7:$K$62)),""),ROWS($G$34:G34)),COLUMNS('DBX Sprint'!$A$1:A1)),"")} | I34: {=IFERROR(INDEX('DBX Sprint'!$A$7:$K$62, SMALL(IF((INDEX('DBX Sprint'!$A$7:$K$62, ,16)=("Complete"))*(INDEX('DBX Sprint'!$A$7:$K$62, ,16)="Complete"),MATCH(ROW('DBX Sprint'!$A$7:$K$62),ROW('DBX Sprint'!$A$7:$K$62)),""),ROWS($I$34:I34)),COLUMNS('DBX Sprint'!$A$1:A1)),"")} | J34: {=IFERROR(INDEX('DBX Sprint'!$A$7:$K$62, SMALL(IF((INDEX('DBX Sprint'!$A$7:$K$62, ,16)<(TODAY()))*(INDEX('DBX Sprint'!$A$7:$K$62, ,16)<>"Complete"),MATCH(ROW('DBX Sprint'!$A$7:$K$62),ROW('DBX Sprint'!$A$7:$K$62)),""),ROWS($J$34:J34)),COLUMNS('DBX Sprint'!$A$1:A1)),"")} | K34: {=IFERROR(INDEX('DBX Sprint'!$A$7:$K$62, SMALL(IF((INDEX('DBX Sprint'!$A$7:$K$62, ,16)<=(TODAY()+1))*(INDEX('DBX Sprint'!$A$7:$K$62, ,16)>=TODAY()),MATCH(ROW('DBX Sprint'!$A$7:$K$62),ROW('DBX Sprint'!$A$7:$K$62)),""),ROWS($K$34:K34)),COLUMNS('DBX Sprint'!$A$1:A1)),"")} | L34: {=IFERROR(INDEX('DBX Sprint'!$A$7:$K$62, SMALL(IF((INDEX('DBX Sprint'!$A$7:$K$62, ,16)<=(TODAY()+5))*(INDEX('DBX Sprint'!$A$7:$K$62, ,16)>(TODAY()+1)),MATCH(ROW('DBX Sprint'!$A$7:$K$62),ROW('DBX Sprint'!$A$7:$K$62)),""),ROWS($L$34:L34)),COLUMNS('DBX Sprint'!$A$1:A1)),"")} | M34: {=IFERROR(INDEX('DBX Sprint'!$A$7:$K$62, SMALL(IF((INDEX('DBX Sprint'!$A$7:$K$62, ,16)<=(TODAY()+10))*(INDEX('DBX Sprint'!$A$7:$K$62, ,16)>(TODAY()+5)),MATCH(ROW('DBX Sprint'!$A$7:$K$62),ROW('DBX Sprint'!$A$7:$K$62)),""),ROWS($M$34:M34)),COLUMNS('DBX Sprint'!$A$1:A1)),"")} | O34: {=IFERROR(INDEX('DBX Sprint'!$A$7:$K$62, SMALL(IF((INDEX('DBX Sprint'!$A$7:$K$62, ,19)=("Complete"))*(INDEX('DBX Sprint'!$A$7:$K$62, ,19)="Complete"),MATCH(ROW('DBX Sprint'!$A$7:$K$62),ROW('DBX Sprint'!$A$7:$K$62)),""),ROWS($O$34:O34)),COLUMNS('DBX Sprint'!$A$1:A1)),"")} | P34: {=IFERROR(INDEX('DBX Sprint'!$A$7:$K$62, SMALL(IF((INDEX('DBX Sprint'!$A$7:$K$62, ,19)<(TODAY()))*(INDEX('DBX Sprint'!$A$7:$K$62, ,19)<>"Complete"),MATCH(ROW('DBX Sprint'!$A$7:$K$62),ROW('DBX Sprint'!$A$7:$K$62)),""),ROWS($P$34:P34)),COLUMNS('DBX Sprint'!$A$1:A1)),"")} | Q34: {=IFERROR(INDEX('DBX Sprint'!$A$7:$K$62, SMALL(IF((INDEX('DBX Sprint'!$A$7:$K$62, ,19)<=(TODAY()+1))*(INDEX('DBX Sprint'!$A$7:$K$62, ,19)>=TODAY()),MATCH(ROW('DBX Sprint'!$A$7:$K$62),ROW('DBX Sprint'!$A$7:$K$62)),""),ROWS($Q$34:Q34)),COLUMNS('DBX Sprint'!$A$1:A1)),"")} | R34: {=IFERROR(INDEX('DBX Sprint'!$A$7:$K$62, SMALL(IF((INDEX('DBX Sprint'!$A$7:$K$62, ,19)<=(TODAY()+5))*(INDEX('DBX Sprint'!$A$7:$K$62, ,19)>(TODAY()+1)),MATCH(ROW('DBX Sprint'!$A$7:$K$62),ROW('DBX Sprint'!$A$7:$K$62)),""),ROWS($R$34:R34)),COLUMNS('DBX Sprint'!$A$1:A1)),"")} | S34: {=IFERROR(INDEX('DBX Sprint'!$A$7:$K$62, SMALL(IF((INDEX('DBX Sprint'!$A$7:$K$62, ,19)<=(TODAY()+10))*(INDEX('DBX Sprint'!$A$7:$K$62, ,19)>(TODAY()+5)),MATCH(ROW('DBX Sprint'!$A$7:$K$62),ROW('DBX Sprint'!$A$7:$K$62)),""),ROWS($S$34:S34)),COLUMNS('DBX Sprint'!$A$1:A1)),"")} | U34: {=IFERROR(INDEX('DBX Sprint'!$A$7:$K$62, SMALL(IF((INDEX('DBX Sprint'!$A$7:$K$62, ,22)=("Complete"))*(INDEX('DBX Sprint'!$A$7:$K$62, ,22)="Complete"),MATCH(ROW('DBX Sprint'!$A$7:$K$62),ROW('DBX Sprint'!$A$7:$K$62)),""),ROWS($U$34:U34)),COLUMNS('DBX Sprint'!$A$1:A1)),"")} | V34: {=IFERROR(INDEX('DBX Sprint'!$A$7:$K$62, SMALL(IF((INDEX('DBX Sprint'!$A$7:$K$62, ,22)<(TODAY()))*(INDEX('DBX Sprint'!$A$7:$K$62, ,22)<>"Complete"),MATCH(ROW('DBX Sprint'!$A$7:$K$62),ROW('DBX Sprint'!$A$7:$K$62)),""),ROWS($V$34:V34)),COLUMNS('DBX Sprint'!$A$1:A1)),"")} | W34: {=IFERROR(INDEX('DBX Sprint'!$A$7:$K$62, SMALL(IF((INDEX('DBX Sprint'!$A$7:$K$62, ,22)<=(TODAY()+1))*(INDEX('DBX Sprint'!$A$7:$K$62, ,22)>=TODAY()),MATCH(ROW('DBX Sprint'!$A$7:$K$62),ROW('DBX Sprint'!$A$7:$K$62)),""),ROWS($W$34:W34)),COLUMNS('DBX Sprint'!$A$1:A1)),"")} | X34: {=IFERROR(INDEX('DBX Sprint'!$A$7:$K$62, SMALL(IF((INDEX('DBX Sprint'!$A$7:$K$62, ,22)<=(TODAY()+5))*(INDEX('DBX Sprint'!$A$7:$K$62, ,22)>(TODAY()+1)),MATCH(ROW('DBX Sprint'!$A$7:$K$62),ROW('DBX Sprint'!$A$7:$K$62)),""),ROWS($X$34:X34)),COLUMNS('DBX Sprint'!$A$1:A1)),"")} | Y34: {=IFERROR(INDEX('DBX Sprint'!$A$7:$K$62, SMALL(IF((INDEX('DBX Sprint'!$A$7:$K$62, ,22)<=(TODAY()+10))*(INDEX('DBX Sprint'!$A$7:$K$62, ,22)>(TODAY()+5)),MATCH(ROW('DBX Sprint'!$A$7:$K$62),ROW('DBX Sprint'!$A$7:$K$62)),""),ROWS($Y$34:Y34)),COLUMNS('DBX Sprint'!$A$1:A1)),"")} | AA34: {=IFERROR(INDEX('DBX Sprint'!$A$7:$K$62, SMALL(IF((INDEX('DBX Sprint'!$A$7:$K$62, ,25)=("Complete"))*(INDEX('DBX Sprint'!$A$7:$K$62, ,25)="Complete"),MATCH(ROW('DBX Sprint'!$A$7:$K$62),ROW('DBX Sprint'!$A$7:$K$62)),""),ROWS($AA$34:AA34)),COLUMNS('DBX Sprint'!$A$1:A1)),"")} | AB34: {=IFERROR(INDEX('DBX Sprint'!$A$7:$K$62, SMALL(IF((INDEX('DBX Sprint'!$A$7:$K$62, ,25)<(TODAY()))*(INDEX('DBX Sprint'!$A$7:$K$62, ,25)<>"Complete"),MATCH(ROW('DBX Sprint'!$A$7:$K$62),ROW('DBX Sprint'!$A$7:$K$62)),""),ROWS($AB$34:AB34)),COLUMNS('DBX Sprint'!$A$1:A1)),"")} | AC34: {=IFERROR(INDEX('DBX Sprint'!$A$7:$K$62, SMALL(IF((INDEX('DBX Sprint'!$A$7:$K$62, ,25)<=(TODAY()+1))*(INDEX('DBX Sprint'!$A$7:$K$62, ,25)>=TODAY()),MATCH(ROW('DBX Sprint'!$A$7:$K$62),ROW('DBX Sprint'!$A$7:$K$62)),""),ROWS($AC$34:AC34)),COLUMNS('DBX Sprint'!$A$1:A1)),"")} | AD34: {=IFERROR(INDEX('DBX Sprint'!$A$7:$K$62, SMALL(IF((INDEX('DBX Sprint'!$A$7:$K$62, ,25)<=(TODAY()+5))*(INDEX('DBX Sprint'!$A$7:$K$62, ,25)>(TODAY()+1)),MATCH(ROW('DBX Sprint'!$A$7:$K$62),ROW('DBX Sprint'!$A$7:$K$62)),""),ROWS($AD$34:AD34)),COLUMNS('DBX Sprint'!$A$1:A1)),"")} | AE34: {=IFERROR(INDEX('DBX Sprint'!$A$7:$K$62, SMALL(IF((INDEX('DBX Sprint'!$A$7:$K$62, ,25)<=(TODAY()+10))*(INDEX('DBX Sprint'!$A$7:$K$62, ,25)>(TODAY()+5)),MATCH(ROW('DBX Sprint'!$A$7:$K$62),ROW('DBX Sprint'!$A$7:$K$62)),""),ROWS($AE$34:AE34)),COLUMNS('DBX Sprint'!$A$1:A1)),"")} | AG34: {=IFERROR(INDEX('DBX Sprint'!$A$7:$K$62, SMALL(IF((INDEX('DBX Sprint'!$A$7:$K$62, ,29)=("Complete"))*(INDEX('DBX Sprint'!$A$7:$K$62, ,29)="Complete"),MATCH(ROW('DBX Sprint'!$A$7:$K$62),ROW('DBX Sprint'!$A$7:$K$62)),""),ROWS($AG$34:AG34)),COLUMNS('DBX Sprint'!$A$1:A1)),"")} | AH34: {=IFERROR(INDEX('DBX Sprint'!$A$7:$K$62, SMALL(IF((INDEX('DBX Sprint'!$A$7:$K$62, ,29)<(TODAY()))*(INDEX('DBX Sprint'!$A$7:$K$62, ,29)<>"Complete"),MATCH(ROW('DBX Sprint'!$A$7:$K$62),ROW('DBX Sprint'!$A$7:$K$62)),""),ROWS($AH$34:AH34)),COLUMNS('DBX Sprint'!$A$1:A1)),"")} | AI34: {=IFERROR(INDEX('DBX Sprint'!$A$7:$K$62, SMALL(IF((INDEX('DBX Sprint'!$A$7:$K$62, ,29)<=(TODAY()+1))*(INDEX('DBX Sprint'!$A$7:$K$62, ,29)>=TODAY()),MATCH(ROW('DBX Sprint'!$A$7:$K$62),ROW('DBX Sprint'!$A$7:$K$62)),""),ROWS($AI$34:AI34)),COLUMNS('DBX Sprint'!$A$1:A1)),"")} | AJ34: {=IFERROR(INDEX('DBX Sprint'!$A$7:$K$62, SMALL(IF((INDEX('DBX Sprint'!$A$7:$K$62, ,29)<=(TODAY()+5))*(INDEX('DBX Sprint'!$A$7:$K$62, ,29)>(TODAY()+1)),MATCH(ROW('DBX Sprint'!$A$7:$K$62),ROW('DBX Sprint'!$A$7:$K$62)),""),ROWS($AJ$34:AJ34)),COLUMNS('DBX Sprint'!$A$1:A1)),"")} | AK34: {=IFERROR(INDEX('DBX Sprint'!$A$7:$K$62, SMALL(IF((INDEX('DBX Sprint'!$A$7:$K$62, ,29)<=(TODAY()+10))*(INDEX('DBX Sprint'!$A$7:$K$62, ,29)>(TODAY()+5)),MATCH(ROW('DBX Sprint'!$A$7:$K$62),ROW('DBX Sprint'!$A$7:$K$62)),""),ROWS($AK$34:AK34)),COLUMNS('DBX Sprint'!$A$1:A1)),"")} | AM34: {=IFERROR(INDEX('DBX Sprint'!$A$7:$K$62, SMALL(IF((INDEX('DBX Sprint'!$A$7:$K$62, ,32)=("Complete"))*(INDEX('DBX Sprint'!$A$7:$K$62, ,32)="Complete"),MATCH(ROW('DBX Sprint'!$A$7:$K$62),ROW('DBX Sprint'!$A$7:$K$62)),""),ROWS($AM$34:AM34)),COLUMNS('DBX Sprint'!$A$1:A1)),"")} | AN34: {=IFERROR(INDEX('DBX Sprint'!$A$7:$K$62, SMALL(IF((INDEX('DBX Sprint'!$A$7:$K$62, ,32)<(TODAY()))*(INDEX('DBX Sprint'!$A$7:$K$62, ,32)<>"Complete"),MATCH(ROW('DBX Sprint'!$A$7:$K$62),ROW('DBX Sprint'!$A$7:$K$62)),""),ROWS($AN$34:AN34)),COLUMNS('DBX Sprint'!$A$1:A1)),"")} | AO34: {=IFERROR(INDEX('DBX Sprint'!$A$7:$K$62, SMALL(IF((INDEX('DBX Sprint'!$A$7:$K$62, ,32)<=(TODAY()+1))*(INDEX('DBX Sprint'!$A$7:$K$62, ,32)>=TODAY()),MATCH(ROW('DBX Sprint'!$A$7:$K$62),ROW('DBX Sprint'!$A$7:$K$62)),""),ROWS($AO$34:AO34)),COLUMNS('DBX Sprint'!$A$1:A1)),"")} | AP34: {=IFERROR(INDEX('DBX Sprint'!$A$7:$K$62, SMALL(IF((INDEX('DBX Sprint'!$A$7:$K$62, ,32)<=(TODAY()+5))*(INDEX('DBX Sprint'!$A$7:$K$62, ,32)>(TODAY()+1)),MATCH(ROW('DBX Sprint'!$A$7:$K$62),ROW('DBX Sprint'!$A$7:$K$62)),""),ROWS($AP$34:AP34)),COLUMNS('DBX Sprint'!$A$1:A1)),"")} | AQ34: {=IFERROR(INDEX('DBX Sprint'!$A$7:$K$62, SMALL(IF((INDEX('DBX Sprint'!$A$7:$K$62, ,32)<=(TODAY()+10))*(INDEX('DBX Sprint'!$A$7:$K$62, ,32)>(TODAY()+5)),MATCH(ROW('DBX Sprint'!$A$7:$K$62),ROW('DBX Sprint'!$A$7:$K$62)),""),ROWS($AQ$34:AQ34)),COLUMNS('DBX Sprint'!$A$1:A1)),"")}
C35: {=IFERROR(INDEX('DBX Sprint'!$A$7:$K$62, SMALL(IF((INDEX('DBX Sprint'!$A$7:$K$62, ,13)=("Complete"))*(INDEX('DBX Sprint'!$A$7:$K$62, ,13)="Complete"),MATCH(ROW('DBX Sprint'!$A$7:$K$62),ROW('DBX Sprint'!$A$7:$K$62)),""),ROWS(C$34:$C35)),COLUMNS('DBX Sprint'!$A$1:A7)),"")} | D35: {=IFERROR(INDEX('DBX Sprint'!$A$7:$K$62, SMALL(IF((INDEX('DBX Sprint'!$A$7:$K$62, ,13)<(TODAY()))*(INDEX('DBX Sprint'!$A$7:$K$62, ,13)<>"Complete"),MATCH(ROW('DBX Sprint'!$A$7:$K$62),ROW('DBX Sprint'!$A$7:$K$62)),""),ROWS(D$34:$D35)),COLUMNS('DBX Sprint'!$A$1:A7)),"")} | E35: {=IFERROR(INDEX('DBX Sprint'!$A$7:$K$62, SMALL(IF((INDEX('DBX Sprint'!$A$7:$K$62, ,13)<=(TODAY()+1))*(INDEX('DBX Sprint'!$A$7:$K$62, ,13)>=TODAY()),MATCH(ROW('DBX Sprint'!$A$7:$K$62),ROW('DBX Sprint'!$A$7:$K$62)),""),ROWS(E$34:$E35)),COLUMNS('DBX Sprint'!$A$1:A7)),"")} | F35: {=IFERROR(INDEX('DBX Sprint'!$A$7:$K$62, SMALL(IF((INDEX('DBX Sprint'!$A$7:$K$62, ,13)<=(TODAY()+5))*(INDEX('DBX Sprint'!$A$7:$K$62, ,13)>(TODAY()+1)),MATCH(ROW('DBX Sprint'!$A$7:$K$62),ROW('DBX Sprint'!$A$7:$K$62)),""),ROWS($F$34:F35)),COLUMNS('DBX Sprint'!$A$1:A7)),"")} | G35: {=IFERROR(INDEX('DBX Sprint'!$A$7:$K$62, SMALL(IF((INDEX('DBX Sprint'!$A$7:$K$62, ,13)<=(TODAY()+10))*(INDEX('DBX Sprint'!$A$7:$K$62, ,13)>(TODAY()+5)),MATCH(ROW('DBX Sprint'!$A$7:$K$62),ROW('DBX Sprint'!$A$7:$K$62)),""),ROWS($G$34:G35)),COLUMNS('DBX Sprint'!$A$1:A7)),"")} | I35: {=IFERROR(INDEX('DBX Sprint'!$A$7:$K$62, SMALL(IF((INDEX('DBX Sprint'!$A$7:$K$62, ,16)=("Complete"))*(INDEX('DBX Sprint'!$A$7:$K$62, ,16)="Complete"),MATCH(ROW('DBX Sprint'!$A$7:$K$62),ROW('DBX Sprint'!$A$7:$K$62)),""),ROWS($I$34:I35)),COLUMNS('DBX Sprint'!$A$1:A7)),"")} | J35: {=IFERROR(INDEX('DBX Sprint'!$A$7:$K$62, SMALL(IF((INDEX('DBX Sprint'!$A$7:$K$62, ,16)<(TODAY()))*(INDEX('DBX Sprint'!$A$7:$K$62, ,16)<>"Complete"),MATCH(ROW('DBX Sprint'!$A$7:$K$62),ROW('DBX Sprint'!$A$7:$K$62)),""),ROWS($J$34:J35)),COLUMNS('DBX Sprint'!$A$1:A7)),"")} | K35: {=IFERROR(INDEX('DBX Sprint'!$A$7:$K$62, SMALL(IF((INDEX('DBX Sprint'!$A$7:$K$62, ,16)<=(TODAY()+1))*(INDEX('DBX Sprint'!$A$7:$K$62, ,16)>=TODAY()),MATCH(ROW('DBX Sprint'!$A$7:$K$62),ROW('DBX Sprint'!$A$7:$K$62)),""),ROWS($K$34:K35)),COLUMNS('DBX Sprint'!$A$1:A7)),"")} | L35: {=IFERROR(INDEX('DBX Sprint'!$A$7:$K$62, SMALL(IF((INDEX('DBX Sprint'!$A$7:$K$62, ,16)<=(TODAY()+5))*(INDEX('DBX Sprint'!$A$7:$K$62, ,16)>(TODAY()+1)),MATCH(ROW('DBX Sprint'!$A$7:$K$62),ROW('DBX Sprint'!$A$7:$K$62)),""),ROWS($L$34:L35)),COLUMNS('DBX Sprint'!$A$1:A7)),"")} | M35: {=IFERROR(INDEX('DBX Sprint'!$A$7:$K$62, SMALL(IF((INDEX('DBX Sprint'!$A$7:$K$62, ,16)<=(TODAY()+10))*(INDEX('DBX Sprint'!$A$7:$K$62, ,16)>(TODAY()+5)),MATCH(ROW('DBX Sprint'!$A$7:$K$62),ROW('DBX Sprint'!$A$7:$K$62)),""),ROWS($M$34:M35)),COLUMNS('DBX Sprint'!$A$1:A7)),"")} | O35: {=IFERROR(INDEX('DBX Sprint'!$A$7:$K$62, SMALL(IF((INDEX('DBX Sprint'!$A$7:$K$62, ,19)=("Complete"))*(INDEX('DBX Sprint'!$A$7:$K$62, ,19)="Complete"),MATCH(ROW('DBX Sprint'!$A$7:$K$62),ROW('DBX Sprint'!$A$7:$K$62)),""),ROWS($O$34:O35)),COLUMNS('DBX Sprint'!$A$1:A7)),"")} | P35: {=IFERROR(INDEX('DBX Sprint'!$A$7:$K$62, SMALL(IF((INDEX('DBX Sprint'!$A$7:$K$62, ,19)<(TODAY()))*(INDEX('DBX Sprint'!$A$7:$K$62, ,19)<>"Complete"),MATCH(ROW('DBX Sprint'!$A$7:$K$62),ROW('DBX Sprint'!$A$7:$K$62)),""),ROWS($P$34:P35)),COLUMNS('DBX Sprint'!$A$1:A7)),"")} | Q35: {=IFERROR(INDEX('DBX Sprint'!$A$7:$K$62, SMALL(IF((INDEX('DBX Sprint'!$A$7:$K$62, ,19)<=(TODAY()+1))*(INDEX('DBX Sprint'!$A$7:$K$62, ,19)>=TODAY()),MATCH(ROW('DBX Sprint'!$A$7:$K$62),ROW('DBX Sprint'!$A$7:$K$62)),""),ROWS($Q$34:Q35)),COLUMNS('DBX Sprint'!$A$1:A7)),"")} | R35: {=IFERROR(INDEX('DBX Sprint'!$A$7:$K$62, SMALL(IF((INDEX('DBX Sprint'!$A$7:$K$62, ,19)<=(TODAY()+5))*(INDEX('DBX Sprint'!$A$7:$K$62, ,19)>(TODAY()+1)),MATCH(ROW('DBX Sprint'!$A$7:$K$62),ROW('DBX Sprint'!$A$7:$K$62)),""),ROWS($R$34:R35)),COLUMNS('DBX Sprint'!$A$1:A7)),"")} | S35: {=IFERROR(INDEX('DBX Sprint'!$A$7:$K$62, SMALL(IF((INDEX('DBX Sprint'!$A$7:$K$62, ,19)<=(TODAY()+10))*(INDEX('DBX Sprint'!$A$7:$K$62, ,19)>(TODAY()+5)),MATCH(ROW('DBX Sprint'!$A$7:$K$62),ROW('DBX Sprint'!$A$7:$K$62)),""),ROWS($S$34:S35)),COLUMNS('DBX Sprint'!$A$1:A7)),"")} | U35: {=IFERROR(INDEX('DBX Sprint'!$A$7:$K$62, SMALL(IF((INDEX('DBX Sprint'!$A$7:$K$62, ,22)=("Complete"))*(INDEX('DBX Sprint'!$A$7:$K$62, ,22)="Complete"),MATCH(ROW('DBX Sprint'!$A$7:$K$62),ROW('DBX Sprint'!$A$7:$K$62)),""),ROWS($U$34:U35)),COLUMNS('DBX Sprint'!$A$1:A7)),"")} | V35: {=IFERROR(INDEX('DBX Sprint'!$A$7:$K$62, SMALL(IF((INDEX('DBX Sprint'!$A$7:$K$62, ,22)<(TODAY()))*(INDEX('DBX Sprint'!$A$7:$K$62, ,22)<>"Complete"),MATCH(ROW('DBX Sprint'!$A$7:$K$62),ROW('DBX Sprint'!$A$7:$K$62)),""),ROWS($V$34:V35)),COLUMNS('DBX Sprint'!$A$1:A7)),"")} | W35: {=IFERROR(INDEX('DBX Sprint'!$A$7:$K$62, SMALL(IF((INDEX('DBX Sprint'!$A$7:$K$62, ,22)<=(TODAY()+1))*(INDEX('DBX Sprint'!$A$7:$K$62, ,22)>=TODAY()),MATCH(ROW('DBX Sprint'!$A$7:$K$62),ROW('DBX Sprint'!$A$7:$K$62)),""),ROWS($W$34:W35)),COLUMNS('DBX Sprint'!$A$1:A7)),"")} | X35: {=IFERROR(INDEX('DBX Sprint'!$A$7:$K$62, SMALL(IF((INDEX('DBX Sprint'!$A$7:$K$62, ,22)<=(TODAY()+5))*(INDEX('DBX Sprint'!$A$7:$K$62, ,22)>(TODAY()+1)),MATCH(ROW('DBX Sprint'!$A$7:$K$62),ROW('DBX Sprint'!$A$7:$K$62)),""),ROWS($X$34:X35)),COLUMNS('DBX Sprint'!$A$1:A7)),"")} | Y35: {=IFERROR(INDEX('DBX Sprint'!$A$7:$K$62, SMALL(IF((INDEX('DBX Sprint'!$A$7:$K$62, ,22)<=(TODAY()+10))*(INDEX('DBX Sprint'!$A$7:$K$62, ,22)>(TODAY()+5)),MATCH(ROW('DBX Sprint'!$A$7:$K$62),ROW('DBX Sprint'!$A$7:$K$62)),""),ROWS($Y$34:Y35)),COLUMNS('DBX Sprint'!$A$1:A7)),"")} | AA35: {=IFERROR(INDEX('DBX Sprint'!$A$7:$K$62, SMALL(IF((INDEX('DBX Sprint'!$A$7:$K$62, ,25)=("Complete"))*(INDEX('DBX Sprint'!$A$7:$K$62, ,25)="Complete"),MATCH(ROW('DBX Sprint'!$A$7:$K$62),ROW('DBX Sprint'!$A$7:$K$62)),""),ROWS($AA$34:AA35)),COLUMNS('DBX Sprint'!$A$1:A7)),"")} | AB35: {=IFERROR(INDEX('DBX Sprint'!$A$7:$K$62, SMALL(IF((INDEX('DBX Sprint'!$A$7:$K$62, ,25)<(TODAY()))*(INDEX('DBX Sprint'!$A$7:$K$62, ,25)<>"Complete"),MATCH(ROW('DBX Sprint'!$A$7:$K$62),ROW('DBX Sprint'!$A$7:$K$62)),""),ROWS($AB$34:AB35)),COLUMNS('DBX Sprint'!$A$1:A7)),"")} | AC35: {=IFERROR(INDEX('DBX Sprint'!$A$7:$K$62, SMALL(IF((INDEX('DBX Sprint'!$A$7:$K$62, ,25)<=(TODAY()+1))*(INDEX('DBX Sprint'!$A$7:$K$62, ,25)>=TODAY()),MATCH(ROW('DBX Sprint'!$A$7:$K$62),ROW('DBX Sprint'!$A$7:$K$62)),""),ROWS($AC$34:AC35)),COLUMNS('DBX Sprint'!$A$1:A7)),"")} | AD35: {=IFERROR(INDEX('DBX Sprint'!$A$7:$K$62, SMALL(IF((INDEX('DBX Sprint'!$A$7:$K$62, ,25)<=(TODAY()+5))*(INDEX('DBX Sprint'!$A$7:$K$62, ,25)>(TODAY()+1)),MATCH(ROW('DBX Sprint'!$A$7:$K$62),ROW('DBX Sprint'!$A$7:$K$62)),""),ROWS($AD$34:AD35)),COLUMNS('DBX Sprint'!$A$1:A7)),"")} | AE35: {=IFERROR(INDEX('DBX Sprint'!$A$7:$K$62, SMALL(IF((INDEX('DBX Sprint'!$A$7:$K$62, ,25)<=(TODAY()+10))*(INDEX('DBX Sprint'!$A$7:$K$62, ,25)>(TODAY()+5)),MATCH(ROW('DBX Sprint'!$A$7:$K$62),ROW('DBX Sprint'!$A$7:$K$62)),""),ROWS($AE$34:AE35)),COLUMNS('DBX Sprint'!$A$1:A7)),"")} | AG35: {=IFERROR(INDEX('DBX Sprint'!$A$7:$K$62, SMALL(IF((INDEX('DBX Sprint'!$A$7:$K$62, ,29)=("Complete"))*(INDEX('DBX Sprint'!$A$7:$K$62, ,29)="Complete"),MATCH(ROW('DBX Sprint'!$A$7:$K$62),ROW('DBX Sprint'!$A$7:$K$62)),""),ROWS($AG$34:AG35)),COLUMNS('DBX Sprint'!$A$1:A7)),"")} | AH35: {=IFERROR(INDEX('DBX Sprint'!$A$7:$K$62, SMALL(IF((INDEX('DBX Sprint'!$A$7:$K$62, ,29)<(TODAY()))*(INDEX('DBX Sprint'!$A$7:$K$62, ,29)<>"Complete"),MATCH(ROW('DBX Sprint'!$A$7:$K$62),ROW('DBX Sprint'!$A$7:$K$62)),""),ROWS($AH$34:AH35)),COLUMNS('DBX Sprint'!$A$1:A7)),"")} | AI35: {=IFERROR(INDEX('DBX Sprint'!$A$7:$K$62, SMALL(IF((INDEX('DBX Sprint'!$A$7:$K$62, ,29)<=(TODAY()+1))*(INDEX('DBX Sprint'!$A$7:$K$62, ,29)>=TODAY()),MATCH(ROW('DBX Sprint'!$A$7:$K$62),ROW('DBX Sprint'!$A$7:$K$62)),""),ROWS($AI$34:AI35)),COLUMNS('DBX Sprint'!$A$1:A7)),"")} | AJ35: {=IFERROR(INDEX('DBX Sprint'!$A$7:$K$62, SMALL(IF((INDEX('DBX Sprint'!$A$7:$K$62, ,29)<=(TODAY()+5))*(INDEX('DBX Sprint'!$A$7:$K$62, ,29)>(TODAY()+1)),MATCH(ROW('DBX Sprint'!$A$7:$K$62),ROW('DBX Sprint'!$A$7:$K$62)),""),ROWS($AJ$34:AJ35)),COLUMNS('DBX Sprint'!$A$1:A7)),"")} | AK35: {=IFERROR(INDEX('DBX Sprint'!$A$7:$K$62, SMALL(IF((INDEX('DBX Sprint'!$A$7:$K$62, ,29)<=(TODAY()+10))*(INDEX('DBX Sprint'!$A$7:$K$62, ,29)>(TODAY()+5)),MATCH(ROW('DBX Sprint'!$A$7:$K$62),ROW('DBX Sprint'!$A$7:$K$62)),""),ROWS($AK$34:AK35)),COLUMNS('DBX Sprint'!$A$1:A7)),"")} | AM35: {=IFERROR(INDEX('DBX Sprint'!$A$7:$K$62, SMALL(IF((INDEX('DBX Sprint'!$A$7:$K$62, ,32)=("Complete"))*(INDEX('DBX Sprint'!$A$7:$K$62, ,32)="Complete"),MATCH(ROW('DBX Sprint'!$A$7:$K$62),ROW('DBX Sprint'!$A$7:$K$62)),""),ROWS($AM$34:AM35)),COLUMNS('DBX Sprint'!$A$1:A7)),"")} | AN35: {=IFERROR(INDEX('DBX Sprint'!$A$7:$K$62, SMALL(IF((INDEX('DBX Sprint'!$A$7:$K$62, ,32)<(TODAY()))*(INDEX('DBX Sprint'!$A$7:$K$62, ,32)<>"Complete"),MATCH(ROW('DBX Sprint'!$A$7:$K$62),ROW('DBX Sprint'!$A$7:$K$62)),""),ROWS($AN$34:AN35)),COLUMNS('DBX Sprint'!$A$1:A7)),"")} | AO35: {=IFERROR(INDEX('DBX Sprint'!$A$7:$K$62, SMALL(IF((INDEX('DBX Sprint'!$A$7:$K$62, ,32)<=(TODAY()+1))*(INDEX('DBX Sprint'!$A$7:$K$62, ,32)>=TODAY()),MATCH(ROW('DBX Sprint'!$A$7:$K$62),ROW('DBX Sprint'!$A$7:$K$62)),""),ROWS($AO$34:AO35)),COLUMNS('DBX Sprint'!$A$1:A7)),"")} | AP35: {=IFERROR(INDEX('DBX Sprint'!$A$7:$K$62, SMALL(IF((INDEX('DBX Sprint'!$A$7:$K$62, ,32)<=(TODAY()+5))*(INDEX('DBX Sprint'!$A$7:$K$62, ,32)>(TODAY()+1)),MATCH(ROW('DBX Sprint'!$A$7:$K$62),ROW('DBX Sprint'!$A$7:$K$62)),""),ROWS($AP$34:AP35)),COLUMNS('DBX Sprint'!$A$1:A7)),"")} | AQ35: {=IFERROR(INDEX('DBX Sprint'!$A$7:$K$62, SMALL(IF((INDEX('DBX Sprint'!$A$7:$K$62, ,32)<=(TODAY()+10))*(INDEX('DBX Sprint'!$A$7:$K$62, ,32)>(TODAY()+5)),MATCH(ROW('DBX Sprint'!$A$7:$K$62),ROW('DBX Sprint'!$A$7:$K$62)),""),ROWS($AQ$34:AQ35)),COLUMNS('DBX Sprint'!$A$1:A7)),"")}
C36: {=IFERROR(INDEX('DBX Sprint'!$A$7:$K$62, SMALL(IF((INDEX('DBX Sprint'!$A$7:$K$62, ,13)=("Complete"))*(INDEX('DBX Sprint'!$A$7:$K$62, ,13)="Complete"),MATCH(ROW('DBX Sprint'!$A$7:$K$62),ROW('DBX Sprint'!$A$7:$K$62)),""),ROWS(C$34:$C36)),COLUMNS('DBX Sprint'!$A$1:A8)),"")} | D36: {=IFERROR(INDEX('DBX Sprint'!$A$7:$K$62, SMALL(IF((INDEX('DBX Sprint'!$A$7:$K$62, ,13)<(TODAY()))*(INDEX('DBX Sprint'!$A$7:$K$62, ,13)<>"Complete"),MATCH(ROW('DBX Sprint'!$A$7:$K$62),ROW('DBX Sprint'!$A$7:$K$62)),""),ROWS(D$34:$D36)),COLUMNS('DBX Sprint'!$A$1:A8)),"")} | E36: {=IFERROR(INDEX('DBX Sprint'!$A$7:$K$62, SMALL(IF((INDEX('DBX Sprint'!$A$7:$K$62, ,13)<=(TODAY()+1))*(INDEX('DBX Sprint'!$A$7:$K$62, ,13)>=TODAY()),MATCH(ROW('DBX Sprint'!$A$7:$K$62),ROW('DBX Sprint'!$A$7:$K$62)),""),ROWS(E$34:$E36)),COLUMNS('DBX Sprint'!$A$1:A8)),"")} | F36: {=IFERROR(INDEX('DBX Sprint'!$A$7:$K$62, SMALL(IF((INDEX('DBX Sprint'!$A$7:$K$62, ,13)<=(TODAY()+5))*(INDEX('DBX Sprint'!$A$7:$K$62, ,13)>(TODAY()+1)),MATCH(ROW('DBX Sprint'!$A$7:$K$62),ROW('DBX Sprint'!$A$7:$K$62)),""),ROWS($F$34:F36)),COLUMNS('DBX Sprint'!$A$1:A8)),"")} | G36: {=IFERROR(INDEX('DBX Sprint'!$A$7:$K$62, SMALL(IF((INDEX('DBX Sprint'!$A$7:$K$62, ,13)<=(TODAY()+10))*(INDEX('DBX Sprint'!$A$7:$K$62, ,13)>(TODAY()+5)),MATCH(ROW('DBX Sprint'!$A$7:$K$62),ROW('DBX Sprint'!$A$7:$K$62)),""),ROWS($G$34:G36)),COLUMNS('DBX Sprint'!$A$1:A8)),"")} | I36: {=IFERROR(INDEX('DBX Sprint'!$A$7:$K$62, SMALL(IF((INDEX('DBX Sprint'!$A$7:$K$62, ,16)=("Complete"))*(INDEX('DBX Sprint'!$A$7:$K$62, ,16)="Complete"),MATCH(ROW('DBX Sprint'!$A$7:$K$62),ROW('DBX Sprint'!$A$7:$K$62)),""),ROWS($I$34:I36)),COLUMNS('DBX Sprint'!$A$1:A8)),"")} | J36: {=IFERROR(INDEX('DBX Sprint'!$A$7:$K$62, SMALL(IF((INDEX('DBX Sprint'!$A$7:$K$62, ,16)<(TODAY()))*(INDEX('DBX Sprint'!$A$7:$K$62, ,16)<>"Complete"),MATCH(ROW('DBX Sprint'!$A$7:$K$62),ROW('DBX Sprint'!$A$7:$K$62)),""),ROWS($J$34:J36)),COLUMNS('DBX Sprint'!$A$1:A8)),"")} | K36: {=IFERROR(INDEX('DBX Sprint'!$A$7:$K$62, SMALL(IF((INDEX('DBX Sprint'!$A$7:$K$62, ,16)<=(TODAY()+1))*(INDEX('DBX Sprint'!$A$7:$K$62, ,16)>=TODAY()),MATCH(ROW('DBX Sprint'!$A$7:$K$62),ROW('DBX Sprint'!$A$7:$K$62)),""),ROWS($K$34:K36)),COLUMNS('DBX Sprint'!$A$1:A8)),"")} | L36: {=IFERROR(INDEX('DBX Sprint'!$A$7:$K$62, SMALL(IF((INDEX('DBX Sprint'!$A$7:$K$62, ,16)<=(TODAY()+5))*(INDEX('DBX Sprint'!$A$7:$K$62, ,16)>(TODAY()+1)),MATCH(ROW('DBX Sprint'!$A$7:$K$62),ROW('DBX Sprint'!$A$7:$K$62)),""),ROWS($L$34:L36)),COLUMNS('DBX Sprint'!$A$1:A8)),"")} | M36: {=IFERROR(INDEX('DBX Sprint'!$A$7:$K$62, SMALL(IF((INDEX('DBX Sprint'!$A$7:$K$62, ,16)<=(TODAY()+10))*(INDEX('DBX Sprint'!$A$7:$K$62, ,16)>(TODAY()+5)),MATCH(ROW('DBX Sprint'!$A$7:$K$62),ROW('DBX Sprint'!$A$7:$K$62)),""),ROWS($M$34:M36)),COLUMNS('DBX Sprint'!$A$1:A8)),"")} | O36: {=IFERROR(INDEX('DBX Sprint'!$A$7:$K$62, SMALL(IF((INDEX('DBX Sprint'!$A$7:$K$62, ,19)=("Complete"))*(INDEX('DBX Sprint'!$A$7:$K$62, ,19)="Complete"),MATCH(ROW('DBX Sprint'!$A$7:$K$62),ROW('DBX Sprint'!$A$7:$K$62)),""),ROWS($O$34:O36)),COLUMNS('DBX Sprint'!$A$1:A8)),"")} | P36: {=IFERROR(INDEX('DBX Sprint'!$A$7:$K$62, SMALL(IF((INDEX('DBX Sprint'!$A$7:$K$62, ,19)<(TODAY()))*(INDEX('DBX Sprint'!$A$7:$K$62, ,19)<>"Complete"),MATCH(ROW('DBX Sprint'!$A$7:$K$62),ROW('DBX Sprint'!$A$7:$K$62)),""),ROWS($P$34:P36)),COLUMNS('DBX Sprint'!$A$1:A8)),"")} | Q36: {=IFERROR(INDEX('DBX Sprint'!$A$7:$K$62, SMALL(IF((INDEX('DBX Sprint'!$A$7:$K$62, ,19)<=(TODAY()+1))*(INDEX('DBX Sprint'!$A$7:$K$62, ,19)>=TODAY()),MATCH(ROW('DBX Sprint'!$A$7:$K$62),ROW('DBX Sprint'!$A$7:$K$62)),""),ROWS($Q$34:Q36)),COLUMNS('DBX Sprint'!$A$1:A8)),"")} | R36: {=IFERROR(INDEX('DBX Sprint'!$A$7:$K$62, SMALL(IF((INDEX('DBX Sprint'!$A$7:$K$62, ,19)<=(TODAY()+5))*(INDEX('DBX Sprint'!$A$7:$K$62, ,19)>(TODAY()+1)),MATCH(ROW('DBX Sprint'!$A$7:$K$62),ROW('DBX Sprint'!$A$7:$K$62)),""),ROWS($R$34:R36)),COLUMNS('DBX Sprint'!$A$1:A8)),"")} | S36: {=IFERROR(INDEX('DBX Sprint'!$A$7:$K$62, SMALL(IF((INDEX('DBX Sprint'!$A$7:$K$62, ,19)<=(TODAY()+10))*(INDEX('DBX Sprint'!$A$7:$K$62, ,19)>(TODAY()+5)),MATCH(ROW('DBX Sprint'!$A$7:$K$62),ROW('DBX Sprint'!$A$7:$K$62)),""),ROWS($S$34:S36)),COLUMNS('DBX Sprint'!$A$1:A8)),"")} | U36: {=IFERROR(INDEX('DBX Sprint'!$A$7:$K$62, SMALL(IF((INDEX('DBX Sprint'!$A$7:$K$62, ,22)=("Complete"))*(INDEX('DBX Sprint'!$A$7:$K$62, ,22)="Complete"),MATCH(ROW('DBX Sprint'!$A$7:$K$62),ROW('DBX Sprint'!$A$7:$K$62)),""),ROWS($U$34:U36)),COLUMNS('DBX Sprint'!$A$1:A8)),"")} | V36: {=IFERROR(INDEX('DBX Sprint'!$A$7:$K$62, SMALL(IF((INDEX('DBX Sprint'!$A$7:$K$62, ,22)<(TODAY()))*(INDEX('DBX Sprint'!$A$7:$K$62, ,22)<>"Complete"),MATCH(ROW('DBX Sprint'!$A$7:$K$62),ROW('DBX Sprint'!$A$7:$K$62)),""),ROWS($V$34:V36)),COLUMNS('DBX Sprint'!$A$1:A8)),"")} | W36: {=IFERROR(INDEX('DBX Sprint'!$A$7:$K$62, SMALL(IF((INDEX('DBX Sprint'!$A$7:$K$62, ,22)<=(TODAY()+1))*(INDEX('DBX Sprint'!$A$7:$K$62, ,22)>=TODAY()),MATCH(ROW('DBX Sprint'!$A$7:$K$62),ROW('DBX Sprint'!$A$7:$K$62)),""),ROWS($W$34:W36)),COLUMNS('DBX Sprint'!$A$1:A8)),"")} | X36: {=IFERROR(INDEX('DBX Sprint'!$A$7:$K$62, SMALL(IF((INDEX('DBX Sprint'!$A$7:$K$62, ,22)<=(TODAY()+5))*(INDEX('DBX Sprint'!$A$7:$K$62, ,22)>(TODAY()+1)),MATCH(ROW('DBX Sprint'!$A$7:$K$62),ROW('DBX Sprint'!$A$7:$K$62)),""),ROWS($X$34:X36)),COLUMNS('DBX Sprint'!$A$1:A8)),"")} | Y36: {=IFERROR(INDEX('DBX Sprint'!$A$7:$K$62, SMALL(IF((INDEX('DBX Sprint'!$A$7:$K$62, ,22)<=(TODAY()+10))*(INDEX('DBX Sprint'!$A$7:$K$62, ,22)>(TODAY()+5)),MATCH(ROW('DBX Sprint'!$A$7:$K$62),ROW('DBX Sprint'!$A$7:$K$62)),""),ROWS($Y$34:Y36)),COLUMNS('DBX Sprint'!$A$1:A8)),"")} | AA36: {=IFERROR(INDEX('DBX Sprint'!$A$7:$K$62, SMALL(IF((INDEX('DBX Sprint'!$A$7:$K$62, ,25)=("Complete"))*(INDEX('DBX Sprint'!$A$7:$K$62, ,25)="Complete"),MATCH(ROW('DBX Sprint'!$A$7:$K$62),ROW('DBX Sprint'!$A$7:$K$62)),""),ROWS($AA$34:AA36)),COLUMNS('DBX Sprint'!$A$1:A8)),"")} | AB36: {=IFERROR(INDEX('DBX Sprint'!$A$7:$K$62, SMALL(IF((INDEX('DBX Sprint'!$A$7:$K$62, ,25)<(TODAY()))*(INDEX('DBX Sprint'!$A$7:$K$62, ,25)<>"Complete"),MATCH(ROW('DBX Sprint'!$A$7:$K$62),ROW('DBX Sprint'!$A$7:$K$62)),""),ROWS($AB$34:AB36)),COLUMNS('DBX Sprint'!$A$1:A8)),"")} | AC36: {=IFERROR(INDEX('DBX Sprint'!$A$7:$K$62, SMALL(IF((INDEX('DBX Sprint'!$A$7:$K$62, ,25)<=(TODAY()+1))*(INDEX('DBX Sprint'!$A$7:$K$62, ,25)>=TODAY()),MATCH(ROW('DBX Sprint'!$A$7:$K$62),ROW('DBX Sprint'!$A$7:$K$62)),""),ROWS($AC$34:AC36)),COLUMNS('DBX Sprint'!$A$1:A8)),"")} | AD36: {=IFERROR(INDEX('DBX Sprint'!$A$7:$K$62, SMALL(IF((INDEX('DBX Sprint'!$A$7:$K$62, ,25)<=(TODAY()+5))*(INDEX('DBX Sprint'!$A$7:$K$62, ,25)>(TODAY()+1)),MATCH(ROW('DBX Sprint'!$A$7:$K$62),ROW('DBX Sprint'!$A$7:$K$62)),""),ROWS($AD$34:AD36)),COLUMNS('DBX Sprint'!$A$1:A8)),"")} | AE36: {=IFERROR(INDEX('DBX Sprint'!$A$7:$K$62, SMALL(IF((INDEX('DBX Sprint'!$A$7:$K$62, ,25)<=(TODAY()+10))*(INDEX('DBX Sprint'!$A$7:$K$62, ,25)>(TODAY()+5)),MATCH(ROW('DBX Sprint'!$A$7:$K$62),ROW('DBX Sprint'!$A$7:$K$62)),""),ROWS($AE$34:AE36)),COLUMNS('DBX Sprint'!$A$1:A8)),"")} | AG36: {=IFERROR(INDEX('DBX Sprint'!$A$7:$K$62, SMALL(IF((INDEX('DBX Sprint'!$A$7:$K$62, ,29)=("Complete"))*(INDEX('DBX Sprint'!$A$7:$K$62, ,29)="Complete"),MATCH(ROW('DBX Sprint'!$A$7:$K$62),ROW('DBX Sprint'!$A$7:$K$62)),""),ROWS($AG$34:AG36)),COLUMNS('DBX Sprint'!$A$1:A8)),"")} | AH36: {=IFERROR(INDEX('DBX Sprint'!$A$7:$K$62, SMALL(IF((INDEX('DBX Sprint'!$A$7:$K$62, ,29)<(TODAY()))*(INDEX('DBX Sprint'!$A$7:$K$62, ,29)<>"Complete"),MATCH(ROW('DBX Sprint'!$A$7:$K$62),ROW('DBX Sprint'!$A$7:$K$62)),""),ROWS($AH$34:AH36)),COLUMNS('DBX Sprint'!$A$1:A8)),"")} | AI36: {=IFERROR(INDEX('DBX Sprint'!$A$7:$K$62, SMALL(IF((INDEX('DBX Sprint'!$A$7:$K$62, ,29)<=(TODAY()+1))*(INDEX('DBX Sprint'!$A$7:$K$62, ,29)>=TODAY()),MATCH(ROW('DBX Sprint'!$A$7:$K$62),ROW('DBX Sprint'!$A$7:$K$62)),""),ROWS($AI$34:AI36)),COLUMNS('DBX Sprint'!$A$1:A8)),"")} | AJ36: {=IFERROR(INDEX('DBX Sprint'!$A$7:$K$62, SMALL(IF((INDEX('DBX Sprint'!$A$7:$K$62, ,29)<=(TODAY()+5))*(INDEX('DBX Sprint'!$A$7:$K$62, ,29)>(TODAY()+1)),MATCH(ROW('DBX Sprint'!$A$7:$K$62),ROW('DBX Sprint'!$A$7:$K$62)),""),ROWS($AJ$34:AJ36)),COLUMNS('DBX Sprint'!$A$1:A8)),"")} | AK36: {=IFERROR(INDEX('DBX Sprint'!$A$7:$K$62, SMALL(IF((INDEX('DBX Sprint'!$A$7:$K$62, ,29)<=(TODAY()+10))*(INDEX('DBX Sprint'!$A$7:$K$62, ,29)>(TODAY()+5)),MATCH(ROW('DBX Sprint'!$A$7:$K$62),ROW('DBX Sprint'!$A$7:$K$62)),""),ROWS($AK$34:AK36)),COLUMNS('DBX Sprint'!$A$1:A8)),"")} | AM36: {=IFERROR(INDEX('DBX Sprint'!$A$7:$K$62, SMALL(IF((INDEX('DBX Sprint'!$A$7:$K$62, ,32)=("Complete"))*(INDEX('DBX Sprint'!$A$7:$K$62, ,32)="Complete"),MATCH(ROW('DBX Sprint'!$A$7:$K$62),ROW('DBX Sprint'!$A$7:$K$62)),""),ROWS($AM$34:AM36)),COLUMNS('DBX Sprint'!$A$1:A8)),"")} | AN36: {=IFERROR(INDEX('DBX Sprint'!$A$7:$K$62, SMALL(IF((INDEX('DBX Sprint'!$A$7:$K$62, ,32)<(TODAY()))*(INDEX('DBX Sprint'!$A$7:$K$62, ,32)<>"Complete"),MATCH(ROW('DBX Sprint'!$A$7:$K$62),ROW('DBX Sprint'!$A$7:$K$62)),""),ROWS($AN$34:AN36)),COLUMNS('DBX Sprint'!$A$1:A8)),"")} | AO36: {=IFERROR(INDEX('DBX Sprint'!$A$7:$K$62, SMALL(IF((INDEX('DBX Sprint'!$A$7:$K$62, ,32)<=(TODAY()+1))*(INDEX('DBX Sprint'!$A$7:$K$62, ,32)>=TODAY()),MATCH(ROW('DBX Sprint'!$A$7:$K$62),ROW('DBX Sprint'!$A$7:$K$62)),""),ROWS($AO$34:AO36)),COLUMNS('DBX Sprint'!$A$1:A8)),"")} | AP36: {=IFERROR(INDEX('DBX Sprint'!$A$7:$K$62, SMALL(IF((INDEX('DBX Sprint'!$A$7:$K$62, ,32)<=(TODAY()+5))*(INDEX('DBX Sprint'!$A$7:$K$62, ,32)>(TODAY()+1)),MATCH(ROW('DBX Sprint'!$A$7:$K$62),ROW('DBX Sprint'!$A$7:$K$62)),""),ROWS($AP$34:AP36)),COLUMNS('DBX Sprint'!$A$1:A8)),"")} | AQ36: {=IFERROR(INDEX('DBX Sprint'!$A$7:$K$62, SMALL(IF((INDEX('DBX Sprint'!$A$7:$K$62, ,32)<=(TODAY()+10))*(INDEX('DBX Sprint'!$A$7:$K$62, ,32)>(TODAY()+5)),MATCH(ROW('DBX Sprint'!$A$7:$K$62),ROW('DBX Sprint'!$A$7:$K$62)),""),ROWS($AQ$34:AQ36)),COLUMNS('DBX Sprint'!$A$1:A8)),"")}
C37: {=IFERROR(INDEX('DBX Sprint'!$A$7:$K$62, SMALL(IF((INDEX('DBX Sprint'!$A$7:$K$62, ,13)=("Complete"))*(INDEX('DBX Sprint'!$A$7:$K$62, ,13)="Complete"),MATCH(ROW('DBX Sprint'!$A$7:$K$62),ROW('DBX Sprint'!$A$7:$K$62)),""),ROWS(C$34:$C37)),COLUMNS('DBX Sprint'!$A$1:A9)),"")} | D37: {=IFERROR(INDEX('DBX Sprint'!$A$7:$K$62, SMALL(IF((INDEX('DBX Sprint'!$A$7:$K$62, ,13)<(TODAY()))*(INDEX('DBX Sprint'!$A$7:$K$62, ,13)<>"Complete"),MATCH(ROW('DBX Sprint'!$A$7:$K$62),ROW('DBX Sprint'!$A$7:$K$62)),""),ROWS(D$34:$D37)),COLUMNS('DBX Sprint'!$A$1:A9)),"")} | E37: {=IFERROR(INDEX('DBX Sprint'!$A$7:$K$62, SMALL(IF((INDEX('DBX Sprint'!$A$7:$K$62, ,13)<=(TODAY()+1))*(INDEX('DBX Sprint'!$A$7:$K$62, ,13)>=TODAY()),MATCH(ROW('DBX Sprint'!$A$7:$K$62),ROW('DBX Sprint'!$A$7:$K$62)),""),ROWS(E$34:$E37)),COLUMNS('DBX Sprint'!$A$1:A9)),"")} | F37: {=IFERROR(INDEX('DBX Sprint'!$A$7:$K$62, SMALL(IF((INDEX('DBX Sprint'!$A$7:$K$62, ,13)<=(TODAY()+5))*(INDEX('DBX Sprint'!$A$7:$K$62, ,13)>(TODAY()+1)),MATCH(ROW('DBX Sprint'!$A$7:$K$62),ROW('DBX Sprint'!$A$7:$K$62)),""),ROWS($F$34:F37)),COLUMNS('DBX Sprint'!$A$1:A9)),"")} | G37: {=IFERROR(INDEX('DBX Sprint'!$A$7:$K$62, SMALL(IF((INDEX('DBX Sprint'!$A$7:$K$62, ,13)<=(TODAY()+10))*(INDEX('DBX Sprint'!$A$7:$K$62, ,13)>(TODAY()+5)),MATCH(ROW('DBX Sprint'!$A$7:$K$62),ROW('DBX Sprint'!$A$7:$K$62)),""),ROWS($G$34:G37)),COLUMNS('DBX Sprint'!$A$1:A9)),"")} | I37: {=IFERROR(INDEX('DBX Sprint'!$A$7:$K$62, SMALL(IF((INDEX('DBX Sprint'!$A$7:$K$62, ,16)=("Complete"))*(INDEX('DBX Sprint'!$A$7:$K$62, ,16)="Complete"),MATCH(ROW('DBX Sprint'!$A$7:$K$62),ROW('DBX Sprint'!$A$7:$K$62)),""),ROWS($I$34:I37)),COLUMNS('DBX Sprint'!$A$1:A9)),"")} | J37: {=IFERROR(INDEX('DBX Sprint'!$A$7:$K$62, SMALL(IF((INDEX('DBX Sprint'!$A$7:$K$62, ,16)<(TODAY()))*(INDEX('DBX Sprint'!$A$7:$K$62, ,16)<>"Complete"),MATCH(ROW('DBX Sprint'!$A$7:$K$62),ROW('DBX Sprint'!$A$7:$K$62)),""),ROWS($J$34:J37)),COLUMNS('DBX Sprint'!$A$1:A9)),"")} | K37: {=IFERROR(INDEX('DBX Sprint'!$A$7:$K$62, SMALL(IF((INDEX('DBX Sprint'!$A$7:$K$62, ,16)<=(TODAY()+1))*(INDEX('DBX Sprint'!$A$7:$K$62, ,16)>=TODAY()),MATCH(ROW('DBX Sprint'!$A$7:$K$62),ROW('DBX Sprint'!$A$7:$K$62)),""),ROWS($K$34:K37)),COLUMNS('DBX Sprint'!$A$1:A9)),"")} | L37: {=IFERROR(INDEX('DBX Sprint'!$A$7:$K$62, SMALL(IF((INDEX('DBX Sprint'!$A$7:$K$62, ,16)<=(TODAY()+5))*(INDEX('DBX Sprint'!$A$7:$K$62, ,16)>(TODAY()+1)),MATCH(ROW('DBX Sprint'!$A$7:$K$62),ROW('DBX Sprint'!$A$7:$K$62)),""),ROWS($L$34:L37)),COLUMNS('DBX Sprint'!$A$1:A9)),"")} | M37: {=IFERROR(INDEX('DBX Sprint'!$A$7:$K$62, SMALL(IF((INDEX('DBX Sprint'!$A$7:$K$62, ,16)<=(TODAY()+10))*(INDEX('DBX Sprint'!$A$7:$K$62, ,16)>(TODAY()+5)),MATCH(ROW('DBX Sprint'!$A$7:$K$62),ROW('DBX Sprint'!$A$7:$K$62)),""),ROWS($M$34:M37)),COLUMNS('DBX Sprint'!$A$1:A9)),"")} | O37: {=IFERROR(INDEX('DBX Sprint'!$A$7:$K$62, SMALL(IF((INDEX('DBX Sprint'!$A$7:$K$62, ,19)=("Complete"))*(INDEX('DBX Sprint'!$A$7:$K$62, ,19)="Complete"),MATCH(ROW('DBX Sprint'!$A$7:$K$62),ROW('DBX Sprint'!$A$7:$K$62)),""),ROWS($O$34:O37)),COLUMNS('DBX Sprint'!$A$1:A9)),"")} | P37: {=IFERROR(INDEX('DBX Sprint'!$A$7:$K$62, SMALL(IF((INDEX('DBX Sprint'!$A$7:$K$62, ,19)<(TODAY()))*(INDEX('DBX Sprint'!$A$7:$K$62, ,19)<>"Complete"),MATCH(ROW('DBX Sprint'!$A$7:$K$62),ROW('DBX Sprint'!$A$7:$K$62)),""),ROWS($P$34:P37)),COLUMNS('DBX Sprint'!$A$1:A9)),"")} | Q37: {=IFERROR(INDEX('DBX Sprint'!$A$7:$K$62, SMALL(IF((INDEX('DBX Sprint'!$A$7:$K$62, ,19)<=(TODAY()+1))*(INDEX('DBX Sprint'!$A$7:$K$62, ,19)>=TODAY()),MATCH(ROW('DBX Sprint'!$A$7:$K$62),ROW('DBX Sprint'!$A$7:$K$62)),""),ROWS($Q$34:Q37)),COLUMNS('DBX Sprint'!$A$1:A9)),"")} | R37: {=IFERROR(INDEX('DBX Sprint'!$A$7:$K$62, SMALL(IF((INDEX('DBX Sprint'!$A$7:$K$62, ,19)<=(TODAY()+5))*(INDEX('DBX Sprint'!$A$7:$K$62, ,19)>(TODAY()+1)),MATCH(ROW('DBX Sprint'!$A$7:$K$62),ROW('DBX Sprint'!$A$7:$K$62)),""),ROWS($R$34:R37)),COLUMNS('DBX Sprint'!$A$1:A9)),"")} | S37: {=IFERROR(INDEX('DBX Sprint'!$A$7:$K$62, SMALL(IF((INDEX('DBX Sprint'!$A$7:$K$62, ,19)<=(TODAY()+10))*(INDEX('DBX Sprint'!$A$7:$K$62, ,19)>(TODAY()+5)),MATCH(ROW('DBX Sprint'!$A$7:$K$62),ROW('DBX Sprint'!$A$7:$K$62)),""),ROWS($S$34:S37)),COLUMNS('DBX Sprint'!$A$1:A9)),"")} | U37: {=IFERROR(INDEX('DBX Sprint'!$A$7:$K$62, SMALL(IF((INDEX('DBX Sprint'!$A$7:$K$62, ,22)=("Complete"))*(INDEX('DBX Sprint'!$A$7:$K$62, ,22)="Complete"),MATCH(ROW('DBX Sprint'!$A$7:$K$62),ROW('DBX Sprint'!$A$7:$K$62)),""),ROWS($U$34:U37)),COLUMNS('DBX Sprint'!$A$1:A9)),"")} | V37: {=IFERROR(INDEX('DBX Sprint'!$A$7:$K$62, SMALL(IF((INDEX('DBX Sprint'!$A$7:$K$62, ,22)<(TODAY()))*(INDEX('DBX Sprint'!$A$7:$K$62, ,22)<>"Complete"),MATCH(ROW('DBX Sprint'!$A$7:$K$62),ROW('DBX Sprint'!$A$7:$K$62)),""),ROWS($V$34:V37)),COLUMNS('DBX Sprint'!$A$1:A9)),"")} | W37: {=IFERROR(INDEX('DBX Sprint'!$A$7:$K$62, SMALL(IF((INDEX('DBX Sprint'!$A$7:$K$62, ,22)<=(TODAY()+1))*(INDEX('DBX Sprint'!$A$7:$K$62, ,22)>=TODAY()),MATCH(ROW('DBX Sprint'!$A$7:$K$62),ROW('DBX Sprint'!$A$7:$K$62)),""),ROWS($W$34:W37)),COLUMNS('DBX Sprint'!$A$1:A9)),"")} | X37: {=IFERROR(INDEX('DBX Sprint'!$A$7:$K$62, SMALL(IF((INDEX('DBX Sprint'!$A$7:$K$62, ,22)<=(TODAY()+5))*(INDEX('DBX Sprint'!$A$7:$K$62, ,22)>(TODAY()+1)),MATCH(ROW('DBX Sprint'!$A$7:$K$62),ROW('DBX Sprint'!$A$7:$K$62)),""),ROWS($X$34:X37)),COLUMNS('DBX Sprint'!$A$1:A9)),"")} | Y37: {=IFERROR(INDEX('DBX Sprint'!$A$7:$K$62, SMALL(IF((INDEX('DBX Sprint'!$A$7:$K$62, ,22)<=(TODAY()+10))*(INDEX('DBX Sprint'!$A$7:$K$62, ,22)>(TODAY()+5)),MATCH(ROW('DBX Sprint'!$A$7:$K$62),ROW('DBX Sprint'!$A$7:$K$62)),""),ROWS($Y$34:Y37)),COLUMNS('DBX Sprint'!$A$1:A9)),"")} | AA37: {=IFERROR(INDEX('DBX Sprint'!$A$7:$K$62, SMALL(IF((INDEX('DBX Sprint'!$A$7:$K$62, ,25)=("Complete"))*(INDEX('DBX Sprint'!$A$7:$K$62, ,25)="Complete"),MATCH(ROW('DBX Sprint'!$A$7:$K$62),ROW('DBX Sprint'!$A$7:$K$62)),""),ROWS($AA$34:AA37)),COLUMNS('DBX Sprint'!$A$1:A9)),"")} | AB37: {=IFERROR(INDEX('DBX Sprint'!$A$7:$K$62, SMALL(IF((INDEX('DBX Sprint'!$A$7:$K$62, ,25)<(TODAY()))*(INDEX('DBX Sprint'!$A$7:$K$62, ,25)<>"Complete"),MATCH(ROW('DBX Sprint'!$A$7:$K$62),ROW('DBX Sprint'!$A$7:$K$62)),""),ROWS($AB$34:AB37)),COLUMNS('DBX Sprint'!$A$1:A9)),"")} | AC37: {=IFERROR(INDEX('DBX Sprint'!$A$7:$K$62, SMALL(IF((INDEX('DBX Sprint'!$A$7:$K$62, ,25)<=(TODAY()+1))*(INDEX('DBX Sprint'!$A$7:$K$62, ,25)>=TODAY()),MATCH(ROW('DBX Sprint'!$A$7:$K$62),ROW('DBX Sprint'!$A$7:$K$62)),""),ROWS($AC$34:AC37)),COLUMNS('DBX Sprint'!$A$1:A9)),"")} | AD37: {=IFERROR(INDEX('DBX Sprint'!$A$7:$K$62, SMALL(IF((INDEX('DBX Sprint'!$A$7:$K$62, ,25)<=(TODAY()+5))*(INDEX('DBX Sprint'!$A$7:$K$62, ,25)>(TODAY()+1)),MATCH(ROW('DBX Sprint'!$A$7:$K$62),ROW('DBX Sprint'!$A$7:$K$62)),""),ROWS($AD$34:AD37)),COLUMNS('DBX Sprint'!$A$1:A9)),"")} | AE37: {=IFERROR(INDEX('DBX Sprint'!$A$7:$K$62, SMALL(IF((INDEX('DBX Sprint'!$A$7:$K$62, ,25)<=(TODAY()+10))*(INDEX('DBX Sprint'!$A$7:$K$62, ,25)>(TODAY()+5)),MATCH(ROW('DBX Sprint'!$A$7:$K$62),ROW('DBX Sprint'!$A$7:$K$62)),""),ROWS($AE$34:AE37)),COLUMNS('DBX Sprint'!$A$1:A9)),"")} | AG37: {=IFERROR(INDEX('DBX Sprint'!$A$7:$K$62, SMALL(IF((INDEX('DBX Sprint'!$A$7:$K$62, ,29)=("Complete"))*(INDEX('DBX Sprint'!$A$7:$K$62, ,29)="Complete"),MATCH(ROW('DBX Sprint'!$A$7:$K$62),ROW('DBX Sprint'!$A$7:$K$62)),""),ROWS($AG$34:AG37)),COLUMNS('DBX Sprint'!$A$1:A9)),"")} | AH37: {=IFERROR(INDEX('DBX Sprint'!$A$7:$K$62, SMALL(IF((INDEX('DBX Sprint'!$A$7:$K$62, ,29)<(TODAY()))*(INDEX('DBX Sprint'!$A$7:$K$62, ,29)<>"Complete"),MATCH(ROW('DBX Sprint'!$A$7:$K$62),ROW('DBX Sprint'!$A$7:$K$62)),""),ROWS($AH$34:AH37)),COLUMNS('DBX Sprint'!$A$1:A9)),"")} | AI37: {=IFERROR(INDEX('DBX Sprint'!$A$7:$K$62, SMALL(IF((INDEX('DBX Sprint'!$A$7:$K$62, ,29)<=(TODAY()+1))*(INDEX('DBX Sprint'!$A$7:$K$62, ,29)>=TODAY()),MATCH(ROW('DBX Sprint'!$A$7:$K$62),ROW('DBX Sprint'!$A$7:$K$62)),""),ROWS($AI$34:AI37)),COLUMNS('DBX Sprint'!$A$1:A9)),"")} | AJ37: {=IFERROR(INDEX('DBX Sprint'!$A$7:$K$62, SMALL(IF((INDEX('DBX Sprint'!$A$7:$K$62, ,29)<=(TODAY()+5))*(INDEX('DBX Sprint'!$A$7:$K$62, ,29)>(TODAY()+1)),MATCH(ROW('DBX Sprint'!$A$7:$K$62),ROW('DBX Sprint'!$A$7:$K$62)),""),ROWS($AJ$34:AJ37)),COLUMNS('DBX Sprint'!$A$1:A9)),"")} | AK37: {=IFERROR(INDEX('DBX Sprint'!$A$7:$K$62, SMALL(IF((INDEX('DBX Sprint'!$A$7:$K$62, ,29)<=(TODAY()+10))*(INDEX('DBX Sprint'!$A$7:$K$62, ,29)>(TODAY()+5)),MATCH(ROW('DBX Sprint'!$A$7:$K$62),ROW('DBX Sprint'!$A$7:$K$62)),""),ROWS($AK$34:AK37)),COLUMNS('DBX Sprint'!$A$1:A9)),"")} | AM37: {=IFERROR(INDEX('DBX Sprint'!$A$7:$K$62, SMALL(IF((INDEX('DBX Sprint'!$A$7:$K$62, ,32)=("Complete"))*(INDEX('DBX Sprint'!$A$7:$K$62, ,32)="Complete"),MATCH(ROW('DBX Sprint'!$A$7:$K$62),ROW('DBX Sprint'!$A$7:$K$62)),""),ROWS($AM$34:AM37)),COLUMNS('DBX Sprint'!$A$1:A9)),"")} | AN37: {=IFERROR(INDEX('DBX Sprint'!$A$7:$K$62, SMALL(IF((INDEX('DBX Sprint'!$A$7:$K$62, ,32)<(TODAY()))*(INDEX('DBX Sprint'!$A$7:$K$62, ,32)<>"Complete"),MATCH(ROW('DBX Sprint'!$A$7:$K$62),ROW('DBX Sprint'!$A$7:$K$62)),""),ROWS($AN$34:AN37)),COLUMNS('DBX Sprint'!$A$1:A9)),"")} | AO37: {=IFERROR(INDEX('DBX Sprint'!$A$7:$K$62, SMALL(IF((INDEX('DBX Sprint'!$A$7:$K$62, ,32)<=(TODAY()+1))*(INDEX('DBX Sprint'!$A$7:$K$62, ,32)>=TODAY()),MATCH(ROW('DBX Sprint'!$A$7:$K$62),ROW('DBX Sprint'!$A$7:$K$62)),""),ROWS($AO$34:AO37)),COLUMNS('DBX Sprint'!$A$1:A9)),"")} | AP37: {=IFERROR(INDEX('DBX Sprint'!$A$7:$K$62, SMALL(IF((INDEX('DBX Sprint'!$A$7:$K$62, ,32)<=(TODAY()+5))*(INDEX('DBX Sprint'!$A$7:$K$62, ,32)>(TODAY()+1)),MATCH(ROW('DBX Sprint'!$A$7:$K$62),ROW('DBX Sprint'!$A$7:$K$62)),""),ROWS($AP$34:AP37)),COLUMNS('DBX Sprint'!$A$1:A9)),"")} | AQ37: {=IFERROR(INDEX('DBX Sprint'!$A$7:$K$62, SMALL(IF((INDEX('DBX Sprint'!$A$7:$K$62, ,32)<=(TODAY()+10))*(INDEX('DBX Sprint'!$A$7:$K$62, ,32)>(TODAY()+5)),MATCH(ROW('DBX Sprint'!$A$7:$K$62),ROW('DBX Sprint'!$A$7:$K$62)),""),ROWS($AQ$34:AQ37)),COLUMNS('DBX Sprint'!$A$1:A9)),"")}
C38: {=IFERROR(INDEX('DBX Sprint'!$A$7:$K$62, SMALL(IF((INDEX('DBX Sprint'!$A$7:$K$62, ,13)=("Complete"))*(INDEX('DBX Sprint'!$A$7:$K$62, ,13)="Complete"),MATCH(ROW('DBX Sprint'!$A$7:$K$62),ROW('DBX Sprint'!$A$7:$K$62)),""),ROWS(C$34:$C38)),COLUMNS('DBX Sprint'!$A$1:A10)),"")} | D38: {=IFERROR(INDEX('DBX Sprint'!$A$7:$K$62, SMALL(IF((INDEX('DBX Sprint'!$A$7:$K$62, ,13)<(TODAY()))*(INDEX('DBX Sprint'!$A$7:$K$62, ,13)<>"Complete"),MATCH(ROW('DBX Sprint'!$A$7:$K$62),ROW('DBX Sprint'!$A$7:$K$62)),""),ROWS(D$34:$D38)),COLUMNS('DBX Sprint'!$A$1:A10)),"")} | E38: {=IFERROR(INDEX('DBX Sprint'!$A$7:$K$62, SMALL(IF((INDEX('DBX Sprint'!$A$7:$K$62, ,13)<=(TODAY()+1))*(INDEX('DBX Sprint'!$A$7:$K$62, ,13)>=TODAY()),MATCH(ROW('DBX Sprint'!$A$7:$K$62),ROW('DBX Sprint'!$A$7:$K$62)),""),ROWS(E$34:$E38)),COLUMNS('DBX Sprint'!$A$1:A10)),"")} | F38: {=IFERROR(INDEX('DBX Sprint'!$A$7:$K$62, SMALL(IF((INDEX('DBX Sprint'!$A$7:$K$62, ,13)<=(TODAY()+5))*(INDEX('DBX Sprint'!$A$7:$K$62, ,13)>(TODAY()+1)),MATCH(ROW('DBX Sprint'!$A$7:$K$62),ROW('DBX Sprint'!$A$7:$K$62)),""),ROWS($F$34:F38)),COLUMNS('DBX Sprint'!$A$1:A10)),"")} | G38: {=IFERROR(INDEX('DBX Sprint'!$A$7:$K$62, SMALL(IF((INDEX('DBX Sprint'!$A$7:$K$62, ,13)<=(TODAY()+10))*(INDEX('DBX Sprint'!$A$7:$K$62, ,13)>(TODAY()+5)),MATCH(ROW('DBX Sprint'!$A$7:$K$62),ROW('DBX Sprint'!$A$7:$K$62)),""),ROWS($G$34:G38)),COLUMNS('DBX Sprint'!$A$1:A10)),"")} | I38: {=IFERROR(INDEX('DBX Sprint'!$A$7:$K$62, SMALL(IF((INDEX('DBX Sprint'!$A$7:$K$62, ,16)=("Complete"))*(INDEX('DBX Sprint'!$A$7:$K$62, ,16)="Complete"),MATCH(ROW('DBX Sprint'!$A$7:$K$62),ROW('DBX Sprint'!$A$7:$K$62)),""),ROWS($I$34:I38)),COLUMNS('DBX Sprint'!$A$1:A10)),"")} | J38: {=IFERROR(INDEX('DBX Sprint'!$A$7:$K$62, SMALL(IF((INDEX('DBX Sprint'!$A$7:$K$62, ,16)<(TODAY()))*(INDEX('DBX Sprint'!$A$7:$K$62, ,16)<>"Complete"),MATCH(ROW('DBX Sprint'!$A$7:$K$62),ROW('DBX Sprint'!$A$7:$K$62)),""),ROWS($J$34:J38)),COLUMNS('DBX Sprint'!$A$1:A10)),"")} | K38: {=IFERROR(INDEX('DBX Sprint'!$A$7:$K$62, SMALL(IF((INDEX('DBX Sprint'!$A$7:$K$62, ,16)<=(TODAY()+1))*(INDEX('DBX Sprint'!$A$7:$K$62, ,16)>=TODAY()),MATCH(ROW('DBX Sprint'!$A$7:$K$62),ROW('DBX Sprint'!$A$7:$K$62)),""),ROWS($K$34:K38)),COLUMNS('DBX Sprint'!$A$1:A10)),"")} | L38: {=IFERROR(INDEX('DBX Sprint'!$A$7:$K$62, SMALL(IF((INDEX('DBX Sprint'!$A$7:$K$62, ,16)<=(TODAY()+5))*(INDEX('DBX Sprint'!$A$7:$K$62, ,16)>(TODAY()+1)),MATCH(ROW('DBX Sprint'!$A$7:$K$62),ROW('DBX Sprint'!$A$7:$K$62)),""),ROWS($L$34:L38)),COLUMNS('DBX Sprint'!$A$1:A10)),"")} | M38: {=IFERROR(INDEX('DBX Sprint'!$A$7:$K$62, SMALL(IF((INDEX('DBX Sprint'!$A$7:$K$62, ,16)<=(TODAY()+10))*(INDEX('DBX Sprint'!$A$7:$K$62, ,16)>(TODAY()+5)),MATCH(ROW('DBX Sprint'!$A$7:$K$62),ROW('DBX Sprint'!$A$7:$K$62)),""),ROWS($M$34:M38)),COLUMNS('DBX Sprint'!$A$1:A10)),"")} | O38: {=IFERROR(INDEX('DBX Sprint'!$A$7:$K$62, SMALL(IF((INDEX('DBX Sprint'!$A$7:$K$62, ,19)=("Complete"))*(INDEX('DBX Sprint'!$A$7:$K$62, ,19)="Complete"),MATCH(ROW('DBX Sprint'!$A$7:$K$62),ROW('DBX Sprint'!$A$7:$K$62)),""),ROWS($O$34:O38)),COLUMNS('DBX Sprint'!$A$1:A10)),"")} | P38: {=IFERROR(INDEX('DBX Sprint'!$A$7:$K$62, SMALL(IF((INDEX('DBX Sprint'!$A$7:$K$62, ,19)<(TODAY()))*(INDEX('DBX Sprint'!$A$7:$K$62, ,19)<>"Complete"),MATCH(ROW('DBX Sprint'!$A$7:$K$62),ROW('DBX Sprint'!$A$7:$K$62)),""),ROWS($P$34:P38)),COLUMNS('DBX Sprint'!$A$1:A10)),"")} | Q38: {=IFERROR(INDEX('DBX Sprint'!$A$7:$K$62, SMALL(IF((INDEX('DBX Sprint'!$A$7:$K$62, ,19)<=(TODAY()+1))*(INDEX('DBX Sprint'!$A$7:$K$62, ,19)>=TODAY()),MATCH(ROW('DBX Sprint'!$A$7:$K$62),ROW('DBX Sprint'!$A$7:$K$62)),""),ROWS($Q$34:Q38)),COLUMNS('DBX Sprint'!$A$1:A10)),"")} | R38: {=IFERROR(INDEX('DBX Sprint'!$A$7:$K$62, SMALL(IF((INDEX('DBX Sprint'!$A$7:$K$62, ,19)<=(TODAY()+5))*(INDEX('DBX Sprint'!$A$7:$K$62, ,19)>(TODAY()+1)),MATCH(ROW('DBX Sprint'!$A$7:$K$62),ROW('DBX Sprint'!$A$7:$K$62)),""),ROWS($R$34:R38)),COLUMNS('DBX Sprint'!$A$1:A10)),"")} | S38: {=IFERROR(INDEX('DBX Sprint'!$A$7:$K$62, SMALL(IF((INDEX('DBX Sprint'!$A$7:$K$62, ,19)<=(TODAY()+10))*(INDEX('DBX Sprint'!$A$7:$K$62, ,19)>(TODAY()+5)),MATCH(ROW('DBX Sprint'!$A$7:$K$62),ROW('DBX Sprint'!$A$7:$K$62)),""),ROWS($S$34:S38)),COLUMNS('DBX Sprint'!$A$1:A10)),"")} | U38: {=IFERROR(INDEX('DBX Sprint'!$A$7:$K$62, SMALL(IF((INDEX('DBX Sprint'!$A$7:$K$62, ,22)=("Complete"))*(INDEX('DBX Sprint'!$A$7:$K$62, ,22)="Complete"),MATCH(ROW('DBX Sprint'!$A$7:$K$62),ROW('DBX Sprint'!$A$7:$K$62)),""),ROWS($U$34:U38)),COLUMNS('DBX Sprint'!$A$1:A10)),"")} | V38: {=IFERROR(INDEX('DBX Sprint'!$A$7:$K$62, SMALL(IF((INDEX('DBX Sprint'!$A$7:$K$62, ,22)<(TODAY()))*(INDEX('DBX Sprint'!$A$7:$K$62, ,22)<>"Complete"),MATCH(ROW('DBX Sprint'!$A$7:$K$62),ROW('DBX Sprint'!$A$7:$K$62)),""),ROWS($V$34:V38)),COLUMNS('DBX Sprint'!$A$1:A10)),"")} | W38: {=IFERROR(INDEX('DBX Sprint'!$A$7:$K$62, SMALL(IF((INDEX('DBX Sprint'!$A$7:$K$62, ,22)<=(TODAY()+1))*(INDEX('DBX Sprint'!$A$7:$K$62, ,22)>=TODAY()),MATCH(ROW('DBX Sprint'!$A$7:$K$62),ROW('DBX Sprint'!$A$7:$K$62)),""),ROWS($W$34:W38)),COLUMNS('DBX Sprint'!$A$1:A10)),"")} | X38: {=IFERROR(INDEX('DBX Sprint'!$A$7:$K$62, SMALL(IF((INDEX('DBX Sprint'!$A$7:$K$62, ,22)<=(TODAY()+5))*(INDEX('DBX Sprint'!$A$7:$K$62, ,22)>(TODAY()+1)),MATCH(ROW('DBX Sprint'!$A$7:$K$62),ROW('DBX Sprint'!$A$7:$K$62)),""),ROWS($X$34:X38)),COLUMNS('DBX Sprint'!$A$1:A10)),"")} | Y38: {=IFERROR(INDEX('DBX Sprint'!$A$7:$K$62, SMALL(IF((INDEX('DBX Sprint'!$A$7:$K$62, ,22)<=(TODAY()+10))*(INDEX('DBX Sprint'!$A$7:$K$62, ,22)>(TODAY()+5)),MATCH(ROW('DBX Sprint'!$A$7:$K$62),ROW('DBX Sprint'!$A$7:$K$62)),""),ROWS($Y$34:Y38)),COLUMNS('DBX Sprint'!$A$1:A10)),"")} | AA38: {=IFERROR(INDEX('DBX Sprint'!$A$7:$K$62, SMALL(IF((INDEX('DBX Sprint'!$A$7:$K$62, ,25)=("Complete"))*(INDEX('DBX Sprint'!$A$7:$K$62, ,25)="Complete"),MATCH(ROW('DBX Sprint'!$A$7:$K$62),ROW('DBX Sprint'!$A$7:$K$62)),""),ROWS($AA$34:AA38)),COLUMNS('DBX Sprint'!$A$1:A10)),"")} | AB38: {=IFERROR(INDEX('DBX Sprint'!$A$7:$K$62, SMALL(IF((INDEX('DBX Sprint'!$A$7:$K$62, ,25)<(TODAY()))*(INDEX('DBX Sprint'!$A$7:$K$62, ,25)<>"Complete"),MATCH(ROW('DBX Sprint'!$A$7:$K$62),ROW('DBX Sprint'!$A$7:$K$62)),""),ROWS($AB$34:AB38)),COLUMNS('DBX Sprint'!$A$1:A10)),"")} | AC38: {=IFERROR(INDEX('DBX Sprint'!$A$7:$K$62, SMALL(IF((INDEX('DBX Sprint'!$A$7:$K$62, ,25)<=(TODAY()+1))*(INDEX('DBX Sprint'!$A$7:$K$62, ,25)>=TODAY()),MATCH(ROW('DBX Sprint'!$A$7:$K$62),ROW('DBX Sprint'!$A$7:$K$62)),""),ROWS($AC$34:AC38)),COLUMNS('DBX Sprint'!$A$1:A10)),"")} | AD38: {=IFERROR(INDEX('DBX Sprint'!$A$7:$K$62, SMALL(IF((INDEX('DBX Sprint'!$A$7:$K$62, ,25)<=(TODAY()+5))*(INDEX('DBX Sprint'!$A$7:$K$62, ,25)>(TODAY()+1)),MATCH(ROW('DBX Sprint'!$A$7:$K$62),ROW('DBX Sprint'!$A$7:$K$62)),""),ROWS($AD$34:AD38)),COLUMNS('DBX Sprint'!$A$1:A10)),"")} | AE38: {=IFERROR(INDEX('DBX Sprint'!$A$7:$K$62, SMALL(IF((INDEX('DBX Sprint'!$A$7:$K$62, ,25)<=(TODAY()+10))*(INDEX('DBX Sprint'!$A$7:$K$62, ,25)>(TODAY()+5)),MATCH(ROW('DBX Sprint'!$A$7:$K$62),ROW('DBX Sprint'!$A$7:$K$62)),""),ROWS($AE$34:AE38)),COLUMNS('DBX Sprint'!$A$1:A10)),"")} | AG38: {=IFERROR(INDEX('DBX Sprint'!$A$7:$K$62, SMALL(IF((INDEX('DBX Sprint'!$A$7:$K$62, ,29)=("Complete"))*(INDEX('DBX Sprint'!$A$7:$K$62, ,29)="Complete"),MATCH(ROW('DBX Sprint'!$A$7:$K$62),ROW('DBX Sprint'!$A$7:$K$62)),""),ROWS($AG$34:AG38)),COLUMNS('DBX Sprint'!$A$1:A10)),"")} | AH38: {=IFERROR(INDEX('DBX Sprint'!$A$7:$K$62, SMALL(IF((INDEX('DBX Sprint'!$A$7:$K$62, ,29)<(TODAY()))*(INDEX('DBX Sprint'!$A$7:$K$62, ,29)<>"Complete"),MATCH(ROW('DBX Sprint'!$A$7:$K$62),ROW('DBX Sprint'!$A$7:$K$62)),""),ROWS($AH$34:AH38)),COLUMNS('DBX Sprint'!$A$1:A10)),"")} | AI38: {=IFERROR(INDEX('DBX Sprint'!$A$7:$K$62, SMALL(IF((INDEX('DBX Sprint'!$A$7:$K$62, ,29)<=(TODAY()+1))*(INDEX('DBX Sprint'!$A$7:$K$62, ,29)>=TODAY()),MATCH(ROW('DBX Sprint'!$A$7:$K$62),ROW('DBX Sprint'!$A$7:$K$62)),""),ROWS($AI$34:AI38)),COLUMNS('DBX Sprint'!$A$1:A10)),"")} | AJ38: {=IFERROR(INDEX('DBX Sprint'!$A$7:$K$62, SMALL(IF((INDEX('DBX Sprint'!$A$7:$K$62, ,29)<=(TODAY()+5))*(INDEX('DBX Sprint'!$A$7:$K$62, ,29)>(TODAY()+1)),MATCH(ROW('DBX Sprint'!$A$7:$K$62),ROW('DBX Sprint'!$A$7:$K$62)),""),ROWS($AJ$34:AJ38)),COLUMNS('DBX Sprint'!$A$1:A10)),"")} | AK38: {=IFERROR(INDEX('DBX Sprint'!$A$7:$K$62, SMALL(IF((INDEX('DBX Sprint'!$A$7:$K$62, ,29)<=(TODAY()+10))*(INDEX('DBX Sprint'!$A$7:$K$62, ,29)>(TODAY()+5)),MATCH(ROW('DBX Sprint'!$A$7:$K$62),ROW('DBX Sprint'!$A$7:$K$62)),""),ROWS($AK$34:AK38)),COLUMNS('DBX Sprint'!$A$1:A10)),"")} | AM38: {=IFERROR(INDEX('DBX Sprint'!$A$7:$K$62, SMALL(IF((INDEX('DBX Sprint'!$A$7:$K$62, ,32)=("Complete"))*(INDEX('DBX Sprint'!$A$7:$K$62, ,32)="Complete"),MATCH(ROW('DBX Sprint'!$A$7:$K$62),ROW('DBX Sprint'!$A$7:$K$62)),""),ROWS($AM$34:AM38)),COLUMNS('DBX Sprint'!$A$1:A10)),"")} | AN38: {=IFERROR(INDEX('DBX Sprint'!$A$7:$K$62, SMALL(IF((INDEX('DBX Sprint'!$A$7:$K$62, ,32)<(TODAY()))*(INDEX('DBX Sprint'!$A$7:$K$62, ,32)<>"Complete"),MATCH(ROW('DBX Sprint'!$A$7:$K$62),ROW('DBX Sprint'!$A$7:$K$62)),""),ROWS($AN$34:AN38)),COLUMNS('DBX Sprint'!$A$1:A10)),"")} | AO38: {=IFERROR(INDEX('DBX Sprint'!$A$7:$K$62, SMALL(IF((INDEX('DBX Sprint'!$A$7:$K$62, ,32)<=(TODAY()+1))*(INDEX('DBX Sprint'!$A$7:$K$62, ,32)>=TODAY()),MATCH(ROW('DBX Sprint'!$A$7:$K$62),ROW('DBX Sprint'!$A$7:$K$62)),""),ROWS($AO$34:AO38)),COLUMNS('DBX Sprint'!$A$1:A10)),"")} | AP38: {=IFERROR(INDEX('DBX Sprint'!$A$7:$K$62, SMALL(IF((INDEX('DBX Sprint'!$A$7:$K$62, ,32)<=(TODAY()+5))*(INDEX('DBX Sprint'!$A$7:$K$62, ,32)>(TODAY()+1)),MATCH(ROW('DBX Sprint'!$A$7:$K$62),ROW('DBX Sprint'!$A$7:$K$62)),""),ROWS($AP$34:AP38)),COLUMNS('DBX Sprint'!$A$1:A10)),"")} | AQ38: {=IFERROR(INDEX('DBX Sprint'!$A$7:$K$62, SMALL(IF((INDEX('DBX Sprint'!$A$7:$K$62, ,32)<=(TODAY()+10))*(INDEX('DBX Sprint'!$A$7:$K$62, ,32)>(TODAY()+5)),MATCH(ROW('DBX Sprint'!$A$7:$K$62),ROW('DBX Sprint'!$A$7:$K$62)),""),ROWS($AQ$34:AQ38)),COLUMNS('DBX Sprint'!$A$1:A10)),"")}
C39: {=IFERROR(INDEX('DBX Sprint'!$A$7:$K$62, SMALL(IF((INDEX('DBX Sprint'!$A$7:$K$62, ,13)=("Complete"))*(INDEX('DBX Sprint'!$A$7:$K$62, ,13)="Complete"),MATCH(ROW('DBX Sprint'!$A$7:$K$62),ROW('DBX Sprint'!$A$7:$K$62)),""),ROWS(C$34:$C39)),COLUMNS('DBX Sprint'!$A$1:A11)),"")} | D39: {=IFERROR(INDEX('DBX Sprint'!$A$7:$K$62, SMALL(IF((INDEX('DBX Sprint'!$A$7:$K$62, ,13)<(TODAY()))*(INDEX('DBX Sprint'!$A$7:$K$62, ,13)<>"Complete"),MATCH(ROW('DBX Sprint'!$A$7:$K$62),ROW('DBX Sprint'!$A$7:$K$62)),""),ROWS(D$34:$D39)),COLUMNS('DBX Sprint'!$A$1:A11)),"")} | E39: {=IFERROR(INDEX('DBX Sprint'!$A$7:$K$62, SMALL(IF((INDEX('DBX Sprint'!$A$7:$K$62, ,13)<=(TODAY()+1))*(INDEX('DBX Sprint'!$A$7:$K$62, ,13)>=TODAY()),MATCH(ROW('DBX Sprint'!$A$7:$K$62),ROW('DBX Sprint'!$A$7:$K$62)),""),ROWS(E$34:$E39)),COLUMNS('DBX Sprint'!$A$1:A11)),"")} | F39: {=IFERROR(INDEX('DBX Sprint'!$A$7:$K$62, SMALL(IF((INDEX('DBX Sprint'!$A$7:$K$62, ,13)<=(TODAY()+5))*(INDEX('DBX Sprint'!$A$7:$K$62, ,13)>(TODAY()+1)),MATCH(ROW('DBX Sprint'!$A$7:$K$62),ROW('DBX Sprint'!$A$7:$K$62)),""),ROWS($F$34:F39)),COLUMNS('DBX Sprint'!$A$1:A11)),"")} | G39: {=IFERROR(INDEX('DBX Sprint'!$A$7:$K$62, SMALL(IF((INDEX('DBX Sprint'!$A$7:$K$62, ,13)<=(TODAY()+10))*(INDEX('DBX Sprint'!$A$7:$K$62, ,13)>(TODAY()+5)),MATCH(ROW('DBX Sprint'!$A$7:$K$62),ROW('DBX Sprint'!$A$7:$K$62)),""),ROWS($G$34:G39)),COLUMNS('DBX Sprint'!$A$1:A11)),"")} | I39: {=IFERROR(INDEX('DBX Sprint'!$A$7:$K$62, SMALL(IF((INDEX('DBX Sprint'!$A$7:$K$62, ,16)=("Complete"))*(INDEX('DBX Sprint'!$A$7:$K$62, ,16)="Complete"),MATCH(ROW('DBX Sprint'!$A$7:$K$62),ROW('DBX Sprint'!$A$7:$K$62)),""),ROWS($I$34:I39)),COLUMNS('DBX Sprint'!$A$1:A11)),"")} | J39: {=IFERROR(INDEX('DBX Sprint'!$A$7:$K$62, SMALL(IF((INDEX('DBX Sprint'!$A$7:$K$62, ,16)<(TODAY()))*(INDEX('DBX Sprint'!$A$7:$K$62, ,16)<>"Complete"),MATCH(ROW('DBX Sprint'!$A$7:$K$62),ROW('DBX Sprint'!$A$7:$K$62)),""),ROWS($J$34:J39)),COLUMNS('DBX Sprint'!$A$1:A11)),"")} | K39: {=IFERROR(INDEX('DBX Sprint'!$A$7:$K$62, SMALL(IF((INDEX('DBX Sprint'!$A$7:$K$62, ,16)<=(TODAY()+1))*(INDEX('DBX Sprint'!$A$7:$K$62, ,16)>=TODAY()),MATCH(ROW('DBX Sprint'!$A$7:$K$62),ROW('DBX Sprint'!$A$7:$K$62)),""),ROWS($K$34:K39)),COLUMNS('DBX Sprint'!$A$1:A11)),"")} | L39: {=IFERROR(INDEX('DBX Sprint'!$A$7:$K$62, SMALL(IF((INDEX('DBX Sprint'!$A$7:$K$62, ,16)<=(TODAY()+5))*(INDEX('DBX Sprint'!$A$7:$K$62, ,16)>(TODAY()+1)),MATCH(ROW('DBX Sprint'!$A$7:$K$62),ROW('DBX Sprint'!$A$7:$K$62)),""),ROWS($L$34:L39)),COLUMNS('DBX Sprint'!$A$1:A11)),"")} | M39: {=IFERROR(INDEX('DBX Sprint'!$A$7:$K$62, SMALL(IF((INDEX('DBX Sprint'!$A$7:$K$62, ,16)<=(TODAY()+10))*(INDEX('DBX Sprint'!$A$7:$K$62, ,16)>(TODAY()+5)),MATCH(ROW('DBX Sprint'!$A$7:$K$62),ROW('DBX Sprint'!$A$7:$K$62)),""),ROWS($M$34:M39)),COLUMNS('DBX Sprint'!$A$1:A11)),"")} | O39: {=IFERROR(INDEX('DBX Sprint'!$A$7:$K$62, SMALL(IF((INDEX('DBX Sprint'!$A$7:$K$62, ,19)=("Complete"))*(INDEX('DBX Sprint'!$A$7:$K$62, ,19)="Complete"),MATCH(ROW('DBX Sprint'!$A$7:$K$62),ROW('DBX Sprint'!$A$7:$K$62)),""),ROWS($O$34:O39)),COLUMNS('DBX Sprint'!$A$1:A11)),"")} | P39: {=IFERROR(INDEX('DBX Sprint'!$A$7:$K$62, SMALL(IF((INDEX('DBX Sprint'!$A$7:$K$62, ,19)<(TODAY()))*(INDEX('DBX Sprint'!$A$7:$K$62, ,19)<>"Complete"),MATCH(ROW('DBX Sprint'!$A$7:$K$62),ROW('DBX Sprint'!$A$7:$K$62)),""),ROWS($P$34:P39)),COLUMNS('DBX Sprint'!$A$1:A11)),"")} | Q39: {=IFERROR(INDEX('DBX Sprint'!$A$7:$K$62, SMALL(IF((INDEX('DBX Sprint'!$A$7:$K$62, ,19)<=(TODAY()+1))*(INDEX('DBX Sprint'!$A$7:$K$62, ,19)>=TODAY()),MATCH(ROW('DBX Sprint'!$A$7:$K$62),ROW('DBX Sprint'!$A$7:$K$62)),""),ROWS($Q$34:Q39)),COLUMNS('DBX Sprint'!$A$1:A11)),"")} | R39: {=IFERROR(INDEX('DBX Sprint'!$A$7:$K$62, SMALL(IF((INDEX('DBX Sprint'!$A$7:$K$62, ,19)<=(TODAY()+5))*(INDEX('DBX Sprint'!$A$7:$K$62, ,19)>(TODAY()+1)),MATCH(ROW('DBX Sprint'!$A$7:$K$62),ROW('DBX Sprint'!$A$7:$K$62)),""),ROWS($R$34:R39)),COLUMNS('DBX Sprint'!$A$1:A11)),"")} | S39: {=IFERROR(INDEX('DBX Sprint'!$A$7:$K$62, SMALL(IF((INDEX('DBX Sprint'!$A$7:$K$62, ,19)<=(TODAY()+10))*(INDEX('DBX Sprint'!$A$7:$K$62, ,19)>(TODAY()+5)),MATCH(ROW('DBX Sprint'!$A$7:$K$62),ROW('DBX Sprint'!$A$7:$K$62)),""),ROWS($S$34:S39)),COLUMNS('DBX Sprint'!$A$1:A11)),"")} | U39: {=IFERROR(INDEX('DBX Sprint'!$A$7:$K$62, SMALL(IF((INDEX('DBX Sprint'!$A$7:$K$62, ,22)=("Complete"))*(INDEX('DBX Sprint'!$A$7:$K$62, ,22)="Complete"),MATCH(ROW('DBX Sprint'!$A$7:$K$62),ROW('DBX Sprint'!$A$7:$K$62)),""),ROWS($U$34:U39)),COLUMNS('DBX Sprint'!$A$1:A11)),"")} | V39: {=IFERROR(INDEX('DBX Sprint'!$A$7:$K$62, SMALL(IF((INDEX('DBX Sprint'!$A$7:$K$62, ,22)<(TODAY()))*(INDEX('DBX Sprint'!$A$7:$K$62, ,22)<>"Complete"),MATCH(ROW('DBX Sprint'!$A$7:$K$62),ROW('DBX Sprint'!$A$7:$K$62)),""),ROWS($V$34:V39)),COLUMNS('DBX Sprint'!$A$1:A11)),"")} | W39: {=IFERROR(INDEX('DBX Sprint'!$A$7:$K$62, SMALL(IF((INDEX('DBX Sprint'!$A$7:$K$62, ,22)<=(TODAY()+1))*(INDEX('DBX Sprint'!$A$7:$K$62, ,22)>=TODAY()),MATCH(ROW('DBX Sprint'!$A$7:$K$62),ROW('DBX Sprint'!$A$7:$K$62)),""),ROWS($W$34:W39)),COLUMNS('DBX Sprint'!$A$1:A11)),"")} | X39: {=IFERROR(INDEX('DBX Sprint'!$A$7:$K$62, SMALL(IF((INDEX('DBX Sprint'!$A$7:$K$62, ,22)<=(TODAY()+5))*(INDEX('DBX Sprint'!$A$7:$K$62, ,22)>(TODAY()+1)),MATCH(ROW('DBX Sprint'!$A$7:$K$62),ROW('DBX Sprint'!$A$7:$K$62)),""),ROWS($X$34:X39)),COLUMNS('DBX Sprint'!$A$1:A11)),"")} | Y39: {=IFERROR(INDEX('DBX Sprint'!$A$7:$K$62, SMALL(IF((INDEX('DBX Sprint'!$A$7:$K$62, ,22)<=(TODAY()+10))*(INDEX('DBX Sprint'!$A$7:$K$62, ,22)>(TODAY()+5)),MATCH(ROW('DBX Sprint'!$A$7:$K$62),ROW('DBX Sprint'!$A$7:$K$62)),""),ROWS($Y$34:Y39)),COLUMNS('DBX Sprint'!$A$1:A11)),"")} | AA39: {=IFERROR(INDEX('DBX Sprint'!$A$7:$K$62, SMALL(IF((INDEX('DBX Sprint'!$A$7:$K$62, ,25)=("Complete"))*(INDEX('DBX Sprint'!$A$7:$K$62, ,25)="Complete"),MATCH(ROW('DBX Sprint'!$A$7:$K$62),ROW('DBX Sprint'!$A$7:$K$62)),""),ROWS($AA$34:AA39)),COLUMNS('DBX Sprint'!$A$1:A11)),"")} | AB39: {=IFERROR(INDEX('DBX Sprint'!$A$7:$K$62, SMALL(IF((INDEX('DBX Sprint'!$A$7:$K$62, ,25)<(TODAY()))*(INDEX('DBX Sprint'!$A$7:$K$62, ,25)<>"Complete"),MATCH(ROW('DBX Sprint'!$A$7:$K$62),ROW('DBX Sprint'!$A$7:$K$62)),""),ROWS($AB$34:AB39)),COLUMNS('DBX Sprint'!$A$1:A11)),"")} | AC39: {=IFERROR(INDEX('DBX Sprint'!$A$7:$K$62, SMALL(IF((INDEX('DBX Sprint'!$A$7:$K$62, ,25)<=(TODAY()+1))*(INDEX('DBX Sprint'!$A$7:$K$62, ,25)>=TODAY()),MATCH(ROW('DBX Sprint'!$A$7:$K$62),ROW('DBX Sprint'!$A$7:$K$62)),""),ROWS($AC$34:AC39)),COLUMNS('DBX Sprint'!$A$1:A11)),"")} | AD39: {=IFERROR(INDEX('DBX Sprint'!$A$7:$K$62, SMALL(IF((INDEX('DBX Sprint'!$A$7:$K$62, ,25)<=(TODAY()+5))*(INDEX('DBX Sprint'!$A$7:$K$62, ,25)>(TODAY()+1)),MATCH(ROW('DBX Sprint'!$A$7:$K$62),ROW('DBX Sprint'!$A$7:$K$62)),""),ROWS($AD$34:AD39)),COLUMNS('DBX Sprint'!$A$1:A11)),"")} | AE39: {=IFERROR(INDEX('DBX Sprint'!$A$7:$K$62, SMALL(IF((INDEX('DBX Sprint'!$A$7:$K$62, ,25)<=(TODAY()+10))*(INDEX('DBX Sprint'!$A$7:$K$62, ,25)>(TODAY()+5)),MATCH(ROW('DBX Sprint'!$A$7:$K$62),ROW('DBX Sprint'!$A$7:$K$62)),""),ROWS($AE$34:AE39)),COLUMNS('DBX Sprint'!$A$1:A11)),"")} | AG39: {=IFERROR(INDEX('DBX Sprint'!$A$7:$K$62, SMALL(IF((INDEX('DBX Sprint'!$A$7:$K$62, ,29)=("Complete"))*(INDEX('DBX Sprint'!$A$7:$K$62, ,29)="Complete"),MATCH(ROW('DBX Sprint'!$A$7:$K$62),ROW('DBX Sprint'!$A$7:$K$62)),""),ROWS($AG$34:AG39)),COLUMNS('DBX Sprint'!$A$1:A11)),"")} | AH39: {=IFERROR(INDEX('DBX Sprint'!$A$7:$K$62, SMALL(IF((INDEX('DBX Sprint'!$A$7:$K$62, ,29)<(TODAY()))*(INDEX('DBX Sprint'!$A$7:$K$62, ,29)<>"Complete"),MATCH(ROW('DBX Sprint'!$A$7:$K$62),ROW('DBX Sprint'!$A$7:$K$62)),""),ROWS($AH$34:AH39)),COLUMNS('DBX Sprint'!$A$1:A11)),"")} | AI39: {=IFERROR(INDEX('DBX Sprint'!$A$7:$K$62, SMALL(IF((INDEX('DBX Sprint'!$A$7:$K$62, ,29)<=(TODAY()+1))*(INDEX('DBX Sprint'!$A$7:$K$62, ,29)>=TODAY()),MATCH(ROW('DBX Sprint'!$A$7:$K$62),ROW('DBX Sprint'!$A$7:$K$62)),""),ROWS($AI$34:AI39)),COLUMNS('DBX Sprint'!$A$1:A11)),"")} | AJ39: {=IFERROR(INDEX('DBX Sprint'!$A$7:$K$62, SMALL(IF((INDEX('DBX Sprint'!$A$7:$K$62, ,29)<=(TODAY()+5))*(INDEX('DBX Sprint'!$A$7:$K$62, ,29)>(TODAY()+1)),MATCH(ROW('DBX Sprint'!$A$7:$K$62),ROW('DBX Sprint'!$A$7:$K$62)),""),ROWS($AJ$34:AJ39)),COLUMNS('DBX Sprint'!$A$1:A11)),"")} | AK39: {=IFERROR(INDEX('DBX Sprint'!$A$7:$K$62, SMALL(IF((INDEX('DBX Sprint'!$A$7:$K$62, ,29)<=(TODAY()+10))*(INDEX('DBX Sprint'!$A$7:$K$62, ,29)>(TODAY()+5)),MATCH(ROW('DBX Sprint'!$A$7:$K$62),ROW('DBX Sprint'!$A$7:$K$62)),""),ROWS($AK$34:AK39)),COLUMNS('DBX Sprint'!$A$1:A11)),"")} | AM39: {=IFERROR(INDEX('DBX Sprint'!$A$7:$K$62, SMALL(IF((INDEX('DBX Sprint'!$A$7:$K$62, ,32)=("Complete"))*(INDEX('DBX Sprint'!$A$7:$K$62, ,32)="Complete"),MATCH(ROW('DBX Sprint'!$A$7:$K$62),ROW('DBX Sprint'!$A$7:$K$62)),""),ROWS($AM$34:AM39)),COLUMNS('DBX Sprint'!$A$1:A11)),"")} | AN39: {=IFERROR(INDEX('DBX Sprint'!$A$7:$K$62, SMALL(IF((INDEX('DBX Sprint'!$A$7:$K$62, ,32)<(TODAY()))*(INDEX('DBX Sprint'!$A$7:$K$62, ,32)<>"Complete"),MATCH(ROW('DBX Sprint'!$A$7:$K$62),ROW('DBX Sprint'!$A$7:$K$62)),""),ROWS($AN$34:AN39)),COLUMNS('DBX Sprint'!$A$1:A11)),"")} | AO39: {=IFERROR(INDEX('DBX Sprint'!$A$7:$K$62, SMALL(IF((INDEX('DBX Sprint'!$A$7:$K$62, ,32)<=(TODAY()+1))*(INDEX('DBX Sprint'!$A$7:$K$62, ,32)>=TODAY()),MATCH(ROW('DBX Sprint'!$A$7:$K$62),ROW('DBX Sprint'!$A$7:$K$62)),""),ROWS($AO$34:AO39)),COLUMNS('DBX Sprint'!$A$1:A11)),"")} | AP39: {=IFERROR(INDEX('DBX Sprint'!$A$7:$K$62, SMALL(IF((INDEX('DBX Sprint'!$A$7:$K$62, ,32)<=(TODAY()+5))*(INDEX('DBX Sprint'!$A$7:$K$62, ,32)>(TODAY()+1)),MATCH(ROW('DBX Sprint'!$A$7:$K$62),ROW('DBX Sprint'!$A$7:$K$62)),""),ROWS($AP$34:AP39)),COLUMNS('DBX Sprint'!$A$1:A11)),"")} | AQ39: {=IFERROR(INDEX('DBX Sprint'!$A$7:$K$62, SMALL(IF((INDEX('DBX Sprint'!$A$7:$K$62, ,32)<=(TODAY()+10))*(INDEX('DBX Sprint'!$A$7:$K$62, ,32)>(TODAY()+5)),MATCH(ROW('DBX Sprint'!$A$7:$K$62),ROW('DBX Sprint'!$A$7:$K$62)),""),ROWS($AQ$34:AQ39)),COLUMNS('DBX Sprint'!$A$1:A11)),"")}
C40: {=IFERROR(INDEX('DBX Sprint'!$A$7:$K$62, SMALL(IF((INDEX('DBX Sprint'!$A$7:$K$62, ,13)=("Complete"))*(INDEX('DBX Sprint'!$A$7:$K$62, ,13)="Complete"),MATCH(ROW('DBX Sprint'!$A$7:$K$62),ROW('DBX Sprint'!$A$7:$K$62)),""),ROWS(C$34:$C40)),COLUMNS('DBX Sprint'!$A$1:A12)),"")} | D40: {=IFERROR(INDEX('DBX Sprint'!$A$7:$K$62, SMALL(IF((INDEX('DBX Sprint'!$A$7:$K$62, ,13)<(TODAY()))*(INDEX('DBX Sprint'!$A$7:$K$62, ,13)<>"Complete"),MATCH(ROW('DBX Sprint'!$A$7:$K$62),ROW('DBX Sprint'!$A$7:$K$62)),""),ROWS(D$34:$D40)),COLUMNS('DBX Sprint'!$A$1:A12)),"")} | E40: {=IFERROR(INDEX('DBX Sprint'!$A$7:$K$62, SMALL(IF((INDEX('DBX Sprint'!$A$7:$K$62, ,13)<=(TODAY()+1))*(INDEX('DBX Sprint'!$A$7:$K$62, ,13)>=TODAY()),MATCH(ROW('DBX Sprint'!$A$7:$K$62),ROW('DBX Sprint'!$A$7:$K$62)),""),ROWS(E$34:$E40)),COLUMNS('DBX Sprint'!$A$1:A12)),"")} | F40: {=IFERROR(INDEX('DBX Sprint'!$A$7:$K$62, SMALL(IF((INDEX('DBX Sprint'!$A$7:$K$62, ,13)<=(TODAY()+5))*(INDEX('DBX Sprint'!$A$7:$K$62, ,13)>(TODAY()+1)),MATCH(ROW('DBX Sprint'!$A$7:$K$62),ROW('DBX Sprint'!$A$7:$K$62)),""),ROWS($F$34:F40)),COLUMNS('DBX Sprint'!$A$1:A12)),"")} | G40: {=IFERROR(INDEX('DBX Sprint'!$A$7:$K$62, SMALL(IF((INDEX('DBX Sprint'!$A$7:$K$62, ,13)<=(TODAY()+10))*(INDEX('DBX Sprint'!$A$7:$K$62, ,13)>(TODAY()+5)),MATCH(ROW('DBX Sprint'!$A$7:$K$62),ROW('DBX Sprint'!$A$7:$K$62)),""),ROWS($G$34:G40)),COLUMNS('DBX Sprint'!$A$1:A12)),"")} | I40: {=IFERROR(INDEX('DBX Sprint'!$A$7:$K$62, SMALL(IF((INDEX('DBX Sprint'!$A$7:$K$62, ,16)=("Complete"))*(INDEX('DBX Sprint'!$A$7:$K$62, ,16)="Complete"),MATCH(ROW('DBX Sprint'!$A$7:$K$62),ROW('DBX Sprint'!$A$7:$K$62)),""),ROWS($I$34:I40)),COLUMNS('DBX Sprint'!$A$1:A12)),"")} | J40: {=IFERROR(INDEX('DBX Sprint'!$A$7:$K$62, SMALL(IF((INDEX('DBX Sprint'!$A$7:$K$62, ,16)<(TODAY()))*(INDEX('DBX Sprint'!$A$7:$K$62, ,16)<>"Complete"),MATCH(ROW('DBX Sprint'!$A$7:$K$62),ROW('DBX Sprint'!$A$7:$K$62)),""),ROWS($J$34:J40)),COLUMNS('DBX Sprint'!$A$1:A12)),"")} | K40: {=IFERROR(INDEX('DBX Sprint'!$A$7:$K$62, SMALL(IF((INDEX('DBX Sprint'!$A$7:$K$62, ,16)<=(TODAY()+1))*(INDEX('DBX Sprint'!$A$7:$K$62, ,16)>=TODAY()),MATCH(ROW('DBX Sprint'!$A$7:$K$62),ROW('DBX Sprint'!$A$7:$K$62)),""),ROWS($K$34:K40)),COLUMNS('DBX Sprint'!$A$1:A12)),"")} | L40: {=IFERROR(INDEX('DBX Sprint'!$A$7:$K$62, SMALL(IF((INDEX('DBX Sprint'!$A$7:$K$62, ,16)<=(TODAY()+5))*(INDEX('DBX Sprint'!$A$7:$K$62, ,16)>(TODAY()+1)),MATCH(ROW('DBX Sprint'!$A$7:$K$62),ROW('DBX Sprint'!$A$7:$K$62)),""),ROWS($L$34:L40)),COLUMNS('DBX Sprint'!$A$1:A12)),"")} | M40: {=IFERROR(INDEX('DBX Sprint'!$A$7:$K$62, SMALL(IF((INDEX('DBX Sprint'!$A$7:$K$62, ,16)<=(TODAY()+10))*(INDEX('DBX Sprint'!$A$7:$K$62, ,16)>(TODAY()+5)),MATCH(ROW('DBX Sprint'!$A$7:$K$62),ROW('DBX Sprint'!$A$7:$K$62)),""),ROWS($M$34:M40)),COLUMNS('DBX Sprint'!$A$1:A12)),"")} | O40: {=IFERROR(INDEX('DBX Sprint'!$A$7:$K$62, SMALL(IF((INDEX('DBX Sprint'!$A$7:$K$62, ,19)=("Complete"))*(INDEX('DBX Sprint'!$A$7:$K$62, ,19)="Complete"),MATCH(ROW('DBX Sprint'!$A$7:$K$62),ROW('DBX Sprint'!$A$7:$K$62)),""),ROWS($O$34:O40)),COLUMNS('DBX Sprint'!$A$1:A12)),"")} | P40: {=IFERROR(INDEX('DBX Sprint'!$A$7:$K$62, SMALL(IF((INDEX('DBX Sprint'!$A$7:$K$62, ,19)<(TODAY()))*(INDEX('DBX Sprint'!$A$7:$K$62, ,19)<>"Complete"),MATCH(ROW('DBX Sprint'!$A$7:$K$62),ROW('DBX Sprint'!$A$7:$K$62)),""),ROWS($P$34:P40)),COLUMNS('DBX Sprint'!$A$1:A12)),"")} | Q40: {=IFERROR(INDEX('DBX Sprint'!$A$7:$K$62, SMALL(IF((INDEX('DBX Sprint'!$A$7:$K$62, ,19)<=(TODAY()+1))*(INDEX('DBX Sprint'!$A$7:$K$62, ,19)>=TODAY()),MATCH(ROW('DBX Sprint'!$A$7:$K$62),ROW('DBX Sprint'!$A$7:$K$62)),""),ROWS($Q$34:Q40)),COLUMNS('DBX Sprint'!$A$1:A12)),"")} | R40: {=IFERROR(INDEX('DBX Sprint'!$A$7:$K$62, SMALL(IF((INDEX('DBX Sprint'!$A$7:$K$62, ,19)<=(TODAY()+5))*(INDEX('DBX Sprint'!$A$7:$K$62, ,19)>(TODAY()+1)),MATCH(ROW('DBX Sprint'!$A$7:$K$62),ROW('DBX Sprint'!$A$7:$K$62)),""),ROWS($R$34:R40)),COLUMNS('DBX Sprint'!$A$1:A12)),"")} | S40: {=IFERROR(INDEX('DBX Sprint'!$A$7:$K$62, SMALL(IF((INDEX('DBX Sprint'!$A$7:$K$62, ,19)<=(TODAY()+10))*(INDEX('DBX Sprint'!$A$7:$K$62, ,19)>(TODAY()+5)),MATCH(ROW('DBX Sprint'!$A$7:$K$62),ROW('DBX Sprint'!$A$7:$K$62)),""),ROWS($S$34:S40)),COLUMNS('DBX Sprint'!$A$1:A12)),"")} | U40: {=IFERROR(INDEX('DBX Sprint'!$A$7:$K$62, SMALL(IF((INDEX('DBX Sprint'!$A$7:$K$62, ,22)=("Complete"))*(INDEX('DBX Sprint'!$A$7:$K$62, ,22)="Complete"),MATCH(ROW('DBX Sprint'!$A$7:$K$62),ROW('DBX Sprint'!$A$7:$K$62)),""),ROWS($U$34:U40)),COLUMNS('DBX Sprint'!$A$1:A12)),"")} | V40: {=IFERROR(INDEX('DBX Sprint'!$A$7:$K$62, SMALL(IF((INDEX('DBX Sprint'!$A$7:$K$62, ,22)<(TODAY()))*(INDEX('DBX Sprint'!$A$7:$K$62, ,22)<>"Complete"),MATCH(ROW('DBX Sprint'!$A$7:$K$62),ROW('DBX Sprint'!$A$7:$K$62)),""),ROWS($V$34:V40)),COLUMNS('DBX Sprint'!$A$1:A12)),"")} | W40: {=IFERROR(INDEX('DBX Sprint'!$A$7:$K$62, SMALL(IF((INDEX('DBX Sprint'!$A$7:$K$62, ,22)<=(TODAY()+1))*(INDEX('DBX Sprint'!$A$7:$K$62, ,22)>=TODAY()),MATCH(ROW('DBX Sprint'!$A$7:$K$62),ROW('DBX Sprint'!$A$7:$K$62)),""),ROWS($W$34:W40)),COLUMNS('DBX Sprint'!$A$1:A12)),"")} | X40: {=IFERROR(INDEX('DBX Sprint'!$A$7:$K$62, SMALL(IF((INDEX('DBX Sprint'!$A$7:$K$62, ,22)<=(TODAY()+5))*(INDEX('DBX Sprint'!$A$7:$K$62, ,22)>(TODAY()+1)),MATCH(ROW('DBX Sprint'!$A$7:$K$62),ROW('DBX Sprint'!$A$7:$K$62)),""),ROWS($X$34:X40)),COLUMNS('DBX Sprint'!$A$1:A12)),"")} | Y40: {=IFERROR(INDEX('DBX Sprint'!$A$7:$K$62, SMALL(IF((INDEX('DBX Sprint'!$A$7:$K$62, ,22)<=(TODAY()+10))*(INDEX('DBX Sprint'!$A$7:$K$62, ,22)>(TODAY()+5)),MATCH(ROW('DBX Sprint'!$A$7:$K$62),ROW('DBX Sprint'!$A$7:$K$62)),""),ROWS($Y$34:Y40)),COLUMNS('DBX Sprint'!$A$1:A12)),"")} | AA40: {=IFERROR(INDEX('DBX Sprint'!$A$7:$K$62, SMALL(IF((INDEX('DBX Sprint'!$A$7:$K$62, ,25)=("Complete"))*(INDEX('DBX Sprint'!$A$7:$K$62, ,25)="Complete"),MATCH(ROW('DBX Sprint'!$A$7:$K$62),ROW('DBX Sprint'!$A$7:$K$62)),""),ROWS($AA$34:AA40)),COLUMNS('DBX Sprint'!$A$1:A12)),"")} | AB40: {=IFERROR(INDEX('DBX Sprint'!$A$7:$K$62, SMALL(IF((INDEX('DBX Sprint'!$A$7:$K$62, ,25)<(TODAY()))*(INDEX('DBX Sprint'!$A$7:$K$62, ,25)<>"Complete"),MATCH(ROW('DBX Sprint'!$A$7:$K$62),ROW('DBX Sprint'!$A$7:$K$62)),""),ROWS($AB$34:AB40)),COLUMNS('DBX Sprint'!$A$1:A12)),"")} | AC40: {=IFERROR(INDEX('DBX Sprint'!$A$7:$K$62, SMALL(IF((INDEX('DBX Sprint'!$A$7:$K$62, ,25)<=(TODAY()+1))*(INDEX('DBX Sprint'!$A$7:$K$62, ,25)>=TODAY()),MATCH(ROW('DBX Sprint'!$A$7:$K$62),ROW('DBX Sprint'!$A$7:$K$62)),""),ROWS($AC$34:AC40)),COLUMNS('DBX Sprint'!$A$1:A12)),"")} | AD40: {=IFERROR(INDEX('DBX Sprint'!$A$7:$K$62, SMALL(IF((INDEX('DBX Sprint'!$A$7:$K$62, ,25)<=(TODAY()+5))*(INDEX('DBX Sprint'!$A$7:$K$62, ,25)>(TODAY()+1)),MATCH(ROW('DBX Sprint'!$A$7:$K$62),ROW('DBX Sprint'!$A$7:$K$62)),""),ROWS($AD$34:AD40)),COLUMNS('DBX Sprint'!$A$1:A12)),"")} | AE40: {=IFERROR(INDEX('DBX Sprint'!$A$7:$K$62, SMALL(IF((INDEX('DBX Sprint'!$A$7:$K$62, ,25)<=(TODAY()+10))*(INDEX('DBX Sprint'!$A$7:$K$62, ,25)>(TODAY()+5)),MATCH(ROW('DBX Sprint'!$A$7:$K$62),ROW('DBX Sprint'!$A$7:$K$62)),""),ROWS($AE$34:AE40)),COLUMNS('DBX Sprint'!$A$1:A12)),"")} | AG40: {=IFERROR(INDEX('DBX Sprint'!$A$7:$K$62, SMALL(IF((INDEX('DBX Sprint'!$A$7:$K$62, ,29)=("Complete"))*(INDEX('DBX Sprint'!$A$7:$K$62, ,29)="Complete"),MATCH(ROW('DBX Sprint'!$A$7:$K$62),ROW('DBX Sprint'!$A$7:$K$62)),""),ROWS($AG$34:AG40)),COLUMNS('DBX Sprint'!$A$1:A12)),"")} | AH40: {=IFERROR(INDEX('DBX Sprint'!$A$7:$K$62, SMALL(IF((INDEX('DBX Sprint'!$A$7:$K$62, ,29)<(TODAY()))*(INDEX('DBX Sprint'!$A$7:$K$62, ,29)<>"Complete"),MATCH(ROW('DBX Sprint'!$A$7:$K$62),ROW('DBX Sprint'!$A$7:$K$62)),""),ROWS($AH$34:AH40)),COLUMNS('DBX Sprint'!$A$1:A12)),"")} | AI40: {=IFERROR(INDEX('DBX Sprint'!$A$7:$K$62, SMALL(IF((INDEX('DBX Sprint'!$A$7:$K$62, ,29)<=(TODAY()+1))*(INDEX('DBX Sprint'!$A$7:$K$62, ,29)>=TODAY()),MATCH(ROW('DBX Sprint'!$A$7:$K$62),ROW('DBX Sprint'!$A$7:$K$62)),""),ROWS($AI$34:AI40)),COLUMNS('DBX Sprint'!$A$1:A12)),"")} | AJ40: {=IFERROR(INDEX('DBX Sprint'!$A$7:$K$62, SMALL(IF((INDEX('DBX Sprint'!$A$7:$K$62, ,29)<=(TODAY()+5))*(INDEX('DBX Sprint'!$A$7:$K$62, ,29)>(TODAY()+1)),MATCH(ROW('DBX Sprint'!$A$7:$K$62),ROW('DBX Sprint'!$A$7:$K$62)),""),ROWS($AJ$34:AJ40)),COLUMNS('DBX Sprint'!$A$1:A12)),"")} | AK40: {=IFERROR(INDEX('DBX Sprint'!$A$7:$K$62, SMALL(IF((INDEX('DBX Sprint'!$A$7:$K$62, ,29)<=(TODAY()+10))*(INDEX('DBX Sprint'!$A$7:$K$62, ,29)>(TODAY()+5)),MATCH(ROW('DBX Sprint'!$A$7:$K$62),ROW('DBX Sprint'!$A$7:$K$62)),""),ROWS($AK$34:AK40)),COLUMNS('DBX Sprint'!$A$1:A12)),"")} | AM40: {=IFERROR(INDEX('DBX Sprint'!$A$7:$K$62, SMALL(IF((INDEX('DBX Sprint'!$A$7:$K$62, ,32)=("Complete"))*(INDEX('DBX Sprint'!$A$7:$K$62, ,32)="Complete"),MATCH(ROW('DBX Sprint'!$A$7:$K$62),ROW('DBX Sprint'!$A$7:$K$62)),""),ROWS($AM$34:AM40)),COLUMNS('DBX Sprint'!$A$1:A12)),"")} | AN40: {=IFERROR(INDEX('DBX Sprint'!$A$7:$K$62, SMALL(IF((INDEX('DBX Sprint'!$A$7:$K$62, ,32)<(TODAY()))*(INDEX('DBX Sprint'!$A$7:$K$62, ,32)<>"Complete"),MATCH(ROW('DBX Sprint'!$A$7:$K$62),ROW('DBX Sprint'!$A$7:$K$62)),""),ROWS($AN$34:AN40)),COLUMNS('DBX Sprint'!$A$1:A12)),"")} | AO40: {=IFERROR(INDEX('DBX Sprint'!$A$7:$K$62, SMALL(IF((INDEX('DBX Sprint'!$A$7:$K$62, ,32)<=(TODAY()+1))*(INDEX('DBX Sprint'!$A$7:$K$62, ,32)>=TODAY()),MATCH(ROW('DBX Sprint'!$A$7:$K$62),ROW('DBX Sprint'!$A$7:$K$62)),""),ROWS($AO$34:AO40)),COLUMNS('DBX Sprint'!$A$1:A12)),"")} | AP40: {=IFERROR(INDEX('DBX Sprint'!$A$7:$K$62, SMALL(IF((INDEX('DBX Sprint'!$A$7:$K$62, ,32)<=(TODAY()+5))*(INDEX('DBX Sprint'!$A$7:$K$62, ,32)>(TODAY()+1)),MATCH(ROW('DBX Sprint'!$A$7:$K$62),ROW('DBX Sprint'!$A$7:$K$62)),""),ROWS($AP$34:AP40)),COLUMNS('DBX Sprint'!$A$1:A12)),"")} | AQ40: {=IFERROR(INDEX('DBX Sprint'!$A$7:$K$62, SMALL(IF((INDEX('DBX Sprint'!$A$7:$K$62, ,32)<=(TODAY()+10))*(INDEX('DBX Sprint'!$A$7:$K$62, ,32)>(TODAY()+5)),MATCH(ROW('DBX Sprint'!$A$7:$K$62),ROW('DBX Sprint'!$A$7:$K$62)),""),ROWS($AQ$34:AQ40)),COLUMNS('DBX Sprint'!$A$1:A12)),"")}
C41: {=IFERROR(INDEX('DBX Sprint'!$A$7:$K$62, SMALL(IF((INDEX('DBX Sprint'!$A$7:$K$62, ,13)=("Complete"))*(INDEX('DBX Sprint'!$A$7:$K$62, ,13)="Complete"),MATCH(ROW('DBX Sprint'!$A$7:$K$62),ROW('DBX Sprint'!$A$7:$K$62)),""),ROWS(C$34:$C41)),COLUMNS('DBX Sprint'!$A$1:A12)),"")} | D41: {=IFERROR(INDEX('DBX Sprint'!$A$7:$K$62, SMALL(IF((INDEX('DBX Sprint'!$A$7:$K$62, ,13)<(TODAY()))*(INDEX('DBX Sprint'!$A$7:$K$62, ,13)<>"Complete"),MATCH(ROW('DBX Sprint'!$A$7:$K$62),ROW('DBX Sprint'!$A$7:$K$62)),""),ROWS(D$34:$D41)),COLUMNS('DBX Sprint'!$A$1:A12)),"")} | E41: {=IFERROR(INDEX('DBX Sprint'!$A$7:$K$62, SMALL(IF((INDEX('DBX Sprint'!$A$7:$K$62, ,13)<=(TODAY()+1))*(INDEX('DBX Sprint'!$A$7:$K$62, ,13)>=TODAY()),MATCH(ROW('DBX Sprint'!$A$7:$K$62),ROW('DBX Sprint'!$A$7:$K$62)),""),ROWS(E$34:$E41)),COLUMNS('DBX Sprint'!$A$1:A12)),"")} | F41: {=IFERROR(INDEX('DBX Sprint'!$A$7:$K$62, SMALL(IF((INDEX('DBX Sprint'!$A$7:$K$62, ,13)<=(TODAY()+5))*(INDEX('DBX Sprint'!$A$7:$K$62, ,13)>(TODAY()+1)),MATCH(ROW('DBX Sprint'!$A$7:$K$62),ROW('DBX Sprint'!$A$7:$K$62)),""),ROWS($F$34:F41)),COLUMNS('DBX Sprint'!$A$1:A12)),"")} | G41: {=IFERROR(INDEX('DBX Sprint'!$A$7:$K$62, SMALL(IF((INDEX('DBX Sprint'!$A$7:$K$62, ,13)<=(TODAY()+10))*(INDEX('DBX Sprint'!$A$7:$K$62, ,13)>(TODAY()+5)),MATCH(ROW('DBX Sprint'!$A$7:$K$62),ROW('DBX Sprint'!$A$7:$K$62)),""),ROWS($G$34:G41)),COLUMNS('DBX Sprint'!$A$1:A12)),"")} | I41: {=IFERROR(INDEX('DBX Sprint'!$A$7:$K$62, SMALL(IF((INDEX('DBX Sprint'!$A$7:$K$62, ,16)=("Complete"))*(INDEX('DBX Sprint'!$A$7:$K$62, ,16)="Complete"),MATCH(ROW('DBX Sprint'!$A$7:$K$62),ROW('DBX Sprint'!$A$7:$K$62)),""),ROWS($I$34:I41)),COLUMNS('DBX Sprint'!$A$1:A12)),"")} | J41: {=IFERROR(INDEX('DBX Sprint'!$A$7:$K$62, SMALL(IF((INDEX('DBX Sprint'!$A$7:$K$62, ,16)<(TODAY()))*(INDEX('DBX Sprint'!$A$7:$K$62, ,16)<>"Complete"),MATCH(ROW('DBX Sprint'!$A$7:$K$62),ROW('DBX Sprint'!$A$7:$K$62)),""),ROWS($J$34:J41)),COLUMNS('DBX Sprint'!$A$1:A12)),"")} | K41: {=IFERROR(INDEX('DBX Sprint'!$A$7:$K$62, SMALL(IF((INDEX('DBX Sprint'!$A$7:$K$62, ,16)<=(TODAY()+1))*(INDEX('DBX Sprint'!$A$7:$K$62, ,16)>=TODAY()),MATCH(ROW('DBX Sprint'!$A$7:$K$62),ROW('DBX Sprint'!$A$7:$K$62)),""),ROWS($K$34:K41)),COLUMNS('DBX Sprint'!$A$1:A12)),"")} | L41: {=IFERROR(INDEX('DBX Sprint'!$A$7:$K$62, SMALL(IF((INDEX('DBX Sprint'!$A$7:$K$62, ,16)<=(TODAY()+5))*(INDEX('DBX Sprint'!$A$7:$K$62, ,16)>(TODAY()+1)),MATCH(ROW('DBX Sprint'!$A$7:$K$62),ROW('DBX Sprint'!$A$7:$K$62)),""),ROWS($L$34:L41)),COLUMNS('DBX Sprint'!$A$1:A12)),"")} | M41: {=IFERROR(INDEX('DBX Sprint'!$A$7:$K$62, SMALL(IF((INDEX('DBX Sprint'!$A$7:$K$62, ,16)<=(TODAY()+10))*(INDEX('DBX Sprint'!$A$7:$K$62, ,16)>(TODAY()+5)),MATCH(ROW('DBX Sprint'!$A$7:$K$62),ROW('DBX Sprint'!$A$7:$K$62)),""),ROWS($M$34:M41)),COLUMNS('DBX Sprint'!$A$1:A12)),"")} | O41: {=IFERROR(INDEX('DBX Sprint'!$A$7:$K$62, SMALL(IF((INDEX('DBX Sprint'!$A$7:$K$62, ,19)=("Complete"))*(INDEX('DBX Sprint'!$A$7:$K$62, ,19)="Complete"),MATCH(ROW('DBX Sprint'!$A$7:$K$62),ROW('DBX Sprint'!$A$7:$K$62)),""),ROWS($O$34:O41)),COLUMNS('DBX Sprint'!$A$1:A12)),"")} | P41: {=IFERROR(INDEX('DBX Sprint'!$A$7:$K$62, SMALL(IF((INDEX('DBX Sprint'!$A$7:$K$62, ,19)<(TODAY()))*(INDEX('DBX Sprint'!$A$7:$K$62, ,19)<>"Complete"),MATCH(ROW('DBX Sprint'!$A$7:$K$62),ROW('DBX Sprint'!$A$7:$K$62)),""),ROWS($P$34:P41)),COLUMNS('DBX Sprint'!$A$1:A12)),"")} | Q41: {=IFERROR(INDEX('DBX Sprint'!$A$7:$K$62, SMALL(IF((INDEX('DBX Sprint'!$A$7:$K$62, ,19)<=(TODAY()+1))*(INDEX('DBX Sprint'!$A$7:$K$62, ,19)>=TODAY()),MATCH(ROW('DBX Sprint'!$A$7:$K$62),ROW('DBX Sprint'!$A$7:$K$62)),""),ROWS($Q$34:Q41)),COLUMNS('DBX Sprint'!$A$1:A12)),"")} | R41: {=IFERROR(INDEX('DBX Sprint'!$A$7:$K$62, SMALL(IF((INDEX('DBX Sprint'!$A$7:$K$62, ,19)<=(TODAY()+5))*(INDEX('DBX Sprint'!$A$7:$K$62, ,19)>(TODAY()+1)),MATCH(ROW('DBX Sprint'!$A$7:$K$62),ROW('DBX Sprint'!$A$7:$K$62)),""),ROWS($R$34:R41)),COLUMNS('DBX Sprint'!$A$1:A12)),"")} | S41: {=IFERROR(INDEX('DBX Sprint'!$A$7:$K$62, SMALL(IF((INDEX('DBX Sprint'!$A$7:$K$62, ,19)<=(TODAY()+10))*(INDEX('DBX Sprint'!$A$7:$K$62, ,19)>(TODAY()+5)),MATCH(ROW('DBX Sprint'!$A$7:$K$62),ROW('DBX Sprint'!$A$7:$K$62)),""),ROWS($S$34:S41)),COLUMNS('DBX Sprint'!$A$1:A12)),"")} | U41: {=IFERROR(INDEX('DBX Sprint'!$A$7:$K$62, SMALL(IF((INDEX('DBX Sprint'!$A$7:$K$62, ,22)=("Complete"))*(INDEX('DBX Sprint'!$A$7:$K$62, ,22)="Complete"),MATCH(ROW('DBX Sprint'!$A$7:$K$62),ROW('DBX Sprint'!$A$7:$K$62)),""),ROWS($U$34:U41)),COLUMNS('DBX Sprint'!$A$1:A12)),"")} | V41: {=IFERROR(INDEX('DBX Sprint'!$A$7:$K$62, SMALL(IF((INDEX('DBX Sprint'!$A$7:$K$62, ,22)<(TODAY()))*(INDEX('DBX Sprint'!$A$7:$K$62, ,22)<>"Complete"),MATCH(ROW('DBX Sprint'!$A$7:$K$62),ROW('DBX Sprint'!$A$7:$K$62)),""),ROWS($V$34:V41)),COLUMNS('DBX Sprint'!$A$1:A12)),"")} | W41: {=IFERROR(INDEX('DBX Sprint'!$A$7:$K$62, SMALL(IF((INDEX('DBX Sprint'!$A$7:$K$62, ,22)<=(TODAY()+1))*(INDEX('DBX Sprint'!$A$7:$K$62, ,22)>=TODAY()),MATCH(ROW('DBX Sprint'!$A$7:$K$62),ROW('DBX Sprint'!$A$7:$K$62)),""),ROWS($W$34:W41)),COLUMNS('DBX Sprint'!$A$1:A12)),"")} | X41: {=IFERROR(INDEX('DBX Sprint'!$A$7:$K$62, SMALL(IF((INDEX('DBX Sprint'!$A$7:$K$62, ,22)<=(TODAY()+5))*(INDEX('DBX Sprint'!$A$7:$K$62, ,22)>(TODAY()+1)),MATCH(ROW('DBX Sprint'!$A$7:$K$62),ROW('DBX Sprint'!$A$7:$K$62)),""),ROWS($X$34:X41)),COLUMNS('DBX Sprint'!$A$1:A12)),"")} | Y41: {=IFERROR(INDEX('DBX Sprint'!$A$7:$K$62, SMALL(IF((INDEX('DBX Sprint'!$A$7:$K$62, ,22)<=(TODAY()+10))*(INDEX('DBX Sprint'!$A$7:$K$62, ,22)>(TODAY()+5)),MATCH(ROW('DBX Sprint'!$A$7:$K$62),ROW('DBX Sprint'!$A$7:$K$62)),""),ROWS($Y$34:Y41)),COLUMNS('DBX Sprint'!$A$1:A12)),"")} | AA41: {=IFERROR(INDEX('DBX Sprint'!$A$7:$K$62, SMALL(IF((INDEX('DBX Sprint'!$A$7:$K$62, ,25)=("Complete"))*(INDEX('DBX Sprint'!$A$7:$K$62, ,25)="Complete"),MATCH(ROW('DBX Sprint'!$A$7:$K$62),ROW('DBX Sprint'!$A$7:$K$62)),""),ROWS($AA$34:AA41)),COLUMNS('DBX Sprint'!$A$1:A12)),"")} | AB41: {=IFERROR(INDEX('DBX Sprint'!$A$7:$K$62, SMALL(IF((INDEX('DBX Sprint'!$A$7:$K$62, ,25)<(TODAY()))*(INDEX('DBX Sprint'!$A$7:$K$62, ,25)<>"Complete"),MATCH(ROW('DBX Sprint'!$A$7:$K$62),ROW('DBX Sprint'!$A$7:$K$62)),""),ROWS($AB$34:AB41)),COLUMNS('DBX Sprint'!$A$1:A12)),"")} | AC41: {=IFERROR(INDEX('DBX Sprint'!$A$7:$K$62, SMALL(IF((INDEX('DBX Sprint'!$A$7:$K$62, ,25)<=(TODAY()+1))*(INDEX('DBX Sprint'!$A$7:$K$62, ,25)>=TODAY()),MATCH(ROW('DBX Sprint'!$A$7:$K$62),ROW('DBX Sprint'!$A$7:$K$62)),""),ROWS($AC$34:AC41)),COLUMNS('DBX Sprint'!$A$1:A12)),"")} | AD41: {=IFERROR(INDEX('DBX Sprint'!$A$7:$K$62, SMALL(IF((INDEX('DBX Sprint'!$A$7:$K$62, ,25)<=(TODAY()+5))*(INDEX('DBX Sprint'!$A$7:$K$62, ,25)>(TODAY()+1)),MATCH(ROW('DBX Sprint'!$A$7:$K$62),ROW('DBX Sprint'!$A$7:$K$62)),""),ROWS($AD$34:AD41)),COLUMNS('DBX Sprint'!$A$1:A12)),"")} | AE41: {=IFERROR(INDEX('DBX Sprint'!$A$7:$K$62, SMALL(IF((INDEX('DBX Sprint'!$A$7:$K$62, ,25)<=(TODAY()+10))*(INDEX('DBX Sprint'!$A$7:$K$62, ,25)>(TODAY()+5)),MATCH(ROW('DBX Sprint'!$A$7:$K$62),ROW('DBX Sprint'!$A$7:$K$62)),""),ROWS($AE$34:AE41)),COLUMNS('DBX Sprint'!$A$1:A12)),"")} | AG41: {=IFERROR(INDEX('DBX Sprint'!$A$7:$K$62, SMALL(IF((INDEX('DBX Sprint'!$A$7:$K$62, ,29)=("Complete"))*(INDEX('DBX Sprint'!$A$7:$K$62, ,29)="Complete"),MATCH(ROW('DBX Sprint'!$A$7:$K$62),ROW('DBX Sprint'!$A$7:$K$62)),""),ROWS($AG$34:AG41)),COLUMNS('DBX Sprint'!$A$1:A12)),"")} | AH41: {=IFERROR(INDEX('DBX Sprint'!$A$7:$K$62, SMALL(IF((INDEX('DBX Sprint'!$A$7:$K$62, ,29)<(TODAY()))*(INDEX('DBX Sprint'!$A$7:$K$62, ,29)<>"Complete"),MATCH(ROW('DBX Sprint'!$A$7:$K$62),ROW('DBX Sprint'!$A$7:$K$62)),""),ROWS($AH$34:AH41)),COLUMNS('DBX Sprint'!$A$1:A12)),"")} | AI41: {=IFERROR(INDEX('DBX Sprint'!$A$7:$K$62, SMALL(IF((INDEX('DBX Sprint'!$A$7:$K$62, ,29)<=(TODAY()+1))*(INDEX('DBX Sprint'!$A$7:$K$62, ,29)>=TODAY()),MATCH(ROW('DBX Sprint'!$A$7:$K$62),ROW('DBX Sprint'!$A$7:$K$62)),""),ROWS($AI$34:AI41)),COLUMNS('DBX Sprint'!$A$1:A12)),"")} | AJ41: {=IFERROR(INDEX('DBX Sprint'!$A$7:$K$62, SMALL(IF((INDEX('DBX Sprint'!$A$7:$K$62, ,29)<=(TODAY()+5))*(INDEX('DBX Sprint'!$A$7:$K$62, ,29)>(TODAY()+1)),MATCH(ROW('DBX Sprint'!$A$7:$K$62),ROW('DBX Sprint'!$A$7:$K$62)),""),ROWS($AJ$34:AJ41)),COLUMNS('DBX Sprint'!$A$1:A12)),"")} | AK41: {=IFERROR(INDEX('DBX Sprint'!$A$7:$K$62, SMALL(IF((INDEX('DBX Sprint'!$A$7:$K$62, ,29)<=(TODAY()+10))*(INDEX('DBX Sprint'!$A$7:$K$62, ,29)>(TODAY()+5)),MATCH(ROW('DBX Sprint'!$A$7:$K$62),ROW('DBX Sprint'!$A$7:$K$62)),""),ROWS($AK$34:AK41)),COLUMNS('DBX Sprint'!$A$1:A12)),"")} | AM41: {=IFERROR(INDEX('DBX Sprint'!$A$7:$K$62, SMALL(IF((INDEX('DBX Sprint'!$A$7:$K$62, ,32)=("Complete"))*(INDEX('DBX Sprint'!$A$7:$K$62, ,32)="Complete"),MATCH(ROW('DBX Sprint'!$A$7:$K$62),ROW('DBX Sprint'!$A$7:$K$62)),""),ROWS($AM$34:AM41)),COLUMNS('DBX Sprint'!$A$1:A12)),"")} | AN41: {=IFERROR(INDEX('DBX Sprint'!$A$7:$K$62, SMALL(IF((INDEX('DBX Sprint'!$A$7:$K$62, ,32)<(TODAY()))*(INDEX('DBX Sprint'!$A$7:$K$62, ,32)<>"Complete"),MATCH(ROW('DBX Sprint'!$A$7:$K$62),ROW('DBX Sprint'!$A$7:$K$62)),""),ROWS($AN$34:AN41)),COLUMNS('DBX Sprint'!$A$1:A12)),"")} | AO41: {=IFERROR(INDEX('DBX Sprint'!$A$7:$K$62, SMALL(IF((INDEX('DBX Sprint'!$A$7:$K$62, ,32)<=(TODAY()+1))*(INDEX('DBX Sprint'!$A$7:$K$62, ,32)>=TODAY()),MATCH(ROW('DBX Sprint'!$A$7:$K$62),ROW('DBX Sprint'!$A$7:$K$62)),""),ROWS($AO$34:AO41)),COLUMNS('DBX Sprint'!$A$1:A12)),"")} | AP41: {=IFERROR(INDEX('DBX Sprint'!$A$7:$K$62, SMALL(IF((INDEX('DBX Sprint'!$A$7:$K$62, ,32)<=(TODAY()+5))*(INDEX('DBX Sprint'!$A$7:$K$62, ,32)>(TODAY()+1)),MATCH(ROW('DBX Sprint'!$A$7:$K$62),ROW('DBX Sprint'!$A$7:$K$62)),""),ROWS($AP$34:AP41)),COLUMNS('DBX Sprint'!$A$1:A12)),"")} | AQ41: {=IFERROR(INDEX('DBX Sprint'!$A$7:$K$62, SMALL(IF((INDEX('DBX Sprint'!$A$7:$K$62, ,32)<=(TODAY()+10))*(INDEX('DBX Sprint'!$A$7:$K$62, ,32)>(TODAY()+5)),MATCH(ROW('DBX Sprint'!$A$7:$K$62),ROW('DBX Sprint'!$A$7:$K$62)),""),ROWS($AQ$34:AQ41)),COLUMNS('DBX Sprint'!$A$1:A12)),"")}
C42: {=IFERROR(INDEX('DBX Sprint'!$A$7:$K$62, SMALL(IF((INDEX('DBX Sprint'!$A$7:$K$62, ,13)=("Complete"))*(INDEX('DBX Sprint'!$A$7:$K$62, ,13)="Complete"),MATCH(ROW('DBX Sprint'!$A$7:$K$62),ROW('DBX Sprint'!$A$7:$K$62)),""),ROWS(C$34:$C42)),COLUMNS('DBX Sprint'!$A$1:A12)),"")} | D42: {=IFERROR(INDEX('DBX Sprint'!$A$7:$K$62, SMALL(IF((INDEX('DBX Sprint'!$A$7:$K$62, ,13)<(TODAY()))*(INDEX('DBX Sprint'!$A$7:$K$62, ,13)<>"Complete"),MATCH(ROW('DBX Sprint'!$A$7:$K$62),ROW('DBX Sprint'!$A$7:$K$62)),""),ROWS(D$34:$D42)),COLUMNS('DBX Sprint'!$A$1:A12)),"")} | E42: {=IFERROR(INDEX('DBX Sprint'!$A$7:$K$62, SMALL(IF((INDEX('DBX Sprint'!$A$7:$K$62, ,13)<=(TODAY()+1))*(INDEX('DBX Sprint'!$A$7:$K$62, ,13)>=TODAY()),MATCH(ROW('DBX Sprint'!$A$7:$K$62),ROW('DBX Sprint'!$A$7:$K$62)),""),ROWS(E$34:$E42)),COLUMNS('DBX Sprint'!$A$1:A12)),"")} | F42: {=IFERROR(INDEX('DBX Sprint'!$A$7:$K$62, SMALL(IF((INDEX('DBX Sprint'!$A$7:$K$62, ,13)<=(TODAY()+5))*(INDEX('DBX Sprint'!$A$7:$K$62, ,13)>(TODAY()+1)),MATCH(ROW('DBX Sprint'!$A$7:$K$62),ROW('DBX Sprint'!$A$7:$K$62)),""),ROWS($F$34:F42)),COLUMNS('DBX Sprint'!$A$1:A12)),"")} | G42: {=IFERROR(INDEX('DBX Sprint'!$A$7:$K$62, SMALL(IF((INDEX('DBX Sprint'!$A$7:$K$62, ,13)<=(TODAY()+10))*(INDEX('DBX Sprint'!$A$7:$K$62, ,13)>(TODAY()+5)),MATCH(ROW('DBX Sprint'!$A$7:$K$62),ROW('DBX Sprint'!$A$7:$K$62)),""),ROWS($G$34:G42)),COLUMNS('DBX Sprint'!$A$1:A12)),"")} | I42: {=IFERROR(INDEX('DBX Sprint'!$A$7:$K$62, SMALL(IF((INDEX('DBX Sprint'!$A$7:$K$62, ,16)=("Complete"))*(INDEX('DBX Sprint'!$A$7:$K$62, ,16)="Complete"),MATCH(ROW('DBX Sprint'!$A$7:$K$62),ROW('DBX Sprint'!$A$7:$K$62)),""),ROWS($I$34:I42)),COLUMNS('DBX Sprint'!$A$1:A12)),"")} | J42: {=IFERROR(INDEX('DBX Sprint'!$A$7:$K$62, SMALL(IF((INDEX('DBX Sprint'!$A$7:$K$62, ,16)<(TODAY()))*(INDEX('DBX Sprint'!$A$7:$K$62, ,16)<>"Complete"),MATCH(ROW('DBX Sprint'!$A$7:$K$62),ROW('DBX Sprint'!$A$7:$K$62)),""),ROWS($J$34:J42)),COLUMNS('DBX Sprint'!$A$1:A12)),"")} | K42: {=IFERROR(INDEX('DBX Sprint'!$A$7:$K$62, SMALL(IF((INDEX('DBX Sprint'!$A$7:$K$62, ,16)<=(TODAY()+1))*(INDEX('DBX Sprint'!$A$7:$K$62, ,16)>=TODAY()),MATCH(ROW('DBX Sprint'!$A$7:$K$62),ROW('DBX Sprint'!$A$7:$K$62)),""),ROWS($K$34:K42)),COLUMNS('DBX Sprint'!$A$1:A12)),"")} | L42: {=IFERROR(INDEX('DBX Sprint'!$A$7:$K$62, SMALL(IF((INDEX('DBX Sprint'!$A$7:$K$62, ,16)<=(TODAY()+5))*(INDEX('DBX Sprint'!$A$7:$K$62, ,16)>(TODAY()+1)),MATCH(ROW('DBX Sprint'!$A$7:$K$62),ROW('DBX Sprint'!$A$7:$K$62)),""),ROWS($L$34:L42)),COLUMNS('DBX Sprint'!$A$1:A12)),"")} | M42: {=IFERROR(INDEX('DBX Sprint'!$A$7:$K$62, SMALL(IF((INDEX('DBX Sprint'!$A$7:$K$62, ,16)<=(TODAY()+10))*(INDEX('DBX Sprint'!$A$7:$K$62, ,16)>(TODAY()+5)),MATCH(ROW('DBX Sprint'!$A$7:$K$62),ROW('DBX Sprint'!$A$7:$K$62)),""),ROWS($M$34:M42)),COLUMNS('DBX Sprint'!$A$1:A12)),"")} | O42: {=IFERROR(INDEX('DBX Sprint'!$A$7:$K$62, SMALL(IF((INDEX('DBX Sprint'!$A$7:$K$62, ,19)=("Complete"))*(INDEX('DBX Sprint'!$A$7:$K$62, ,19)="Complete"),MATCH(ROW('DBX Sprint'!$A$7:$K$62),ROW('DBX Sprint'!$A$7:$K$62)),""),ROWS($O$34:O42)),COLUMNS('DBX Sprint'!$A$1:A12)),"")} | P42: {=IFERROR(INDEX('DBX Sprint'!$A$7:$K$62, SMALL(IF((INDEX('DBX Sprint'!$A$7:$K$62, ,19)<(TODAY()))*(INDEX('DBX Sprint'!$A$7:$K$62, ,19)<>"Complete"),MATCH(ROW('DBX Sprint'!$A$7:$K$62),ROW('DBX Sprint'!$A$7:$K$62)),""),ROWS($P$34:P42)),COLUMNS('DBX Sprint'!$A$1:A12)),"")} | Q42: {=IFERROR(INDEX('DBX Sprint'!$A$7:$K$62, SMALL(IF((INDEX('DBX Sprint'!$A$7:$K$62, ,19)<=(TODAY()+1))*(INDEX('DBX Sprint'!$A$7:$K$62, ,19)>=TODAY()),MATCH(ROW('DBX Sprint'!$A$7:$K$62),ROW('DBX Sprint'!$A$7:$K$62)),""),ROWS($Q$34:Q42)),COLUMNS('DBX Sprint'!$A$1:A12)),"")} | R42: {=IFERROR(INDEX('DBX Sprint'!$A$7:$K$62, SMALL(IF((INDEX('DBX Sprint'!$A$7:$K$62, ,19)<=(TODAY()+5))*(INDEX('DBX Sprint'!$A$7:$K$62, ,19)>(TODAY()+1)),MATCH(ROW('DBX Sprint'!$A$7:$K$62),ROW('DBX Sprint'!$A$7:$K$62)),""),ROWS($R$34:R42)),COLUMNS('DBX Sprint'!$A$1:A12)),"")} | S42: {=IFERROR(INDEX('DBX Sprint'!$A$7:$K$62, SMALL(IF((INDEX('DBX Sprint'!$A$7:$K$62, ,19)<=(TODAY()+10))*(INDEX('DBX Sprint'!$A$7:$K$62, ,19)>(TODAY()+5)),MATCH(ROW('DBX Sprint'!$A$7:$K$62),ROW('DBX Sprint'!$A$7:$K$62)),""),ROWS($S$34:S42)),COLUMNS('DBX Sprint'!$A$1:A12)),"")} | U42: {=IFERROR(INDEX('DBX Sprint'!$A$7:$K$62, SMALL(IF((INDEX('DBX Sprint'!$A$7:$K$62, ,22)=("Complete"))*(INDEX('DBX Sprint'!$A$7:$K$62, ,22)="Complete"),MATCH(ROW('DBX Sprint'!$A$7:$K$62),ROW('DBX Sprint'!$A$7:$K$62)),""),ROWS($U$34:U42)),COLUMNS('DBX Sprint'!$A$1:A12)),"")} | V42: {=IFERROR(INDEX('DBX Sprint'!$A$7:$K$62, SMALL(IF((INDEX('DBX Sprint'!$A$7:$K$62, ,22)<(TODAY()))*(INDEX('DBX Sprint'!$A$7:$K$62, ,22)<>"Complete"),MATCH(ROW('DBX Sprint'!$A$7:$K$62),ROW('DBX Sprint'!$A$7:$K$62)),""),ROWS($V$34:V42)),COLUMNS('DBX Sprint'!$A$1:A12)),"")} | W42: {=IFERROR(INDEX('DBX Sprint'!$A$7:$K$62, SMALL(IF((INDEX('DBX Sprint'!$A$7:$K$62, ,22)<=(TODAY()+1))*(INDEX('DBX Sprint'!$A$7:$K$62, ,22)>=TODAY()),MATCH(ROW('DBX Sprint'!$A$7:$K$62),ROW('DBX Sprint'!$A$7:$K$62)),""),ROWS($W$34:W42)),COLUMNS('DBX Sprint'!$A$1:A12)),"")} | X42: {=IFERROR(INDEX('DBX Sprint'!$A$7:$K$62, SMALL(IF((INDEX('DBX Sprint'!$A$7:$K$62, ,22)<=(TODAY()+5))*(INDEX('DBX Sprint'!$A$7:$K$62, ,22)>(TODAY()+1)),MATCH(ROW('DBX Sprint'!$A$7:$K$62),ROW('DBX Sprint'!$A$7:$K$62)),""),ROWS($X$34:X42)),COLUMNS('DBX Sprint'!$A$1:A12)),"")} | Y42: {=IFERROR(INDEX('DBX Sprint'!$A$7:$K$62, SMALL(IF((INDEX('DBX Sprint'!$A$7:$K$62, ,22)<=(TODAY()+10))*(INDEX('DBX Sprint'!$A$7:$K$62, ,22)>(TODAY()+5)),MATCH(ROW('DBX Sprint'!$A$7:$K$62),ROW('DBX Sprint'!$A$7:$K$62)),""),ROWS($Y$34:Y42)),COLUMNS('DBX Sprint'!$A$1:A12)),"")} | AA42: {=IFERROR(INDEX('DBX Sprint'!$A$7:$K$62, SMALL(IF((INDEX('DBX Sprint'!$A$7:$K$62, ,25)=("Complete"))*(INDEX('DBX Sprint'!$A$7:$K$62, ,25)="Complete"),MATCH(ROW('DBX Sprint'!$A$7:$K$62),ROW('DBX Sprint'!$A$7:$K$62)),""),ROWS($AA$34:AA42)),COLUMNS('DBX Sprint'!$A$1:A12)),"")} | AB42: {=IFERROR(INDEX('DBX Sprint'!$A$7:$K$62, SMALL(IF((INDEX('DBX Sprint'!$A$7:$K$62, ,25)<(TODAY()))*(INDEX('DBX Sprint'!$A$7:$K$62, ,25)<>"Complete"),MATCH(ROW('DBX Sprint'!$A$7:$K$62),ROW('DBX Sprint'!$A$7:$K$62)),""),ROWS($AB$34:AB42)),COLUMNS('DBX Sprint'!$A$1:A12)),"")} | AC42: {=IFERROR(INDEX('DBX Sprint'!$A$7:$K$62, SMALL(IF((INDEX('DBX Sprint'!$A$7:$K$62, ,25)<=(TODAY()+1))*(INDEX('DBX Sprint'!$A$7:$K$62, ,25)>=TODAY()),MATCH(ROW('DBX Sprint'!$A$7:$K$62),ROW('DBX Sprint'!$A$7:$K$62)),""),ROWS($AC$34:AC42)),COLUMNS('DBX Sprint'!$A$1:A12)),"")} | AD42: {=IFERROR(INDEX('DBX Sprint'!$A$7:$K$62, SMALL(IF((INDEX('DBX Sprint'!$A$7:$K$62, ,25)<=(TODAY()+5))*(INDEX('DBX Sprint'!$A$7:$K$62, ,25)>(TODAY()+1)),MATCH(ROW('DBX Sprint'!$A$7:$K$62),ROW('DBX Sprint'!$A$7:$K$62)),""),ROWS($AD$34:AD42)),COLUMNS('DBX Sprint'!$A$1:A12)),"")} | AE42: {=IFERROR(INDEX('DBX Sprint'!$A$7:$K$62, SMALL(IF((INDEX('DBX Sprint'!$A$7:$K$62, ,25)<=(TODAY()+10))*(INDEX('DBX Sprint'!$A$7:$K$62, ,25)>(TODAY()+5)),MATCH(ROW('DBX Sprint'!$A$7:$K$62),ROW('DBX Sprint'!$A$7:$K$62)),""),ROWS($AE$34:AE42)),COLUMNS('DBX Sprint'!$A$1:A12)),"")} | AG42: {=IFERROR(INDEX('DBX Sprint'!$A$7:$K$62, SMALL(IF((INDEX('DBX Sprint'!$A$7:$K$62, ,29)=("Complete"))*(INDEX('DBX Sprint'!$A$7:$K$62, ,29)="Complete"),MATCH(ROW('DBX Sprint'!$A$7:$K$62),ROW('DBX Sprint'!$A$7:$K$62)),""),ROWS($AG$34:AG42)),COLUMNS('DBX Sprint'!$A$1:A12)),"")} | AH42: {=IFERROR(INDEX('DBX Sprint'!$A$7:$K$62, SMALL(IF((INDEX('DBX Sprint'!$A$7:$K$62, ,29)<(TODAY()))*(INDEX('DBX Sprint'!$A$7:$K$62, ,29)<>"Complete"),MATCH(ROW('DBX Sprint'!$A$7:$K$62),ROW('DBX Sprint'!$A$7:$K$62)),""),ROWS($AH$34:AH42)),COLUMNS('DBX Sprint'!$A$1:A12)),"")} | AI42: {=IFERROR(INDEX('DBX Sprint'!$A$7:$K$62, SMALL(IF((INDEX('DBX Sprint'!$A$7:$K$62, ,29)<=(TODAY()+1))*(INDEX('DBX Sprint'!$A$7:$K$62, ,29)>=TODAY()),MATCH(ROW('DBX Sprint'!$A$7:$K$62),ROW('DBX Sprint'!$A$7:$K$62)),""),ROWS($AI$34:AI42)),COLUMNS('DBX Sprint'!$A$1:A12)),"")} | AJ42: {=IFERROR(INDEX('DBX Sprint'!$A$7:$K$62, SMALL(IF((INDEX('DBX Sprint'!$A$7:$K$62, ,29)<=(TODAY()+5))*(INDEX('DBX Sprint'!$A$7:$K$62, ,29)>(TODAY()+1)),MATCH(ROW('DBX Sprint'!$A$7:$K$62),ROW('DBX Sprint'!$A$7:$K$62)),""),ROWS($AJ$34:AJ42)),COLUMNS('DBX Sprint'!$A$1:A12)),"")} | AK42: {=IFERROR(INDEX('DBX Sprint'!$A$7:$K$62, SMALL(IF((INDEX('DBX Sprint'!$A$7:$K$62, ,29)<=(TODAY()+10))*(INDEX('DBX Sprint'!$A$7:$K$62, ,29)>(TODAY()+5)),MATCH(ROW('DBX Sprint'!$A$7:$K$62),ROW('DBX Sprint'!$A$7:$K$62)),""),ROWS($AK$34:AK42)),COLUMNS('DBX Sprint'!$A$1:A12)),"")} | AM42: {=IFERROR(INDEX('DBX Sprint'!$A$7:$K$62, SMALL(IF((INDEX('DBX Sprint'!$A$7:$K$62, ,32)=("Complete"))*(INDEX('DBX Sprint'!$A$7:$K$62, ,32)="Complete"),MATCH(ROW('DBX Sprint'!$A$7:$K$62),ROW('DBX Sprint'!$A$7:$K$62)),""),ROWS($AM$34:AM42)),COLUMNS('DBX Sprint'!$A$1:A12)),"")} | AN42: {=IFERROR(INDEX('DBX Sprint'!$A$7:$K$62, SMALL(IF((INDEX('DBX Sprint'!$A$7:$K$62, ,32)<(TODAY()))*(INDEX('DBX Sprint'!$A$7:$K$62, ,32)<>"Complete"),MATCH(ROW('DBX Sprint'!$A$7:$K$62),ROW('DBX Sprint'!$A$7:$K$62)),""),ROWS($AN$34:AN42)),COLUMNS('DBX Sprint'!$A$1:A12)),"")} | AO42: {=IFERROR(INDEX('DBX Sprint'!$A$7:$K$62, SMALL(IF((INDEX('DBX Sprint'!$A$7:$K$62, ,32)<=(TODAY()+1))*(INDEX('DBX Sprint'!$A$7:$K$62, ,32)>=TODAY()),MATCH(ROW('DBX Sprint'!$A$7:$K$62),ROW('DBX Sprint'!$A$7:$K$62)),""),ROWS($AO$34:AO42)),COLUMNS('DBX Sprint'!$A$1:A12)),"")} | AP42: {=IFERROR(INDEX('DBX Sprint'!$A$7:$K$62, SMALL(IF((INDEX('DBX Sprint'!$A$7:$K$62, ,32)<=(TODAY()+5))*(INDEX('DBX Sprint'!$A$7:$K$62, ,32)>(TODAY()+1)),MATCH(ROW('DBX Sprint'!$A$7:$K$62),ROW('DBX Sprint'!$A$7:$K$62)),""),ROWS($AP$34:AP42)),COLUMNS('DBX Sprint'!$A$1:A12)),"")} | AQ42: {=IFERROR(INDEX('DBX Sprint'!$A$7:$K$62, SMALL(IF((INDEX('DBX Sprint'!$A$7:$K$62, ,32)<=(TODAY()+10))*(INDEX('DBX Sprint'!$A$7:$K$62, ,32)>(TODAY()+5)),MATCH(ROW('DBX Sprint'!$A$7:$K$62),ROW('DBX Sprint'!$A$7:$K$62)),""),ROWS($AQ$34:AQ42)),COLUMNS('DBX Sprint'!$A$1:A12)),"")}
C43: {=IFERROR(INDEX('DBX Sprint'!$A$7:$K$62, SMALL(IF((INDEX('DBX Sprint'!$A$7:$K$62, ,13)=("Complete"))*(INDEX('DBX Sprint'!$A$7:$K$62, ,13)="Complete"),MATCH(ROW('DBX Sprint'!$A$7:$K$62),ROW('DBX Sprint'!$A$7:$K$62)),""),ROWS(C$34:$C43)),COLUMNS('DBX Sprint'!$A$1:A12)),"")} | D43: {=IFERROR(INDEX('DBX Sprint'!$A$7:$K$62, SMALL(IF((INDEX('DBX Sprint'!$A$7:$K$62, ,13)<(TODAY()))*(INDEX('DBX Sprint'!$A$7:$K$62, ,13)<>"Complete"),MATCH(ROW('DBX Sprint'!$A$7:$K$62),ROW('DBX Sprint'!$A$7:$K$62)),""),ROWS(D$34:$D43)),COLUMNS('DBX Sprint'!$A$1:A12)),"")} | E43: {=IFERROR(INDEX('DBX Sprint'!$A$7:$K$62, SMALL(IF((INDEX('DBX Sprint'!$A$7:$K$62, ,13)<=(TODAY()+1))*(INDEX('DBX Sprint'!$A$7:$K$62, ,13)>=TODAY()),MATCH(ROW('DBX Sprint'!$A$7:$K$62),ROW('DBX Sprint'!$A$7:$K$62)),""),ROWS(E$34:$E43)),COLUMNS('DBX Sprint'!$A$1:A12)),"")} | F43: {=IFERROR(INDEX('DBX Sprint'!$A$7:$K$62, SMALL(IF((INDEX('DBX Sprint'!$A$7:$K$62, ,13)<=(TODAY()+5))*(INDEX('DBX Sprint'!$A$7:$K$62, ,13)>(TODAY()+1)),MATCH(ROW('DBX Sprint'!$A$7:$K$62),ROW('DBX Sprint'!$A$7:$K$62)),""),ROWS($F$34:F43)),COLUMNS('DBX Sprint'!$A$1:A12)),"")} | G43: {=IFERROR(INDEX('DBX Sprint'!$A$7:$K$62, SMALL(IF((INDEX('DBX Sprint'!$A$7:$K$62, ,13)<=(TODAY()+10))*(INDEX('DBX Sprint'!$A$7:$K$62, ,13)>(TODAY()+5)),MATCH(ROW('DBX Sprint'!$A$7:$K$62),ROW('DBX Sprint'!$A$7:$K$62)),""),ROWS($G$34:G43)),COLUMNS('DBX Sprint'!$A$1:A12)),"")} | I43: {=IFERROR(INDEX('DBX Sprint'!$A$7:$K$62, SMALL(IF((INDEX('DBX Sprint'!$A$7:$K$62, ,16)=("Complete"))*(INDEX('DBX Sprint'!$A$7:$K$62, ,16)="Complete"),MATCH(ROW('DBX Sprint'!$A$7:$K$62),ROW('DBX Sprint'!$A$7:$K$62)),""),ROWS($I$34:I43)),COLUMNS('DBX Sprint'!$A$1:A12)),"")} | J43: {=IFERROR(INDEX('DBX Sprint'!$A$7:$K$62, SMALL(IF((INDEX('DBX Sprint'!$A$7:$K$62, ,16)<(TODAY()))*(INDEX('DBX Sprint'!$A$7:$K$62, ,16)<>"Complete"),MATCH(ROW('DBX Sprint'!$A$7:$K$62),ROW('DBX Sprint'!$A$7:$K$62)),""),ROWS($J$34:J43)),COLUMNS('DBX Sprint'!$A$1:A12)),"")} | K43: {=IFERROR(INDEX('DBX Sprint'!$A$7:$K$62, SMALL(IF((INDEX('DBX Sprint'!$A$7:$K$62, ,16)<=(TODAY()+1))*(INDEX('DBX Sprint'!$A$7:$K$62, ,16)>=TODAY()),MATCH(ROW('DBX Sprint'!$A$7:$K$62),ROW('DBX Sprint'!$A$7:$K$62)),""),ROWS($K$34:K43)),COLUMNS('DBX Sprint'!$A$1:A12)),"")} | L43: {=IFERROR(INDEX('DBX Sprint'!$A$7:$K$62, SMALL(IF((INDEX('DBX Sprint'!$A$7:$K$62, ,16)<=(TODAY()+5))*(INDEX('DBX Sprint'!$A$7:$K$62, ,16)>(TODAY()+1)),MATCH(ROW('DBX Sprint'!$A$7:$K$62),ROW('DBX Sprint'!$A$7:$K$62)),""),ROWS($L$34:L43)),COLUMNS('DBX Sprint'!$A$1:A12)),"")} | M43: {=IFERROR(INDEX('DBX Sprint'!$A$7:$K$62, SMALL(IF((INDEX('DBX Sprint'!$A$7:$K$62, ,16)<=(TODAY()+10))*(INDEX('DBX Sprint'!$A$7:$K$62, ,16)>(TODAY()+5)),MATCH(ROW('DBX Sprint'!$A$7:$K$62),ROW('DBX Sprint'!$A$7:$K$62)),""),ROWS($M$34:M43)),COLUMNS('DBX Sprint'!$A$1:A12)),"")} | O43: {=IFERROR(INDEX('DBX Sprint'!$A$7:$K$62, SMALL(IF((INDEX('DBX Sprint'!$A$7:$K$62, ,19)=("Complete"))*(INDEX('DBX Sprint'!$A$7:$K$62, ,19)="Complete"),MATCH(ROW('DBX Sprint'!$A$7:$K$62),ROW('DBX Sprint'!$A$7:$K$62)),""),ROWS($O$34:O43)),COLUMNS('DBX Sprint'!$A$1:A12)),"")} | P43: {=IFERROR(INDEX('DBX Sprint'!$A$7:$K$62, SMALL(IF((INDEX('DBX Sprint'!$A$7:$K$62, ,19)<(TODAY()))*(INDEX('DBX Sprint'!$A$7:$K$62, ,19)<>"Complete"),MATCH(ROW('DBX Sprint'!$A$7:$K$62),ROW('DBX Sprint'!$A$7:$K$62)),""),ROWS($P$34:P43)),COLUMNS('DBX Sprint'!$A$1:A12)),"")} | Q43: {=IFERROR(INDEX('DBX Sprint'!$A$7:$K$62, SMALL(IF((INDEX('DBX Sprint'!$A$7:$K$62, ,19)<=(TODAY()+1))*(INDEX('DBX Sprint'!$A$7:$K$62, ,19)>=TODAY()),MATCH(ROW('DBX Sprint'!$A$7:$K$62),ROW('DBX Sprint'!$A$7:$K$62)),""),ROWS($Q$34:Q43)),COLUMNS('DBX Sprint'!$A$1:A12)),"")} | R43: {=IFERROR(INDEX('DBX Sprint'!$A$7:$K$62, SMALL(IF((INDEX('DBX Sprint'!$A$7:$K$62, ,19)<=(TODAY()+5))*(INDEX('DBX Sprint'!$A$7:$K$62, ,19)>(TODAY()+1)),MATCH(ROW('DBX Sprint'!$A$7:$K$62),ROW('DBX Sprint'!$A$7:$K$62)),""),ROWS($R$34:R43)),COLUMNS('DBX Sprint'!$A$1:A12)),"")} | S43: {=IFERROR(INDEX('DBX Sprint'!$A$7:$K$62, SMALL(IF((INDEX('DBX Sprint'!$A$7:$K$62, ,19)<=(TODAY()+10))*(INDEX('DBX Sprint'!$A$7:$K$62, ,19)>(TODAY()+5)),MATCH(ROW('DBX Sprint'!$A$7:$K$62),ROW('DBX Sprint'!$A$7:$K$62)),""),ROWS($S$34:S43)),COLUMNS('DBX Sprint'!$A$1:A12)),"")} | U43: {=IFERROR(INDEX('DBX Sprint'!$A$7:$K$62, SMALL(IF((INDEX('DBX Sprint'!$A$7:$K$62, ,22)=("Complete"))*(INDEX('DBX Sprint'!$A$7:$K$62, ,22)="Complete"),MATCH(ROW('DBX Sprint'!$A$7:$K$62),ROW('DBX Sprint'!$A$7:$K$62)),""),ROWS($U$34:U43)),COLUMNS('DBX Sprint'!$A$1:A12)),"")} | V43: {=IFERROR(INDEX('DBX Sprint'!$A$7:$K$62, SMALL(IF((INDEX('DBX Sprint'!$A$7:$K$62, ,22)<(TODAY()))*(INDEX('DBX Sprint'!$A$7:$K$62, ,22)<>"Complete"),MATCH(ROW('DBX Sprint'!$A$7:$K$62),ROW('DBX Sprint'!$A$7:$K$62)),""),ROWS($V$34:V43)),COLUMNS('DBX Sprint'!$A$1:A12)),"")} | W43: {=IFERROR(INDEX('DBX Sprint'!$A$7:$K$62, SMALL(IF((INDEX('DBX Sprint'!$A$7:$K$62, ,22)<=(TODAY()+1))*(INDEX('DBX Sprint'!$A$7:$K$62, ,22)>=TODAY()),MATCH(ROW('DBX Sprint'!$A$7:$K$62),ROW('DBX Sprint'!$A$7:$K$62)),""),ROWS($W$34:W43)),COLUMNS('DBX Sprint'!$A$1:A12)),"")} | X43: {=IFERROR(INDEX('DBX Sprint'!$A$7:$K$62, SMALL(IF((INDEX('DBX Sprint'!$A$7:$K$62, ,22)<=(TODAY()+5))*(INDEX('DBX Sprint'!$A$7:$K$62, ,22)>(TODAY()+1)),MATCH(ROW('DBX Sprint'!$A$7:$K$62),ROW('DBX Sprint'!$A$7:$K$62)),""),ROWS($X$34:X43)),COLUMNS('DBX Sprint'!$A$1:A12)),"")} | Y43: {=IFERROR(INDEX('DBX Sprint'!$A$7:$K$62, SMALL(IF((INDEX('DBX Sprint'!$A$7:$K$62, ,22)<=(TODAY()+10))*(INDEX('DBX Sprint'!$A$7:$K$62, ,22)>(TODAY()+5)),MATCH(ROW('DBX Sprint'!$A$7:$K$62),ROW('DBX Sprint'!$A$7:$K$62)),""),ROWS($Y$34:Y43)),COLUMNS('DBX Sprint'!$A$1:A12)),"")} | AA43: {=IFERROR(INDEX('DBX Sprint'!$A$7:$K$62, SMALL(IF((INDEX('DBX Sprint'!$A$7:$K$62, ,25)=("Complete"))*(INDEX('DBX Sprint'!$A$7:$K$62, ,25)="Complete"),MATCH(ROW('DBX Sprint'!$A$7:$K$62),ROW('DBX Sprint'!$A$7:$K$62)),""),ROWS($AA$34:AA43)),COLUMNS('DBX Sprint'!$A$1:A12)),"")} | AB43: {=IFERROR(INDEX('DBX Sprint'!$A$7:$K$62, SMALL(IF((INDEX('DBX Sprint'!$A$7:$K$62, ,25)<(TODAY()))*(INDEX('DBX Sprint'!$A$7:$K$62, ,25)<>"Complete"),MATCH(ROW('DBX Sprint'!$A$7:$K$62),ROW('DBX Sprint'!$A$7:$K$62)),""),ROWS($AB$34:AB43)),COLUMNS('DBX Sprint'!$A$1:A12)),"")} | AC43: {=IFERROR(INDEX('DBX Sprint'!$A$7:$K$62, SMALL(IF((INDEX('DBX Sprint'!$A$7:$K$62, ,25)<=(TODAY()+1))*(INDEX('DBX Sprint'!$A$7:$K$62, ,25)>=TODAY()),MATCH(ROW('DBX Sprint'!$A$7:$K$62),ROW('DBX Sprint'!$A$7:$K$62)),""),ROWS($AC$34:AC43)),COLUMNS('DBX Sprint'!$A$1:A12)),"")} | AD43: {=IFERROR(INDEX('DBX Sprint'!$A$7:$K$62, SMALL(IF((INDEX('DBX Sprint'!$A$7:$K$62, ,25)<=(TODAY()+5))*(INDEX('DBX Sprint'!$A$7:$K$62, ,25)>(TODAY()+1)),MATCH(ROW('DBX Sprint'!$A$7:$K$62),ROW('DBX Sprint'!$A$7:$K$62)),""),ROWS($AD$34:AD43)),COLUMNS('DBX Sprint'!$A$1:A12)),"")} | AE43: {=IFERROR(INDEX('DBX Sprint'!$A$7:$K$62, SMALL(IF((INDEX('DBX Sprint'!$A$7:$K$62, ,25)<=(TODAY()+10))*(INDEX('DBX Sprint'!$A$7:$K$62, ,25)>(TODAY()+5)),MATCH(ROW('DBX Sprint'!$A$7:$K$62),ROW('DBX Sprint'!$A$7:$K$62)),""),ROWS($AE$34:AE43)),COLUMNS('DBX Sprint'!$A$1:A12)),"")} | AG43: {=IFERROR(INDEX('DBX Sprint'!$A$7:$K$62, SMALL(IF((INDEX('DBX Sprint'!$A$7:$K$62, ,29)=("Complete"))*(INDEX('DBX Sprint'!$A$7:$K$62, ,29)="Complete"),MATCH(ROW('DBX Sprint'!$A$7:$K$62),ROW('DBX Sprint'!$A$7:$K$62)),""),ROWS($AG$34:AG43)),COLUMNS('DBX Sprint'!$A$1:A12)),"")} | AH43: {=IFERROR(INDEX('DBX Sprint'!$A$7:$K$62, SMALL(IF((INDEX('DBX Sprint'!$A$7:$K$62, ,29)<(TODAY()))*(INDEX('DBX Sprint'!$A$7:$K$62, ,29)<>"Complete"),MATCH(ROW('DBX Sprint'!$A$7:$K$62),ROW('DBX Sprint'!$A$7:$K$62)),""),ROWS($AH$34:AH43)),COLUMNS('DBX Sprint'!$A$1:A12)),"")} | AI43: {=IFERROR(INDEX('DBX Sprint'!$A$7:$K$62, SMALL(IF((INDEX('DBX Sprint'!$A$7:$K$62, ,29)<=(TODAY()+1))*(INDEX('DBX Sprint'!$A$7:$K$62, ,29)>=TODAY()),MATCH(ROW('DBX Sprint'!$A$7:$K$62),ROW('DBX Sprint'!$A$7:$K$62)),""),ROWS($AI$34:AI43)),COLUMNS('DBX Sprint'!$A$1:A12)),"")} | AJ43: {=IFERROR(INDEX('DBX Sprint'!$A$7:$K$62, SMALL(IF((INDEX('DBX Sprint'!$A$7:$K$62, ,29)<=(TODAY()+5))*(INDEX('DBX Sprint'!$A$7:$K$62, ,29)>(TODAY()+1)),MATCH(ROW('DBX Sprint'!$A$7:$K$62),ROW('DBX Sprint'!$A$7:$K$62)),""),ROWS($AJ$34:AJ43)),COLUMNS('DBX Sprint'!$A$1:A12)),"")} | AK43: {=IFERROR(INDEX('DBX Sprint'!$A$7:$K$62, SMALL(IF((INDEX('DBX Sprint'!$A$7:$K$62, ,29)<=(TODAY()+10))*(INDEX('DBX Sprint'!$A$7:$K$62, ,29)>(TODAY()+5)),MATCH(ROW('DBX Sprint'!$A$7:$K$62),ROW('DBX Sprint'!$A$7:$K$62)),""),ROWS($AK$34:AK43)),COLUMNS('DBX Sprint'!$A$1:A12)),"")} | AM43: {=IFERROR(INDEX('DBX Sprint'!$A$7:$K$62, SMALL(IF((INDEX('DBX Sprint'!$A$7:$K$62, ,32)=("Complete"))*(INDEX('DBX Sprint'!$A$7:$K$62, ,32)="Complete"),MATCH(ROW('DBX Sprint'!$A$7:$K$62),ROW('DBX Sprint'!$A$7:$K$62)),""),ROWS($AM$34:AM43)),COLUMNS('DBX Sprint'!$A$1:A12)),"")} | AN43: {=IFERROR(INDEX('DBX Sprint'!$A$7:$K$62, SMALL(IF((INDEX('DBX Sprint'!$A$7:$K$62, ,32)<(TODAY()))*(INDEX('DBX Sprint'!$A$7:$K$62, ,32)<>"Complete"),MATCH(ROW('DBX Sprint'!$A$7:$K$62),ROW('DBX Sprint'!$A$7:$K$62)),""),ROWS($AN$34:AN43)),COLUMNS('DBX Sprint'!$A$1:A12)),"")} | AO43: {=IFERROR(INDEX('DBX Sprint'!$A$7:$K$62, SMALL(IF((INDEX('DBX Sprint'!$A$7:$K$62, ,32)<=(TODAY()+1))*(INDEX('DBX Sprint'!$A$7:$K$62, ,32)>=TODAY()),MATCH(ROW('DBX Sprint'!$A$7:$K$62),ROW('DBX Sprint'!$A$7:$K$62)),""),ROWS($AO$34:AO43)),COLUMNS('DBX Sprint'!$A$1:A12)),"")} | AP43: {=IFERROR(INDEX('DBX Sprint'!$A$7:$K$62, SMALL(IF((INDEX('DBX Sprint'!$A$7:$K$62, ,32)<=(TODAY()+5))*(INDEX('DBX Sprint'!$A$7:$K$62, ,32)>(TODAY()+1)),MATCH(ROW('DBX Sprint'!$A$7:$K$62),ROW('DBX Sprint'!$A$7:$K$62)),""),ROWS($AP$34:AP43)),COLUMNS('DBX Sprint'!$A$1:A12)),"")} | AQ43: {=IFERROR(INDEX('DBX Sprint'!$A$7:$K$62, SMALL(IF((INDEX('DBX Sprint'!$A$7:$K$62, ,32)<=(TODAY()+10))*(INDEX('DBX Sprint'!$A$7:$K$62, ,32)>(TODAY()+5)),MATCH(ROW('DBX Sprint'!$A$7:$K$62),ROW('DBX Sprint'!$A$7:$K$62)),""),ROWS($AQ$34:AQ43)),COLUMNS('DBX Sprint'!$A$1:A12)),"")}
C44: {=IFERROR(INDEX('DBX Sprint'!$A$7:$K$62, SMALL(IF((INDEX('DBX Sprint'!$A$7:$K$62, ,13)=("Complete"))*(INDEX('DBX Sprint'!$A$7:$K$62, ,13)="Complete"),MATCH(ROW('DBX Sprint'!$A$7:$K$62),ROW('DBX Sprint'!$A$7:$K$62)),""),ROWS(C$34:$C44)),COLUMNS('DBX Sprint'!$A$1:A12)),"")} | D44: {=IFERROR(INDEX('DBX Sprint'!$A$7:$K$62, SMALL(IF((INDEX('DBX Sprint'!$A$7:$K$62, ,13)<(TODAY()))*(INDEX('DBX Sprint'!$A$7:$K$62, ,13)<>"Complete"),MATCH(ROW('DBX Sprint'!$A$7:$K$62),ROW('DBX Sprint'!$A$7:$K$62)),""),ROWS(D$34:$D44)),COLUMNS('DBX Sprint'!$A$1:A12)),"")} | E44: {=IFERROR(INDEX('DBX Sprint'!$A$7:$K$62, SMALL(IF((INDEX('DBX Sprint'!$A$7:$K$62, ,13)<=(TODAY()+1))*(INDEX('DBX Sprint'!$A$7:$K$62, ,13)>=TODAY()),MATCH(ROW('DBX Sprint'!$A$7:$K$62),ROW('DBX Sprint'!$A$7:$K$62)),""),ROWS(E$34:$E44)),COLUMNS('DBX Sprint'!$A$1:A12)),"")} | F44: {=IFERROR(INDEX('DBX Sprint'!$A$7:$K$62, SMALL(IF((INDEX('DBX Sprint'!$A$7:$K$62, ,13)<=(TODAY()+5))*(INDEX('DBX Sprint'!$A$7:$K$62, ,13)>(TODAY()+1)),MATCH(ROW('DBX Sprint'!$A$7:$K$62),ROW('DBX Sprint'!$A$7:$K$62)),""),ROWS($F$34:F44)),COLUMNS('DBX Sprint'!$A$1:A12)),"")} | G44: {=IFERROR(INDEX('DBX Sprint'!$A$7:$K$62, SMALL(IF((INDEX('DBX Sprint'!$A$7:$K$62, ,13)<=(TODAY()+10))*(INDEX('DBX Sprint'!$A$7:$K$62, ,13)>(TODAY()+5)),MATCH(ROW('DBX Sprint'!$A$7:$K$62),ROW('DBX Sprint'!$A$7:$K$62)),""),ROWS($G$34:G44)),COLUMNS('DBX Sprint'!$A$1:A12)),"")} | I44: {=IFERROR(INDEX('DBX Sprint'!$A$7:$K$62, SMALL(IF((INDEX('DBX Sprint'!$A$7:$K$62, ,16)=("Complete"))*(INDEX('DBX Sprint'!$A$7:$K$62, ,16)="Complete"),MATCH(ROW('DBX Sprint'!$A$7:$K$62),ROW('DBX Sprint'!$A$7:$K$62)),""),ROWS($I$34:I44)),COLUMNS('DBX Sprint'!$A$1:A12)),"")} | J44: {=IFERROR(INDEX('DBX Sprint'!$A$7:$K$62, SMALL(IF((INDEX('DBX Sprint'!$A$7:$K$62, ,16)<(TODAY()))*(INDEX('DBX Sprint'!$A$7:$K$62, ,16)<>"Complete"),MATCH(ROW('DBX Sprint'!$A$7:$K$62),ROW('DBX Sprint'!$A$7:$K$62)),""),ROWS($J$34:J44)),COLUMNS('DBX Sprint'!$A$1:A12)),"")} | K44: {=IFERROR(INDEX('DBX Sprint'!$A$7:$K$62, SMALL(IF((INDEX('DBX Sprint'!$A$7:$K$62, ,16)<=(TODAY()+1))*(INDEX('DBX Sprint'!$A$7:$K$62, ,16)>=TODAY()),MATCH(ROW('DBX Sprint'!$A$7:$K$62),ROW('DBX Sprint'!$A$7:$K$62)),""),ROWS($K$34:K44)),COLUMNS('DBX Sprint'!$A$1:A12)),"")} | L44: {=IFERROR(INDEX('DBX Sprint'!$A$7:$K$62, SMALL(IF((INDEX('DBX Sprint'!$A$7:$K$62, ,16)<=(TODAY()+5))*(INDEX('DBX Sprint'!$A$7:$K$62, ,16)>(TODAY()+1)),MATCH(ROW('DBX Sprint'!$A$7:$K$62),ROW('DBX Sprint'!$A$7:$K$62)),""),ROWS($L$34:L44)),COLUMNS('DBX Sprint'!$A$1:A12)),"")} | M44: {=IFERROR(INDEX('DBX Sprint'!$A$7:$K$62, SMALL(IF((INDEX('DBX Sprint'!$A$7:$K$62, ,16)<=(TODAY()+10))*(INDEX('DBX Sprint'!$A$7:$K$62, ,16)>(TODAY()+5)),MATCH(ROW('DBX Sprint'!$A$7:$K$62),ROW('DBX Sprint'!$A$7:$K$62)),""),ROWS($M$34:M44)),COLUMNS('DBX Sprint'!$A$1:A12)),"")} | O44: {=IFERROR(INDEX('DBX Sprint'!$A$7:$K$62, SMALL(IF((INDEX('DBX Sprint'!$A$7:$K$62, ,19)=("Complete"))*(INDEX('DBX Sprint'!$A$7:$K$62, ,19)="Complete"),MATCH(ROW('DBX Sprint'!$A$7:$K$62),ROW('DBX Sprint'!$A$7:$K$62)),""),ROWS($O$34:O44)),COLUMNS('DBX Sprint'!$A$1:A12)),"")} | P44: {=IFERROR(INDEX('DBX Sprint'!$A$7:$K$62, SMALL(IF((INDEX('DBX Sprint'!$A$7:$K$62, ,19)<(TODAY()))*(INDEX('DBX Sprint'!$A$7:$K$62, ,19)<>"Complete"),MATCH(ROW('DBX Sprint'!$A$7:$K$62),ROW('DBX Sprint'!$A$7:$K$62)),""),ROWS($P$34:P44)),COLUMNS('DBX Sprint'!$A$1:A12)),"")} | Q44: {=IFERROR(INDEX('DBX Sprint'!$A$7:$K$62, SMALL(IF((INDEX('DBX Sprint'!$A$7:$K$62, ,19)<=(TODAY()+1))*(INDEX('DBX Sprint'!$A$7:$K$62, ,19)>=TODAY()),MATCH(ROW('DBX Sprint'!$A$7:$K$62),ROW('DBX Sprint'!$A$7:$K$62)),""),ROWS($Q$34:Q44)),COLUMNS('DBX Sprint'!$A$1:A12)),"")} | R44: {=IFERROR(INDEX('DBX Sprint'!$A$7:$K$62, SMALL(IF((INDEX('DBX Sprint'!$A$7:$K$62, ,19)<=(TODAY()+5))*(INDEX('DBX Sprint'!$A$7:$K$62, ,19)>(TODAY()+1)),MATCH(ROW('DBX Sprint'!$A$7:$K$62),ROW('DBX Sprint'!$A$7:$K$62)),""),ROWS($R$34:R44)),COLUMNS('DBX Sprint'!$A$1:A12)),"")} | S44: {=IFERROR(INDEX('DBX Sprint'!$A$7:$K$62, SMALL(IF((INDEX('DBX Sprint'!$A$7:$K$62, ,19)<=(TODAY()+10))*(INDEX('DBX Sprint'!$A$7:$K$62, ,19)>(TODAY()+5)),MATCH(ROW('DBX Sprint'!$A$7:$K$62),ROW('DBX Sprint'!$A$7:$K$62)),""),ROWS($S$34:S44)),COLUMNS('DBX Sprint'!$A$1:A12)),"")} | U44: {=IFERROR(INDEX('DBX Sprint'!$A$7:$K$62, SMALL(IF((INDEX('DBX Sprint'!$A$7:$K$62, ,22)=("Complete"))*(INDEX('DBX Sprint'!$A$7:$K$62, ,22)="Complete"),MATCH(ROW('DBX Sprint'!$A$7:$K$62),ROW('DBX Sprint'!$A$7:$K$62)),""),ROWS($U$34:U44)),COLUMNS('DBX Sprint'!$A$1:A12)),"")} | V44: {=IFERROR(INDEX('DBX Sprint'!$A$7:$K$62, SMALL(IF((INDEX('DBX Sprint'!$A$7:$K$62, ,22)<(TODAY()))*(INDEX('DBX Sprint'!$A$7:$K$62, ,22)<>"Complete"),MATCH(ROW('DBX Sprint'!$A$7:$K$62),ROW('DBX Sprint'!$A$7:$K$62)),""),ROWS($V$34:V44)),COLUMNS('DBX Sprint'!$A$1:A12)),"")} | W44: {=IFERROR(INDEX('DBX Sprint'!$A$7:$K$62, SMALL(IF((INDEX('DBX Sprint'!$A$7:$K$62, ,22)<=(TODAY()+1))*(INDEX('DBX Sprint'!$A$7:$K$62, ,22)>=TODAY()),MATCH(ROW('DBX Sprint'!$A$7:$K$62),ROW('DBX Sprint'!$A$7:$K$62)),""),ROWS($W$34:W44)),COLUMNS('DBX Sprint'!$A$1:A12)),"")} | X44: {=IFERROR(INDEX('DBX Sprint'!$A$7:$K$62, SMALL(IF((INDEX('DBX Sprint'!$A$7:$K$62, ,22)<=(TODAY()+5))*(INDEX('DBX Sprint'!$A$7:$K$62, ,22)>(TODAY()+1)),MATCH(ROW('DBX Sprint'!$A$7:$K$62),ROW('DBX Sprint'!$A$7:$K$62)),""),ROWS($X$34:X44)),COLUMNS('DBX Sprint'!$A$1:A12)),"")} | Y44: {=IFERROR(INDEX('DBX Sprint'!$A$7:$K$62, SMALL(IF((INDEX('DBX Sprint'!$A$7:$K$62, ,22)<=(TODAY()+10))*(INDEX('DBX Sprint'!$A$7:$K$62, ,22)>(TODAY()+5)),MATCH(ROW('DBX Sprint'!$A$7:$K$62),ROW('DBX Sprint'!$A$7:$K$62)),""),ROWS($Y$34:Y44)),COLUMNS('DBX Sprint'!$A$1:A12)),"")} | AA44: {=IFERROR(INDEX('DBX Sprint'!$A$7:$K$62, SMALL(IF((INDEX('DBX Sprint'!$A$7:$K$62, ,25)=("Complete"))*(INDEX('DBX Sprint'!$A$7:$K$62, ,25)="Complete"),MATCH(ROW('DBX Sprint'!$A$7:$K$62),ROW('DBX Sprint'!$A$7:$K$62)),""),ROWS($AA$34:AA44)),COLUMNS('DBX Sprint'!$A$1:A12)),"")} | AB44: {=IFERROR(INDEX('DBX Sprint'!$A$7:$K$62, SMALL(IF((INDEX('DBX Sprint'!$A$7:$K$62, ,25)<(TODAY()))*(INDEX('DBX Sprint'!$A$7:$K$62, ,25)<>"Complete"),MATCH(ROW('DBX Sprint'!$A$7:$K$62),ROW('DBX Sprint'!$A$7:$K$62)),""),ROWS($AB$34:AB44)),COLUMNS('DBX Sprint'!$A$1:A12)),"")} | AC44: {=IFERROR(INDEX('DBX Sprint'!$A$7:$K$62, SMALL(IF((INDEX('DBX Sprint'!$A$7:$K$62, ,25)<=(TODAY()+1))*(INDEX('DBX Sprint'!$A$7:$K$62, ,25)>=TODAY()),MATCH(ROW('DBX Sprint'!$A$7:$K$62),ROW('DBX Sprint'!$A$7:$K$62)),""),ROWS($AC$34:AC44)),COLUMNS('DBX Sprint'!$A$1:A12)),"")} | AD44: {=IFERROR(INDEX('DBX Sprint'!$A$7:$K$62, SMALL(IF((INDEX('DBX Sprint'!$A$7:$K$62, ,25)<=(TODAY()+5))*(INDEX('DBX Sprint'!$A$7:$K$62, ,25)>(TODAY()+1)),MATCH(ROW('DBX Sprint'!$A$7:$K$62),ROW('DBX Sprint'!$A$7:$K$62)),""),ROWS($AD$34:AD44)),COLUMNS('DBX Sprint'!$A$1:A12)),"")} | AE44: {=IFERROR(INDEX('DBX Sprint'!$A$7:$K$62, SMALL(IF((INDEX('DBX Sprint'!$A$7:$K$62, ,25)<=(TODAY()+10))*(INDEX('DBX Sprint'!$A$7:$K$62, ,25)>(TODAY()+5)),MATCH(ROW('DBX Sprint'!$A$7:$K$62),ROW('DBX Sprint'!$A$7:$K$62)),""),ROWS($AE$34:AE44)),COLUMNS('DBX Sprint'!$A$1:A12)),"")} | AG44: {=IFERROR(INDEX('DBX Sprint'!$A$7:$K$62, SMALL(IF((INDEX('DBX Sprint'!$A$7:$K$62, ,29)=("Complete"))*(INDEX('DBX Sprint'!$A$7:$K$62, ,29)="Complete"),MATCH(ROW('DBX Sprint'!$A$7:$K$62),ROW('DBX Sprint'!$A$7:$K$62)),""),ROWS($AG$34:AG44)),COLUMNS('DBX Sprint'!$A$1:A12)),"")} | AH44: {=IFERROR(INDEX('DBX Sprint'!$A$7:$K$62, SMALL(IF((INDEX('DBX Sprint'!$A$7:$K$62, ,29)<(TODAY()))*(INDEX('DBX Sprint'!$A$7:$K$62, ,29)<>"Complete"),MATCH(ROW('DBX Sprint'!$A$7:$K$62),ROW('DBX Sprint'!$A$7:$K$62)),""),ROWS($AH$34:AH44)),COLUMNS('DBX Sprint'!$A$1:A12)),"")} | AI44: {=IFERROR(INDEX('DBX Sprint'!$A$7:$K$62, SMALL(IF((INDEX('DBX Sprint'!$A$7:$K$62, ,29)<=(TODAY()+1))*(INDEX('DBX Sprint'!$A$7:$K$62, ,29)>=TODAY()),MATCH(ROW('DBX Sprint'!$A$7:$K$62),ROW('DBX Sprint'!$A$7:$K$62)),""),ROWS($AI$34:AI44)),COLUMNS('DBX Sprint'!$A$1:A12)),"")} | AJ44: {=IFERROR(INDEX('DBX Sprint'!$A$7:$K$62, SMALL(IF((INDEX('DBX Sprint'!$A$7:$K$62, ,29)<=(TODAY()+5))*(INDEX('DBX Sprint'!$A$7:$K$62, ,29)>(TODAY()+1)),MATCH(ROW('DBX Sprint'!$A$7:$K$62),ROW('DBX Sprint'!$A$7:$K$62)),""),ROWS($AJ$34:AJ44)),COLUMNS('DBX Sprint'!$A$1:A12)),"")} | AK44: {=IFERROR(INDEX('DBX Sprint'!$A$7:$K$62, SMALL(IF((INDEX('DBX Sprint'!$A$7:$K$62, ,29)<=(TODAY()+10))*(INDEX('DBX Sprint'!$A$7:$K$62, ,29)>(TODAY()+5)),MATCH(ROW('DBX Sprint'!$A$7:$K$62),ROW('DBX Sprint'!$A$7:$K$62)),""),ROWS($AK$34:AK44)),COLUMNS('DBX Sprint'!$A$1:A12)),"")} | AM44: {=IFERROR(INDEX('DBX Sprint'!$A$7:$K$62, SMALL(IF((INDEX('DBX Sprint'!$A$7:$K$62, ,32)=("Complete"))*(INDEX('DBX Sprint'!$A$7:$K$62, ,32)="Complete"),MATCH(ROW('DBX Sprint'!$A$7:$K$62),ROW('DBX Sprint'!$A$7:$K$62)),""),ROWS($AM$34:AM44)),COLUMNS('DBX Sprint'!$A$1:A12)),"")} | AN44: {=IFERROR(INDEX('DBX Sprint'!$A$7:$K$62, SMALL(IF((INDEX('DBX Sprint'!$A$7:$K$62, ,32)<(TODAY()))*(INDEX('DBX Sprint'!$A$7:$K$62, ,32)<>"Complete"),MATCH(ROW('DBX Sprint'!$A$7:$K$62),ROW('DBX Sprint'!$A$7:$K$62)),""),ROWS($AN$34:AN44)),COLUMNS('DBX Sprint'!$A$1:A12)),"")} | AO44: {=IFERROR(INDEX('DBX Sprint'!$A$7:$K$62, SMALL(IF((INDEX('DBX Sprint'!$A$7:$K$62, ,32)<=(TODAY()+1))*(INDEX('DBX Sprint'!$A$7:$K$62, ,32)>=TODAY()),MATCH(ROW('DBX Sprint'!$A$7:$K$62),ROW('DBX Sprint'!$A$7:$K$62)),""),ROWS($AO$34:AO44)),COLUMNS('DBX Sprint'!$A$1:A12)),"")} | AP44: {=IFERROR(INDEX('DBX Sprint'!$A$7:$K$62, SMALL(IF((INDEX('DBX Sprint'!$A$7:$K$62, ,32)<=(TODAY()+5))*(INDEX('DBX Sprint'!$A$7:$K$62, ,32)>(TODAY()+1)),MATCH(ROW('DBX Sprint'!$A$7:$K$62),ROW('DBX Sprint'!$A$7:$K$62)),""),ROWS($AP$34:AP44)),COLUMNS('DBX Sprint'!$A$1:A12)),"")} | AQ44: {=IFERROR(INDEX('DBX Sprint'!$A$7:$K$62, SMALL(IF((INDEX('DBX Sprint'!$A$7:$K$62, ,32)<=(TODAY()+10))*(INDEX('DBX Sprint'!$A$7:$K$62, ,32)>(TODAY()+5)),MATCH(ROW('DBX Sprint'!$A$7:$K$62),ROW('DBX Sprint'!$A$7:$K$62)),""),ROWS($AQ$34:AQ44)),COLUMNS('DBX Sprint'!$A$1:A12)),"")}
C45: {=IFERROR(INDEX('DBX Sprint'!$A$7:$K$62, SMALL(IF((INDEX('DBX Sprint'!$A$7:$K$62, ,13)=("Complete"))*(INDEX('DBX Sprint'!$A$7:$K$62, ,13)="Complete"),MATCH(ROW('DBX Sprint'!$A$7:$K$62),ROW('DBX Sprint'!$A$7:$K$62)),""),ROWS(C$34:$C45)),COLUMNS('DBX Sprint'!$A$1:A12)),"")} | D45: {=IFERROR(INDEX('DBX Sprint'!$A$7:$K$62, SMALL(IF((INDEX('DBX Sprint'!$A$7:$K$62, ,13)<(TODAY()))*(INDEX('DBX Sprint'!$A$7:$K$62, ,13)<>"Complete"),MATCH(ROW('DBX Sprint'!$A$7:$K$62),ROW('DBX Sprint'!$A$7:$K$62)),""),ROWS(D$34:$D45)),COLUMNS('DBX Sprint'!$A$1:A12)),"")} | E45: {=IFERROR(INDEX('DBX Sprint'!$A$7:$K$62, SMALL(IF((INDEX('DBX Sprint'!$A$7:$K$62, ,13)<=(TODAY()+1))*(INDEX('DBX Sprint'!$A$7:$K$62, ,13)>=TODAY()),MATCH(ROW('DBX Sprint'!$A$7:$K$62),ROW('DBX Sprint'!$A$7:$K$62)),""),ROWS(E$34:$E45)),COLUMNS('DBX Sprint'!$A$1:A12)),"")} | F45: {=IFERROR(INDEX('DBX Sprint'!$A$7:$K$62, SMALL(IF((INDEX('DBX Sprint'!$A$7:$K$62, ,13)<=(TODAY()+5))*(INDEX('DBX Sprint'!$A$7:$K$62, ,13)>(TODAY()+1)),MATCH(ROW('DBX Sprint'!$A$7:$K$62),ROW('DBX Sprint'!$A$7:$K$62)),""),ROWS($F$34:F45)),COLUMNS('DBX Sprint'!$A$1:A12)),"")} | G45: {=IFERROR(INDEX('DBX Sprint'!$A$7:$K$62, SMALL(IF((INDEX('DBX Sprint'!$A$7:$K$62, ,13)<=(TODAY()+10))*(INDEX('DBX Sprint'!$A$7:$K$62, ,13)>(TODAY()+5)),MATCH(ROW('DBX Sprint'!$A$7:$K$62),ROW('DBX Sprint'!$A$7:$K$62)),""),ROWS($G$34:G45)),COLUMNS('DBX Sprint'!$A$1:A12)),"")} | I45: {=IFERROR(INDEX('DBX Sprint'!$A$7:$K$62, SMALL(IF((INDEX('DBX Sprint'!$A$7:$K$62, ,16)=("Complete"))*(INDEX('DBX Sprint'!$A$7:$K$62, ,16)="Complete"),MATCH(ROW('DBX Sprint'!$A$7:$K$62),ROW('DBX Sprint'!$A$7:$K$62)),""),ROWS($I$34:I45)),COLUMNS('DBX Sprint'!$A$1:A12)),"")} | J45: {=IFERROR(INDEX('DBX Sprint'!$A$7:$K$62, SMALL(IF((INDEX('DBX Sprint'!$A$7:$K$62, ,16)<(TODAY()))*(INDEX('DBX Sprint'!$A$7:$K$62, ,16)<>"Complete"),MATCH(ROW('DBX Sprint'!$A$7:$K$62),ROW('DBX Sprint'!$A$7:$K$62)),""),ROWS($J$34:J45)),COLUMNS('DBX Sprint'!$A$1:A12)),"")} | K45: {=IFERROR(INDEX('DBX Sprint'!$A$7:$K$62, SMALL(IF((INDEX('DBX Sprint'!$A$7:$K$62, ,16)<=(TODAY()+1))*(INDEX('DBX Sprint'!$A$7:$K$62, ,16)>=TODAY()),MATCH(ROW('DBX Sprint'!$A$7:$K$62),ROW('DBX Sprint'!$A$7:$K$62)),""),ROWS($K$34:K45)),COLUMNS('DBX Sprint'!$A$1:A12)),"")} | L45: {=IFERROR(INDEX('DBX Sprint'!$A$7:$K$62, SMALL(IF((INDEX('DBX Sprint'!$A$7:$K$62, ,16)<=(TODAY()+5))*(INDEX('DBX Sprint'!$A$7:$K$62, ,16)>(TODAY()+1)),MATCH(ROW('DBX Sprint'!$A$7:$K$62),ROW('DBX Sprint'!$A$7:$K$62)),""),ROWS($L$34:L45)),COLUMNS('DBX Sprint'!$A$1:A12)),"")} | M45: {=IFERROR(INDEX('DBX Sprint'!$A$7:$K$62, SMALL(IF((INDEX('DBX Sprint'!$A$7:$K$62, ,16)<=(TODAY()+10))*(INDEX('DBX Sprint'!$A$7:$K$62, ,16)>(TODAY()+5)),MATCH(ROW('DBX Sprint'!$A$7:$K$62),ROW('DBX Sprint'!$A$7:$K$62)),""),ROWS($M$34:M45)),COLUMNS('DBX Sprint'!$A$1:A12)),"")} | O45: {=IFERROR(INDEX('DBX Sprint'!$A$7:$K$62, SMALL(IF((INDEX('DBX Sprint'!$A$7:$K$62, ,19)=("Complete"))*(INDEX('DBX Sprint'!$A$7:$K$62, ,19)="Complete"),MATCH(ROW('DBX Sprint'!$A$7:$K$62),ROW('DBX Sprint'!$A$7:$K$62)),""),ROWS($O$34:O45)),COLUMNS('DBX Sprint'!$A$1:A12)),"")} | P45: {=IFERROR(INDEX('DBX Sprint'!$A$7:$K$62, SMALL(IF((INDEX('DBX Sprint'!$A$7:$K$62, ,19)<(TODAY()))*(INDEX('DBX Sprint'!$A$7:$K$62, ,19)<>"Complete"),MATCH(ROW('DBX Sprint'!$A$7:$K$62),ROW('DBX Sprint'!$A$7:$K$62)),""),ROWS($P$34:P45)),COLUMNS('DBX Sprint'!$A$1:A12)),"")} | Q45: {=IFERROR(INDEX('DBX Sprint'!$A$7:$K$62, SMALL(IF((INDEX('DBX Sprint'!$A$7:$K$62, ,19)<=(TODAY()+1))*(INDEX('DBX Sprint'!$A$7:$K$62, ,19)>=TODAY()),MATCH(ROW('DBX Sprint'!$A$7:$K$62),ROW('DBX Sprint'!$A$7:$K$62)),""),ROWS($Q$34:Q45)),COLUMNS('DBX Sprint'!$A$1:A12)),"")} | R45: {=IFERROR(INDEX('DBX Sprint'!$A$7:$K$62, SMALL(IF((INDEX('DBX Sprint'!$A$7:$K$62, ,19)<=(TODAY()+5))*(INDEX('DBX Sprint'!$A$7:$K$62, ,19)>(TODAY()+1)),MATCH(ROW('DBX Sprint'!$A$7:$K$62),ROW('DBX Sprint'!$A$7:$K$62)),""),ROWS($R$34:R45)),COLUMNS('DBX Sprint'!$A$1:A12)),"")} | S45: {=IFERROR(INDEX('DBX Sprint'!$A$7:$K$62, SMALL(IF((INDEX('DBX Sprint'!$A$7:$K$62, ,19)<=(TODAY()+10))*(INDEX('DBX Sprint'!$A$7:$K$62, ,19)>(TODAY()+5)),MATCH(ROW('DBX Sprint'!$A$7:$K$62),ROW('DBX Sprint'!$A$7:$K$62)),""),ROWS($S$34:S45)),COLUMNS('DBX Sprint'!$A$1:A12)),"")} | U45: {=IFERROR(INDEX('DBX Sprint'!$A$7:$K$62, SMALL(IF((INDEX('DBX Sprint'!$A$7:$K$62, ,22)=("Complete"))*(INDEX('DBX Sprint'!$A$7:$K$62, ,22)="Complete"),MATCH(ROW('DBX Sprint'!$A$7:$K$62),ROW('DBX Sprint'!$A$7:$K$62)),""),ROWS($U$34:U45)),COLUMNS('DBX Sprint'!$A$1:A12)),"")} | V45: {=IFERROR(INDEX('DBX Sprint'!$A$7:$K$62, SMALL(IF((INDEX('DBX Sprint'!$A$7:$K$62, ,22)<(TODAY()))*(INDEX('DBX Sprint'!$A$7:$K$62, ,22)<>"Complete"),MATCH(ROW('DBX Sprint'!$A$7:$K$62),ROW('DBX Sprint'!$A$7:$K$62)),""),ROWS($V$34:V45)),COLUMNS('DBX Sprint'!$A$1:A12)),"")} | W45: {=IFERROR(INDEX('DBX Sprint'!$A$7:$K$62, SMALL(IF((INDEX('DBX Sprint'!$A$7:$K$62, ,22)<=(TODAY()+1))*(INDEX('DBX Sprint'!$A$7:$K$62, ,22)>=TODAY()),MATCH(ROW('DBX Sprint'!$A$7:$K$62),ROW('DBX Sprint'!$A$7:$K$62)),""),ROWS($W$34:W45)),COLUMNS('DBX Sprint'!$A$1:A12)),"")} | X45: {=IFERROR(INDEX('DBX Sprint'!$A$7:$K$62, SMALL(IF((INDEX('DBX Sprint'!$A$7:$K$62, ,22)<=(TODAY()+5))*(INDEX('DBX Sprint'!$A$7:$K$62, ,22)>(TODAY()+1)),MATCH(ROW('DBX Sprint'!$A$7:$K$62),ROW('DBX Sprint'!$A$7:$K$62)),""),ROWS($X$34:X45)),COLUMNS('DBX Sprint'!$A$1:A12)),"")} | Y45: {=IFERROR(INDEX('DBX Sprint'!$A$7:$K$62, SMALL(IF((INDEX('DBX Sprint'!$A$7:$K$62, ,22)<=(TODAY()+10))*(INDEX('DBX Sprint'!$A$7:$K$62, ,22)>(TODAY()+5)),MATCH(ROW('DBX Sprint'!$A$7:$K$62),ROW('DBX Sprint'!$A$7:$K$62)),""),ROWS($Y$34:Y45)),COLUMNS('DBX Sprint'!$A$1:A12)),"")} | AA45: {=IFERROR(INDEX('DBX Sprint'!$A$7:$K$62, SMALL(IF((INDEX('DBX Sprint'!$A$7:$K$62, ,25)=("Complete"))*(INDEX('DBX Sprint'!$A$7:$K$62, ,25)="Complete"),MATCH(ROW('DBX Sprint'!$A$7:$K$62),ROW('DBX Sprint'!$A$7:$K$62)),""),ROWS($AA$34:AA45)),COLUMNS('DBX Sprint'!$A$1:A12)),"")} | AB45: {=IFERROR(INDEX('DBX Sprint'!$A$7:$K$62, SMALL(IF((INDEX('DBX Sprint'!$A$7:$K$62, ,25)<(TODAY()))*(INDEX('DBX Sprint'!$A$7:$K$62, ,25)<>"Complete"),MATCH(ROW('DBX Sprint'!$A$7:$K$62),ROW('DBX Sprint'!$A$7:$K$62)),""),ROWS($AB$34:AB45)),COLUMNS('DBX Sprint'!$A$1:A12)),"")} | AC45: {=IFERROR(INDEX('DBX Sprint'!$A$7:$K$62, SMALL(IF((INDEX('DBX Sprint'!$A$7:$K$62, ,25)<=(TODAY()+1))*(INDEX('DBX Sprint'!$A$7:$K$62, ,25)>=TODAY()),MATCH(ROW('DBX Sprint'!$A$7:$K$62),ROW('DBX Sprint'!$A$7:$K$62)),""),ROWS($AC$34:AC45)),COLUMNS('DBX Sprint'!$A$1:A12)),"")} | AD45: {=IFERROR(INDEX('DBX Sprint'!$A$7:$K$62, SMALL(IF((INDEX('DBX Sprint'!$A$7:$K$62, ,25)<=(TODAY()+5))*(INDEX('DBX Sprint'!$A$7:$K$62, ,25)>(TODAY()+1)),MATCH(ROW('DBX Sprint'!$A$7:$K$62),ROW('DBX Sprint'!$A$7:$K$62)),""),ROWS($AD$34:AD45)),COLUMNS('DBX Sprint'!$A$1:A12)),"")} | AE45: {=IFERROR(INDEX('DBX Sprint'!$A$7:$K$62, SMALL(IF((INDEX('DBX Sprint'!$A$7:$K$62, ,25)<=(TODAY()+10))*(INDEX('DBX Sprint'!$A$7:$K$62, ,25)>(TODAY()+5)),MATCH(ROW('DBX Sprint'!$A$7:$K$62),ROW('DBX Sprint'!$A$7:$K$62)),""),ROWS($AE$34:AE45)),COLUMNS('DBX Sprint'!$A$1:A12)),"")} | AG45: {=IFERROR(INDEX('DBX Sprint'!$A$7:$K$62, SMALL(IF((INDEX('DBX Sprint'!$A$7:$K$62, ,29)=("Complete"))*(INDEX('DBX Sprint'!$A$7:$K$62, ,29)="Complete"),MATCH(ROW('DBX Sprint'!$A$7:$K$62),ROW('DBX Sprint'!$A$7:$K$62)),""),ROWS($AG$34:AG45)),COLUMNS('DBX Sprint'!$A$1:A12)),"")} | AH45: {=IFERROR(INDEX('DBX Sprint'!$A$7:$K$62, SMALL(IF((INDEX('DBX Sprint'!$A$7:$K$62, ,29)<(TODAY()))*(INDEX('DBX Sprint'!$A$7:$K$62, ,29)<>"Complete"),MATCH(ROW('DBX Sprint'!$A$7:$K$62),ROW('DBX Sprint'!$A$7:$K$62)),""),ROWS($AH$34:AH45)),COLUMNS('DBX Sprint'!$A$1:A12)),"")} | AI45: {=IFERROR(INDEX('DBX Sprint'!$A$7:$K$62, SMALL(IF((INDEX('DBX Sprint'!$A$7:$K$62, ,29)<=(TODAY()+1))*(INDEX('DBX Sprint'!$A$7:$K$62, ,29)>=TODAY()),MATCH(ROW('DBX Sprint'!$A$7:$K$62),ROW('DBX Sprint'!$A$7:$K$62)),""),ROWS($AI$34:AI45)),COLUMNS('DBX Sprint'!$A$1:A12)),"")} | AJ45: {=IFERROR(INDEX('DBX Sprint'!$A$7:$K$62, SMALL(IF((INDEX('DBX Sprint'!$A$7:$K$62, ,29)<=(TODAY()+5))*(INDEX('DBX Sprint'!$A$7:$K$62, ,29)>(TODAY()+1)),MATCH(ROW('DBX Sprint'!$A$7:$K$62),ROW('DBX Sprint'!$A$7:$K$62)),""),ROWS($AJ$34:AJ45)),COLUMNS('DBX Sprint'!$A$1:A12)),"")} | AK45: {=IFERROR(INDEX('DBX Sprint'!$A$7:$K$62, SMALL(IF((INDEX('DBX Sprint'!$A$7:$K$62, ,29)<=(TODAY()+10))*(INDEX('DBX Sprint'!$A$7:$K$62, ,29)>(TODAY()+5)),MATCH(ROW('DBX Sprint'!$A$7:$K$62),ROW('DBX Sprint'!$A$7:$K$62)),""),ROWS($AK$34:AK45)),COLUMNS('DBX Sprint'!$A$1:A12)),"")} | AM45: {=IFERROR(INDEX('DBX Sprint'!$A$7:$K$62, SMALL(IF((INDEX('DBX Sprint'!$A$7:$K$62, ,32)=("Complete"))*(INDEX('DBX Sprint'!$A$7:$K$62, ,32)="Complete"),MATCH(ROW('DBX Sprint'!$A$7:$K$62),ROW('DBX Sprint'!$A$7:$K$62)),""),ROWS($AM$34:AM45)),COLUMNS('DBX Sprint'!$A$1:A12)),"")} | AN45: {=IFERROR(INDEX('DBX Sprint'!$A$7:$K$62, SMALL(IF((INDEX('DBX Sprint'!$A$7:$K$62, ,32)<(TODAY()))*(INDEX('DBX Sprint'!$A$7:$K$62, ,32)<>"Complete"),MATCH(ROW('DBX Sprint'!$A$7:$K$62),ROW('DBX Sprint'!$A$7:$K$62)),""),ROWS($AN$34:AN45)),COLUMNS('DBX Sprint'!$A$1:A12)),"")} | AO45: {=IFERROR(INDEX('DBX Sprint'!$A$7:$K$62, SMALL(IF((INDEX('DBX Sprint'!$A$7:$K$62, ,32)<=(TODAY()+1))*(INDEX('DBX Sprint'!$A$7:$K$62, ,32)>=TODAY()),MATCH(ROW('DBX Sprint'!$A$7:$K$62),ROW('DBX Sprint'!$A$7:$K$62)),""),ROWS($AO$34:AO45)),COLUMNS('DBX Sprint'!$A$1:A12)),"")} | AP45: {=IFERROR(INDEX('DBX Sprint'!$A$7:$K$62, SMALL(IF((INDEX('DBX Sprint'!$A$7:$K$62, ,32)<=(TODAY()+5))*(INDEX('DBX Sprint'!$A$7:$K$62, ,32)>(TODAY()+1)),MATCH(ROW('DBX Sprint'!$A$7:$K$62),ROW('DBX Sprint'!$A$7:$K$62)),""),ROWS($AP$34:AP45)),COLUMNS('DBX Sprint'!$A$1:A12)),"")} | AQ45: {=IFERROR(INDEX('DBX Sprint'!$A$7:$K$62, SMALL(IF((INDEX('DBX Sprint'!$A$7:$K$62, ,32)<=(TODAY()+10))*(INDEX('DBX Sprint'!$A$7:$K$62, ,32)>(TODAY()+5)),MATCH(ROW('DBX Sprint'!$A$7:$K$62),ROW('DBX Sprint'!$A$7:$K$62)),""),ROWS($AQ$34:AQ45)),COLUMNS('DBX Sprint'!$A$1:A12)),"")}
C46: {=IFERROR(INDEX('DBX Sprint'!$A$7:$K$62, SMALL(IF((INDEX('DBX Sprint'!$A$7:$K$62, ,13)=("Complete"))*(INDEX('DBX Sprint'!$A$7:$K$62, ,13)="Complete"),MATCH(ROW('DBX Sprint'!$A$7:$K$62),ROW('DBX Sprint'!$A$7:$K$62)),""),ROWS(C$34:$C46)),COLUMNS('DBX Sprint'!$A$1:A12)),"")} | D46: {=IFERROR(INDEX('DBX Sprint'!$A$7:$K$62, SMALL(IF((INDEX('DBX Sprint'!$A$7:$K$62, ,13)<(TODAY()))*(INDEX('DBX Sprint'!$A$7:$K$62, ,13)<>"Complete"),MATCH(ROW('DBX Sprint'!$A$7:$K$62),ROW('DBX Sprint'!$A$7:$K$62)),""),ROWS(D$34:$D46)),COLUMNS('DBX Sprint'!$A$1:A12)),"")} | E46: {=IFERROR(INDEX('DBX Sprint'!$A$7:$K$62, SMALL(IF((INDEX('DBX Sprint'!$A$7:$K$62, ,13)<=(TODAY()+1))*(INDEX('DBX Sprint'!$A$7:$K$62, ,13)>=TODAY()),MATCH(ROW('DBX Sprint'!$A$7:$K$62),ROW('DBX Sprint'!$A$7:$K$62)),""),ROWS(E$34:$E46)),COLUMNS('DBX Sprint'!$A$1:A12)),"")} | F46: {=IFERROR(INDEX('DBX Sprint'!$A$7:$K$62, SMALL(IF((INDEX('DBX Sprint'!$A$7:$K$62, ,13)<=(TODAY()+5))*(INDEX('DBX Sprint'!$A$7:$K$62, ,13)>(TODAY()+1)),MATCH(ROW('DBX Sprint'!$A$7:$K$62),ROW('DBX Sprint'!$A$7:$K$62)),""),ROWS($F$34:F46)),COLUMNS('DBX Sprint'!$A$1:A12)),"")} | G46: {=IFERROR(INDEX('DBX Sprint'!$A$7:$K$62, SMALL(IF((INDEX('DBX Sprint'!$A$7:$K$62, ,13)<=(TODAY()+10))*(INDEX('DBX Sprint'!$A$7:$K$62, ,13)>(TODAY()+5)),MATCH(ROW('DBX Sprint'!$A$7:$K$62),ROW('DBX Sprint'!$A$7:$K$62)),""),ROWS($G$34:G46)),COLUMNS('DBX Sprint'!$A$1:A12)),"")} | I46: {=IFERROR(INDEX('DBX Sprint'!$A$7:$K$62, SMALL(IF((INDEX('DBX Sprint'!$A$7:$K$62, ,16)=("Complete"))*(INDEX('DBX Sprint'!$A$7:$K$62, ,16)="Complete"),MATCH(ROW('DBX Sprint'!$A$7:$K$62),ROW('DBX Sprint'!$A$7:$K$62)),""),ROWS($I$34:I46)),COLUMNS('DBX Sprint'!$A$1:A12)),"")} | J46: {=IFERROR(INDEX('DBX Sprint'!$A$7:$K$62, SMALL(IF((INDEX('DBX Sprint'!$A$7:$K$62, ,16)<(TODAY()))*(INDEX('DBX Sprint'!$A$7:$K$62, ,16)<>"Complete"),MATCH(ROW('DBX Sprint'!$A$7:$K$62),ROW('DBX Sprint'!$A$7:$K$62)),""),ROWS($J$34:J46)),COLUMNS('DBX Sprint'!$A$1:A12)),"")} | K46: {=IFERROR(INDEX('DBX Sprint'!$A$7:$K$62, SMALL(IF((INDEX('DBX Sprint'!$A$7:$K$62, ,16)<=(TODAY()+1))*(INDEX('DBX Sprint'!$A$7:$K$62, ,16)>=TODAY()),MATCH(ROW('DBX Sprint'!$A$7:$K$62),ROW('DBX Sprint'!$A$7:$K$62)),""),ROWS($K$34:K46)),COLUMNS('DBX Sprint'!$A$1:A12)),"")} | L46: {=IFERROR(INDEX('DBX Sprint'!$A$7:$K$62, SMALL(IF((INDEX('DBX Sprint'!$A$7:$K$62, ,16)<=(TODAY()+5))*(INDEX('DBX Sprint'!$A$7:$K$62, ,16)>(TODAY()+1)),MATCH(ROW('DBX Sprint'!$A$7:$K$62),ROW('DBX Sprint'!$A$7:$K$62)),""),ROWS($L$34:L46)),COLUMNS('DBX Sprint'!$A$1:A12)),"")} | M46: {=IFERROR(INDEX('DBX Sprint'!$A$7:$K$62, SMALL(IF((INDEX('DBX Sprint'!$A$7:$K$62, ,16)<=(TODAY()+10))*(INDEX('DBX Sprint'!$A$7:$K$62, ,16)>(TODAY()+5)),MATCH(ROW('DBX Sprint'!$A$7:$K$62),ROW('DBX Sprint'!$A$7:$K$62)),""),ROWS($M$34:M46)),COLUMNS('DBX Sprint'!$A$1:A12)),"")} | O46: {=IFERROR(INDEX('DBX Sprint'!$A$7:$K$62, SMALL(IF((INDEX('DBX Sprint'!$A$7:$K$62, ,19)=("Complete"))*(INDEX('DBX Sprint'!$A$7:$K$62, ,19)="Complete"),MATCH(ROW('DBX Sprint'!$A$7:$K$62),ROW('DBX Sprint'!$A$7:$K$62)),""),ROWS($O$34:O46)),COLUMNS('DBX Sprint'!$A$1:A12)),"")} | P46: {=IFERROR(INDEX('DBX Sprint'!$A$7:$K$62, SMALL(IF((INDEX('DBX Sprint'!$A$7:$K$62, ,19)<(TODAY()))*(INDEX('DBX Sprint'!$A$7:$K$62, ,19)<>"Complete"),MATCH(ROW('DBX Sprint'!$A$7:$K$62),ROW('DBX Sprint'!$A$7:$K$62)),""),ROWS($P$34:P46)),COLUMNS('DBX Sprint'!$A$1:A12)),"")} | Q46: {=IFERROR(INDEX('DBX Sprint'!$A$7:$K$62, SMALL(IF((INDEX('DBX Sprint'!$A$7:$K$62, ,19)<=(TODAY()+1))*(INDEX('DBX Sprint'!$A$7:$K$62, ,19)>=TODAY()),MATCH(ROW('DBX Sprint'!$A$7:$K$62),ROW('DBX Sprint'!$A$7:$K$62)),""),ROWS($Q$34:Q46)),COLUMNS('DBX Sprint'!$A$1:A12)),"")} | R46: {=IFERROR(INDEX('DBX Sprint'!$A$7:$K$62, SMALL(IF((INDEX('DBX Sprint'!$A$7:$K$62, ,19)<=(TODAY()+5))*(INDEX('DBX Sprint'!$A$7:$K$62, ,19)>(TODAY()+1)),MATCH(ROW('DBX Sprint'!$A$7:$K$62),ROW('DBX Sprint'!$A$7:$K$62)),""),ROWS($R$34:R46)),COLUMNS('DBX Sprint'!$A$1:A12)),"")} | S46: {=IFERROR(INDEX('DBX Sprint'!$A$7:$K$62, SMALL(IF((INDEX('DBX Sprint'!$A$7:$K$62, ,19)<=(TODAY()+10))*(INDEX('DBX Sprint'!$A$7:$K$62, ,19)>(TODAY()+5)),MATCH(ROW('DBX Sprint'!$A$7:$K$62),ROW('DBX Sprint'!$A$7:$K$62)),""),ROWS($S$34:S46)),COLUMNS('DBX Sprint'!$A$1:A12)),"")} | U46: {=IFERROR(INDEX('DBX Sprint'!$A$7:$K$62, SMALL(IF((INDEX('DBX Sprint'!$A$7:$K$62, ,22)=("Complete"))*(INDEX('DBX Sprint'!$A$7:$K$62, ,22)="Complete"),MATCH(ROW('DBX Sprint'!$A$7:$K$62),ROW('DBX Sprint'!$A$7:$K$62)),""),ROWS($U$34:U46)),COLUMNS('DBX Sprint'!$A$1:A12)),"")} | V46: {=IFERROR(INDEX('DBX Sprint'!$A$7:$K$62, SMALL(IF((INDEX('DBX Sprint'!$A$7:$K$62, ,22)<(TODAY()))*(INDEX('DBX Sprint'!$A$7:$K$62, ,22)<>"Complete"),MATCH(ROW('DBX Sprint'!$A$7:$K$62),ROW('DBX Sprint'!$A$7:$K$62)),""),ROWS($V$34:V46)),COLUMNS('DBX Sprint'!$A$1:A12)),"")} | W46: {=IFERROR(INDEX('DBX Sprint'!$A$7:$K$62, SMALL(IF((INDEX('DBX Sprint'!$A$7:$K$62, ,22)<=(TODAY()+1))*(INDEX('DBX Sprint'!$A$7:$K$62, ,22)>=TODAY()),MATCH(ROW('DBX Sprint'!$A$7:$K$62),ROW('DBX Sprint'!$A$7:$K$62)),""),ROWS($W$34:W46)),COLUMNS('DBX Sprint'!$A$1:A12)),"")} | X46: {=IFERROR(INDEX('DBX Sprint'!$A$7:$K$62, SMALL(IF((INDEX('DBX Sprint'!$A$7:$K$62, ,22)<=(TODAY()+5))*(INDEX('DBX Sprint'!$A$7:$K$62, ,22)>(TODAY()+1)),MATCH(ROW('DBX Sprint'!$A$7:$K$62),ROW('DBX Sprint'!$A$7:$K$62)),""),ROWS($X$34:X46)),COLUMNS('DBX Sprint'!$A$1:A12)),"")} | Y46: {=IFERROR(INDEX('DBX Sprint'!$A$7:$K$62, SMALL(IF((INDEX('DBX Sprint'!$A$7:$K$62, ,22)<=(TODAY()+10))*(INDEX('DBX Sprint'!$A$7:$K$62, ,22)>(TODAY()+5)),MATCH(ROW('DBX Sprint'!$A$7:$K$62),ROW('DBX Sprint'!$A$7:$K$62)),""),ROWS($Y$34:Y46)),COLUMNS('DBX Sprint'!$A$1:A12)),"")} | AA46: {=IFERROR(INDEX('DBX Sprint'!$A$7:$K$62, SMALL(IF((INDEX('DBX Sprint'!$A$7:$K$62, ,25)=("Complete"))*(INDEX('DBX Sprint'!$A$7:$K$62, ,25)="Complete"),MATCH(ROW('DBX Sprint'!$A$7:$K$62),ROW('DBX Sprint'!$A$7:$K$62)),""),ROWS($AA$34:AA46)),COLUMNS('DBX Sprint'!$A$1:A12)),"")} | AB46: {=IFERROR(INDEX('DBX Sprint'!$A$7:$K$62, SMALL(IF((INDEX('DBX Sprint'!$A$7:$K$62, ,25)<(TODAY()))*(INDEX('DBX Sprint'!$A$7:$K$62, ,25)<>"Complete"),MATCH(ROW('DBX Sprint'!$A$7:$K$62),ROW('DBX Sprint'!$A$7:$K$62)),""),ROWS($AB$34:AB46)),COLUMNS('DBX Sprint'!$A$1:A12)),"")} | AC46: {=IFERROR(INDEX('DBX Sprint'!$A$7:$K$62, SMALL(IF((INDEX('DBX Sprint'!$A$7:$K$62, ,25)<=(TODAY()+1))*(INDEX('DBX Sprint'!$A$7:$K$62, ,25)>=TODAY()),MATCH(ROW('DBX Sprint'!$A$7:$K$62),ROW('DBX Sprint'!$A$7:$K$62)),""),ROWS($AC$34:AC46)),COLUMNS('DBX Sprint'!$A$1:A12)),"")} | AD46: {=IFERROR(INDEX('DBX Sprint'!$A$7:$K$62, SMALL(IF((INDEX('DBX Sprint'!$A$7:$K$62, ,25)<=(TODAY()+5))*(INDEX('DBX Sprint'!$A$7:$K$62, ,25)>(TODAY()+1)),MATCH(ROW('DBX Sprint'!$A$7:$K$62),ROW('DBX Sprint'!$A$7:$K$62)),""),ROWS($AD$34:AD46)),COLUMNS('DBX Sprint'!$A$1:A12)),"")} | AE46: {=IFERROR(INDEX('DBX Sprint'!$A$7:$K$62, SMALL(IF((INDEX('DBX Sprint'!$A$7:$K$62, ,25)<=(TODAY()+10))*(INDEX('DBX Sprint'!$A$7:$K$62, ,25)>(TODAY()+5)),MATCH(ROW('DBX Sprint'!$A$7:$K$62),ROW('DBX Sprint'!$A$7:$K$62)),""),ROWS($AE$34:AE46)),COLUMNS('DBX Sprint'!$A$1:A12)),"")} | AG46: {=IFERROR(INDEX('DBX Sprint'!$A$7:$K$62, SMALL(IF((INDEX('DBX Sprint'!$A$7:$K$62, ,29)=("Complete"))*(INDEX('DBX Sprint'!$A$7:$K$62, ,29)="Complete"),MATCH(ROW('DBX Sprint'!$A$7:$K$62),ROW('DBX Sprint'!$A$7:$K$62)),""),ROWS($AG$34:AG46)),COLUMNS('DBX Sprint'!$A$1:A12)),"")} | AH46: {=IFERROR(INDEX('DBX Sprint'!$A$7:$K$62, SMALL(IF((INDEX('DBX Sprint'!$A$7:$K$62, ,29)<(TODAY()))*(INDEX('DBX Sprint'!$A$7:$K$62, ,29)<>"Complete"),MATCH(ROW('DBX Sprint'!$A$7:$K$62),ROW('DBX Sprint'!$A$7:$K$62)),""),ROWS($AH$34:AH46)),COLUMNS('DBX Sprint'!$A$1:A12)),"")} | AI46: {=IFERROR(INDEX('DBX Sprint'!$A$7:$K$62, SMALL(IF((INDEX('DBX Sprint'!$A$7:$K$62, ,29)<=(TODAY()+1))*(INDEX('DBX Sprint'!$A$7:$K$62, ,29)>=TODAY()),MATCH(ROW('DBX Sprint'!$A$7:$K$62),ROW('DBX Sprint'!$A$7:$K$62)),""),ROWS($AI$34:AI46)),COLUMNS('DBX Sprint'!$A$1:A12)),"")} | AJ46: {=IFERROR(INDEX('DBX Sprint'!$A$7:$K$62, SMALL(IF((INDEX('DBX Sprint'!$A$7:$K$62, ,29)<=(TODAY()+5))*(INDEX('DBX Sprint'!$A$7:$K$62, ,29)>(TODAY()+1)),MATCH(ROW('DBX Sprint'!$A$7:$K$62),ROW('DBX Sprint'!$A$7:$K$62)),""),ROWS($AJ$34:AJ46)),COLUMNS('DBX Sprint'!$A$1:A12)),"")} | AK46: {=IFERROR(INDEX('DBX Sprint'!$A$7:$K$62, SMALL(IF((INDEX('DBX Sprint'!$A$7:$K$62, ,29)<=(TODAY()+10))*(INDEX('DBX Sprint'!$A$7:$K$62, ,29)>(TODAY()+5)),MATCH(ROW('DBX Sprint'!$A$7:$K$62),ROW('DBX Sprint'!$A$7:$K$62)),""),ROWS($AK$34:AK46)),COLUMNS('DBX Sprint'!$A$1:A12)),"")} | AM46: {=IFERROR(INDEX('DBX Sprint'!$A$7:$K$62, SMALL(IF((INDEX('DBX Sprint'!$A$7:$K$62, ,32)=("Complete"))*(INDEX('DBX Sprint'!$A$7:$K$62, ,32)="Complete"),MATCH(ROW('DBX Sprint'!$A$7:$K$62),ROW('DBX Sprint'!$A$7:$K$62)),""),ROWS($AM$34:AM46)),COLUMNS('DBX Sprint'!$A$1:A12)),"")} | AN46: {=IFERROR(INDEX('DBX Sprint'!$A$7:$K$62, SMALL(IF((INDEX('DBX Sprint'!$A$7:$K$62, ,32)<(TODAY()))*(INDEX('DBX Sprint'!$A$7:$K$62, ,32)<>"Complete"),MATCH(ROW('DBX Sprint'!$A$7:$K$62),ROW('DBX Sprint'!$A$7:$K$62)),""),ROWS($AN$34:AN46)),COLUMNS('DBX Sprint'!$A$1:A12)),"")} | AO46: {=IFERROR(INDEX('DBX Sprint'!$A$7:$K$62, SMALL(IF((INDEX('DBX Sprint'!$A$7:$K$62, ,32)<=(TODAY()+1))*(INDEX('DBX Sprint'!$A$7:$K$62, ,32)>=TODAY()),MATCH(ROW('DBX Sprint'!$A$7:$K$62),ROW('DBX Sprint'!$A$7:$K$62)),""),ROWS($AO$34:AO46)),COLUMNS('DBX Sprint'!$A$1:A12)),"")} | AP46: {=IFERROR(INDEX('DBX Sprint'!$A$7:$K$62, SMALL(IF((INDEX('DBX Sprint'!$A$7:$K$62, ,32)<=(TODAY()+5))*(INDEX('DBX Sprint'!$A$7:$K$62, ,32)>(TODAY()+1)),MATCH(ROW('DBX Sprint'!$A$7:$K$62),ROW('DBX Sprint'!$A$7:$K$62)),""),ROWS($AP$34:AP46)),COLUMNS('DBX Sprint'!$A$1:A12)),"")} | AQ46: {=IFERROR(INDEX('DBX Sprint'!$A$7:$K$62, SMALL(IF((INDEX('DBX Sprint'!$A$7:$K$62, ,32)<=(TODAY()+10))*(INDEX('DBX Sprint'!$A$7:$K$62, ,32)>(TODAY()+5)),MATCH(ROW('DBX Sprint'!$A$7:$K$62),ROW('DBX Sprint'!$A$7:$K$62)),""),ROWS($AQ$34:AQ46)),COLUMNS('DBX Sprint'!$A$1:A12)),"")}
C47: {=IFERROR(INDEX('DBX Sprint'!$A$7:$K$62, SMALL(IF((INDEX('DBX Sprint'!$A$7:$K$62, ,13)=("Complete"))*(INDEX('DBX Sprint'!$A$7:$K$62, ,13)="Complete"),MATCH(ROW('DBX Sprint'!$A$7:$K$62),ROW('DBX Sprint'!$A$7:$K$62)),""),ROWS(C$34:$C47)),COLUMNS('DBX Sprint'!$A$1:A12)),"")} | D47: {=IFERROR(INDEX('DBX Sprint'!$A$7:$K$62, SMALL(IF((INDEX('DBX Sprint'!$A$7:$K$62, ,13)<(TODAY()))*(INDEX('DBX Sprint'!$A$7:$K$62, ,13)<>"Complete"),MATCH(ROW('DBX Sprint'!$A$7:$K$62),ROW('DBX Sprint'!$A$7:$K$62)),""),ROWS(D$34:$D47)),COLUMNS('DBX Sprint'!$A$1:A12)),"")} | E47: {=IFERROR(INDEX('DBX Sprint'!$A$7:$K$62, SMALL(IF((INDEX('DBX Sprint'!$A$7:$K$62, ,13)<=(TODAY()+1))*(INDEX('DBX Sprint'!$A$7:$K$62, ,13)>=TODAY()),MATCH(ROW('DBX Sprint'!$A$7:$K$62),ROW('DBX Sprint'!$A$7:$K$62)),""),ROWS(E$34:$E47)),COLUMNS('DBX Sprint'!$A$1:A12)),"")} | F47: {=IFERROR(INDEX('DBX Sprint'!$A$7:$K$62, SMALL(IF((INDEX('DBX Sprint'!$A$7:$K$62, ,13)<=(TODAY()+5))*(INDEX('DBX Sprint'!$A$7:$K$62, ,13)>(TODAY()+1)),MATCH(ROW('DBX Sprint'!$A$7:$K$62),ROW('DBX Sprint'!$A$7:$K$62)),""),ROWS($F$34:F47)),COLUMNS('DBX Sprint'!$A$1:A12)),"")} | G47: {=IFERROR(INDEX('DBX Sprint'!$A$7:$K$62, SMALL(IF((INDEX('DBX Sprint'!$A$7:$K$62, ,13)<=(TODAY()+10))*(INDEX('DBX Sprint'!$A$7:$K$62, ,13)>(TODAY()+5)),MATCH(ROW('DBX Sprint'!$A$7:$K$62),ROW('DBX Sprint'!$A$7:$K$62)),""),ROWS($G$34:G47)),COLUMNS('DBX Sprint'!$A$1:A12)),"")} | I47: {=IFERROR(INDEX('DBX Sprint'!$A$7:$K$62, SMALL(IF((INDEX('DBX Sprint'!$A$7:$K$62, ,16)=("Complete"))*(INDEX('DBX Sprint'!$A$7:$K$62, ,16)="Complete"),MATCH(ROW('DBX Sprint'!$A$7:$K$62),ROW('DBX Sprint'!$A$7:$K$62)),""),ROWS($I$34:I47)),COLUMNS('DBX Sprint'!$A$1:A12)),"")} | J47: {=IFERROR(INDEX('DBX Sprint'!$A$7:$K$62, SMALL(IF((INDEX('DBX Sprint'!$A$7:$K$62, ,16)<(TODAY()))*(INDEX('DBX Sprint'!$A$7:$K$62, ,16)<>"Complete"),MATCH(ROW('DBX Sprint'!$A$7:$K$62),ROW('DBX Sprint'!$A$7:$K$62)),""),ROWS($J$34:J47)),COLUMNS('DBX Sprint'!$A$1:A12)),"")} | K47: {=IFERROR(INDEX('DBX Sprint'!$A$7:$K$62, SMALL(IF((INDEX('DBX Sprint'!$A$7:$K$62, ,16)<=(TODAY()+1))*(INDEX('DBX Sprint'!$A$7:$K$62, ,16)>=TODAY()),MATCH(ROW('DBX Sprint'!$A$7:$K$62),ROW('DBX Sprint'!$A$7:$K$62)),""),ROWS($K$34:K47)),COLUMNS('DBX Sprint'!$A$1:A12)),"")} | L47: {=IFERROR(INDEX('DBX Sprint'!$A$7:$K$62, SMALL(IF((INDEX('DBX Sprint'!$A$7:$K$62, ,16)<=(TODAY()+5))*(INDEX('DBX Sprint'!$A$7:$K$62, ,16)>(TODAY()+1)),MATCH(ROW('DBX Sprint'!$A$7:$K$62),ROW('DBX Sprint'!$A$7:$K$62)),""),ROWS($L$34:L47)),COLUMNS('DBX Sprint'!$A$1:A12)),"")} | M47: {=IFERROR(INDEX('DBX Sprint'!$A$7:$K$62, SMALL(IF((INDEX('DBX Sprint'!$A$7:$K$62, ,16)<=(TODAY()+10))*(INDEX('DBX Sprint'!$A$7:$K$62, ,16)>(TODAY()+5)),MATCH(ROW('DBX Sprint'!$A$7:$K$62),ROW('DBX Sprint'!$A$7:$K$62)),""),ROWS($M$34:M47)),COLUMNS('DBX Sprint'!$A$1:A12)),"")} | O47: {=IFERROR(INDEX('DBX Sprint'!$A$7:$K$62, SMALL(IF((INDEX('DBX Sprint'!$A$7:$K$62, ,19)=("Complete"))*(INDEX('DBX Sprint'!$A$7:$K$62, ,19)="Complete"),MATCH(ROW('DBX Sprint'!$A$7:$K$62),ROW('DBX Sprint'!$A$7:$K$62)),""),ROWS($O$34:O47)),COLUMNS('DBX Sprint'!$A$1:A12)),"")} | P47: {=IFERROR(INDEX('DBX Sprint'!$A$7:$K$62, SMALL(IF((INDEX('DBX Sprint'!$A$7:$K$62, ,19)<(TODAY()))*(INDEX('DBX Sprint'!$A$7:$K$62, ,19)<>"Complete"),MATCH(ROW('DBX Sprint'!$A$7:$K$62),ROW('DBX Sprint'!$A$7:$K$62)),""),ROWS($P$34:P47)),COLUMNS('DBX Sprint'!$A$1:A12)),"")} | Q47: {=IFERROR(INDEX('DBX Sprint'!$A$7:$K$62, SMALL(IF((INDEX('DBX Sprint'!$A$7:$K$62, ,19)<=(TODAY()+1))*(INDEX('DBX Sprint'!$A$7:$K$62, ,19)>=TODAY()),MATCH(ROW('DBX Sprint'!$A$7:$K$62),ROW('DBX Sprint'!$A$7:$K$62)),""),ROWS($Q$34:Q47)),COLUMNS('DBX Sprint'!$A$1:A12)),"")} | R47: {=IFERROR(INDEX('DBX Sprint'!$A$7:$K$62, SMALL(IF((INDEX('DBX Sprint'!$A$7:$K$62, ,19)<=(TODAY()+5))*(INDEX('DBX Sprint'!$A$7:$K$62, ,19)>(TODAY()+1)),MATCH(ROW('DBX Sprint'!$A$7:$K$62),ROW('DBX Sprint'!$A$7:$K$62)),""),ROWS($R$34:R47)),COLUMNS('DBX Sprint'!$A$1:A12)),"")} | S47: {=IFERROR(INDEX('DBX Sprint'!$A$7:$K$62, SMALL(IF((INDEX('DBX Sprint'!$A$7:$K$62, ,19)<=(TODAY()+10))*(INDEX('DBX Sprint'!$A$7:$K$62, ,19)>(TODAY()+5)),MATCH(ROW('DBX Sprint'!$A$7:$K$62),ROW('DBX Sprint'!$A$7:$K$62)),""),ROWS($S$34:S47)),COLUMNS('DBX Sprint'!$A$1:A12)),"")} | U47: {=IFERROR(INDEX('DBX Sprint'!$A$7:$K$62, SMALL(IF((INDEX('DBX Sprint'!$A$7:$K$62, ,22)=("Complete"))*(INDEX('DBX Sprint'!$A$7:$K$62, ,22)="Complete"),MATCH(ROW('DBX Sprint'!$A$7:$K$62),ROW('DBX Sprint'!$A$7:$K$62)),""),ROWS($U$34:U47)),COLUMNS('DBX Sprint'!$A$1:A12)),"")} | V47: {=IFERROR(INDEX('DBX Sprint'!$A$7:$K$62, SMALL(IF((INDEX('DBX Sprint'!$A$7:$K$62, ,22)<(TODAY()))*(INDEX('DBX Sprint'!$A$7:$K$62, ,22)<>"Complete"),MATCH(ROW('DBX Sprint'!$A$7:$K$62),ROW('DBX Sprint'!$A$7:$K$62)),""),ROWS($V$34:V47)),COLUMNS('DBX Sprint'!$A$1:A12)),"")} | W47: {=IFERROR(INDEX('DBX Sprint'!$A$7:$K$62, SMALL(IF((INDEX('DBX Sprint'!$A$7:$K$62, ,22)<=(TODAY()+1))*(INDEX('DBX Sprint'!$A$7:$K$62, ,22)>=TODAY()),MATCH(ROW('DBX Sprint'!$A$7:$K$62),ROW('DBX Sprint'!$A$7:$K$62)),""),ROWS($W$34:W47)),COLUMNS('DBX Sprint'!$A$1:A12)),"")} | X47: {=IFERROR(INDEX('DBX Sprint'!$A$7:$K$62, SMALL(IF((INDEX('DBX Sprint'!$A$7:$K$62, ,22)<=(TODAY()+5))*(INDEX('DBX Sprint'!$A$7:$K$62, ,22)>(TODAY()+1)),MATCH(ROW('DBX Sprint'!$A$7:$K$62),ROW('DBX Sprint'!$A$7:$K$62)),""),ROWS($X$34:X47)),COLUMNS('DBX Sprint'!$A$1:A12)),"")} | Y47: {=IFERROR(INDEX('DBX Sprint'!$A$7:$K$62, SMALL(IF((INDEX('DBX Sprint'!$A$7:$K$62, ,22)<=(TODAY()+10))*(INDEX('DBX Sprint'!$A$7:$K$62, ,22)>(TODAY()+5)),MATCH(ROW('DBX Sprint'!$A$7:$K$62),ROW('DBX Sprint'!$A$7:$K$62)),""),ROWS($Y$34:Y47)),COLUMNS('DBX Sprint'!$A$1:A12)),"")} | AA47: {=IFERROR(INDEX('DBX Sprint'!$A$7:$K$62, SMALL(IF((INDEX('DBX Sprint'!$A$7:$K$62, ,25)=("Complete"))*(INDEX('DBX Sprint'!$A$7:$K$62, ,25)="Complete"),MATCH(ROW('DBX Sprint'!$A$7:$K$62),ROW('DBX Sprint'!$A$7:$K$62)),""),ROWS($AA$34:AA47)),COLUMNS('DBX Sprint'!$A$1:A12)),"")} | AB47: {=IFERROR(INDEX('DBX Sprint'!$A$7:$K$62, SMALL(IF((INDEX('DBX Sprint'!$A$7:$K$62, ,25)<(TODAY()))*(INDEX('DBX Sprint'!$A$7:$K$62, ,25)<>"Complete"),MATCH(ROW('DBX Sprint'!$A$7:$K$62),ROW('DBX Sprint'!$A$7:$K$62)),""),ROWS($AB$34:AB47)),COLUMNS('DBX Sprint'!$A$1:A12)),"")} | AC47: {=IFERROR(INDEX('DBX Sprint'!$A$7:$K$62, SMALL(IF((INDEX('DBX Sprint'!$A$7:$K$62, ,25)<=(TODAY()+1))*(INDEX('DBX Sprint'!$A$7:$K$62, ,25)>=TODAY()),MATCH(ROW('DBX Sprint'!$A$7:$K$62),ROW('DBX Sprint'!$A$7:$K$62)),""),ROWS($AC$34:AC47)),COLUMNS('DBX Sprint'!$A$1:A12)),"")} | AD47: {=IFERROR(INDEX('DBX Sprint'!$A$7:$K$62, SMALL(IF((INDEX('DBX Sprint'!$A$7:$K$62, ,25)<=(TODAY()+5))*(INDEX('DBX Sprint'!$A$7:$K$62, ,25)>(TODAY()+1)),MATCH(ROW('DBX Sprint'!$A$7:$K$62),ROW('DBX Sprint'!$A$7:$K$62)),""),ROWS($AD$34:AD47)),COLUMNS('DBX Sprint'!$A$1:A12)),"")} | AE47: {=IFERROR(INDEX('DBX Sprint'!$A$7:$K$62, SMALL(IF((INDEX('DBX Sprint'!$A$7:$K$62, ,25)<=(TODAY()+10))*(INDEX('DBX Sprint'!$A$7:$K$62, ,25)>(TODAY()+5)),MATCH(ROW('DBX Sprint'!$A$7:$K$62),ROW('DBX Sprint'!$A$7:$K$62)),""),ROWS($AE$34:AE47)),COLUMNS('DBX Sprint'!$A$1:A12)),"")} | AG47: {=IFERROR(INDEX('DBX Sprint'!$A$7:$K$62, SMALL(IF((INDEX('DBX Sprint'!$A$7:$K$62, ,29)=("Complete"))*(INDEX('DBX Sprint'!$A$7:$K$62, ,29)="Complete"),MATCH(ROW('DBX Sprint'!$A$7:$K$62),ROW('DBX Sprint'!$A$7:$K$62)),""),ROWS($AG$34:AG47)),COLUMNS('DBX Sprint'!$A$1:A12)),"")} | AH47: {=IFERROR(INDEX('DBX Sprint'!$A$7:$K$62, SMALL(IF((INDEX('DBX Sprint'!$A$7:$K$62, ,29)<(TODAY()))*(INDEX('DBX Sprint'!$A$7:$K$62, ,29)<>"Complete"),MATCH(ROW('DBX Sprint'!$A$7:$K$62),ROW('DBX Sprint'!$A$7:$K$62)),""),ROWS($AH$34:AH47)),COLUMNS('DBX Sprint'!$A$1:A12)),"")} | AI47: {=IFERROR(INDEX('DBX Sprint'!$A$7:$K$62, SMALL(IF((INDEX('DBX Sprint'!$A$7:$K$62, ,29)<=(TODAY()+1))*(INDEX('DBX Sprint'!$A$7:$K$62, ,29)>=TODAY()),MATCH(ROW('DBX Sprint'!$A$7:$K$62),ROW('DBX Sprint'!$A$7:$K$62)),""),ROWS($AI$34:AI47)),COLUMNS('DBX Sprint'!$A$1:A12)),"")} | AJ47: {=IFERROR(INDEX('DBX Sprint'!$A$7:$K$62, SMALL(IF((INDEX('DBX Sprint'!$A$7:$K$62, ,29)<=(TODAY()+5))*(INDEX('DBX Sprint'!$A$7:$K$62, ,29)>(TODAY()+1)),MATCH(ROW('DBX Sprint'!$A$7:$K$62),ROW('DBX Sprint'!$A$7:$K$62)),""),ROWS($AJ$34:AJ47)),COLUMNS('DBX Sprint'!$A$1:A12)),"")} | AK47: {=IFERROR(INDEX('DBX Sprint'!$A$7:$K$62, SMALL(IF((INDEX('DBX Sprint'!$A$7:$K$62, ,29)<=(TODAY()+10))*(INDEX('DBX Sprint'!$A$7:$K$62, ,29)>(TODAY()+5)),MATCH(ROW('DBX Sprint'!$A$7:$K$62),ROW('DBX Sprint'!$A$7:$K$62)),""),ROWS($AK$34:AK47)),COLUMNS('DBX Sprint'!$A$1:A12)),"")} | AM47: {=IFERROR(INDEX('DBX Sprint'!$A$7:$K$62, SMALL(IF((INDEX('DBX Sprint'!$A$7:$K$62, ,32)=("Complete"))*(INDEX('DBX Sprint'!$A$7:$K$62, ,32)="Complete"),MATCH(ROW('DBX Sprint'!$A$7:$K$62),ROW('DBX Sprint'!$A$7:$K$62)),""),ROWS($AM$34:AM47)),COLUMNS('DBX Sprint'!$A$1:A12)),"")} | AN47: {=IFERROR(INDEX('DBX Sprint'!$A$7:$K$62, SMALL(IF((INDEX('DBX Sprint'!$A$7:$K$62, ,32)<(TODAY()))*(INDEX('DBX Sprint'!$A$7:$K$62, ,32)<>"Complete"),MATCH(ROW('DBX Sprint'!$A$7:$K$62),ROW('DBX Sprint'!$A$7:$K$62)),""),ROWS($AN$34:AN47)),COLUMNS('DBX Sprint'!$A$1:A12)),"")} | AO47: {=IFERROR(INDEX('DBX Sprint'!$A$7:$K$62, SMALL(IF((INDEX('DBX Sprint'!$A$7:$K$62, ,32)<=(TODAY()+1))*(INDEX('DBX Sprint'!$A$7:$K$62, ,32)>=TODAY()),MATCH(ROW('DBX Sprint'!$A$7:$K$62),ROW('DBX Sprint'!$A$7:$K$62)),""),ROWS($AO$34:AO47)),COLUMNS('DBX Sprint'!$A$1:A12)),"")} | AP47: {=IFERROR(INDEX('DBX Sprint'!$A$7:$K$62, SMALL(IF((INDEX('DBX Sprint'!$A$7:$K$62, ,32)<=(TODAY()+5))*(INDEX('DBX Sprint'!$A$7:$K$62, ,32)>(TODAY()+1)),MATCH(ROW('DBX Sprint'!$A$7:$K$62),ROW('DBX Sprint'!$A$7:$K$62)),""),ROWS($AP$34:AP47)),COLUMNS('DBX Sprint'!$A$1:A12)),"")} | AQ47: {=IFERROR(INDEX('DBX Sprint'!$A$7:$K$62, SMALL(IF((INDEX('DBX Sprint'!$A$7:$K$62, ,32)<=(TODAY()+10))*(INDEX('DBX Sprint'!$A$7:$K$62, ,32)>(TODAY()+5)),MATCH(ROW('DBX Sprint'!$A$7:$K$62),ROW('DBX Sprint'!$A$7:$K$62)),""),ROWS($AQ$34:AQ47)),COLUMNS('DBX Sprint'!$A$1:A12)),"")}
C48: {=IFERROR(INDEX('DBX Sprint'!$A$7:$K$62, SMALL(IF((INDEX('DBX Sprint'!$A$7:$K$62, ,13)=("Complete"))*(INDEX('DBX Sprint'!$A$7:$K$62, ,13)="Complete"),MATCH(ROW('DBX Sprint'!$A$7:$K$62),ROW('DBX Sprint'!$A$7:$K$62)),""),ROWS(C$34:$C48)),COLUMNS('DBX Sprint'!$A$1:A12)),"")} | D48: {=IFERROR(INDEX('DBX Sprint'!$A$7:$K$62, SMALL(IF((INDEX('DBX Sprint'!$A$7:$K$62, ,13)<(TODAY()))*(INDEX('DBX Sprint'!$A$7:$K$62, ,13)<>"Complete"),MATCH(ROW('DBX Sprint'!$A$7:$K$62),ROW('DBX Sprint'!$A$7:$K$62)),""),ROWS(D$34:$D48)),COLUMNS('DBX Sprint'!$A$1:A12)),"")} | E48: {=IFERROR(INDEX('DBX Sprint'!$A$7:$K$62, SMALL(IF((INDEX('DBX Sprint'!$A$7:$K$62, ,13)<=(TODAY()+1))*(INDEX('DBX Sprint'!$A$7:$K$62, ,13)>=TODAY()),MATCH(ROW('DBX Sprint'!$A$7:$K$62),ROW('DBX Sprint'!$A$7:$K$62)),""),ROWS(E$34:$E48)),COLUMNS('DBX Sprint'!$A$1:A12)),"")} | F48: {=IFERROR(INDEX('DBX Sprint'!$A$7:$K$62, SMALL(IF((INDEX('DBX Sprint'!$A$7:$K$62, ,13)<=(TODAY()+5))*(INDEX('DBX Sprint'!$A$7:$K$62, ,13)>(TODAY()+1)),MATCH(ROW('DBX Sprint'!$A$7:$K$62),ROW('DBX Sprint'!$A$7:$K$62)),""),ROWS($F$34:F48)),COLUMNS('DBX Sprint'!$A$1:A12)),"")} | G48: {=IFERROR(INDEX('DBX Sprint'!$A$7:$K$62, SMALL(IF((INDEX('DBX Sprint'!$A$7:$K$62, ,13)<=(TODAY()+10))*(INDEX('DBX Sprint'!$A$7:$K$62, ,13)>(TODAY()+5)),MATCH(ROW('DBX Sprint'!$A$7:$K$62),ROW('DBX Sprint'!$A$7:$K$62)),""),ROWS($G$34:G48)),COLUMNS('DBX Sprint'!$A$1:A12)),"")} | I48: {=IFERROR(INDEX('DBX Sprint'!$A$7:$K$62, SMALL(IF((INDEX('DBX Sprint'!$A$7:$K$62, ,16)=("Complete"))*(INDEX('DBX Sprint'!$A$7:$K$62, ,16)="Complete"),MATCH(ROW('DBX Sprint'!$A$7:$K$62),ROW('DBX Sprint'!$A$7:$K$62)),""),ROWS($I$34:I48)),COLUMNS('DBX Sprint'!$A$1:A12)),"")} | J48: {=IFERROR(INDEX('DBX Sprint'!$A$7:$K$62, SMALL(IF((INDEX('DBX Sprint'!$A$7:$K$62, ,16)<(TODAY()))*(INDEX('DBX Sprint'!$A$7:$K$62, ,16)<>"Complete"),MATCH(ROW('DBX Sprint'!$A$7:$K$62),ROW('DBX Sprint'!$A$7:$K$62)),""),ROWS($J$34:J48)),COLUMNS('DBX Sprint'!$A$1:A12)),"")} | K48: {=IFERROR(INDEX('DBX Sprint'!$A$7:$K$62, SMALL(IF((INDEX('DBX Sprint'!$A$7:$K$62, ,16)<=(TODAY()+1))*(INDEX('DBX Sprint'!$A$7:$K$62, ,16)>=TODAY()),MATCH(ROW('DBX Sprint'!$A$7:$K$62),ROW('DBX Sprint'!$A$7:$K$62)),""),ROWS($K$34:K48)),COLUMNS('DBX Sprint'!$A$1:A12)),"")} | L48: {=IFERROR(INDEX('DBX Sprint'!$A$7:$K$62, SMALL(IF((INDEX('DBX Sprint'!$A$7:$K$62, ,16)<=(TODAY()+5))*(INDEX('DBX Sprint'!$A$7:$K$62, ,16)>(TODAY()+1)),MATCH(ROW('DBX Sprint'!$A$7:$K$62),ROW('DBX Sprint'!$A$7:$K$62)),""),ROWS($L$34:L48)),COLUMNS('DBX Sprint'!$A$1:A12)),"")} | M48: {=IFERROR(INDEX('DBX Sprint'!$A$7:$K$62, SMALL(IF((INDEX('DBX Sprint'!$A$7:$K$62, ,16)<=(TODAY()+10))*(INDEX('DBX Sprint'!$A$7:$K$62, ,16)>(TODAY()+5)),MATCH(ROW('DBX Sprint'!$A$7:$K$62),ROW('DBX Sprint'!$A$7:$K$62)),""),ROWS($M$34:M48)),COLUMNS('DBX Sprint'!$A$1:A12)),"")} | O48: {=IFERROR(INDEX('DBX Sprint'!$A$7:$K$62, SMALL(IF((INDEX('DBX Sprint'!$A$7:$K$62, ,19)=("Complete"))*(INDEX('DBX Sprint'!$A$7:$K$62, ,19)="Complete"),MATCH(ROW('DBX Sprint'!$A$7:$K$62),ROW('DBX Sprint'!$A$7:$K$62)),""),ROWS($O$34:O48)),COLUMNS('DBX Sprint'!$A$1:A12)),"")} | P48: {=IFERROR(INDEX('DBX Sprint'!$A$7:$K$62, SMALL(IF((INDEX('DBX Sprint'!$A$7:$K$62, ,19)<(TODAY()))*(INDEX('DBX Sprint'!$A$7:$K$62, ,19)<>"Complete"),MATCH(ROW('DBX Sprint'!$A$7:$K$62),ROW('DBX Sprint'!$A$7:$K$62)),""),ROWS($P$34:P48)),COLUMNS('DBX Sprint'!$A$1:A12)),"")} | Q48: {=IFERROR(INDEX('DBX Sprint'!$A$7:$K$62, SMALL(IF((INDEX('DBX Sprint'!$A$7:$K$62, ,19)<=(TODAY()+1))*(INDEX('DBX Sprint'!$A$7:$K$62, ,19)>=TODAY()),MATCH(ROW('DBX Sprint'!$A$7:$K$62),ROW('DBX Sprint'!$A$7:$K$62)),""),ROWS($Q$34:Q48)),COLUMNS('DBX Sprint'!$A$1:A12)),"")} | R48: {=IFERROR(INDEX('DBX Sprint'!$A$7:$K$62, SMALL(IF((INDEX('DBX Sprint'!$A$7:$K$62, ,19)<=(TODAY()+5))*(INDEX('DBX Sprint'!$A$7:$K$62, ,19)>(TODAY()+1)),MATCH(ROW('DBX Sprint'!$A$7:$K$62),ROW('DBX Sprint'!$A$7:$K$62)),""),ROWS($R$34:R48)),COLUMNS('DBX Sprint'!$A$1:A12)),"")} | S48: {=IFERROR(INDEX('DBX Sprint'!$A$7:$K$62, SMALL(IF((INDEX('DBX Sprint'!$A$7:$K$62, ,19)<=(TODAY()+10))*(INDEX('DBX Sprint'!$A$7:$K$62, ,19)>(TODAY()+5)),MATCH(ROW('DBX Sprint'!$A$7:$K$62),ROW('DBX Sprint'!$A$7:$K$62)),""),ROWS($S$34:S48)),COLUMNS('DBX Sprint'!$A$1:A12)),"")} | U48: {=IFERROR(INDEX('DBX Sprint'!$A$7:$K$62, SMALL(IF((INDEX('DBX Sprint'!$A$7:$K$62, ,22)=("Complete"))*(INDEX('DBX Sprint'!$A$7:$K$62, ,22)="Complete"),MATCH(ROW('DBX Sprint'!$A$7:$K$62),ROW('DBX Sprint'!$A$7:$K$62)),""),ROWS($U$34:U48)),COLUMNS('DBX Sprint'!$A$1:A12)),"")} | V48: {=IFERROR(INDEX('DBX Sprint'!$A$7:$K$62, SMALL(IF((INDEX('DBX Sprint'!$A$7:$K$62, ,22)<(TODAY()))*(INDEX('DBX Sprint'!$A$7:$K$62, ,22)<>"Complete"),MATCH(ROW('DBX Sprint'!$A$7:$K$62),ROW('DBX Sprint'!$A$7:$K$62)),""),ROWS($V$34:V48)),COLUMNS('DBX Sprint'!$A$1:A12)),"")} | W48: {=IFERROR(INDEX('DBX Sprint'!$A$7:$K$62, SMALL(IF((INDEX('DBX Sprint'!$A$7:$K$62, ,22)<=(TODAY()+1))*(INDEX('DBX Sprint'!$A$7:$K$62, ,22)>=TODAY()),MATCH(ROW('DBX Sprint'!$A$7:$K$62),ROW('DBX Sprint'!$A$7:$K$62)),""),ROWS($W$34:W48)),COLUMNS('DBX Sprint'!$A$1:A12)),"")} | X48: {=IFERROR(INDEX('DBX Sprint'!$A$7:$K$62, SMALL(IF((INDEX('DBX Sprint'!$A$7:$K$62, ,22)<=(TODAY()+5))*(INDEX('DBX Sprint'!$A$7:$K$62, ,22)>(TODAY()+1)),MATCH(ROW('DBX Sprint'!$A$7:$K$62),ROW('DBX Sprint'!$A$7:$K$62)),""),ROWS($X$34:X48)),COLUMNS('DBX Sprint'!$A$1:A12)),"")} | Y48: {=IFERROR(INDEX('DBX Sprint'!$A$7:$K$62, SMALL(IF((INDEX('DBX Sprint'!$A$7:$K$62, ,22)<=(TODAY()+10))*(INDEX('DBX Sprint'!$A$7:$K$62, ,22)>(TODAY()+5)),MATCH(ROW('DBX Sprint'!$A$7:$K$62),ROW('DBX Sprint'!$A$7:$K$62)),""),ROWS($Y$34:Y48)),COLUMNS('DBX Sprint'!$A$1:A12)),"")} | AA48: {=IFERROR(INDEX('DBX Sprint'!$A$7:$K$62, SMALL(IF((INDEX('DBX Sprint'!$A$7:$K$62, ,25)=("Complete"))*(INDEX('DBX Sprint'!$A$7:$K$62, ,25)="Complete"),MATCH(ROW('DBX Sprint'!$A$7:$K$62),ROW('DBX Sprint'!$A$7:$K$62)),""),ROWS($AA$34:AA48)),COLUMNS('DBX Sprint'!$A$1:A12)),"")} | AB48: {=IFERROR(INDEX('DBX Sprint'!$A$7:$K$62, SMALL(IF((INDEX('DBX Sprint'!$A$7:$K$62, ,25)<(TODAY()))*(INDEX('DBX Sprint'!$A$7:$K$62, ,25)<>"Complete"),MATCH(ROW('DBX Sprint'!$A$7:$K$62),ROW('DBX Sprint'!$A$7:$K$62)),""),ROWS($AB$34:AB48)),COLUMNS('DBX Sprint'!$A$1:A12)),"")} | AC48: {=IFERROR(INDEX('DBX Sprint'!$A$7:$K$62, SMALL(IF((INDEX('DBX Sprint'!$A$7:$K$62, ,25)<=(TODAY()+1))*(INDEX('DBX Sprint'!$A$7:$K$62, ,25)>=TODAY()),MATCH(ROW('DBX Sprint'!$A$7:$K$62),ROW('DBX Sprint'!$A$7:$K$62)),""),ROWS($AC$34:AC48)),COLUMNS('DBX Sprint'!$A$1:A12)),"")} | AD48: {=IFERROR(INDEX('DBX Sprint'!$A$7:$K$62, SMALL(IF((INDEX('DBX Sprint'!$A$7:$K$62, ,25)<=(TODAY()+5))*(INDEX('DBX Sprint'!$A$7:$K$62, ,25)>(TODAY()+1)),MATCH(ROW('DBX Sprint'!$A$7:$K$62),ROW('DBX Sprint'!$A$7:$K$62)),""),ROWS($AD$34:AD48)),COLUMNS('DBX Sprint'!$A$1:A12)),"")} | AE48: {=IFERROR(INDEX('DBX Sprint'!$A$7:$K$62, SMALL(IF((INDEX('DBX Sprint'!$A$7:$K$62, ,25)<=(TODAY()+10))*(INDEX('DBX Sprint'!$A$7:$K$62, ,25)>(TODAY()+5)),MATCH(ROW('DBX Sprint'!$A$7:$K$62),ROW('DBX Sprint'!$A$7:$K$62)),""),ROWS($AE$34:AE48)),COLUMNS('DBX Sprint'!$A$1:A12)),"")} | AG48: {=IFERROR(INDEX('DBX Sprint'!$A$7:$K$62, SMALL(IF((INDEX('DBX Sprint'!$A$7:$K$62, ,29)=("Complete"))*(INDEX('DBX Sprint'!$A$7:$K$62, ,29)="Complete"),MATCH(ROW('DBX Sprint'!$A$7:$K$62),ROW('DBX Sprint'!$A$7:$K$62)),""),ROWS($AG$34:AG48)),COLUMNS('DBX Sprint'!$A$1:A12)),"")} | AH48: {=IFERROR(INDEX('DBX Sprint'!$A$7:$K$62, SMALL(IF((INDEX('DBX Sprint'!$A$7:$K$62, ,29)<(TODAY()))*(INDEX('DBX Sprint'!$A$7:$K$62, ,29)<>"Complete"),MATCH(ROW('DBX Sprint'!$A$7:$K$62),ROW('DBX Sprint'!$A$7:$K$62)),""),ROWS($AH$34:AH48)),COLUMNS('DBX Sprint'!$A$1:A12)),"")} | AI48: {=IFERROR(INDEX('DBX Sprint'!$A$7:$K$62, SMALL(IF((INDEX('DBX Sprint'!$A$7:$K$62, ,29)<=(TODAY()+1))*(INDEX('DBX Sprint'!$A$7:$K$62, ,29)>=TODAY()),MATCH(ROW('DBX Sprint'!$A$7:$K$62),ROW('DBX Sprint'!$A$7:$K$62)),""),ROWS($AI$34:AI48)),COLUMNS('DBX Sprint'!$A$1:A12)),"")} | AJ48: {=IFERROR(INDEX('DBX Sprint'!$A$7:$K$62, SMALL(IF((INDEX('DBX Sprint'!$A$7:$K$62, ,29)<=(TODAY()+5))*(INDEX('DBX Sprint'!$A$7:$K$62, ,29)>(TODAY()+1)),MATCH(ROW('DBX Sprint'!$A$7:$K$62),ROW('DBX Sprint'!$A$7:$K$62)),""),ROWS($AJ$34:AJ48)),COLUMNS('DBX Sprint'!$A$1:A12)),"")} | AK48: {=IFERROR(INDEX('DBX Sprint'!$A$7:$K$62, SMALL(IF((INDEX('DBX Sprint'!$A$7:$K$62, ,29)<=(TODAY()+10))*(INDEX('DBX Sprint'!$A$7:$K$62, ,29)>(TODAY()+5)),MATCH(ROW('DBX Sprint'!$A$7:$K$62),ROW('DBX Sprint'!$A$7:$K$62)),""),ROWS($AK$34:AK48)),COLUMNS('DBX Sprint'!$A$1:A12)),"")} | AM48: {=IFERROR(INDEX('DBX Sprint'!$A$7:$K$62, SMALL(IF((INDEX('DBX Sprint'!$A$7:$K$62, ,32)=("Complete"))*(INDEX('DBX Sprint'!$A$7:$K$62, ,32)="Complete"),MATCH(ROW('DBX Sprint'!$A$7:$K$62),ROW('DBX Sprint'!$A$7:$K$62)),""),ROWS($AM$34:AM48)),COLUMNS('DBX Sprint'!$A$1:A12)),"")} | AN48: {=IFERROR(INDEX('DBX Sprint'!$A$7:$K$62, SMALL(IF((INDEX('DBX Sprint'!$A$7:$K$62, ,32)<(TODAY()))*(INDEX('DBX Sprint'!$A$7:$K$62, ,32)<>"Complete"),MATCH(ROW('DBX Sprint'!$A$7:$K$62),ROW('DBX Sprint'!$A$7:$K$62)),""),ROWS($AN$34:AN48)),COLUMNS('DBX Sprint'!$A$1:A12)),"")} | AO48: {=IFERROR(INDEX('DBX Sprint'!$A$7:$K$62, SMALL(IF((INDEX('DBX Sprint'!$A$7:$K$62, ,32)<=(TODAY()+1))*(INDEX('DBX Sprint'!$A$7:$K$62, ,32)>=TODAY()),MATCH(ROW('DBX Sprint'!$A$7:$K$62),ROW('DBX Sprint'!$A$7:$K$62)),""),ROWS($AO$34:AO48)),COLUMNS('DBX Sprint'!$A$1:A12)),"")} | AP48: {=IFERROR(INDEX('DBX Sprint'!$A$7:$K$62, SMALL(IF((INDEX('DBX Sprint'!$A$7:$K$62, ,32)<=(TODAY()+5))*(INDEX('DBX Sprint'!$A$7:$K$62, ,32)>(TODAY()+1)),MATCH(ROW('DBX Sprint'!$A$7:$K$62),ROW('DBX Sprint'!$A$7:$K$62)),""),ROWS($AP$34:AP48)),COLUMNS('DBX Sprint'!$A$1:A12)),"")} | AQ48: {=IFERROR(INDEX('DBX Sprint'!$A$7:$K$62, SMALL(IF((INDEX('DBX Sprint'!$A$7:$K$62, ,32)<=(TODAY()+10))*(INDEX('DBX Sprint'!$A$7:$K$62, ,32)>(TODAY()+5)),MATCH(ROW('DBX Sprint'!$A$7:$K$62),ROW('DBX Sprint'!$A$7:$K$62)),""),ROWS($AQ$34:AQ48)),COLUMNS('DBX Sprint'!$A$1:A12)),"")}
C49: {=IFERROR(INDEX('DBX Sprint'!$A$7:$K$62, SMALL(IF((INDEX('DBX Sprint'!$A$7:$K$62, ,13)=("Complete"))*(INDEX('DBX Sprint'!$A$7:$K$62, ,13)="Complete"),MATCH(ROW('DBX Sprint'!$A$7:$K$62),ROW('DBX Sprint'!$A$7:$K$62)),""),ROWS(C$34:$C49)),COLUMNS('DBX Sprint'!$A$1:A12)),"")} | D49: {=IFERROR(INDEX('DBX Sprint'!$A$7:$K$62, SMALL(IF((INDEX('DBX Sprint'!$A$7:$K$62, ,13)<(TODAY()))*(INDEX('DBX Sprint'!$A$7:$K$62, ,13)<>"Complete"),MATCH(ROW('DBX Sprint'!$A$7:$K$62),ROW('DBX Sprint'!$A$7:$K$62)),""),ROWS(D$34:$D49)),COLUMNS('DBX Sprint'!$A$1:A12)),"")} | E49: {=IFERROR(INDEX('DBX Sprint'!$A$7:$K$62, SMALL(IF((INDEX('DBX Sprint'!$A$7:$K$62, ,13)<=(TODAY()+1))*(INDEX('DBX Sprint'!$A$7:$K$62, ,13)>=TODAY()),MATCH(ROW('DBX Sprint'!$A$7:$K$62),ROW('DBX Sprint'!$A$7:$K$62)),""),ROWS(E$34:$E49)),COLUMNS('DBX Sprint'!$A$1:A12)),"")} | F49: {=IFERROR(INDEX('DBX Sprint'!$A$7:$K$62, SMALL(IF((INDEX('DBX Sprint'!$A$7:$K$62, ,13)<=(TODAY()+5))*(INDEX('DBX Sprint'!$A$7:$K$62, ,13)>(TODAY()+1)),MATCH(ROW('DBX Sprint'!$A$7:$K$62),ROW('DBX Sprint'!$A$7:$K$62)),""),ROWS($F$34:F49)),COLUMNS('DBX Sprint'!$A$1:A12)),"")} | G49: {=IFERROR(INDEX('DBX Sprint'!$A$7:$K$62, SMALL(IF((INDEX('DBX Sprint'!$A$7:$K$62, ,13)<=(TODAY()+10))*(INDEX('DBX Sprint'!$A$7:$K$62, ,13)>(TODAY()+5)),MATCH(ROW('DBX Sprint'!$A$7:$K$62),ROW('DBX Sprint'!$A$7:$K$62)),""),ROWS($G$34:G49)),COLUMNS('DBX Sprint'!$A$1:A12)),"")} | I49: {=IFERROR(INDEX('DBX Sprint'!$A$7:$K$62, SMALL(IF((INDEX('DBX Sprint'!$A$7:$K$62, ,16)=("Complete"))*(INDEX('DBX Sprint'!$A$7:$K$62, ,16)="Complete"),MATCH(ROW('DBX Sprint'!$A$7:$K$62),ROW('DBX Sprint'!$A$7:$K$62)),""),ROWS($I$34:I49)),COLUMNS('DBX Sprint'!$A$1:A12)),"")} | J49: {=IFERROR(INDEX('DBX Sprint'!$A$7:$K$62, SMALL(IF((INDEX('DBX Sprint'!$A$7:$K$62, ,16)<(TODAY()))*(INDEX('DBX Sprint'!$A$7:$K$62, ,16)<>"Complete"),MATCH(ROW('DBX Sprint'!$A$7:$K$62),ROW('DBX Sprint'!$A$7:$K$62)),""),ROWS($J$34:J49)),COLUMNS('DBX Sprint'!$A$1:A12)),"")} | K49: {=IFERROR(INDEX('DBX Sprint'!$A$7:$K$62, SMALL(IF((INDEX('DBX Sprint'!$A$7:$K$62, ,16)<=(TODAY()+1))*(INDEX('DBX Sprint'!$A$7:$K$62, ,16)>=TODAY()),MATCH(ROW('DBX Sprint'!$A$7:$K$62),ROW('DBX Sprint'!$A$7:$K$62)),""),ROWS($K$34:K49)),COLUMNS('DBX Sprint'!$A$1:A12)),"")} | L49: {=IFERROR(INDEX('DBX Sprint'!$A$7:$K$62, SMALL(IF((INDEX('DBX Sprint'!$A$7:$K$62, ,16)<=(TODAY()+5))*(INDEX('DBX Sprint'!$A$7:$K$62, ,16)>(TODAY()+1)),MATCH(ROW('DBX Sprint'!$A$7:$K$62),ROW('DBX Sprint'!$A$7:$K$62)),""),ROWS($L$34:L49)),COLUMNS('DBX Sprint'!$A$1:A12)),"")} | M49: {=IFERROR(INDEX('DBX Sprint'!$A$7:$K$62, SMALL(IF((INDEX('DBX Sprint'!$A$7:$K$62, ,16)<=(TODAY()+10))*(INDEX('DBX Sprint'!$A$7:$K$62, ,16)>(TODAY()+5)),MATCH(ROW('DBX Sprint'!$A$7:$K$62),ROW('DBX Sprint'!$A$7:$K$62)),""),ROWS($M$34:M49)),COLUMNS('DBX Sprint'!$A$1:A12)),"")} | O49: {=IFERROR(INDEX('DBX Sprint'!$A$7:$K$62, SMALL(IF((INDEX('DBX Sprint'!$A$7:$K$62, ,19)=("Complete"))*(INDEX('DBX Sprint'!$A$7:$K$62, ,19)="Complete"),MATCH(ROW('DBX Sprint'!$A$7:$K$62),ROW('DBX Sprint'!$A$7:$K$62)),""),ROWS($O$34:O49)),COLUMNS('DBX Sprint'!$A$1:A12)),"")} | P49: {=IFERROR(INDEX('DBX Sprint'!$A$7:$K$62, SMALL(IF((INDEX('DBX Sprint'!$A$7:$K$62, ,19)<(TODAY()))*(INDEX('DBX Sprint'!$A$7:$K$62, ,19)<>"Complete"),MATCH(ROW('DBX Sprint'!$A$7:$K$62),ROW('DBX Sprint'!$A$7:$K$62)),""),ROWS($P$34:P49)),COLUMNS('DBX Sprint'!$A$1:A12)),"")} | Q49: {=IFERROR(INDEX('DBX Sprint'!$A$7:$K$62, SMALL(IF((INDEX('DBX Sprint'!$A$7:$K$62, ,19)<=(TODAY()+1))*(INDEX('DBX Sprint'!$A$7:$K$62, ,19)>=TODAY()),MATCH(ROW('DBX Sprint'!$A$7:$K$62),ROW('DBX Sprint'!$A$7:$K$62)),""),ROWS($Q$34:Q49)),COLUMNS('DBX Sprint'!$A$1:A12)),"")} | R49: {=IFERROR(INDEX('DBX Sprint'!$A$7:$K$62, SMALL(IF((INDEX('DBX Sprint'!$A$7:$K$62, ,19)<=(TODAY()+5))*(INDEX('DBX Sprint'!$A$7:$K$62, ,19)>(TODAY()+1)),MATCH(ROW('DBX Sprint'!$A$7:$K$62),ROW('DBX Sprint'!$A$7:$K$62)),""),ROWS($R$34:R49)),COLUMNS('DBX Sprint'!$A$1:A12)),"")} | S49: {=IFERROR(INDEX('DBX Sprint'!$A$7:$K$62, SMALL(IF((INDEX('DBX Sprint'!$A$7:$K$62, ,19)<=(TODAY()+10))*(INDEX('DBX Sprint'!$A$7:$K$62, ,19)>(TODAY()+5)),MATCH(ROW('DBX Sprint'!$A$7:$K$62),ROW('DBX Sprint'!$A$7:$K$62)),""),ROWS($S$34:S49)),COLUMNS('DBX Sprint'!$A$1:A12)),"")} | U49: {=IFERROR(INDEX('DBX Sprint'!$A$7:$K$62, SMALL(IF((INDEX('DBX Sprint'!$A$7:$K$62, ,22)=("Complete"))*(INDEX('DBX Sprint'!$A$7:$K$62, ,22)="Complete"),MATCH(ROW('DBX Sprint'!$A$7:$K$62),ROW('DBX Sprint'!$A$7:$K$62)),""),ROWS($U$34:U49)),COLUMNS('DBX Sprint'!$A$1:A12)),"")} | V49: {=IFERROR(INDEX('DBX Sprint'!$A$7:$K$62, SMALL(IF((INDEX('DBX Sprint'!$A$7:$K$62, ,22)<(TODAY()))*(INDEX('DBX Sprint'!$A$7:$K$62, ,22)<>"Complete"),MATCH(ROW('DBX Sprint'!$A$7:$K$62),ROW('DBX Sprint'!$A$7:$K$62)),""),ROWS($V$34:V49)),COLUMNS('DBX Sprint'!$A$1:A12)),"")} | W49: {=IFERROR(INDEX('DBX Sprint'!$A$7:$K$62, SMALL(IF((INDEX('DBX Sprint'!$A$7:$K$62, ,22)<=(TODAY()+1))*(INDEX('DBX Sprint'!$A$7:$K$62, ,22)>=TODAY()),MATCH(ROW('DBX Sprint'!$A$7:$K$62),ROW('DBX Sprint'!$A$7:$K$62)),""),ROWS($W$34:W49)),COLUMNS('DBX Sprint'!$A$1:A12)),"")} | X49: {=IFERROR(INDEX('DBX Sprint'!$A$7:$K$62, SMALL(IF((INDEX('DBX Sprint'!$A$7:$K$62, ,22)<=(TODAY()+5))*(INDEX('DBX Sprint'!$A$7:$K$62, ,22)>(TODAY()+1)),MATCH(ROW('DBX Sprint'!$A$7:$K$62),ROW('DBX Sprint'!$A$7:$K$62)),""),ROWS($X$34:X49)),COLUMNS('DBX Sprint'!$A$1:A12)),"")} | Y49: {=IFERROR(INDEX('DBX Sprint'!$A$7:$K$62, SMALL(IF((INDEX('DBX Sprint'!$A$7:$K$62, ,22)<=(TODAY()+10))*(INDEX('DBX Sprint'!$A$7:$K$62, ,22)>(TODAY()+5)),MATCH(ROW('DBX Sprint'!$A$7:$K$62),ROW('DBX Sprint'!$A$7:$K$62)),""),ROWS($Y$34:Y49)),COLUMNS('DBX Sprint'!$A$1:A12)),"")} | AA49: {=IFERROR(INDEX('DBX Sprint'!$A$7:$K$62, SMALL(IF((INDEX('DBX Sprint'!$A$7:$K$62, ,25)=("Complete"))*(INDEX('DBX Sprint'!$A$7:$K$62, ,25)="Complete"),MATCH(ROW('DBX Sprint'!$A$7:$K$62),ROW('DBX Sprint'!$A$7:$K$62)),""),ROWS($AA$34:AA49)),COLUMNS('DBX Sprint'!$A$1:A12)),"")} | AB49: {=IFERROR(INDEX('DBX Sprint'!$A$7:$K$62, SMALL(IF((INDEX('DBX Sprint'!$A$7:$K$62, ,25)<(TODAY()))*(INDEX('DBX Sprint'!$A$7:$K$62, ,25)<>"Complete"),MATCH(ROW('DBX Sprint'!$A$7:$K$62),ROW('DBX Sprint'!$A$7:$K$62)),""),ROWS($AB$34:AB49)),COLUMNS('DBX Sprint'!$A$1:A12)),"")} | AC49: {=IFERROR(INDEX('DBX Sprint'!$A$7:$K$62, SMALL(IF((INDEX('DBX Sprint'!$A$7:$K$62, ,25)<=(TODAY()+1))*(INDEX('DBX Sprint'!$A$7:$K$62, ,25)>=TODAY()),MATCH(ROW('DBX Sprint'!$A$7:$K$62),ROW('DBX Sprint'!$A$7:$K$62)),""),ROWS($AC$34:AC49)),COLUMNS('DBX Sprint'!$A$1:A12)),"")} | AD49: {=IFERROR(INDEX('DBX Sprint'!$A$7:$K$62, SMALL(IF((INDEX('DBX Sprint'!$A$7:$K$62, ,25)<=(TODAY()+5))*(INDEX('DBX Sprint'!$A$7:$K$62, ,25)>(TODAY()+1)),MATCH(ROW('DBX Sprint'!$A$7:$K$62),ROW('DBX Sprint'!$A$7:$K$62)),""),ROWS($AD$34:AD49)),COLUMNS('DBX Sprint'!$A$1:A12)),"")} | AE49: {=IFERROR(INDEX('DBX Sprint'!$A$7:$K$62, SMALL(IF((INDEX('DBX Sprint'!$A$7:$K$62, ,25)<=(TODAY()+10))*(INDEX('DBX Sprint'!$A$7:$K$62, ,25)>(TODAY()+5)),MATCH(ROW('DBX Sprint'!$A$7:$K$62),ROW('DBX Sprint'!$A$7:$K$62)),""),ROWS($AE$34:AE49)),COLUMNS('DBX Sprint'!$A$1:A12)),"")} | AG49: {=IFERROR(INDEX('DBX Sprint'!$A$7:$K$62, SMALL(IF((INDEX('DBX Sprint'!$A$7:$K$62, ,29)=("Complete"))*(INDEX('DBX Sprint'!$A$7:$K$62, ,29)="Complete"),MATCH(ROW('DBX Sprint'!$A$7:$K$62),ROW('DBX Sprint'!$A$7:$K$62)),""),ROWS($AG$34:AG49)),COLUMNS('DBX Sprint'!$A$1:A12)),"")} | AH49: {=IFERROR(INDEX('DBX Sprint'!$A$7:$K$62, SMALL(IF((INDEX('DBX Sprint'!$A$7:$K$62, ,29)<(TODAY()))*(INDEX('DBX Sprint'!$A$7:$K$62, ,29)<>"Complete"),MATCH(ROW('DBX Sprint'!$A$7:$K$62),ROW('DBX Sprint'!$A$7:$K$62)),""),ROWS($AH$34:AH49)),COLUMNS('DBX Sprint'!$A$1:A12)),"")} | AI49: {=IFERROR(INDEX('DBX Sprint'!$A$7:$K$62, SMALL(IF((INDEX('DBX Sprint'!$A$7:$K$62, ,29)<=(TODAY()+1))*(INDEX('DBX Sprint'!$A$7:$K$62, ,29)>=TODAY()),MATCH(ROW('DBX Sprint'!$A$7:$K$62),ROW('DBX Sprint'!$A$7:$K$62)),""),ROWS($AI$34:AI49)),COLUMNS('DBX Sprint'!$A$1:A12)),"")} | AJ49: {=IFERROR(INDEX('DBX Sprint'!$A$7:$K$62, SMALL(IF((INDEX('DBX Sprint'!$A$7:$K$62, ,29)<=(TODAY()+5))*(INDEX('DBX Sprint'!$A$7:$K$62, ,29)>(TODAY()+1)),MATCH(ROW('DBX Sprint'!$A$7:$K$62),ROW('DBX Sprint'!$A$7:$K$62)),""),ROWS($AJ$34:AJ49)),COLUMNS('DBX Sprint'!$A$1:A12)),"")} | AK49: {=IFERROR(INDEX('DBX Sprint'!$A$7:$K$62, SMALL(IF((INDEX('DBX Sprint'!$A$7:$K$62, ,29)<=(TODAY()+10))*(INDEX('DBX Sprint'!$A$7:$K$62, ,29)>(TODAY()+5)),MATCH(ROW('DBX Sprint'!$A$7:$K$62),ROW('DBX Sprint'!$A$7:$K$62)),""),ROWS($AK$34:AK49)),COLUMNS('DBX Sprint'!$A$1:A12)),"")} | AM49: {=IFERROR(INDEX('DBX Sprint'!$A$7:$K$62, SMALL(IF((INDEX('DBX Sprint'!$A$7:$K$62, ,32)=("Complete"))*(INDEX('DBX Sprint'!$A$7:$K$62, ,32)="Complete"),MATCH(ROW('DBX Sprint'!$A$7:$K$62),ROW('DBX Sprint'!$A$7:$K$62)),""),ROWS($AM$34:AM49)),COLUMNS('DBX Sprint'!$A$1:A12)),"")} | AN49: {=IFERROR(INDEX('DBX Sprint'!$A$7:$K$62, SMALL(IF((INDEX('DBX Sprint'!$A$7:$K$62, ,32)<(TODAY()))*(INDEX('DBX Sprint'!$A$7:$K$62, ,32)<>"Complete"),MATCH(ROW('DBX Sprint'!$A$7:$K$62),ROW('DBX Sprint'!$A$7:$K$62)),""),ROWS($AN$34:AN49)),COLUMNS('DBX Sprint'!$A$1:A12)),"")} | AO49: {=IFERROR(INDEX('DBX Sprint'!$A$7:$K$62, SMALL(IF((INDEX('DBX Sprint'!$A$7:$K$62, ,32)<=(TODAY()+1))*(INDEX('DBX Sprint'!$A$7:$K$62, ,32)>=TODAY()),MATCH(ROW('DBX Sprint'!$A$7:$K$62),ROW('DBX Sprint'!$A$7:$K$62)),""),ROWS($AO$34:AO49)),COLUMNS('DBX Sprint'!$A$1:A12)),"")} | AP49: {=IFERROR(INDEX('DBX Sprint'!$A$7:$K$62, SMALL(IF((INDEX('DBX Sprint'!$A$7:$K$62, ,32)<=(TODAY()+5))*(INDEX('DBX Sprint'!$A$7:$K$62, ,32)>(TODAY()+1)),MATCH(ROW('DBX Sprint'!$A$7:$K$62),ROW('DBX Sprint'!$A$7:$K$62)),""),ROWS($AP$34:AP49)),COLUMNS('DBX Sprint'!$A$1:A12)),"")} | AQ49: {=IFERROR(INDEX('DBX Sprint'!$A$7:$K$62, SMALL(IF((INDEX('DBX Sprint'!$A$7:$K$62, ,32)<=(TODAY()+10))*(INDEX('DBX Sprint'!$A$7:$K$62, ,32)>(TODAY()+5)),MATCH(ROW('DBX Sprint'!$A$7:$K$62),ROW('DBX Sprint'!$A$7:$K$62)),""),ROWS($AQ$34:AQ49)),COLUMNS('DBX Sprint'!$A$1:A12)),"")}
