Workbook
Name Custom: Table6[Custom]
Name Development: Table4[Development Category]
Name Effort: Table6[Custom]
Name NoDev: Table7[Product]
Name Product: Table7[Product]

Sheet Summary
A1: <Client> | B1: Readiness: | C1: =IFERROR((D1/SUM(D1:F1))*100,-1) -> -1 | D1: =SUM(D4:D11) -> #REF! | E1: =SUM(E4:E11) -> #REF! | F1: =SUM(F4:F11) -> #REF! | G1: =SUM(G4:G11) -> #REF!
A3: # | B3: Module | C3: Status | D3: 3 | E3: 2 | F3: 1 | G3: 0
A4: 1 | B4: RB User Management | C4: =IFERROR((D4/SUM(D4:F4))*100,-1) -> -1 | D4: =COUNTIFS('Retail Banking'!#REF!,"=" & $A4,'Retail Banking'!#REF!,">2") -> #REF! | E4: =COUNTIFS('Retail Banking'!#REF!,"=" & $A4,'Retail Banking'!#REF!,"=2") -> #REF! | F4: =COUNTIFS('Retail Banking'!#REF!,"=" & $A4,'Retail Banking'!#REF!,"=1") -> #REF! | G4: =COUNTIFS('Retail Banking'!#REF!,"=" & $A4,'Retail Banking'!#REF!,"=0") -> #REF!
A5: 2 | B5: RB Account Management | C5: =IFERROR((D5/SUM(D5:F5))*100,-1) -> -1 | D5: =COUNTIFS('Retail Banking'!#REF!,"=" & $A5,'Retail Banking'!#REF!,">2") -> #REF! | E5: =COUNTIFS('Retail Banking'!#REF!,"=" & $A5,'Retail Banking'!#REF!,"=2") -> #REF! | F5: =COUNTIFS('Retail Banking'!#REF!,"=" & $A5,'Retail Banking'!#REF!,"=1") -> #REF! | G5: =COUNTIFS('Retail Banking'!#REF!,"=" & $A5,'Retail Banking'!#REF!,"=0") -> #REF!
A6: 3 | B6: RB Money Management | C6: =IFERROR((D6/SUM(D6:F6))*100,-1) -> -1 | D6: =COUNTIFS('Retail Banking'!#REF!,"=" & $A6,'Retail Banking'!#REF!,">2") -> #REF! | E6: =COUNTIFS('Retail Banking'!#REF!,"=" & $A6,'Retail Banking'!#REF!,"=2") -> #REF! | F6: =COUNTIFS('Retail Banking'!#REF!,"=" & $A6,'Retail Banking'!#REF!,"=1") -> #REF! | G6: =COUNTIFS('Retail Banking'!#REF!,"=" & $A6,'Retail Banking'!#REF!,"=0") -> #REF!
A7: 4 | B7: RB New User Onboarding | C7: =IFERROR((D7/SUM(D7:F7))*100,-1) -> -1 | D7: =COUNTIFS('Retail Banking'!#REF!,"=" & $A7,'Retail Banking'!#REF!,">2") -> #REF! | E7: =COUNTIFS('Retail Banking'!#REF!,"=" & $A7,'Retail Banking'!#REF!,"=2") -> #REF! | F7: =COUNTIFS('Retail Banking'!#REF!,"=" & $A7,'Retail Banking'!#REF!,"=1") -> #REF! | G7: =COUNTIFS('Retail Banking'!#REF!,"=" & $A7,'Retail Banking'!#REF!,"=0") -> #REF!
A8: 5 | B8: RB Administration | C8: =IFERROR((D8/SUM(D8:F8))*100,-1) -> -1 | D8: =COUNTIFS('Retail Banking'!#REF!,"=" & $A8,'Retail Banking'!#REF!,">2") -> #REF! | E8: =COUNTIFS('Retail Banking'!#REF!,"=" & $A8,'Retail Banking'!#REF!,"=2") -> #REF! | F8: =COUNTIFS('Retail Banking'!#REF!,"=" & $A8,'Retail Banking'!#REF!,"=1") -> #REF! | G8: =COUNTIFS('Retail Banking'!#REF!,"=" & $A8,'Retail Banking'!#REF!,"=0") -> #REF!
A9: 9 | B9: RB Custom | C9: =IFERROR((D9/SUM(D9:F9))*100,-1) -> -1 | D9: =COUNTIFS('Retail Banking'!#REF!,"=" & $A9,'Retail Banking'!#REF!,">2") -> #REF! | E9: =COUNTIFS('Retail Banking'!#REF!,"=" & $A9,'Retail Banking'!#REF!,"=2") -> #REF! | F9: =COUNTIFS('Retail Banking'!#REF!,"=" & $A9,'Retail Banking'!#REF!,"=1") -> #REF! | G9: =COUNTIFS('Retail Banking'!#REF!,"=" & $A9,'Retail Banking'!#REF!,"=0") -> #REF!
A11: 21 | B11: BB User Management | C11: =IFERROR((D11/SUM(D11:F11))*100,-1) -> -1 | D11: =COUNTIFS('Business Banking'!$A$2:$A$200,"=" & $A11,'Business Banking'!#REF!,">2") -> #REF! | E11: =COUNTIFS('Business Banking'!$A$2:$A$200,"=" & $A11,'Business Banking'!#REF!,"=2") -> #REF! | F11: =COUNTIFS('Business Banking'!$A$2:$A$200,"=" & $A11,'Business Banking'!#REF!,"=1") -> #REF! | G11: =COUNTIFS('Business Banking'!$A$2:$A$200,"=" & $A11,'Business Banking'!#REF!,"=0") -> #REF!
A12: 22 | B12: BB Account Management | C12: =IFERROR((D12/SUM(D12:F12))*100,-1) -> -1 | D12: =COUNTIFS('Business Banking'!$A$2:$A$200,"=" & $A12,'Business Banking'!#REF!,">2") -> #REF! | E12: =COUNTIFS('Business Banking'!$A$2:$A$200,"=" & $A12,'Business Banking'!#REF!,"=2") -> #REF! | F12: =COUNTIFS('Business Banking'!$A$2:$A$200,"=" & $A12,'Business Banking'!#REF!,"=1") -> #REF! | G12: =COUNTIFS('Business Banking'!$A$2:$A$200,"=" & $A12,'Business Banking'!#REF!,"=0") -> #REF!
A13: 23 | B13: BB Money Management | C13: =IFERROR((D13/SUM(D13:F13))*100,-1) -> -1 | D13: =COUNTIFS('Business Banking'!$A$2:$A$200,"=" & $A13,'Business Banking'!#REF!,">2") -> #REF! | E13: =COUNTIFS('Business Banking'!$A$2:$A$200,"=" & $A13,'Business Banking'!#REF!,"=2") -> #REF! | F13: =COUNTIFS('Business Banking'!$A$2:$A$200,"=" & $A13,'Business Banking'!#REF!,"=1") -> #REF! | G13: =COUNTIFS('Business Banking'!$A$2:$A$200,"=" & $A13,'Business Banking'!#REF!,"=0") -> #REF!
A14: 24 | B14: BB New Organization Onboarding | C14: =IFERROR((D14/SUM(D14:F14))*100,-1) -> -1 | D14: =COUNTIFS('Business Banking'!$A$2:$A$200,"=" & $A14,'Business Banking'!#REF!,">2") -> #REF! | E14: =COUNTIFS('Business Banking'!$A$2:$A$200,"=" & $A14,'Business Banking'!#REF!,"=2") -> #REF! | F14: =COUNTIFS('Business Banking'!$A$2:$A$200,"=" & $A14,'Business Banking'!#REF!,"=1") -> #REF! | G14: =COUNTIFS('Business Banking'!$A$2:$A$200,"=" & $A14,'Business Banking'!#REF!,"=0") -> #REF!
A15: 25 | B15: BB User Management | C15: =IFERROR((D15/SUM(D15:F15))*100,-1) -> -1 | D15: =COUNTIFS('Business Banking'!$A$2:$A$200,"=" & $A15,'Business Banking'!#REF!,">2") -> #REF! | E15: =COUNTIFS('Business Banking'!$A$2:$A$200,"=" & $A15,'Business Banking'!#REF!,"=2") -> #REF! | F15: =COUNTIFS('Business Banking'!$A$2:$A$200,"=" & $A15,'Business Banking'!#REF!,"=1") -> #REF! | G15: =COUNTIFS('Business Banking'!$A$2:$A$200,"=" & $A15,'Business Banking'!#REF!,"=0") -> #REF!
A16: 29 | B16: BB Custom | C16: =IFERROR((D16/SUM(D16:F16))*100,-1) -> -1 | D16: =COUNTIFS('Business Banking'!$A$2:$A$216,"=" & $A16,'Business Banking'!#REF!,">2") -> #REF! | E16: =COUNTIFS('Business Banking'!$A$2:$A$216,"=" & $A16,'Business Banking'!#REF!,"=2") -> #REF! | F16: =COUNTIFS('Business Banking'!$A$2:$A$216,"=" & $A16,'Business Banking'!#REF!,"=1") -> #REF! | G16: =COUNTIFS('Business Banking'!$A$2:$A$216,"=" & $A16,'Business Banking'!#REF!,"=0") -> #REF!
A18: 31 | B18: C360 User Management | C18: =IFERROR((D18/SUM(D18:F18))*100,-1) -> -1 | D18: =COUNTIFS('Customer 360'!$A$2:$A$230,"=" & $A18,'Customer 360'!$G$2:$G$230,">2") -> 0 | E18: =COUNTIFS('Customer 360'!$A$2:$A$230,"=" & $A18,'Customer 360'!$G$2:$G$230,"=2") -> 0 | F18: =COUNTIFS('Customer 360'!$A$2:$A$230,"=" & $A18,'Customer 360'!$G$2:$G$230,"=1") -> 0 | G18: =COUNTIFS('Customer 360'!$A$2:$A$230,"=" & $A18,'Customer 360'!$G$2:$G$230,"=0") -> 21
A19: 32 | B19: C360 Account Management | C19: =IFERROR((D19/SUM(D19:F19))*100,-1) -> -1 | D19: =COUNTIFS('Customer 360'!$A$2:$A$230,"=" & $A19,'Customer 360'!$G$2:$G$230,">2") -> 0 | E19: =COUNTIFS('Customer 360'!$A$2:$A$230,"=" & $A19,'Customer 360'!$G$2:$G$230,"=2") -> 0 | F19: =COUNTIFS('Customer 360'!$A$2:$A$230,"=" & $A19,'Customer 360'!$G$2:$G$230,"=1") -> 0 | G19: =COUNTIFS('Customer 360'!$A$2:$A$230,"=" & $A19,'Customer 360'!$G$2:$G$230,"=0") -> 6
A20: 35 | B20: C360 User Management | C20: =IFERROR((D20/SUM(D20:F20))*100,-1) -> -1 | D20: =COUNTIFS('Customer 360'!$A$2:$A$230,"=" & $A20,'Customer 360'!$G$2:$G$230,">2") -> 0 | E20: =COUNTIFS('Customer 360'!$A$2:$A$230,"=" & $A20,'Customer 360'!$G$2:$G$230,"=2") -> 0 | F20: =COUNTIFS('Customer 360'!$A$2:$A$230,"=" & $A20,'Customer 360'!$G$2:$G$230,"=1") -> 0 | G20: =COUNTIFS('Customer 360'!$A$2:$A$230,"=" & $A20,'Customer 360'!$G$2:$G$230,"=0") -> 28
A21: 39 | B21: C360 Custom | C21: =IFERROR((D21/SUM(D21:F21))*100,-1) -> -1 | D21: =COUNTIFS('Customer 360'!$A$2:$A$230,"=" & $A21,'Customer 360'!$G$2:$G$230,">2") -> 0 | E21: =COUNTIFS('Customer 360'!$A$2:$A$230,"=" & $A21,'Customer 360'!$G$2:$G$230,"=2") -> 0 | F21: =COUNTIFS('Customer 360'!$A$2:$A$230,"=" & $A21,'Customer 360'!$G$2:$G$230,"=1") -> 0 | G21: =COUNTIFS('Customer 360'!$A$2:$A$230,"=" & $A21,'Customer 360'!$G$2:$G$230,"=0") -> 1

Sheet Kony RB - Services Detail
B2: Kony RB + Custom Enhancements Integration Services Parameters:
B3: Requirement Category | C3: Integration Service | D3: Input / Output | E3: Parameter | F3: Description
B4: Product | C4: getAccountCashFlowDetails | D4: Inputs | E4: - | F4: -
B5: Product | C5: getAccountCashFlowDetails | D5: Outputs | E5: AccountCashFlow | F5: Cash flow array with one or more record
B6: Product | C6: getAccountCashFlowDetails | D6: Outputs | E6: month | F6: Month. For example, Jan, Feb, Mar
B7: Product | C7: getAccountCashFlowDetails | D7: Outputs | E7: monthCash | F7: Amount spent for that month
B8: Product | C8: getAccountCashFlowDetails | D8: Outputs | E8: monthCredit | F8: Credit amount for that month
B9: Product | C9: getAccountCashFlowDetails | D9: Outputs | E9: totalCash | F9: Total cash
B10: Product | C10: getAccountCashFlowDetails | D10: Outputs | E10: totalCreditDebt | F10: Total credit debt
B11: Product | C11: getAccounts | D11: Inputs | E11: accountID | F11: It is an optional URL input parameter. If it is not added, then service should return all the accounts of the user
B12: Product | C12: getAccounts | D12: Inputs | E12: deviceID | F12: Device ID
B13: Product | C13: getAccounts | D13: Inputs | E13: User name | F13: User name
B14: Product | C14: getAccounts | D14: Outputs | E14: ccounts | F14: Array of accounts related to the logged in user
... B369: Product | C369: getCheckOrders | D369: Outputs | E369: zipcode | F369: Delivery address – Zip code
B370: Product | C370: getCheckOrders | D370: Outputs | E370: name
B371: Product | C371: createCheckOrder | D371: Inputs | E371: accountID | F371: ID of the account
B372: Product | C372: createCheckOrder | D372: Inputs | E372: leafCount | F372: Leaf count of the Check Book.
B373: Product | C373: createCheckOrder | D373: Inputs | E373: country | F373: Reason that is entered by the customer while performing the action
B374: Product | C374: createCheckOrder | D374: Inputs | E374: name | F374: Name of the delivery address
B375: Product | C375: createCheckOrder | D375: Inputs | E375: postboxNumber | F375: Post box number of the delivery address
B376: Product | C376: createCheckOrder | D376: Inputs | E376: state | F376: State name of the delivery address
B377: Product | C377: createCheckOrder | D377: Inputs | E377: zipcode | F377: Zip code of the delivery address
B378: Product | C378: createCheckOrder | D378: Outputs | E378: checkOrderID
B379: Product | C379: createCheckOrder | D379: Outputs | E379: Check order ID
B380: Product | C380: registerDevice | D380: Inputs | E380: deviceId | F380: Device ID
B381: Product | C381: registerDevice | D381: Outputs | E381: deviceId | F381: Device ID
B382: Product | C382: deviceRegistrationStatus | D382: Inputs | E382: deviceId | F382: Device ID
B383: Product | C383: deviceRegistrationStatus | D383: Outputs | E383: deviceId | F383: Device ID
B384: Product | C384: deRegisterDevice | D384: Inputs | E384: deviceId | F384: Device ID
B385: Product | C385: deRegisterDevice | D385: Outputs | E385: - | F385: -
B386: Product | C386: createUser | D386: Inputs | E386: accountNumber | F386: Account number that is entered by the user on the screen
B387: Product | C387: createUser | D387: Inputs | E387: accountType | F387: Type of account selected by the user. For example, Savings, Checking, Credit Card etc.
B388: Product | C388: createUser | D388: Inputs | E388: dateOfBirth | F388: Date of the birth entered by the user
B389: Product | C389: createUser | D389: Inputs | E389: email | F389: Email address entered by the user
B390: Product | C390: createUser | D390: Inputs | E390: password | F390: Password entered by the user
B391: Product | C391: createUser | D391: Inputs | E391: phone | F391: Phone number entered by the user
... B495: Product | C495: getUserDetails | D495: Inputs | E495: password | F495: New password selected by the user
B496: Product | C496: getUserDetails | D496: Outputs | E496: User
B497: Product | C497: getUserDetails | D497: Outputs | E497: dateOfBirth | F497: Date of birth of the user
B498: Product | C498: getUserDetails | D498: Outputs | E498: ssn | F498: SSN of the user
B499: Product | C499: getUserDetails | D499: Outputs | E499: userName | F499: Username of the user
B500: Product | C500: getUserDetails | D500: Outputs | E500: email | F500: Email of the user
B501: Product | C501: getUserDetails | D501: Outputs | E501: phone | F501: Phone number of the user
B502: Product | C502: getUserDetails | D502: Outputs | E502: secondaryemail | F502: Secondary email of the user
B503: Product | C503: getUserDetails | D503: Outputs | E503: secondaryphone | F503: Secondary phone number of the user
B504: Product | C504: getUserDetails | D504: Outputs | E504: default_account_deposit | F504: Default account used for deposit transactions
B505: Product | C505: getUserDetails | D505: Outputs | E505: default_account_payments | F505: Default account used for payments
B506: Product | C506: getUserDetails | D506: Outputs | E506: default_account_transfers | F506: Default account used for transfers
B507: Product | C507: getUserDetails | D507: Outputs | E507: default_account_cardless | F507: Default account used for cardless cash withdrawl
B508: Product | C508: getUserDetails | D508: Outputs | E508: lastlogintime | F508: Last log on time of the user in mobile banking
... B798: Product | C798: getLocationAddress(GoogleAPI) | D798: Outputs | E798: status | F798: service response status
B799: Product | C799: getAddressSuggestions(GoogleAPI) | D799: Inputs | E799: query
B800: Product | C800: getAddressSuggestions(GoogleAPI) | D800: Inputs | E800: currLatitude | F800: Current latitude of the user
B801: Product | C801: getAddressSuggestions(GoogleAPI) | D801: Inputs | E801: currLongitude | F801: Current longitude of the user
B802: Product | C802: getAddressSuggestions(GoogleAPI) | D802: Outputs | E802: Locations | F802: List of locations
B803: Product | C803: getAddressSuggestions(GoogleAPI) | D803: Outputs | E803: formattedAddress | F803: complete address of an searched location provided by googleAPI
B804: Product | C804: getAds | D804: Inputs | E804: - | F804: -
B805: Product | C805: getAds | D805: Outputs | E805: Ads | F805: List of advertisements.
B806: Product | C806: getAds | D806: Outputs | E806: action1 | F806: Interactive action for advertisement Image.
B807: Product | C807: getAds | D807: Outputs | E807: action2 | F807: Interactive action for button.
B808: Product | C808: getAds | D808: Outputs | E808: id | F808: Unique Id for the advertisement.
B809: Product | C809: getAds | D809: Outputs | E809: title | F809: Text to be displayed on Interactive button.
B810: Product | C810: getAds | D810: Outputs | E810: adType | F810: Describes type of the advertisement (Infeed and Non-Infeed).
B811: Product | C811: getAds | D811: Outputs | E811: imageURL | F811: URL to download the image for an advertisement.
... B813: Product | C813: getAds | D813: Outputs | E813: imageURL2 | F813: URL to download the image for only Infeed-banner advertisement

Sheet Retail Banking
A1: Category # | B1: Module | C1: Sub-Module | D1: API | E1: Documentation Link * | F1: Description | G1: System of Record | H1: Readiness | I1: NOTES | J1: Standard/Add-on | K1: Mobile | L1: Tablet
A2: 1 | B2: User Management | C2: Login | D2: checkUserEnrolled | E2: https://konydocs.atlassian.net/wiki/spaces/ARBD425/pages/1080820602/checkUserEnrolled+Java+Integration+Service | F2: The API checks whether the user is enrolled or not. | G2: DBX | H2: 0 | J2: Standard
A3: 1 | B3: User Management | C3: Login | D3: createDBXCustomer | E3: https://konydocs.atlassian.net/wiki/spaces/ARBD424/pages/1031440205/createDbxCustomer+Java+Integration+Service | F3: The API enrolls a new user to mobile banking. | G3: DBX | H3: 4 | J3: Add-on
A4: 1 | B4: User Management | C4: Login | D4: createUserSecurityQuestions | E4: https://konydocs.atlassian.net/wiki/spaces/ARBD424/pages/1031439228/createUserSecurityQuestions+Java+Integration+Service | F4: Sets up security questions for the users while enrolling to mobile/online banking. | G4: N/A | H4: 0 | J4: Standard
A5: 1 | B5: User Management | C5: Login | D5: deletePin | E5: https://konydocs.atlassian.net/wiki/spaces/ARBD424/pages/1031439317/deletePin+Java+Integration+Service | F5: The API deletes the PIN defined in case of PIN-based login. | G5: N/A | J5: Standard
A6: 1 | B6: User Management | C6: Login | D6: deRegisterDevice | E6: https://konydocs.atlassian.net/wiki/spaces/ARBD425/pages/1080820137/deRegisterDevice+Java+Integration+Service | F6: The API de-registers a device for a user. | G6: DBX | H6: 3 | J6: Standard
A7: 1 | B7: User Management | C7: Login | D7: deviceRegistrationStatus | E7: https://konydocs.atlassian.net/wiki/spaces/ARBD425/pages/1080820190/deviceRegistrationStatus+Java+Integration+Service | F7: The API identifies the registration status of the device for a user. | G7: DBX | H7: 0 | J7: Standard
A8: 1 | B8: User Management | C8: Login | D8: fetchUserName | E8: https://konydocs.atlassian.net/wiki/spaces/ARBD425/pages/1080821454/fetchUserName+Java+Integration+Service | F8: The API fetches the username. | G8: DBX | H8: 0 | J8: Standard
A9: 1 | B9: User Management | C9: Login | D9: getApplicationProp | E9: https://konydocs.atlassian.net/wiki/spaces/ARBD425/pages/1080821095/getApplicationProp+Java+Integration+Service | F9: The API retrieves the default application parameters, such as currency code, banner URL and more.(System Config params C360) | G9: DBX | H9: 3 | J9: Standard
A10: 1 | B10: User Management | C10: Login | D10: getCustomerContact | E10: https://konydocs.atlassian.net/wiki/spaces/ARBD425/pages/1080820546/getCustomerContact+Java+Integration+Service | F10: The API retrieves user email, and contact numbers. | G10: DBX | H10: 3 | J10: Standard
A11: 1 | B11: User Management | C11: Login | D11: getPasswordPolicies | E11: https://konydocs.atlassian.net/wiki/spaces/ARBD425/pages/1080820544/getPasswordPolicies+Java+Integration+Service | F11: The API gets the username and password policies. | G11: DBX | H11: 0 | J11: Standard
A12: 1 | B12: User Management | C12: Login | D12: getSecurityQuestions | E12: https://konydocs.atlassian.net/wiki/spaces/ARBD424/pages/1031440182/getSecurityQuestions+Java+Integration+Service | F12: The API retrieves the list of security questions after the user logs in. | G12: N/A | H12: 0 | J12: Standard
A13: 1 | B13: User Management | C13: Login | D13: getUserSecurityQuestions | E13: https://konydocs.atlassian.net/wiki/spaces/ARBD425/pages/1080821089/getUserSecurityQuestions+Java+Integration+Service | F13: Retrieves the list of security questions before the user logs in. | G13: N/A | H13: 0 | J13: Standard
A14: 1 | B14: User Management | C14: Login | D14: logout | E14: https://konydocs.atlassian.net/wiki/spaces/ARBD425/pages/1080821536/logout+Java+Integration+Service | F14: The API is called to logout from the application. | G14: DBX | H14: 0 | J14: Standard
A15: 1 | B15: User Management | C15: Login | D15: registerDevice | E15: https://konydocs.atlassian.net/wiki/spaces/ARBD425/pages/1080820130/registerDevice+Java+Integration+Service | F15: The API registers a device for a user. | G15: DBX | H15: 3 | J15: Standard
A16: 1 | B16: User Management | C16: Login | D16: resetUserPassword | E16: https://konydocs.atlassian.net/wiki/spaces/ARBD425/pages/1080820596/resetUserPassword+Java+Integration+Service | F16: The API resets the password of a user. | G16: DBX | H16: 0 | J16: Standard
A17: 1 | B17: User Management | C17: Login | D17: verifyCVV | E17: https://konydocs.atlassian.net/wiki/spaces/ARBD425/pages/1080820843/verifyCVV+Java+Integration+Service | F17: The API verifies the CVV. | G17: DBX | H17: 0 | J17: Standard
A18: 1 | B18: User Management | C18: Login | D18: verifyOTP | E18: https://konydocs.atlassian.net/wiki/spaces/ARBD425/pages/1080821494/verifyOTP+Java+Integration+Service | F18: The API verifies the OTP used during enrollment(with SSN, DOB, LastName and OTP) | H18: 0 | J18: Standard
A19: 1 | B19: User Management | C19: Login | D19: verifyPin | E19: https://konydocs.atlassian.net/wiki/spaces/ARBD424/pages/1031438375/verifyPin+Java+Integration+Service | F19: The API verifies the PIN provided by the user. | G19: N/A | H19: 0 | J19: Standard
A20: 1 | B20: User Management | C20: Login | D20: verifyUserSecurityQuestions | E20: https://konydocs.atlassian.net/wiki/spaces/ARBD425/pages/1080821093/verifyUserSecurityQuestions+Java+Integration+Service | F20: Validates the security questions answered by a user. | G20: N/A | H20: 0 | J20: Standard
A21: 1 | B21: User Management | C21: Login | D21: dbxUserLogin | E21: https://konydocs.atlassian.net/wiki/spaces/ARBD425/pages/1080821850/dbxUserLogin+Orchestration+Service | F21: The API logs in the user. | G21: DBX | H21: 0 | J21: Standard
A22: 1 | B22: User Management | C22: Login | D22: dbxVerifyOTP | E22: https://konydocs.atlassian.net/wiki/spaces/ARBD425/pages/1080821951/dbxVerifyOTP+Java+Integration+Service | F22: The API verifies the OTP used during login and Security checks inside the app | H22: 3 | J22: Standard
A23: 1 | B23: User Management | C23: Login | D23: resetDbxUserPassword | E23: https://konydocs.atlassian.net/wiki/spaces/ARBD425/pages/1080820799/resetDbxUserPassword+Java+Integration+Service | F23: The API resets the password. | G23: DBX | H23: 0 | J23: Standard
A24: 1 | B24: User Management | C24: Login | D24: sendDbxResetPasswordEmail | E24: https://konydocs.atlassian.net/wiki/spaces/ARBD425/pages/1080820562/updateDbxUserStatus+Java+Integration+Service | F24: Sends an email with a link to reset the password | G24: DBX | H24: 0 | J24: Standard
A25: 1 | B25: User Management | C25: Login | D25: updateDbxUserStatus | E25: https://konydocs.atlassian.net/wiki/spaces/ARBD425/pages/1080820562/updateDbxUserStatus+Java+Integration+Service | F25: Toggles the status of a user between 'Active' and 'Suspended' | G25: DBX | J25: Standard
A26: 1 | B26: User Management | C26: Login | D26: getDbxUserStatus | E26: https://konydocs.atlassian.net/wiki/spaces/ARBD425/pages/1080821932/getDbxUserStatus+Java+Integration+Service | F26: Retrieves the status of the user in DBX | G26: DBX | H26: 0 | J26: Standard
A27: 1 | B27: User Management | C27: Login | D27: smsOTP | E27: https://konydocs.atlassian.net/wiki/spaces/ARBD425/pages/1080821953/smsOTP+Java+Integration+Service | F27: Generates an OTP and sends an SMS to the provided phone number. An optional e-Mail can also be provided if the user wants to receive the OTP through this channel. | H27: 2 | J27: Standard
A28: 1 | B28: User Management | C28: Login | D28: dbxRequestOTP | E28: https://konydocs.atlassian.net/wiki/spaces/ARBD425/pages/1080820835/dbxRequestOTP+Java+Integration+Service | F28: The API requests an OTP. | H28: 2
A29: 1 | B29: User Management | C29: Login | D29: getCustomerCommunication | E29: https://konydocs.atlassian.net/wiki/spaces/ARBD425/pages/1080821006/getCustomerCommunication+Java+Integration+Service | F29: Retrieves the communication details for the specified user | G29: DBX | H29: 3 | J29: Standard
A30: 1 | B30: User Management | C30: Login | D30: getUserNameRulesAndPolicy | E30: https://konydocs.atlassian.net/wiki/spaces/ARBD425/pages/1080821036/getUserNameRulesAndPolicy+Java+Integration+Service | F30: Retrieves the policies for user name in DBX | G30: DBX | H30: 0 | J30: Standard
A31: 1 | B31: User Management | C31: Login | D31: getPasswordRulesAndPolicy | E31: https://konydocs.atlassian.net/wiki/spaces/ARBD425/pages/1080820305/getPasswordRulesAndPolicy+Java+Integration+Service | F31: Retrieves the policies for user name in DBXRetrieves the policies for maintaining a password in DBX | G31: DBX | H31: 0 | J31: Standard
A32: 1 | B32: User Management | C32: Login | D32: getUserNameAndPasswordRulesAndPolicies | E32: https://konydocs.atlassian.net/wiki/spaces/ARBD425/pages/1080821007/getUserNameAndPasswordRulesAndPolicies+Java+Integration+Service | F32: Retrieves the policies for maintaining a username and password in DBX | G32: DBX | H32: 0 | J32: Standard
A33: 1 | B33: User Management | C33: Login | D33: getAPIPasswordLockoutSettings | E33: https://konydocs.atlassian.net/wiki/spaces/ARBD425/pages/1080821009/getAPIPasswordLockoutSettings+Java+Integration+Service | F33: Retrieves the password lockout settings maintained in the DBX identity management system | G33: DBX | H33: 0 | J33: Standard
A34: 1 | B34: User Management | C34: Login | D34: getPasswordLockoutSettings | E34: https://konydocs.atlassian.net/wiki/spaces/ARBD425/pages/1080821015/getPasswordLockoutSettings+Java+Integration+Service | F34: Retrieves the password lockout settings maintained in the DBX identity management system | G34: DBX | H34: 0 | J34: Standard
A35: 1 | B35: User Management | C35: Login | D35: updateDbxUserPassword | E35: https://konydocs.atlassian.net/wiki/spaces/ARBD425/pages/1080820207/updateDbxUserPassword+Java+Integration+Service | F35: Updates the password of a user The password provided needs to satisfy the password policies configured in the Customer360 application. | G35: DBX | H35: 0 | J35: Standard
A36: 1 | B36: User Management | C36: Login | D36: requestEnrollOTP | E36: https://konydocs.atlassian.net/wiki/spaces/ARBD425/pages/1080821713/requestEnrollOTP+Java+Integration+Service | F36: The API initiates the MFA process or alernately fetches additional parameters required to initiate the MFA process. This service is invoked in pre-login flows like password reset and user enrollment. | H36: 0 | J36: Standard
A37: 1 | B37: User Management | C37: Login | D37: verifyOTPPreLogin | E37: https://konydocs.atlassian.net/wiki/spaces/ARBD425/pages/1080820317/verifyOTPPreLogin+Java+Integration+Service | F37: The API validates and verifies the OTP passed in from the application for the given pre-login scenario like reset password or user enrollment | H37: 2 | J37: standard
A38: 1 | B38: User Management | C38: Login | D38: requestLoginMFAOTP | E38: https://konydocs.atlassian.net/wiki/spaces/ARBD425/pages/1080821722/requestLoginMFAOTP+Java+Integration+Service | F38: The API initiates the MFA OTP process for the Login flow. | G38: DBX | H38: 2 | J38: standard
A39: 1 | B39: User Management | C39: Login | D39: verifyLoginMFAOTP | E39: https://konydocs.atlassian.net/wiki/spaces/ARBD425/pages/1080821725/verifyLoginMFAOTP+Java+Integration+Service | F39: The API initiates the MFA OTP process for the Login flow. The API validates and verifies the OTP passed in from the application for the given Login scenario. | G39: DBX | H39: 2 | J39: standard
A40: 1 | B40: User Management | C40: Login | D40: verifyLoginMFASecurityQuestions | E40: https://konydocs.atlassian.net/wiki/spaces/ARBD425/pages/1080820386/verifyLoginMFASecurityQuestions+Java+Integration+Service | F40: The API validates and verifies the user's answers to the specified security questions for the given Login scenario. | G40: DBX | H40: 3 | J40: standard
A41: 6 | B41: Notifications | C41: Preferences | D41: deleteNotification | E41: https://konydocs.atlassian.net/wiki/spaces/ARBD425/pages/1080821519/deleteNotification+Java+Integration+Service | F41: The API deletes the notification. The API is used only in Online Banking (OLB). | G41: DBX | H41: 0 | J41: Standard
A42: 6 | B42: Notifications | C42: Preferences | D42: getNotifications | E42: https://konydocs.atlassian.net/wiki/spaces/ARBD425/pages/1080821544/getNotifications+Java+Integration+Service | F42: The API retrieves all the notifications of the user. The API is used only in Online Banking (OLB). | G42: DBX | H42: 0 | J42: Standard
A43: 6 | B43: Notifications | C43: Preferences | D43: getUnreadNotifications | E43: https://konydocs.atlassian.net/wiki/spaces/ARBD425/pages/1080820331/getUnreadNotifications+Java+Integration+Service | F43: The API gets the count of unread notifications. The API is used only in Online Banking (OLB). | G43: DBX | H43: 0 | J43: Standard
A44: 6 | B44: Notifications | C44: Preferences | D44: getUserAccountAlerts | E44: https://konydocs.atlassian.net/wiki/spaces/ARBD425/pages/1080820022/getUserAccountAlerts+Java+Integration+Service | F44: The API retrieves all the account-related alerts of users. | G44: DBX | H44: 0 | J44: Standard
A45: 6 | B45: Notifications | C45: Preferences | D45: getUserAlerts | E45: https://konydocs.atlassian.net/wiki/spaces/ARBD425/pages/1080820046/getUserAlerts+Java+Integration+Service | F45: The API retrieves the user level alerts such as security alerts, deal alerts, and general alerts. | G45: DBX | H45: 4 | J45: Standard
A46: 6 | B46: Notifications | C46: Preferences | D46: updateReadCount | E46: https://konydocs.atlassian.net/wiki/spaces/ARBD425/pages/1080821484/updateReadCount+Java+Integration+Service | F46: The API updates the notifications as Read only. The API is used only in Online Banking (OLB). | G46: DBX | H46: 0 | J46: Standard
A47: 6 | B47: Notifications | C47: Preferences | D47: updateUserAccountAlert | E47: https://konydocs.atlassian.net/wiki/spaces/ARBD40/pages/739770769/updateUserAccountAlert | F47: The API updates various account-level alerts. For example, the value of the minimum balance threshold. | G47: DBX | H47: 0 | J47: Standard
A48: 6 | B48: Notifications | C48: Preferences | D48: updateUserAlert | E48: https://konydocs.atlassian.net/wiki/spaces/ARBD425/pages/1080819958/updateUserAlert+Java+Integration+Service | F48: The API updates user level alerts, for example, turn off the deals expiring alert. | G48: DBX | H48: 3 | J48: Standard
A49: 8 | B49: Profile | C49: Profile Management | D49: activateBillPaymentForUser | E49: https://konydocs.atlassian.net/wiki/spaces/ARBD425/pages/1080820629/activateBillPaymentForUser+Java+Integration+Service | F49: The API enables the Bill Payment functionality for the user. | H49: 0 | J49: Add-on
A50: 8 | B50: Profile | C50: Profile Management | D50: activateP2PForUser | E50: https://konydocs.atlassian.net/wiki/spaces/ARBD425/pages/1080821594/activateP2PForUser+Java+Integration+Service | F50: The API enables the P2P functionality for the user. | H50: 0 | J50: Standard
A51: 8 | B51: Profile | C51: Profile Management | D51: checkSecureAccessCode | E51: https://konydocs.atlassian.net/wiki/spaces/ARBD425/pages/1080821476/checkSecureAccessCode+Java+Integration+Service | F51: The API verifies the email, and phone enabled status for secure access. | H51: 0 | J51: Standard
A52: 8 | B52: Profile | C52: Profile Management | D52: checkSecurityQuestionStatus | E52: https://konydocs.atlassian.net/wiki/spaces/ARBD425/pages/1080821431/checkSecurityQuestionStatus+Java+Integration+Service | F52: The API verifies if the security questions exist for a user. | G52: NA | H52: 0
A53: 8 | B53: Profile | C53: Profile Management | D53: createAddress | E53: https://konydocs.atlassian.net/wiki/spaces/ARBD425/pages/1080821530/createAddress+Java+Integration+Service | F53: The API creates the user address. | G53: DBX | H53: 0 | J53: Standard
A54: 8 | B54: Profile | C54: Profile Management | D54: createPhone | E54: https://konydocs.atlassian.net/wiki/spaces/ARBD425/pages/1080820877/createPhone+Java+Integration+Service | F54: The API creates a new phone number. | G54: DBX | H54: 0 | J54: Standard
A55: 8 | B55: Profile | C55: Profile Management | D55: createUserFeedback | E55: https://konydocs.atlassian.net/wiki/spaces/ARBD425/pages/1080821526/createUserFeedback+Java+Integration+Service | F55: The API submits feedback received from the user. | G55: DBX | H55: 0
A56: 8 | B56: Profile | C56: Profile Management | D56: deleteAddress | E56: https://konydocs.atlassian.net/wiki/spaces/ARBD425/pages/1080820552/deleteAddress+Java+Integration+Service | F56: The API deletes the address. | G56: DBX | H56: 0 | J56: Standard
A57: 8 | B57: Profile | C57: Profile Management | D57: deletePhone | E57: https://konydocs.atlassian.net/wiki/spaces/ARBD425/pages/1080821426/deletePhone+Java+Integration+Service | F57: The API deletes the user phone number. | G57: DBX | H57: 0 | J57: Standard
A58: 8 | B58: Profile | C58: Profile Management | D58: getAllAddress | E58: https://konydocs.atlassian.net/wiki/spaces/ARBD425/pages/1080821621/getAllAddress+Java+Integration+Service | F58: The API fetches all user addresses. | G58: DBX | H58: 0 | J58: Standard
A59: 8 | B59: Profile | C59: Profile Management | D59: getAllPhones | E59: https://konydocs.atlassian.net/wiki/spaces/ARBD425/pages/1080821619/getAllPhones+Java+Integration+Service | F59: The API gets all user phones. | H59: 0 | J59: Standard
A60: 8 | B60: Profile | C60: Profile Management | D60: getNewBrowserCheck | E60: https://konydocs.atlassian.net/wiki/spaces/ARBD425/pages/1080821606/getNewBrowserCheck+Java+Integration+Service | F60: Verifies if the current user access is through a new browser. | G60: DBX | H60: 0 | J60: Standard
A61: 8 | B61: Profile | C61: Profile Management | D61: getUserDetails | E61: https://konydocs.atlassian.net/wiki/spaces/ARBD425/pages/1080819969/getUserDetails+Java+Integration+Service | F61: The API gets the profile details of the user. | G61: DBX | H61: 0 | J61: Standard
A62: 8 | B62: Profile | C62: Profile Management | D62: getUserStatus | E62: https://konydocs.atlassian.net/wiki/spaces/ARBD425/pages/1080820598/getUserStatus+Java+Integration+Service | F62: Retrieves the Enrollment and Lock status of a user. | G62: N/A | H62: 0 | J62: Standard
A63: 8 | B63: Profile | C63: Profile Management | D63: lockUnlockUser | E63: https://konydocs.atlassian.net/wiki/spaces/ARBD425/pages/1080820528/lockUnlockUser+Java+Integration+Service | F63: Issues a lock or unlock request for the user depending on the current lock state. | G63: DBX | H63: 0 | J63: Standard
A64: 8 | B64: Profile | C64: Profile Management | D64: registerP2P | E64: https://konydocs.atlassian.net/wiki/spaces/ARBD425/pages/1080821451/registerP2P+Java+Integration+Service | F64: Register a user for P2P functionality for specific third party vendors. | H64: 4 | J64: Add-on
A65: 8 | B65: Profile | C65: Profile Management | D65: registerP2PStatus | E65: https://konydocs.atlassian.net/wiki/spaces/ARBD425/pages/1080820594/registerP2PStatus+Java+Integration+Service | F65: Retrieves the P2P registration status for a user. | G65: DBX | J65: Standard
A66: 8 | B66: Profile | C66: Profile Management | D66: updateAddress | E66: https://konydocs.atlassian.net/wiki/spaces/ARBD425/pages/1080820881/updateAddress+Java+Integration+Service | F66: The API updates the address. | G66: DBX | H66: 0 | J66: Standard
A67: 8 | B67: Profile | C67: Profile Management | D67: updatePhone | E67: https://konydocs.atlassian.net/wiki/spaces/ARBD425/pages/1080820865/updatePhone+Java+Integration+Service | F67: The API updates the user phone number. | G67: DBX | H67: 0 | J67: Standard
A68: 8 | B68: Profile | C68: Profile Management | D68: updateSecureAccessCode | E68: https://konydocs.atlassian.net/wiki/spaces/ARBD425/pages/1080821483/updateSecureAccessCode+Java+Integration+Service | F68: The API updates the secure access code. | G68: DBX | H68: 0 | J68: Standard
A69: 8 | B69: Profile | C69: Profile Management | D69: updateUserAccountSettings | E69: https://konydocs.atlassian.net/wiki/spaces/ARBD424/pages/1031438732/updateUserAccountSettings+Java+Integration+Service | F69: The API updates the account settings of a user. | G69: DBX | H69: 0 | J69: Standard
A70: 8 | B70: Profile | C70: Profile Management | D70: updateUserDetails | E70: https://konydocs.atlassian.net/wiki/spaces/ARBD425/pages/1080820003/updateUserDetails+Java+Integration+Service | F70: The API updates personal information such as contact details, user name, and password. | G70: DBX | H70: 3 | J70: Standard
A71: 8 | B71: Profile | C71: Profile Management | D71: updateUserSecurityQuestions | E71: https://konydocs.atlassian.net/wiki/spaces/ARBD424/pages/1031438881/updateUserSecurityQuestions+Java+Integration+Service | F71: The API updates a user's security questions and answers. | G71: DBX | H71: 0 | J71: Standard
A72: 8 | B72: Profile | C72: Profile Management | D72: verifyExistingPassword | E72: https://konydocs.atlassian.net/wiki/spaces/ARBD425/pages/1080820847/verifyExistingPassword+Java+Integration+Service | F72: The API verifies the existing password of a user. | H72: 0 | J72: Standard
A73: 8 | B73: Profile | C73: Profile Management | D73: updateDbxUser | E73: https://konydocs.atlassian.net/wiki/spaces/ARBD425/pages/1080821934/updateDbxUser+Java+Integration+Service | F73: Updates personal information such as user name, date of birth and other PII fields. | H73: 0 | J73: Standard
A74: 8 | B74: Profile | C74: Profile Management | D74: lockUnlockCustomer | E74: https://konydocs.atlassian.net/wiki/spaces/ARBD425/pages/1080820271/lockUnlockCustomer+Java+Integration+Service | F74: Issues a lock or unlock request for the user depending on the current lock state. | G74: DBX | H74: 3 | J74: Standard
A75: 8 | B75: Profile | C75: Profile Management | D75: updateDbxCustomer | E75: https://konydocs.atlassian.net/wiki/spaces/ARBD425/pages/1080820119/updateDbxCustomer+Java+Integration+Service | F75: Updates personal information such as user name, date of birth and other PII fields. | G75: DBX | H75: 0 | J75: Standard
A76: 2 | B76: Account Management | C76: Account Services | D76: getAccountPendingTransactions | E76: https://konydocs.atlassian.net/wiki/spaces/ARBD425/pages/1080820518/getAccountPendingTransactions+Java+Integration+Service | F76: The API gets particular account pending transactions in Mobile Banking. | H76: 5 | J76: Add-on
A77: 2 | B77: Account Management | C77: Account Services | D77: getAccountPostedTransactions | E77: https://konydocs.atlassian.net/wiki/spaces/ARBD425/pages/1080820803/getAccountPostedTransactions+Java+Integration+Service | F77: The API gets particular account posted transactions in Mobile Banking. | H77: 5 | J77: Add-on
A78: 2 | B78: Account Management | C78: Account Services | D78: getAccounts | E78: https://konydocs.atlassian.net/wiki/spaces/ARBD425/pages/1080819735/getAccounts+Java+Integration+Service | F78: The API retrieves the list of all accounts for the account preview. | H78: 5 | J78: Add-on
A79: 2 | B79: Account Management | C79: Account Services | D79: getAccountsPostLogin | E79: https://konydocs.atlassian.net/wiki/spaces/ARBD425/pages/1080820887/getAccountsPostLogin+Java+Integration+Service | F79: The API retrieves the list of all accounts for the logged-in user in Online Banking application (OLB). | H79: 5 | J79: Add-on
A80: 2 | B80: Account Management | C80: Account Services | D80: getAccountTransactionsByType | E80: https://konydocs.atlassian.net/wiki/spaces/ARBD425/pages/1080820645/getAccountTransactionsByType+Java+Integration+Service | F80: Gets the list of transactions based on the account type. | H80: 2 | J80: Add-on
A81: 2 | B81: Account Management | C81: Account Services | D81: getAccountType | E81: https://konydocs.atlassian.net/wiki/spaces/ARBD425/pages/1080819907/getAccountType+Java+Integration+Service | F81: The API retrieves the list of all supported account types. | G81: DBX | H81: 0 | J81: Standard
A82: 2 | B82: Account Management | C82: Account Services | D82: getExternalTransactions | E82: https://konydocs.atlassian.net/wiki/spaces/ARBD425/pages/1080821612/getExternalTransactions+Java+Integration+Service | F82: This API retrieves the list of all external transactions for a given account. | H82: 0 | J82: Add-on
A83: 2 | B83: Account Management | C83: Account Services | D83: getFrequentOtherBankAccounts | E83: https://konydocs.atlassian.net/wiki/spaces/ARBD425/pages/1080820576/getFrequentOtherBankAccounts+Java+Integration+Service | F83: Retrieves the list of most frequently used external bank accounts for a given user. | H83: 0 | J83: Add-on
A84: 2 | B84: Account Management | C84: Account Services | D84: getPendingDepositTransactions | E84: https://konydocs.atlassian.net/wiki/spaces/ARBD425/pages/1080821545/getPendingDepositTransactions+Java+Integration+Service | F84: The API gets a list of pending deposit transactions. | H84: 3 | J84: Add-on
A85: 2 | B85: Account Management | C85: Account Services | D85: getPostedDepostTransactions | E85: https://konydocs.atlassian.net/wiki/spaces/ARBD425/pages/1080821610/getPostedDepositTransactions+Java+Integration+Service | F85: The API gets a list of posted deposit transactions. | H85: 3 | J85: Add-on
A86: 2 | B86: Account Management | C86: Account Services | D86: getRecentAccounts | E86: https://konydocs.atlassian.net/wiki/spaces/ARBD425/pages/1080820617/getRecentAccounts+Java+Integration+Service | F86: The API gets the list of recent accounts accessed for the user. | G86: DBX | H86: 0 | J86: Standard
A87: 2 | B87: Account Management | C87: Account Services | D87: getTransactions | E87: https://konydocs.atlassian.net/wiki/spaces/ARBD425/pages/1080819979/getTransactions+Java+Integration+Service | F87: The API retrieves the list of transactions, as well as details of each transaction. The API is consumed only in Online Banking (OLB). The API is used for the following: - Accounts: Recent transactions, search transactions. - Transfers & Payments: Recent and scheduled transfers and payments. | H87: 5 | J87: Add-on
A88: 2 | B88: Account Management | C88: Account Services | D88: getTransactionsDownloaded | E88: https://konydocs.atlassian.net/wiki/spaces/ARBD425/pages/1080820566/getTransactionsDownloaded+Java+Integration+Service | F88: Retrieves the list of transactions and their details formatted in an Excel or CSV file | G88: DBX | H88: 0
A89: 2 | B89: Account Management | C89: Account Services | D89: updateAccountName | E89: https://konydocs.atlassian.net/wiki/spaces/ARBD425/pages/1080819972/updateAccountName+Java+Integration+Service | F89: The API updates the account nickname. | G89: DBX | H89: 0
A90: 2 | B90: Account Management | C90: Account Services | D90: updateAccountPhone | E90: https://konydocs.atlassian.net/wiki/spaces/ARBD425/pages/1080820548/updateAccountPhone+Java+Integration+Service | F90: Updates the phone numbers of the specified accounts. | G90: DBX | H90: 0
A91: 2 | B91: Account Management | C91: Account Services | D91: updateAccountPreference | E91: https://konydocs.atlassian.net/wiki/spaces/ARBD425/pages/1080821566/updateAccountPreference+Java+Integration+Service | F91: Updates the account preference for the specified account. | G91: DBX | H91: 0
A92: 2 | B92: Account Management | C92: Account Services | D92: updateFavouriteStatus | E92: https://konydocs.atlassian.net/wiki/spaces/ARBD425/pages/1080820661/updateFavouriteStatus+Java+Integration+Service | F92: The API updates the favorite status of the account in Online Banking (OLB) application. | G92: DBX | H92: 0 | J92: Standard
A93: 2 | B93: Account Management | C93: PFM | D93: editPFMtransaction | E93: https://konydocs.atlassian.net/wiki/spaces/ARBD425/pages/1080820039/editPFMtransaction+Java+Integration+Service | F93: The API defines the category for an uncategorized expense. | G93: N/A | H93: 0
A94: 2 | B94: Account Management | C94: PFM | D94: getChartTransactions | E94: https://konydocs.atlassian.net/wiki/spaces/ARBD425/pages/1080821298/getChartTransactions+Java+Integration+Service | F94: The API retrieves the expenses for a specific category of a specific month. | G94: N/A | H94: 0
A95: 2 | B95: Account Management | C95: PFM | D95: getPFMBarGraph | E95: https://konydocs.atlassian.net/wiki/spaces/ARBD425/pages/1080821752/getPFMBarGraph+Java+Integration+Service | F95: The API retrieves the amount spent for each month. | G95: N/A | H95: 0
A96: 2 | B96: Account Management | C96: PFM | D96: getPFMBudgetSnapshot | E96: https://konydocs.atlassian.net/wiki/spaces/ARBD425/pages/1080820043/getPFMBudgetSnapshot+Java+Integration+Service | F96: The API displays the budget allocated, and the amount spent for each category, for the current month. | G96: N/A | H96: 0
A97: 2 | B97: Account Management | C97: PFM | D97: getPFMCategories | E97: https://konydocs.atlassian.net/wiki/spaces/ARBD425/pages/1080819959/getPFMCategories+Java+Integration+Service | F97: The API retrieves the list of various PFM categories used to manually categorize an expense. | G97: N/A | H97: 0
A98: 2 | B98: Account Management | C98: PFM | D98: getPFMPieChart | E98: https://konydocs.atlassian.net/wiki/spaces/ARBD425/pages/1080820035/getPFMPieChart+Java+Integration+Service | F98: The API displays the expenditure across various categories for a specific month. | G98: N/A | H98: 0
A99: 2 | B99: Account Management | C99: PFM | D99: getPFMTrasactions | E99: https://konydocs.atlassian.net/wiki/spaces/ARBD425/pages/1080821327/getPFMTransactions+Java+Integration+Service | F99: The API retrieves the list of all uncategorized transactions. | G99: N/A | H99: 0
A100: 2 | B100: Account Management | C100: PFM | D100: updateBulkPFMTransaction | E100: https://konydocs.atlassian.net/wiki/spaces/ARBD425/pages/1080821568/updateBulkPFMTransaction+Java+Integration+Service | F100: The API updates PFM transaction details for multiple users. | G100: N/A | H100: 0
...

Sheet Business Banking
K1: Channel
A2: Category # | B2: Module | C2: Sub-Module | D2: API | E2: Documentation Link | F2: Description | G2: System of Record | H2: Readiness | I2: Integration Notes | J2: Standard/Add-on | K2: Mobile | L2: Tablet | M2: Web | N2: NUO
A3: 21 | B3: User Management | C3: Business Users | D3: CreateOrganizationEmployee | E3: https://konydocs.atlassian.net/wiki/spaces/ARBD425/pages/1080821236/CreateOrganizationEmployee | F3: This API creates a new organization user. | G3: DBX | H3: 0
A4: 21 | B4: User Management | C4: Business Users | D4: getGroupEntitlements | E4: https://docs.kony.com/apps/integration/AdminConsoleServicesDocs/#/Groups_GetGroupEntitlements | F4: This API gets a list of transaction limit and daily limit for the organization. | G4: DBX | H4: 0
A5: 21 | B5: User Management | C5: Business Users | D5: getMembershipAccounts | E5: https://konydocs.atlassian.net/wiki/spaces/ARBD425/pages/1080821956/getMembershipAccounts+Java+Integration+Service | F5: Retrieves the list of accounts associated with an Org Id | G5: DBX | H5: 0
A6: 21 | B6: User Management | C6: Business Users | D6: getGroups | E6: https://docs.kony.com/apps/integration/AdminConsoleServicesDocs/#/Groups_GetGroupRecords | F6: This API gets a list of groups for the organization. | G6: DBX | H6: 0
A7: 21 | B7: User Management | C7: Business Users | D7: getDBXOrganizationDetails | E7: https://konydocs.atlassian.net/wiki/spaces/ARBD422/pages/1015743045/getDbxOrganizationDetails+Java+Integration+Service | F7: This API gets the organization details of the logged in user. | G7: DBX | H7: 0
A8: 21 | B8: User Management | C8: Business Users | D8: CreateOrganizationEmployee | E8: https://konydocs.atlassian.net/wiki/spaces/ARBD425/pages/1080821236/CreateOrganizationEmployee | F8: This API gets the list of all users under the organization. | G8: DBX | H8: 0
A9: 21 | B9: User Management | C9: Business Users | D9: getOrganizationAccounts | E9: https://konydocs.atlassian.net/wiki/spaces/ARBD425/pages/1080820789/getOrganizationAccounts+Java+Integration+Service | F9: This API gets a list of organization Accounts. | G9: DBX | H9: 0
A10: 21 | B10: User Management | C10: Business Users | D10: getOrgEmployeeDetails | E10: https://konydocs.atlassian.net/wiki/spaces/ARBD425/pages/1080820925/getOrgEmployeeDetails+Java+Integration+Service | F10: This API gets the user details. | G10: DBX | H10: 0
A11: 21 | B11: User Management | C11: Business Users | D11: getOrganizationName | E11: https://konydocs.atlassian.net/wiki/spaces/ARBD425/pages/1080821955/getOrganizationName | F11: This API returns the organization Name of the logged in user. | G11: DBX | H11: 0
A12: 21 | B12: User Management | C12: Business Users | D12: setOrgEmployeePassword | E12: https://konydocs.atlassian.net/wiki/spaces/ARBD425/pages/1080821865/SetOrgEmployeePassword | F12: This API helps the User set his / her password when he / she is created by the Business Owner. | G12: DBX | H12: 0
A13: 21 | B13: User Management | C13: Business Users | D13: OFACAndCIPChecks | E13: https://konydocs.atlassian.net/wiki/spaces/ARBD425/pages/1080820917/OFACAndCIPChecks+Java+Integration+Service | F13: This API checks OFAC and CIP for the SSN and DOB. | H13: 0
A14: 21 | B14: User Management | C14: Business Users | D14: ResendActivationLink | E14: https://konydocs.atlassian.net/wiki/spaces/ARBD425/pages/1080821274/ResendActivationLink+Java+Integration+Service | F14: This API resends the activation link. | G14: DBX | H14: 0
A15: 21 | B15: User Management | C15: Business Users | D15: updateDBXUserStatus | E15: https://konydocs.atlassian.net/wiki/spaces/ARBD425/pages/1080820562/updateDbxUserStatus+Java+Integration+Service | F15: This API activates/deactivates the user. | G15: DBX | H15: 0
A16: 21 | B16: User Management | C16: Business Users | D16: resendOrgEmployeeActivationLink | E16: https://konydocs.atlassian.net/wiki/spaces/ARBD425/pages/1080821224/ResendOrgEmployeeActivationLink | F16: This API will help the Business Owner / Admin to resend the activation email. | G16: DBX
A17: 21 | B17: User Management | C17: Business Users | D17: checkIfOrgMemberExists | E17: https://konydocs.atlassian.net/wiki/spaces/ARBD425/pages/1080822039/checkIfOrgMemberExists+Java+Integration+Service | F17: Verifies if a Membership Id exists in core banking system and whether it can be associated with a given user and organization. | G17: DBX | H17: 0
A18: 21 | B18: User Management | C18: Business Users | D18: unlinkOrgAccounts | E18: https://konydocs.atlassian.net/wiki/spaces/ARBD425/pages/1080822001/unLinkOrgAccounts+Java+Integration+Service | F18: Un-links the specified account(s) from an organization | G18: DBX | H18: 0
A19: 21 | B19: User Management | C19: Business Users | D19: validateTIN | E19: https://konydocs.atlassian.net/wiki/spaces/ARBD425/pages/1080822037/validateTin+Java+Integration+Service | F19: Verifies the existence of the Tax Id in DBX | G19: DBX | H19: 0
A20: 21 | B20: User Management | C20: Business Users | D20: verifyDbxUserName | E20: https://konydocs.atlassian.net/wiki/spaces/ARBD425/pages/1080820823/verifyDbxUserName+Java+Integration+Service | F20: This API checks the username availability. | G20: DBX | H20: 0
A21: 1 | B21: User Management | C21: Login | D21: checkUserEnrolled | E21: https://konydocs.atlassian.net/wiki/spaces/ARBD425/pages/1080820602/checkUserEnrolled+Java+Integration+Service | F21: The API checks whether the user is enrolled or not. | G21: DBX | H21: 0 | J21: Standard
A22: 1 | B22: User Management | C22: Login | D22: createDBXCustomer | E22: https://konydocs.atlassian.net/wiki/spaces/ARBD424/pages/1031440205/createDbxCustomer+Java+Integration+Service | F22: The API enrolls a new user to mobile banking. | G22: DBX | H22: 4 | J22: Add-on
A23: 1 | B23: User Management | C23: Login | D23: createUserSecurityQuestions | E23: https://konydocs.atlassian.net/wiki/spaces/ARBD424/pages/1031439228/createUserSecurityQuestions+Java+Integration+Service | F23: Sets up security questions for the users while enrolling to mobile/online banking. | G23: N/A | H23: 0 | J23: Standard
A24: 1 | B24: User Management | C24: Login | D24: deletePin | E24: https://konydocs.atlassian.net/wiki/spaces/ARBD424/pages/1031439317/deletePin+Java+Integration+Service | F24: The API deletes the PIN defined in case of PIN-based login. | G24: N/A | J24: Standard
A25: 1 | B25: User Management | C25: Login | D25: deRegisterDevice | E25: https://konydocs.atlassian.net/wiki/spaces/ARBD425/pages/1080820137/deRegisterDevice+Java+Integration+Service | F25: The API de-registers a device for a user. | G25: DBX | H25: 3 | J25: Standard
A26: 1 | B26: User Management | C26: Login | D26: deviceRegistrationStatus | E26: https://konydocs.atlassian.net/wiki/spaces/ARBD425/pages/1080820190/deviceRegistrationStatus+Java+Integration+Service | F26: The API identifies the registration status of the device for a user. | G26: DBX | H26: 0 | J26: Standard
A27: 1 | B27: User Management | C27: Login | D27: fetchUserName | E27: https://konydocs.atlassian.net/wiki/spaces/ARBD425/pages/1080821454/fetchUserName+Java+Integration+Service | F27: The API fetches the username. | G27: DBX | H27: 0 | J27: Standard
A28: 1 | B28: User Management | C28: Login | D28: getApplicationProp | E28: https://konydocs.atlassian.net/wiki/spaces/ARBD425/pages/1080821095/getApplicationProp+Java+Integration+Service | F28: The API retrieves the default application parameters, such as currency code, banner URL and more.(System Config params C360) | G28: DBX | H28: 3 | J28: Standard
A29: 1 | B29: User Management | C29: Login | D29: getCustomerContact | E29: https://konydocs.atlassian.net/wiki/spaces/ARBD425/pages/1080820546/getCustomerContact+Java+Integration+Service | F29: The API retrieves user email, and contact numbers. | G29: DBX | H29: 3 | J29: Standard
A30: 1 | B30: User Management | C30: Login | D30: getPasswordPolicies | E30: https://konydocs.atlassian.net/wiki/spaces/ARBD425/pages/1080820544/getPasswordPolicies+Java+Integration+Service | F30: The API gets the username and password policies. | G30: DBX | H30: 0 | J30: Standard
A31: 1 | B31: User Management | C31: Login | D31: getSecurityQuestions | E31: https://konydocs.atlassian.net/wiki/spaces/ARBD424/pages/1031440182/getSecurityQuestions+Java+Integration+Service | F31: The API retrieves the list of security questions after the user logs in. | G31: N/A | H31: 0 | J31: Standard
A32: 1 | B32: User Management | C32: Login | D32: getUserSecurityQuestions | E32: https://konydocs.atlassian.net/wiki/spaces/ARBD425/pages/1080821089/getUserSecurityQuestions+Java+Integration+Service | F32: Retrieves the list of security questions before the user logs in. | G32: N/A | H32: 0 | J32: Standard
A33: 1 | B33: User Management | C33: Login | D33: logout | E33: https://konydocs.atlassian.net/wiki/spaces/ARBD425/pages/1080821536/logout+Java+Integration+Service | F33: The API is called to logout from the application. | G33: DBX | H33: 0 | J33: Standard
A34: 1 | B34: User Management | C34: Login | D34: registerDevice | E34: https://konydocs.atlassian.net/wiki/spaces/ARBD425/pages/1080820130/registerDevice+Java+Integration+Service | F34: The API registers a device for a user. | G34: DBX | H34: 3 | J34: Standard
A35: 1 | B35: User Management | C35: Login | D35: resetUserPassword | E35: https://konydocs.atlassian.net/wiki/spaces/ARBD425/pages/1080820596/resetUserPassword+Java+Integration+Service | F35: The API resets the password of a user. | G35: DBX | H35: 0 | J35: Standard
A36: 1 | B36: User Management | C36: Login | D36: verifyCVV | E36: https://konydocs.atlassian.net/wiki/spaces/ARBD425/pages/1080820843/verifyCVV+Java+Integration+Service | F36: The API verifies the CVV. | G36: DBX | H36: 0 | J36: Standard
A37: 1 | B37: User Management | C37: Login | D37: verifyOTP | E37: https://konydocs.atlassian.net/wiki/spaces/ARBD425/pages/1080821494/verifyOTP+Java+Integration+Service | F37: The API verifies the OTP used during enrollment(with SSN, DOB, LastName and OTP) | H37: 0 | J37: Standard
A38: 1 | B38: User Management | C38: Login | D38: verifyPin | E38: https://konydocs.atlassian.net/wiki/spaces/ARBD424/pages/1031438375/verifyPin+Java+Integration+Service | F38: The API verifies the PIN provided by the user. | G38: N/A | H38: 0 | J38: Standard
A39: 1 | B39: User Management | C39: Login | D39: verifyUserSecurityQuestions | E39: https://konydocs.atlassian.net/wiki/spaces/ARBD425/pages/1080821093/verifyUserSecurityQuestions+Java+Integration+Service | F39: Validates the security questions answered by a user. | G39: N/A | H39: 0 | J39: Standard
A40: 1 | B40: User Management | C40: Login | D40: dbxUserLogin | E40: https://konydocs.atlassian.net/wiki/spaces/ARBD425/pages/1080821850/dbxUserLogin+Orchestration+Service | F40: The API logs in the user. | G40: DBX | H40: 0 | J40: Standard
A41: 1 | B41: User Management | C41: Login | D41: dbxVerifyOTP | E41: https://konydocs.atlassian.net/wiki/spaces/ARBD425/pages/1080821951/dbxVerifyOTP+Java+Integration+Service | F41: The API verifies the OTP used during login and Security checks inside the app | H41: 3 | J41: Standard
A42: 1 | B42: User Management | C42: Login | D42: resetDbxUserPassword | E42: https://konydocs.atlassian.net/wiki/spaces/ARBD425/pages/1080820799/resetDbxUserPassword+Java+Integration+Service | F42: The API resets the password. | G42: DBX | H42: 0 | J42: Standard
A43: 1 | B43: User Management | C43: Login | D43: sendDbxResetPasswordEmail | E43: https://konydocs.atlassian.net/wiki/spaces/ARBD425/pages/1080820562/updateDbxUserStatus+Java+Integration+Service | F43: Sends an email with a link to reset the password | G43: DBX | H43: 0 | J43: Standard
A44: 1 | B44: User Management | C44: Login | D44: updateDbxUserStatus | E44: https://konydocs.atlassian.net/wiki/spaces/ARBD425/pages/1080820562/updateDbxUserStatus+Java+Integration+Service | F44: Toggles the status of a user between 'Active' and 'Suspended' | G44: DBX | J44: Standard
A45: 1 | B45: User Management | C45: Login | D45: getDbxUserStatus | E45: https://konydocs.atlassian.net/wiki/spaces/ARBD425/pages/1080821932/getDbxUserStatus+Java+Integration+Service | F45: Retrieves the status of the user in DBX | G45: DBX | H45: 0 | J45: Standard
A46: 1 | B46: User Management | C46: Login | D46: smsOTP | E46: https://konydocs.atlassian.net/wiki/spaces/ARBD425/pages/1080821953/smsOTP+Java+Integration+Service | F46: Generates an OTP and sends an SMS to the provided phone number. An optional e-Mail can also be provided if the user wants to receive the OTP through this channel. | H46: 2 | J46: Standard
A47: 1 | B47: User Management | C47: Login | D47: dbxRequestOTP | E47: https://konydocs.atlassian.net/wiki/spaces/ARBD425/pages/1080820835/dbxRequestOTP+Java+Integration+Service | F47: The API requests an OTP. | H47: 2
A48: 1 | B48: User Management | C48: Login | D48: getCustomerCommunication | E48: https://konydocs.atlassian.net/wiki/spaces/ARBD425/pages/1080821006/getCustomerCommunication+Java+Integration+Service | F48: Retrieves the communication details for the specified user | G48: DBX | H48: 3 | J48: Standard
A49: 1 | B49: User Management | C49: Login | D49: getUserNameRulesAndPolicy | E49: https://konydocs.atlassian.net/wiki/spaces/ARBD425/pages/1080821036/getUserNameRulesAndPolicy+Java+Integration+Service | F49: Retrieves the policies for user name in DBX | G49: DBX | H49: 0 | J49: Standard
A50: 1 | B50: User Management | C50: Login | D50: getPasswordRulesAndPolicy | E50: https://konydocs.atlassian.net/wiki/spaces/ARBD425/pages/1080820305/getPasswordRulesAndPolicy+Java+Integration+Service | F50: Retrieves the policies for user name in DBXRetrieves the policies for maintaining a password in DBX | G50: DBX | H50: 0 | J50: Standard
A51: 1 | B51: User Management | C51: Login | D51: getUserNameAndPasswordRulesAndPolicies | E51: https://konydocs.atlassian.net/wiki/spaces/ARBD425/pages/1080821007/getUserNameAndPasswordRulesAndPolicies+Java+Integration+Service | F51: Retrieves the policies for maintaining a username and password in DBX | G51: DBX | H51: 0 | J51: Standard
A52: 1 | B52: User Management | C52: Login | D52: getAPIPasswordLockoutSettings | E52: https://konydocs.atlassian.net/wiki/spaces/ARBD425/pages/1080821009/getAPIPasswordLockoutSettings+Java+Integration+Service | F52: Retrieves the password lockout settings maintained in the DBX identity management system | G52: DBX | H52: 0 | J52: Standard
A53: 1 | B53: User Management | C53: Login | D53: getPasswordLockoutSettings | E53: https://konydocs.atlassian.net/wiki/spaces/ARBD425/pages/1080821015/getPasswordLockoutSettings+Java+Integration+Service | F53: Retrieves the password lockout settings maintained in the DBX identity management system | G53: DBX | H53: 0 | J53: Standard
A54: 1 | B54: User Management | C54: Login | D54: updateDbxUserPassword | E54: https://konydocs.atlassian.net/wiki/spaces/ARBD425/pages/1080820207/updateDbxUserPassword+Java+Integration+Service | F54: Updates the password of a user The password provided needs to satisfy the password policies configured in the Customer360 application. | G54: DBX | H54: 0 | J54: Standard
A55: 1 | B55: User Management | C55: Login | D55: requestEnrollOTP | E55: https://konydocs.atlassian.net/wiki/spaces/ARBD425/pages/1080821713/requestEnrollOTP+Java+Integration+Service | F55: The API initiates the MFA process or alernately fetches additional parameters required to initiate the MFA process. This service is invoked in pre-login flows like password reset and user enrollment. | H55: 0 | J55: Standard
A56: 1 | B56: User Management | C56: Login | D56: verifyOTPPreLogin | E56: https://konydocs.atlassian.net/wiki/spaces/ARBD425/pages/1080820317/verifyOTPPreLogin+Java+Integration+Service | F56: The API validates and verifies the OTP passed in from the application for the given pre-login scenario like reset password or user enrollment | H56: 2 | J56: standard
A57: 1 | B57: User Management | C57: Login | D57: requestLoginMFAOTP | E57: https://konydocs.atlassian.net/wiki/spaces/ARBD425/pages/1080821722/requestLoginMFAOTP+Java+Integration+Service | F57: The API initiates the MFA OTP process for the Login flow. | G57: DBX | H57: 2 | J57: standard
A58: 1 | B58: User Management | C58: Login | D58: verifyLoginMFAOTP | E58: https://konydocs.atlassian.net/wiki/spaces/ARBD425/pages/1080821725/verifyLoginMFAOTP+Java+Integration+Service | F58: The API initiates the MFA OTP process for the Login flow. The API validates and verifies the OTP passed in from the application for the given Login scenario. | G58: DBX | H58: 2 | J58: standard
A59: 1 | B59: User Management | C59: Login | D59: verifyLoginMFASecurityQuestions | E59: https://konydocs.atlassian.net/wiki/spaces/ARBD425/pages/1080820386/verifyLoginMFASecurityQuestions+Java+Integration+Service | F59: The API validates and verifies the user's answers to the specified security questions for the given Login scenario. | G59: DBX | H59: 3 | J59: standard
A60: 6 | B60: Notifications | C60: Preferences | D60: deleteNotification | E60: https://konydocs.atlassian.net/wiki/spaces/ARBD425/pages/1080821519/deleteNotification+Java+Integration+Service | F60: The API deletes the notification. The API is used only in Online Banking (OLB). | G60: DBX | H60: 0 | J60: Standard
A61: 6 | B61: Notifications | C61: Preferences | D61: getNotifications | E61: https://konydocs.atlassian.net/wiki/spaces/ARBD425/pages/1080821544/getNotifications+Java+Integration+Service | F61: The API retrieves all the notifications of the user. The API is used only in Online Banking (OLB). | G61: DBX | H61: 0 | J61: Standard
A62: 6 | B62: Notifications | C62: Preferences | D62: getUnreadNotifications | E62: https://konydocs.atlassian.net/wiki/spaces/ARBD425/pages/1080820331/getUnreadNotifications+Java+Integration+Service | F62: The API gets the count of unread notifications. The API is used only in Online Banking (OLB). | G62: DBX | H62: 0 | J62: Standard
A63: 6 | B63: Notifications | C63: Preferences | D63: getUserAccountAlerts | E63: https://konydocs.atlassian.net/wiki/spaces/ARBD425/pages/1080820022/getUserAccountAlerts+Java+Integration+Service | F63: The API retrieves all the account-related alerts of users. | G63: DBX | H63: 0 | J63: Standard
A64: 6 | B64: Notifications | C64: Preferences | D64: getUserAlerts | E64: https://konydocs.atlassian.net/wiki/spaces/ARBD425/pages/1080820046/getUserAlerts+Java+Integration+Service | F64: The API retrieves the user level alerts such as security alerts, deal alerts, and general alerts. | G64: DBX | H64: 4 | J64: Standard
A65: 6 | B65: Notifications | C65: Preferences | D65: updateReadCount | E65: https://konydocs.atlassian.net/wiki/spaces/ARBD425/pages/1080821484/updateReadCount+Java+Integration+Service | F65: The API updates the notifications as Read only. The API is used only in Online Banking (OLB). | G65: DBX | H65: 0 | J65: Standard
A66: 6 | B66: Notifications | C66: Preferences | D66: updateUserAccountAlert | E66: https://konydocs.atlassian.net/wiki/spaces/ARBD40/pages/739770769/updateUserAccountAlert | F66: The API updates various account-level alerts. For example, the value of the minimum balance threshold. | G66: DBX | H66: 0 | J66: Standard
A67: 6 | B67: Notifications | C67: Preferences | D67: updateUserAlert | E67: https://konydocs.atlassian.net/wiki/spaces/ARBD425/pages/1080819958/updateUserAlert+Java+Integration+Service | F67: The API updates user level alerts, for example, turn off the deals expiring alert. | G67: DBX | H67: 3 | J67: Standard
A68: 8 | B68: Profile | C68: Profile Management | D68: activateBillPaymentForUser | E68: https://konydocs.atlassian.net/wiki/spaces/ARBD425/pages/1080820629/activateBillPaymentForUser+Java+Integration+Service | F68: The API enables the Bill Payment functionality for the user. | H68: 0 | J68: Add-on
A69: 8 | B69: Profile | C69: Profile Management | D69: activateP2PForUser | E69: https://konydocs.atlassian.net/wiki/spaces/ARBD425/pages/1080821594/activateP2PForUser+Java+Integration+Service | F69: The API enables the P2P functionality for the user. | H69: 0 | J69: Standard
A70: 8 | B70: Profile | C70: Profile Management | D70: checkSecureAccessCode | E70: https://konydocs.atlassian.net/wiki/spaces/ARBD425/pages/1080821476/checkSecureAccessCode+Java+Integration+Service | F70: The API verifies the email, and phone enabled status for secure access. | H70: 0 | J70: Standard
A71: 8 | B71: Profile | C71: Profile Management | D71: checkSecurityQuestionStatus | E71: https://konydocs.atlassian.net/wiki/spaces/ARBD425/pages/1080821431/checkSecurityQuestionStatus+Java+Integration+Service | F71: The API verifies if the security questions exist for a user. | G71: NA | H71: 0
A72: 8 | B72: Profile | C72: Profile Management | D72: createAddress | E72: https://konydocs.atlassian.net/wiki/spaces/ARBD425/pages/1080821530/createAddress+Java+Integration+Service | F72: The API creates the user address. | G72: DBX | H72: 0 | J72: Standard
A73: 8 | B73: Profile | C73: Profile Management | D73: createPhone | E73: https://konydocs.atlassian.net/wiki/spaces/ARBD425/pages/1080820877/createPhone+Java+Integration+Service | F73: The API creates a new phone number. | G73: DBX | H73: 0 | J73: Standard
A74: 8 | B74: Profile | C74: Profile Management | D74: createUserFeedback | E74: https://konydocs.atlassian.net/wiki/spaces/ARBD425/pages/1080821526/createUserFeedback+Java+Integration+Service | F74: The API submits feedback received from the user. | G74: DBX | H74: 0
A75: 8 | B75: Profile | C75: Profile Management | D75: deleteAddress | E75: https://konydocs.atlassian.net/wiki/spaces/ARBD425/pages/1080820552/deleteAddress+Java+Integration+Service | F75: The API deletes the address. | G75: DBX | H75: 0 | J75: Standard
A76: 8 | B76: Profile | C76: Profile Management | D76: deletePhone | E76: https://konydocs.atlassian.net/wiki/spaces/ARBD425/pages/1080821426/deletePhone+Java+Integration+Service | F76: The API deletes the user phone number. | G76: DBX | H76: 0 | J76: Standard
A77: 8 | B77: Profile | C77: Profile Management | D77: getAllAddress | E77: https://konydocs.atlassian.net/wiki/spaces/ARBD425/pages/1080821621/getAllAddress+Java+Integration+Service | F77: The API fetches all user addresses. | G77: DBX | H77: 0 | J77: Standard
A78: 8 | B78: Profile | C78: Profile Management | D78: getAllPhones | E78: https://konydocs.atlassian.net/wiki/spaces/ARBD425/pages/1080821619/getAllPhones+Java+Integration+Service | F78: The API gets all user phones. | H78: 0 | J78: Standard
A79: 8 | B79: Profile | C79: Profile Management | D79: getNewBrowserCheck | E79: https://konydocs.atlassian.net/wiki/spaces/ARBD425/pages/1080821606/getNewBrowserCheck+Java+Integration+Service | F79: Verifies if the current user access is through a new browser. | G79: DBX | H79: 0 | J79: Standard
A80: 8 | B80: Profile | C80: Profile Management | D80: getUserDetails | E80: https://konydocs.atlassian.net/wiki/spaces/ARBD425/pages/1080819969/getUserDetails+Java+Integration+Service | F80: The API gets the profile details of the user. | G80: DBX | H80: 0 | J80: Standard
A81: 8 | B81: Profile | C81: Profile Management | D81: getUserStatus | E81: https://konydocs.atlassian.net/wiki/spaces/ARBD425/pages/1080820598/getUserStatus+Java+Integration+Service | F81: Retrieves the Enrollment and Lock status of a user. | G81: N/A | H81: 0 | J81: Standard
A82: 8 | B82: Profile | C82: Profile Management | D82: lockUnlockUser | E82: https://konydocs.atlassian.net/wiki/spaces/ARBD425/pages/1080820528/lockUnlockUser+Java+Integration+Service | F82: Issues a lock or unlock request for the user depending on the current lock state. | G82: DBX | H82: 0 | J82: Standard
A83: 8 | B83: Profile | C83: Profile Management | D83: registerP2P | E83: https://konydocs.atlassian.net/wiki/spaces/ARBD425/pages/1080821451/registerP2P+Java+Integration+Service | F83: Register a user for P2P functionality for specific third party vendors. | H83: 4 | J83: Add-on
A84: 8 | B84: Profile | C84: Profile Management | D84: registerP2PStatus | E84: https://konydocs.atlassian.net/wiki/spaces/ARBD425/pages/1080820594/registerP2PStatus+Java+Integration+Service | F84: Retrieves the P2P registration status for a user. | G84: DBX | J84: Standard
A85: 8 | B85: Profile | C85: Profile Management | D85: updateAddress | E85: https://konydocs.atlassian.net/wiki/spaces/ARBD425/pages/1080820881/updateAddress+Java+Integration+Service | F85: The API updates the address. | G85: DBX | H85: 0 | J85: Standard
A86: 8 | B86: Profile | C86: Profile Management | D86: updatePhone | E86: https://konydocs.atlassian.net/wiki/spaces/ARBD425/pages/1080820865/updatePhone+Java+Integration+Service | F86: The API updates the user phone number. | G86: DBX | H86: 0 | J86: Standard
A87: 8 | B87: Profile | C87: Profile Management | D87: updateSecureAccessCode | E87: https://konydocs.atlassian.net/wiki/spaces/ARBD425/pages/1080821483/updateSecureAccessCode+Java+Integration+Service | F87: The API updates the secure access code. | G87: DBX | H87: 0 | J87: Standard
A88: 8 | B88: Profile | C88: Profile Management | D88: updateUserAccountSettings | E88: https://konydocs.atlassian.net/wiki/spaces/ARBD424/pages/1031438732/updateUserAccountSettings+Java+Integration+Service | F88: The API updates the account settings of a user. | G88: DBX | H88: 0 | J88: Standard
A89: 8 | B89: Profile | C89: Profile Management | D89: updateUserDetails | E89: https://konydocs.atlassian.net/wiki/spaces/ARBD425/pages/1080820003/updateUserDetails+Java+Integration+Service | F89: The API updates personal information such as contact details, user name, and password. | G89: DBX | H89: 3 | J89: Standard
A90: 8 | B90: Profile | C90: Profile Management | D90: updateUserSecurityQuestions | E90: https://konydocs.atlassian.net/wiki/spaces/ARBD424/pages/1031438881/updateUserSecurityQuestions+Java+Integration+Service | F90: The API updates a user's security questions and answers. | G90: DBX | H90: 0 | J90: Standard
A91: 8 | B91: Profile | C91: Profile Management | D91: verifyExistingPassword | E91: https://konydocs.atlassian.net/wiki/spaces/ARBD425/pages/1080820847/verifyExistingPassword+Java+Integration+Service | F91: The API verifies the existing password of a user. | H91: 0 | J91: Standard
A92: 8 | B92: Profile | C92: Profile Management | D92: updateDbxUser | E92: https://konydocs.atlassian.net/wiki/spaces/ARBD425/pages/1080821934/updateDbxUser+Java+Integration+Service | F92: Updates personal information such as user name, date of birth and other PII fields. | H92: 0 | J92: Standard
A93: 8 | B93: Profile | C93: Profile Management | D93: lockUnlockCustomer | E93: https://konydocs.atlassian.net/wiki/spaces/ARBD425/pages/1080820271/lockUnlockCustomer+Java+Integration+Service | F93: Issues a lock or unlock request for the user depending on the current lock state. | G93: DBX | H93: 3 | J93: Standard
A94: 8 | B94: Profile | C94: Profile Management | D94: updateDbxCustomer | E94: https://konydocs.atlassian.net/wiki/spaces/ARBD425/pages/1080820119/updateDbxCustomer+Java+Integration+Service | F94: Updates personal information such as user name, date of birth and other PII fields. | G94: DBX | H94: 0 | J94: Standard
A95: 2 | B95: Account Management | C95: Account Services | D95: getAccountPendingTransactions | E95: https://konydocs.atlassian.net/wiki/spaces/ARBD425/pages/1080820518/getAccountPendingTransactions+Java+Integration+Service | F95: The API gets particular account pending transactions in Mobile Banking. | H95: 5 | J95: Add-on
A96: 2 | B96: Account Management | C96: Account Services | D96: getAccountPostedTransactions | E96: https://konydocs.atlassian.net/wiki/spaces/ARBD425/pages/1080820803/getAccountPostedTransactions+Java+Integration+Service | F96: The API gets particular account posted transactions in Mobile Banking. | H96: 5 | J96: Add-on
A97: 2 | B97: Account Management | C97: Account Services | D97: getAccounts | E97: https://konydocs.atlassian.net/wiki/spaces/ARBD425/pages/1080819735/getAccounts+Java+Integration+Service | F97: The API retrieves the list of all accounts for the account preview. | H97: 5 | J97: Add-on
A98: 2 | B98: Account Management | C98: Account Services | D98: getAccountsPostLogin | E98: https://konydocs.atlassian.net/wiki/spaces/ARBD425/pages/1080820887/getAccountsPostLogin+Java+Integration+Service | F98: The API retrieves the list of all accounts for the logged-in user in Online Banking application (OLB). | H98: 5 | J98: Add-on
A99: 2 | B99: Account Management | C99: Account Services | D99: getAccountTransactionsByType | E99: https://konydocs.atlassian.net/wiki/spaces/ARBD425/pages/1080820645/getAccountTransactionsByType+Java+Integration+Service | F99: Gets the list of transactions based on the account type. | H99: 2 | J99: Add-on
A100: 2 | B100: Account Management | C100: Account Services | D100: getAccountType | E100: https://konydocs.atlassian.net/wiki/spaces/ARBD425/pages/1080819907/getAccountType+Java+Integration+Service | F100: The API retrieves the list of all supported account types. | G100: DBX | H100: 0 | J100: Standard
...

Sheet Customer 360
J1: Channel
A2: Category # | B2: Module | C2: Sub-Module | D2: API | E2: Description | F2: System of Record | G2: Readiness | H2: Integration Notes | I2: Standard/Add-on | J2: Mobile | K2: Tablet | L2: Web | M2: NUO
A3: 31 | B3: User Management | C3: Login | D3: getAllEntitlements | E3: The API retrieves the list of all entitlements for a user | F3: DBX | G3: 0
A4: 31 | B4: User Management | C4: Login | D4: RegisterCustomerDevice | E4: The API registers a device for a given user in DBX. | F4: DBX | G4: 0
A5: 31 | B5: User Management | C5: Login | D5: trackRegisterCustomerDevice | E5: The API registers a device for a customer | F5: DBX | G5: 0
A6: 31 | B6: User Management | C6: Login | D6: UpdateCustomerDeviceInformation | E6: The API updates the information of a registered device for a given user. | F6: DBX | G6: 0
A7: 31 | B7: User Management | C7: Login | D7: DBX_verifyCustomerSecurityQuestions | E7: The API verifies the answers provided by the customer for their security questions. | F7: DBX | G7: 0
A8: 31 | B8: User Management | C8: Login | D8: createCustomerSecurityQuestions | E8: The API sets up security questions for a customer in DBX. | F8: DBX | G8: 0
A9: 31 | B9: User Management | C9: Login | D9: getRandomCustomerSecurityQuestions | E9: The API retrieves all the security questions of a given customer. | F9: DBX | G9: 0
A10: 31 | B10: User Management | C10: Login | D10: getSecurityQuestions | E10: The API retrieves the list of security questions maintained in DBX | F10: DBX | G10: 0
A11: 31 | B11: User Management | C11: Login | D11: verifyCustomerSecurityQuestions | E11: The API verifies the answers of security questions provided by a customer | F11: DBX | G11: 0
A12: 31 | B12: User Management | C12: Profile Management | D12: getAllAlerts | E12: The API retrieves the list of alerts and alert preferences of a user | F12: DBX | G12: 0
A13: 31 | B13: User Management | C13: Profile Management | D13: updateAlerts | E13: The API updates the details of an alert | F13: DBX | G13: 0
A14: 31 | B14: User Management | C14: Profile Management | D14: fetchCustomerDetailsForOlb | E14: The API retrieves basic customer profile information | F14: DBX | G14: 0
... A57: 35 | B57: Administration | C57: Outage Message | D57: updateOutageMessage | E57: The API updates the content of an outage message | F57: DBX | G57: 0
A59: 39 | B59: Custom | G59: 0

Sheet Vendor List
A2: Backend Requirement for | B2: CWB Current | C2: CWB Future
A3: Core Banking
A4: Remote Deposit Capture System (RDC)
A5: Reporting & Analytics
A6: Check Images
A7: Document Management Database
A8: Bill Pay System
A9: Card Control
A10: PFM / Data Enrichment
A11: Card Processor
A12: P2P / Real Time Payments System (RTP)
A13: Risk Profile System
A14: SMS Aggregator System
... A32: Product

Sheet Lists
B2: Development Category | D2: Product | F2: Custom | J2: Product-Custom
B3: Product | D3: - | F3: 1 - Low | J3: 1 - Low
B4: Custom | F4: 2 - Med | J4: 2 - Med
B5: Product+Custom | F5: 3 - High | J5: 3 - High
B10: Platform Support | D10: Backend | E10: Customer | I10: Product
D11: =IF(#REF!=0,"",#REF!) -> #REF! | E11: =IF(#REF!=0,"",#REF!) -> #REF! | I11: Custom
B12: Y | D12: =IF(#REF!=0,"",#REF!) -> #REF! | E12: =IF(#REF!=0,"",#REF!) -> #REF!
B13: N | D13: =IF(#REF!=0,"",#REF!) -> #REF! | E13: =IF(#REF!=0,"",#REF!) -> #REF!
B14: N/A | D14: =IF(#REF!=0,"",#REF!) -> #REF! | E14: =IF(#REF!=0,"",#REF!) -> #REF!
D15: =IF(#REF!=0,"",#REF!) -> #REF! | E15: =IF(#REF!=0,"",#REF!) -> #REF!
D16: =IF(#REF!=0,"",#REF!) -> #REF! | E16: =IF(#REF!=0,"",#REF!) -> #REF!
D17: =IF(#REF!=0,"",#REF!) -> #REF! | E17: =IF(#REF!=0,"",#REF!) -> #REF!
D18: =IF(#REF!=0,"",#REF!) -> #REF! | E18: =IF(#REF!=0,"",#REF!) -> #REF!
D19: =IF(#REF!=0,"",#REF!) -> #REF! | E19: =IF(#REF!=0,"",#REF!) -> #REF!
D20: =IF(#REF!=0,"",#REF!) -> #REF! | E20: =IF(#REF!=0,"",#REF!) -> #REF!
D21: =IF(#REF!=0,"",#REF!) -> #REF! | E21: =IF(#REF!=0,"",#REF!) -> #REF!
D22: =IF(#REF!=0,"",#REF!) -> #REF! | E22: =IF(#REF!=0,"",#REF!) -> #REF!
D23: =IF(#REF!=0,"",#REF!) -> #REF! | E23: =IF(#REF!=0,"",#REF!) -> #REF!
D24: =IF(#REF!=0,"",#REF!) -> #REF! | E24: =IF(#REF!=0,"",#REF!) -> #REF!
D25: =IF(#REF!=0,"",#REF!) -> #REF! | E25: =IF(#REF!=0,"",#REF!) -> #REF!
D26: =IF(#REF!=0,"",#REF!) -> #REF! | E26: =IF(#REF!=0,"",#REF!) -> #REF!
... D70: =IF(#REF!=0,"",#REF!) -> #REF! | E70: =IF(#REF!=0,"",#REF!) -> #REF!
D71: =IF(#REF!=0,"",#REF!) -> #REF!
